Workbook
Name _ftn1: DIP!$M$14
Name _ftn2: DIP!#REF!
Name _ftn3: DIP!$M$15
Name _Hlk49441128: 'Credit terms'!$C$82
Name _Hlk49441128: 'Lawyers terms'!$C$103
Name _Hlk83203796: DIP!$A$83
Name _Hlk84245425: DIP!$A$57
Name _Hlk98754409: DIP!$K$59
Name _Hlk99544404: 'Credit terms'!$C$23
Name _Hlk99544404: 'Lawyers terms'!$C$28
Name Amber_P: #REF!
Name Amber_P: #REF!
Name APR: #REF!
Name APR: #REF!
Name APR: #REF!
Name APR: 'KB_CRITERIA AND CALCULATION '!$L$32
Name Bank_Rate: 'EBITDA calc_'!#REF!
Name Bank_Rate: #REF!
Name Bank_Rate: #REF!
Name BankBase: #REF!
Name BankBase: #REF!
Name BBR: #REF!
Name BBR: #REF!
Name BBR: #REF!
Name BBR: 'Product Data'!$E$3
Name BBR_Override: 'BTL Calculator WIP'!$K$28
Name BBR_Override: #REF!
Name BBR_Override: #REF!
Name BBR_Override: #REF!
Name BBR_Override: 'BTL Calculator'!$H$31
Name Core_Net_loan: #REF!
Name Core_Net_loan: #REF!
Name Core_Net_loan: #REF!
Name Core_Net_loan: 'KB_CRITERIA AND CALCULATION '!$D$29
Name CoreList: 'Product Data'!#REF!
Name CoreListAdj: 'Product Data'!$Y$22:$Y$24
Name CoreSpecialist: OFFSET('Product Data'!$BR$2, 0, 0, SUMPRODUCT(--(LEN('Product Data'!$BR$2:$BR$100)>0)), 1)
Name CoreTypes: 'Product Data'!$BU$2
Name CoreTypes_All: 'Product Data'!$BU$2:$BU$3
Name CoreTypes2: 'Product Data'!$BU$3
Name Custom_Defer: 'BTL Calculator WIP'!$I$59
Name Custom_Defer: 'BTL Calculator'!$I$67
Name Custom_Rolled: 'BTL Calculator WIP'!$AR$2
Name Custom_Rolled: 'BTL Calculator'!$AS$3
Name Custom_Rolled_Actual: 'KB_CRITERIA AND CALCULATION '!$K$88
Name DD_In_Month1: 'DD (2)'!$T$15
Name DD_In_Month1: #REF!
Name DD_In_Month1: #REF!
Name DD_In_Month1: #REF!
Name DD_In_Month1: DD!$T$15
Name Defer_int: 'BTL Calculator WIP'!$I$59
Name Defer_int: 'BTL Calculator'!$I$67
Name Defer_Term_Override: 'BTL Calculator WIP'!$AN$26
Name Defer_Term_Override: #REF!
Name Defer_Term_Override: #REF!
Name Defer_Term_Override: #REF!
Name Defer_Term_Override: 'BTL Calculator'!$CY$8
Name Defer2: #REF!
Name Defer2: #REF!
Name Defer2: #REF!

Sheet BTL Calculator WIP
J1: UNDERWRITER BTL Calculator | W1: Version 03.08.23 | AO1: BDM? | AP1: Messages | AQ1: Term Radio Button | AR1: RADIO ROLLED | AT1: Radio Rolled vs Deferred
B2: User Inputs | AO2: Hide: Section 3 and row 150 onwards. Only include calc and holiday let tabs | AQ2: 1 | AR2: 4
B4: The Borrower | I4: Hubspot Loan Ref: | K4: 0000000000 | R4: Property Details | AA4: Property Value | AB4: 450000 | AO4: Message formula check with underwriters, compared to the product fee, less the proc fee not just product fee
I5: Borrower Name: | K5: Borrower Name | AA5: Rent Charged | AB5: Monthly
AA6: ="Estimated "&AB5&" Gross Rent" -> Estimated Monthly Gross Rent | AB6: 2200 | AD6: Obtained from broker enquiry or AST if already rented
I7: Property Address: | K7: Property Address | AB7: =Monthly_Rent -> 0
AA8: Property Postcode | AB8: SE18 | AD8: ="HPI Adjusted in 2022 "&TEXT(HPIAdjusted2022/1000000,"£ #0.##0")&"m, 2023 "&TEXT(HPIAdjusted2023/1000000,"£ #0.##0")&"m, 2024 "&TEXT(HPIAdjusted2024/1000000,"£ #0.##0")&"m, 2025 "&TEXT(HPIAdjusted2025/1000000,"£ #0.##0")&"m" -> #N/A
AA9: Property Region | AB9: London | AD9: =IFERROR("Recommended from postcode - "&'KB_CRITERIA AND CALCULATION '!F21,"")
I10: First time Landlord? | K10: No | AA10: Borrower in a restricted country? | AB10: No | AD10: Restricted countries: **Afghanistan, Bosnia Herzegovina, Burundi, Central African Republic, Cuba, Democratic People's Republic of Korea, Democratic Republic of the Congo, Eritrea, Ethiopia, Iran (Islamic Republic of), Iraq, Laos People's Democratic Republic, Libyan Arab Jamahiriya, Myanmar, Pakistan, Somalia, South Sudan, Sudan, Syrian Arab Republic, Uganda, Vanuatu, Venezuela, Yemen.
I11: Expat/ Foreign National? | K11: No | AA11: HMO? | AB11: No
I12: Have a UK Footprint? | K12: Yes | AA12: MUFB? | AB12: No
I13: Offshore Company/Trust? | K13: No | AA13: Flat above restricted* commercial? | AB13: No | AH13: ='KB_CRITERIA AND CALCULATION '!$L$2 -> Available Funding lines are: Zircon or Pearl
I14: Qualifying adverse credit? | K14: No | AA14: Holiday/ Short term Let? | AB14: No | AH14: =TRIM('KB_CRITERIA AND CALCULATION '!$L$3) -> #N/A | AO14: 1
I15: Missed Mortgage Payments (incl. 2nds) | K15: 0 missed last 24m | AA15: Development Exit? | AB15: No | AO15: 2
I16: Unsecured Card/Loan Payments: (ignore balance<£500) | K16: 0 missed last 24m | O16: (ignore where balance<= £500) | AA16: New Build? | AB16: No | AI16: Pick an investor: | AO16: 3
I17: Qualifying CCJs & Defaults: | K17: 0 in last 24m | O17: (ignore<=£350,telecom, utility) | AI17: ZBL | AO17: 4
I18: Bankruptcy/IVA/DRO: | K18: Never | T18: Summary Loan Outputs | AJ18: DO we need rule to say which lines can do 4/6% product?
T19: Basic | W19: Fully R+D (Broker) | Z19: Fully R+D (Underwriter) | AB19: Custom
B21: Loan Details | I21: Initial Term: | K21: =IF(AQ2=2,36,24) -> 24 | R21: Gross Loan | S21: Tier 1 | T21: =IFERROR(IF(RoundDown,'KB_CRITERIA AND CALCULATION '!R76,'KB_CRITERIA AND CALCULATION '!Q76),"-") -> 0 | W21: =IFERROR(IF(RoundDown,'KB_CRITERIA AND CALCULATION '!R79,'KB_CRITERIA AND CALCULATION '!Q79),"-") -> 0 | Z21: =IFERROR(IF(RoundDown,'KB_CRITERIA AND CALCULATION '!R82,'KB_CRITERIA AND CALCULATION '!Q82),"-") -> 0 | AB21: =IFERROR(IF(RoundDown,'KB_CRITERIA AND CALCULATION '!R85,'KB_CRITERIA AND CALCULATION '!Q85),"-") -> 0 | AD21: =IF(Tier1_Eligible,"","Ineligible for Tier 1") | AO21: ="ERC - "&'Product Data'!AO9&'Product Data'!AO10&'Product Data'!AO11&'Product Data'!AO12&" Final month is ERC free" -> #N/A
I22: Customer Type: | K22: New Customer | S22: Tier 2 | T22: =IF(RoundDown,'KB_CRITERIA AND CALCULATION '!R77,'KB_CRITERIA AND CALCULATION '!Q77) -> 0 | W22: =IF(RoundDown,'KB_CRITERIA AND CALCULATION '!R80,'KB_CRITERIA AND CALCULATION '!Q80) -> 0 | Z22: =IF(RoundDown,'KB_CRITERIA AND CALCULATION '!R83,'KB_CRITERIA AND CALCULATION '!Q83) -> 0 | AB22: =IF(RoundDown,'KB_CRITERIA AND CALCULATION '!R86,'KB_CRITERIA AND CALCULATION '!Q86) -> 0 | AD22: =IF(Tier2_Eligible,"","Ineligible for Tier 2")
I23: Rates: | K23: Tracker | S23: Tier 3 | T23: =IF(RoundDown,'KB_CRITERIA AND CALCULATION '!R78,'KB_CRITERIA AND CALCULATION '!Q78) | W23: =IF(RoundDown,'KB_CRITERIA AND CALCULATION '!R81,'KB_CRITERIA AND CALCULATION '!Q81) | Z23: =IF(RoundDown,'KB_CRITERIA AND CALCULATION '!R84,'KB_CRITERIA AND CALCULATION '!Q84) | AB23: =IF(RoundDown,'KB_CRITERIA AND CALCULATION '!R87,'KB_CRITERIA AND CALCULATION '!Q87) | AD23: =IF(Tier3_Eligible,"","Ineligible for Tier 3") | AE23: Pull down - show all or only tier selected?
I24: Estimated Cheapest Tier: | K24: ='KB_CRITERIA AND CALCULATION '!D36 -> 1) Standard BTL | O24: Select 2/4/6 | S24: Tier 4 | T24: =IF(RoundDown,'KB_CRITERIA AND CALCULATION '!#REF!,'KB_CRITERIA AND CALCULATION '!#REF!) -> #REF! | W24: =IF(RoundDown,'KB_CRITERIA AND CALCULATION '!#REF!,'KB_CRITERIA AND CALCULATION '!#REF!) -> #REF! | Z24: =IF(RoundDown,'KB_CRITERIA AND CALCULATION '!#REF!,'KB_CRITERIA AND CALCULATION '!#REF!) -> #REF! | AB24: =IF(RoundDown,'KB_CRITERIA AND CALCULATION '!#REF!,'KB_CRITERIA AND CALCULATION '!#REF!) -> #REF! | AD24: =IF(Tier4_Eligible,"","Ineligible for Tier 4") | AL24: Additional Calculation Settings:
F25: Tier Rate: | K25: =INDEX('Product Data'!$C$9:$C$16,MATCH($K$24,'Product Data'!$B$9:$B$16,0)) -> 0.0764 | O25: Return correct 2/4/6 rate
I26: Revert Rate: | K26: =INDEX('Product Data'!I:I,MATCH('BTL Calculator WIP'!K24,'Product Data'!B:B,0))+'Product Data'!$E$3 -> 0.1329 | O26: BBR + Margin or MVR | AK26: ="(Tracker Override) Deferred at full term? ("&Term&" months)" -> (Tracker Override) Deferred at full term? (24 months) | AN26: Default (Yes)
I27: Override Rate? | X27: Do we replace with a full grid of products - 2/4/6 for the tier selected? | AK27: (Tracker Override) Set rolled months to: | AN27: Default (Pay Rate)
I28: BBR Override? | X28: Could not do 4 tiers, for three options. Display max loan, max roll defer etc | AK28: Borrower prefers interest to be: | AN28: Rolled | AO28: ="Note: To use setting 'I want a specific amount (Net)', set the preference to be "&'KB_CRITERIA AND CALCULATION '!#REF! -> #REF! | AP28: =IF('KB_CRITERIA AND CALCULATION '!$F$36<=$AO15,TRUE,FALSE) -> TRUE | AR28: =INDEX(AQ32:AQ35,MATCH($AS$32,AP32:AP35,0)) -> TRUE
I29: Product Fee: | K29: =INDEX('Product Data'!F:F,MATCH('BTL Calculator WIP'!K24,'Product Data'!B:B,0)) -> Withdrawn | O29: Return correct 2/4/6 fee | X29: Could also display gross, net in one grid | AK29: Spread Rolled Months to reduce DD? | AN29: No | AO29: Start reduced DD amount in month 1 (not after rolled period) | AP29: =IF('KB_CRITERIA AND CALCULATION '!$F$36<=$AO16,TRUE,FALSE) -> TRUE
AK30: Round Gross Loan to Nearest £'000?
I31: Product Fee Override? | T31: Basic | W31: Fully R+D (Broker) | Z31: Fully R+D (Underwriter) | AB31: Custom | AS31: Selected Tier eligible?
I32: Max Gross LTV for tier: | K32: ='KB_CRITERIA AND CALCULATION '!S36 -> 0.75 | AE32: Table? | AK32: Stress BBR Override? | AP32: ='Product Data'!B9 -> 1) Standard BTL | AQ32: =IF('KB_CRITERIA AND CALCULATION '!$F$36<=$AO14,TRUE,FALSE) -> TRUE | AS32: =Product_Selected -> 1) Standard BTL
I33: Submission route | K33: Broker Direct | R33: Net Loan | S33: Tier 1 | T33: =IFERROR('KB_CRITERIA AND CALCULATION '!AL76,"-") -> 0 | W33: =IFERROR('KB_CRITERIA AND CALCULATION '!AL79,"-") -> 0 | Z33: =IFERROR('KB_CRITERIA AND CALCULATION '!AL82,"-") -> 0 | AB33: =IFERROR('KB_CRITERIA AND CALCULATION '!AL85,"-") -> 0 | AE33: Tier / Prod Fee % & £ / basic max G.loan & LTV / fully roll defer & LTV / custom / roll & defer used / basic max N.loan / fully roll defer / custom / monthly DD
I34: ="Gross "&'Product Data'!$AF$4&" Proc Fee:" -> Gross Broker Proc Fee: | K34: =IFERROR(INDEX('Product Data'!$AE$9:$AE$16,MATCH(K33,'Product Data'!$AD$9:$AD$16,0)),1%) -> 0.01 | S34: Tier 2 | T34: ='KB_CRITERIA AND CALCULATION '!AL77 -> 0 | W34: ='KB_CRITERIA AND CALCULATION '!AL80 -> 0 | Z34: ='KB_CRITERIA AND CALCULATION '!AL83 -> 0 | AB34: ='KB_CRITERIA AND CALCULATION '!AL86 -> 0 | AE34: DO we need ICR in revert period?
I35: ="Gross "&'Product Data'!$AF$4&" Proc Fee override:"&" %" -> Gross Broker Proc Fee override: % | K35: 0.01 | S35: Tier 3 | T35: ='KB_CRITERIA AND CALCULATION '!AL78 | W35: ='KB_CRITERIA AND CALCULATION '!AL81 | Z35: ='KB_CRITERIA AND CALCULATION '!AL84 | AB35: ='KB_CRITERIA AND CALCULATION '!AL87 | AP35: ='Product Data'!B12 -> 0 | AQ35: =IF('KB_CRITERIA AND CALCULATION '!$F$36<=$AO17,TRUE,FALSE) -> TRUE
I36: £ | S36: Tier 4 | T36: ='KB_CRITERIA AND CALCULATION '!#REF! -> #REF! | W36: ='KB_CRITERIA AND CALCULATION '!#REF! -> #REF! | Z36: ='KB_CRITERIA AND CALCULATION '!#REF! -> #REF! | AB36: ='KB_CRITERIA AND CALCULATION '!#REF! -> #REF!
I37: ="Optional Broker fee?"&" %" -> Optional Broker fee? % | O37: =IF(K37>0.01,"Warning: High broker fee","") | AO37: =IF(K38+K37*AJ52<0,"Invalid",IF(K38+K37*AJ52>'BTL Calculator WIP'!M150,"Broker Fee Should be less than the "&TEXT('BTL Calculator WIP'!M150,"£0,0")&" product fee","")) -> #N/A
I38: £ | O38: If red please remove so only the % or the £ is populated!
I39: ERC: | K39: ='Product Data'!AO9&'Product Data'!AO10&'Product Data'!AO11&'Product Data'!AO12&" Final month is ERC free" -> #N/A
R40: ="Max Gross Loan is "&TEXT(MaxGrossLoan,"£ 0,0") -> Max Gross Loan is £ 00 | AB40: ="@ "&TEXT(MaxGrossLoan/$AB$4,"0%")&" LTV" -> @ 0% LTV | AD40: ="On Tier "&'KB_CRITERIA AND CALCULATION '!D36 -> On Tier 1) Standard BTL
B41: =IF(OR('Product Data'!AF4="Broker",'Product Data'!AF4="Client"),"","Please note for this case you do not pay the broker directly, you will be paying the "&'Product Data'!$AF$4)
S42: =IFERROR("Max Net Loan is "&TEXT(IF(COUNTIF(K24,"*1*")=1,MAX(T33:AC36),IF(COUNTIF(K24,"*2*")=1,MAX(T34:AC36),IF(COUNTIF(K24,"*3*")=1,MAX(T35:AC36),IF(COUNTIF(K24,"*4*")=1,MAX(T36:AC36),"")))),"£ 0,0"),0) -> 0 | AC42: =IFERROR("@ "&TEXT(IF(COUNTIF(K24,"*1*")=1,MAX(T33:AC36),IF(COUNTIF(K24,"*2*")=1,MAX(T34:AC36),IF(COUNTIF(K24,"*3*")=1,MAX(T35:AC36),IF(COUNTIF(K24,"*4*")=1,MAX(T36:AC36),""))))/$AB$4,"0%")&" LTV",0) -> 0
AF44: =IF(Rate_Type="Tracker","BBR: "&TEXT('Product Data'!E3,"0.00%")&" & Stressed BBR: "&TEXT('Product Data'!K3,"0.00%"),"") -> BBR: 4.00% & Stressed BBR: 4.25%
C48: Select product/rate combination you wish to proceed with to illustrate below and select for the DIP | AF48: =IF($K$23="Tracker",IF('KB_CRITERIA AND CALCULATION '!X90<120%,"FAIL: BBR Stress test ICR below 120% (@"&TEXT('KB_CRITERIA AND CALCULATION '!X90,"000%")&"). Reduce Loan Size or Roll/Defer more",IF(('KB_CRITERIA AND CALCULATION '!X90>=120%)*('KB_CRITERIA AND CALCULATION '!X90<130%),"WARNING: BBR Stress test ICR below 130% (@"&TEXT('KB_CRITERIA AND CALCULATION '!X90,"000%")&"). UW Mgr Exception, Reduce Loan Size, Roll/Defer more, & review non-BTL income/assets.",IF('KB_CRITERIA AND CALCULATION '!X90>=130%,"This tracker loan passes BBR stress test! ("&TEXT('KB_CRITERIA AND CALCULATION '!X90,"000%")&")",0))),"") -> This tracker loan passes BBR stress test! ()
C49: ='KB_CRITERIA AND CALCULATION '!#REF! -> #REF!
V50: =IF(AB16="Yes","Please ensure LTV is below 70% due to New Build","") | AF50: Simple Selected Product Summary
C52: Select Loan/CalculationType: | G52: Basic Loan | N52: Loan Amount Required: | R52: 700000 | V52: =IF(Specific_Loan=FALSE,"",IF(Loan_Required<'Product Data'!P15,"Loan size too small, please use a higher amount",IF(OR(Loan_Required>'Product Data'!P16,Loan_Required>'Product Data'!P16),"Loan size above max, please consider a lower amount",IF(Loan_Required>Property_Value,"Loan Size bigger than property value, please reduce",IF(Loan_Required>'KB_CRITERIA AND CALCULATION '!N90,"Loan size above max LTV for property, please reduce","")))))&IF(G52='KB_CRITERIA AND CALCULATION '!#REF!,IF(Loan_Required>MaxNetLoan," Loan size (NET), above Max Net loan of "&TEXT(MaxNetLoan,"£#,###"),IF(Loan_Required>AJ59,W59,"")),"")&IF(G52='KB_CRITERIA AND CALCULATION '!#REF!,IF(Loan_Required>MaxGrossLoan," Loan size (Gross), above Max Gross Loan of "&TEXT(MaxGrossLoan,"£#,###"),""),"") -> #REF! | AF52: Tier: | AG52: =AD78 -> 1) Standard BTL | AI52: Gross Loan: | AJ52: =M136 -> #N/A | AK52: =IF(Rate_Type="Tracker",IF(('KB_CRITERIA AND CALCULATION '!$AV$90="Y")*($O$59>'Product Data'!$P$20),"ICR above "&TEXT('Product Data'!$P$19,"000%")&", Please reduce Rolled Months",""),"") -> #N/A
C54: Select Tier Required: | G54: =K24 -> 1) Standard BTL | AF54: Full Rate: | AG54: =TEXT(M134,"#.##%")&IF(K23="Yes"," - Tracker","") -> #N/A | AI54: Product Fee: | AJ54: =TEXT(M135,"0.00%")&" ("&TEXT(Product_Fee_GBP,"£#0,0")&")" -> #N/A
AI55: Rolled Months: | AJ55: =IFERROR(IF(RollupMonths=0,"None",TEXT(RollupMonths,"#")&"m ("&TEXT('BTL Calculator WIP'!$M$141,"£#,#")&")"),0) -> 0
AF56: Pay Rate: | AG56: =Pay_Rate -> #N/A
AG57: =TEXT('KB_CRITERIA AND CALCULATION '!J90,"0.00%")&" deferred" -> #N/A | AI57: Defer Int: | AJ57: =IF(DeferedIntPercent=0%,"None",TEXT(DeferedIntPercent,"0.#0%")&" ("&TEXT('BTL Calculator WIP'!$M$140,"£#,#0")&")") -> #N/A
C58: CUSTOMISE THE LOAN: | G58: Deferred Interest: | M58: Rolled Months: | P58: Top Slice - £ surplus used pcm:
I59: 0.02 | O59: =Custom_Rolled -> 4 | W59: ='KB_CRITERIA AND CALCULATION '!#REF! -> #REF! | AF59: Term: | AG59: =Term&"m" -> 24m | AI59: Net Loan: | AJ59: =IFERROR(AD98,0) -> 0
AF60: ICR: | AG60: =AD95 -> -
AI61: Gross / Net LTV: | AJ61: =IFERROR(TEXT('KB_CRITERIA AND CALCULATION '!AN90,"#%")&" / "&TEXT('KB_CRITERIA AND CALCULATION '!AM90,"#%"),0) -> 0
AF62: Monthly DD: | AG62: =Monthly_DD -> - | AI62: =G52 -> Basic Loan
X63: =IF('KB_CRITERIA AND CALCULATION '!AN90='KB_CRITERIA AND CALCULATION '!M90,"ALREADY AT MAX LTV - ANY EXTRA ROLL/DEFER/TOP SLICE NOT REQUIRED","") -> #N/A | AF63: =IF('KB_CRITERIA AND CALCULATION '!AN90='KB_CRITERIA AND CALCULATION '!M90,"Note: Gross Loan capped at max LTV of "&TEXT('KB_CRITERIA AND CALCULATION '!M90,"0%"),"") -> #N/A
I64: Hint: Case capped LTV or client wants specific gross LTV of | K64: =K32 -> 0.75 | L64: ="= Set gross loan wanted to "&TEXT(K64*Property_Value,"£0,0") -> = Set gross loan wanted to £337,500
C67: Max Loan/Tier Grid - Detailed | J67: Tier X | L67: ='KB_CRITERIA AND CALCULATION '!D36 -> 1) Standard BTL
R68: Notes
C70: Roll / Defer | H70: 9 | I70: 0.02 | K70: 9 | L70: 0.02 | N70: 9 | O70: 0.02 | AB70: This needs a bit of love
C71: hint: optimum roll & defer | H71: 9m / 0.56% | K71: 9m / 0.56% | N71: 9m / 0.56% | S71: Tier rationale? | AB71: ="Product Selected from the '"&G52&"' section, tier "&$G$54 -> Product Selected from the 'Basic Loan' section, tier 1) Standard BTL
AB72: Summary of Terms - Indicative Illustration
H73: 6% fee range | K73: 4% fee range | N73: Core 2% fee
C74: Full Rate | H74: =[0]!Tier_Standard_rate -> #N/A | I74: =TEXT([0]!Tier_Standard_rate-'Product Data'!E3,"0.00%")&"+ BBR" -> #N/A | K74: 0.085 | L74: (BBR+3.25%) | N74: 0.096 | O74: (BBR+4.35%) | AC74: £ Gross Loan | AD74: ='BTL Calculator WIP'!M136 -> #N/A | AG74: Amount repayable at redemption
C75: Pay Rate | H75: =#REF! -> #REF! | I75: =TEXT(#REF!-'Product Data'!E3,"0.00%")&"+ BBR" -> #REF! | K75: =K74-L70 -> 0.065 | L75: BBR + xx | N75: =N74-O70 -> 0.076 | O75: BBR + xx | AB75: Gross Loan LTV | AD75: =TEXT('KB_CRITERIA AND CALCULATION '!AN90,"#%")&" LTV (on estimated valuation of "&TEXT(Property_Value,"£#,#")&")" -> #N/A
AB76: Total loan term | AD76: =Funders!L2 -> 3 years, made up of an initial fixed rate for 2 years, then followed by a variable tracker rate for the remaining term (also known as a 'revert' or 'reversion rate')
C77: Max Gross Loan | H77: =[0]!MaxGrossLoan -> 0 | K77: 865782.49 | L77: @ 64.1% LTV | N77: 751727.31 | O77: @ 55.7% LTV
C78: Max Net Loan | H78: =[0]!MaxNetLoan -> #N/A | I78: @ 64% LTV | K78: 754313 | L78: @ 56% LTV | N78: 663775.22 | O78: @ 49% LTV | AB78: Tier Anticipated | AD78: =G54 -> 1) Standard BTL
AB79: Annual Interest Rate | AD79: ="For the first "&('KB_CRITERIA AND CALCULATION '!D24/12)&" years, a "&IF(Rate_Type="tracker","variable rate made up of the Bank of England Base rate (BBR) as that rate varies, currently "&TEXT('Product Data'!E3,"0.00%")&", plus a set margin of "&TEXT(INDEX('KB_CRITERIA AND CALCULATION '!H76:H78,MATCH('BTL Calculator WIP'!G54,'KB_CRITERIA AND CALCULATION '!F76:F78,0))-'Product Data'!E3,"#.00%")&", giving a current rate payable of "&TEXT(AG54, "#.00%")&". Following any change to BBR, your mortgage rate and monthly payment will be adjusted on the 1st day of the next calendar month. "&(Term/12)&" years from the date of completion the set margin will change to "&TEXT(INDEX('Product Data'!I:I,MATCH('BTL Calculator WIP'!G54,'Product Data'!B:B,0)),"#.00%")&" above BBR for the remaining 1 year.", "fixed rate of "&TEXT('BTL Calculator WIP'!M134, "#.00%")&", followed by "&(3-('KB_CRITERIA AND CALCULATION '!D24/12))&" year at a variable rate made up of the Bank of England Base Rate (BBR) as that rate varies, currently "&TEXT('Product Data'!E3, "#.00%")&", plus a set margin of "&TEXT(INDEX('Product Data'!I:I,MATCH('BTL Calculator WIP'!G54,'Product Data'!B:B,0)),"#.00%")&", giving a current rate payable of "&TEXT((INDEX('Product Data'!I:I,MATCH('BTL Calculator WIP'!G54,'Product Data'!B:B,0)))+'Product Data'!E3, "#.00%")&". Following any change to BBR whilst on the variable revert rate, your mortgage rate and monthly payment will be adjusted on the 1st day of the next calendar month.") -> #N/A
C80: Rolled months £ | H80: 41427.692 | I80: -1538.9057 | K80: 42206.897 | L80: -759.70146 | N80: 42848.457
C81: Defer Int £ | H81: 40172.308 | I81: 10943.329 | K81: 34631.3 | L81: 5402.3215 | N81: 30069.093
C83: Initial Pay rate ICR | H83: 1.4772727 | I83: 0.052910482 | K83: 1.45 | L83: 0.025637755 | N83: 1.4282895 | O83: 0.0039272288
AB84: APRC | AD84: =APR -> -
C85: Product Fee | H85: 0.06 | K85: 0.04 | N85: 0.02 | AB85: Admin Fee | AD85: £199 (Per property) | AG85: Payable when DIP signed (i.e. applying)
C86: Standard Fee (Max 2%) | H86: 20086.154 | I86: 6202.3892 | K86: 17315.65 | L86: 3431.8852 | N86: 15034.546 | O86: 1150.7816 | AB86: Valuation Fee | AD86: TBC by Underwriter | AG86: Payable when DIP signed (i.e. applying)
C87: Enhanced Fee (> 2%) | H87: 40172.308 | I87: 26288.543 | K87: 17315.65 | L87: 3431.8852 | N87: n/a | AB87: Lender Legal Fees | AD87: TBC by Underwriter | AG87: (excludes borrowers own legal costs)
C88: Total Product Fee | H88: 60258.462 | I88: 46374.697 | K88: 60258.462 | L88: 46374.697 | N88: 60258.462 | O88: 46374.697 | AB88: Product Fee | AD88: ='KB_CRITERIA AND CALCULATION '!AK90&IF(Existing_Customer="Yes",". 0.15% existing customer discount applied.","")&"." -> #N/A
AB89: Optional Broker Fee | AD89: =TEXT(K38+K37*AJ52,"£#,##0") -> #N/A | AF89: =IF(AD89="£0","","Deducted from advance by solicitor at completion") -> #N/A
C90: Total Interest Due In 24m | H90: 150646.15 | I90: 6839.5809 | K90: 147183.02 | L90: 3376.4509 | N90: 144331.64 | O90: 525.07147 | AB90: Early Repayment Charge | AD90: ='Product Data'!AO9&'Product Data'!AO10&" "&'Product Data'!AO11&'Product Data'!AO12&" Final month is ERC free " -> #N/A
C91: Remaining Serviced Int | H91: 69046.154 | I91: -2564.8428 | K91: 70344.828 | L91: -1266.1691 | N91: 71414.095 | O91: -196.9018 | AB91: Gross Broker Commission | AD91: =IF('KB_CRITERIA AND CALCULATION '!D28=0,"n/a",TEXT('KB_CRITERIA AND CALCULATION '!D28,"0.00%")&" ("&TEXT('KB_CRITERIA AND CALCULATION '!F28,"£#,#")&")") -> n/a
AB92: Deferred Interest? | AD92: =IF(DeferedIntPercent=0%,"No","Yes, "&TEXT(DeferedIntPercent,"0.#0%")&". ICR based on "&TEXT('BTL Calculator WIP'!$M$138,"0.#0%")&". "&TEXT('BTL Calculator WIP'!$M$140,"£#,#0")&" payable at redemption") -> #N/A
C93: NPB (Net Loan + max 2% fee) | H93: 882535.38 | I93: @ 65% LTV | K93: 771628.65 | L93: @ 57% LTV | N93: 678809.77 | O93: @ 50% LTV | AB93: Monthly Interest Roll Up? | AD93: =IF(RollupMonths=0,"No - interest paid by monthly DD","Yes, "&TEXT(RollupMonths,"#")&" month(s). "&TEXT('BTL Calculator WIP'!$M$141,"£#,#")&" equivalent payable at redemption") -> #N/A
H94: 224006.5 | I94: P.Fee cap @ 2% | K94: 113099.77 | L94: P.Fee cap @ 2% | N94: 20280.885 | AB94: Top Slicing Used? | AD94: =IF(Top_Slice_PCM_GBP<>0,"Yes, "&TEXT(Top_Slice_PCM_GBP,"£#,#0")&" pcm of surplus income/wealth/rent","No") -> No
AB95: ICR Used | AD95: ='KB_CRITERIA AND CALCULATION '!$W$90 -> -
C96: Monthly DD | H96: £4603 from month x | I96: -170.98952 | K96: £4603 from month x | N96: £4603 from month x | AB96: Direct Debit | AD96: ="Direct Debit of "&TEXT(Monthly_DD,"£#,#.00")&" will start in month "&TEXT((RollupMonths-IF(AN29="Yes",RollupMonths,0))+1,"#") -> #N/A
C97: Total Cost to Borrower | H97: Gross + Serviced | K97: Gross + Serviced | N97: Gross + Serviced | AD97: =IF($K$23="Tracker"," (If BBR were to increase by "&TEXT('KB_CRITERIA AND CALCULATION '!$U$73,"#0.#0%")&" monthly payments would increase to "&TEXT('KB_CRITERIA AND CALCULATION '!$U$90,"£#,#.00")&")","") -> (If BBR were to increase by 0.50% monthly payments would increase to )
AB98: Net Loan Advance | AD98: =NetLoanUsed -> #N/A | AJ98: =IF(OR('KB_CRITERIA AND CALCULATION '!AD90>0,'KB_CRITERIA AND CALCULATION '!AE90>0),"<-- Net Loan Advance reduced by deferred/ rolled interest £total. Ensures equity remains in the property to protect borrower & lender","") -> #N/A
C99: Revert Rate | H99: 0.0899 | I99: MVR | K99: 0.0899 | L99: MVR | N99: 0.0924 | O99: (BBR+3.99%) | AB99: Total Amount Payable | AD99: =IFERROR(Gross_Loan+'BTL Calculator WIP'!M145,0) -> 0 | AM99: ="Max Loan "&TEXT(MaxGrossLoan/1000000,"£0.00")&"m minus deferred interest of "&TEXT(Deferred_Int_Owed,"£0,0") -> #N/A
AB100: ="Tier Adverse limit: "&INDEX(('Product Data'!L9:L12),MATCH(AD78,'Product Data'!B9:B12,0)) -> Tier Adverse limit: Clean - Missed Mortgage Payments - 0 missed in last 48 months Unsecured Card/Loan Payments (ignore when balance < £500) - 0 missed in last 48m CCJs & Defaults (ignore <= £350, telecom, utility) - 0 in last 48m. No unsatisfied Bankruptcy/IVA - Never
AM101: =IF(AND(K27>0,K27<>"",ISERROR(SEARCH("Bespoke",G54))),"Caution: rate override normally only on Bespoke tier","")
AB102: Please note: indicative only, subject to full underwrite, valuation, credit report and other supporting evidence
AB103: This Document is confidential to the intended recipient. If you are not the intended recipient, do not use, copy or disclose the information in any way or act in reliance on it, and notify the sender immediately, then delete it from your system. Market Financial Solutions Ltd accepts no liability (to the fullest extent permitted by law) for opinions, conclusions and other information in this message which do not relate to its official business. No contracts or official orders will be confirmed by means of this document.
AC108: Investor Requested Funds: | AE108: ='BTL Calculator WIP'!M149 -> #N/A | AG108: ="Investor Funds LTV "&TEXT(AE108/Property_Value,"00%") -> #N/A
AC109: Product Fee: | AE109: ='BTL Calculator WIP'!M150 -> #N/A
AC110: Net Loan: | AE110: ='BTL Calculator WIP'!M151 -> #N/A | AG110: ="=Investor Funds "&TEXT(AE108,"£0,0")&" less Product Fee "&TEXT(AE109,"£0,0") -> #N/A
AA111: ='KB_CRITERIA AND CALCULATION '!$L$2 -> Available Funding lines are: Zircon or Pearl
AA112: ='KB_CRITERIA AND CALCULATION '!$L$3 -> #N/A
A114: Other outputs - FYI
D115: Waterfall Graph - Gross & Net Loan Summary
AB118: Gross loan | AC118: =Gross_Loan -> #N/A
AB119: Prod fee | AC119: =-'KB_CRITERIA AND CALCULATION '!$AH$90 -> #N/A
...

Sheet HomePage (2)
A1: MFS Underwriter Loan Hub - Main Menu

Sheet HomePage
B2: MFS Underwriter Loan Hub - Main Menu
A15: All links
A17: Hidden sheets | D17: Underwriters | G17: Loan Management
A18: Link | B18: Info | D18: Link | E18: Info | G18: Link | I18: Info
A19: HPI | B19: inputs for Forecast property data | D19: ICR Main calculator | E19: Main Loan info/ calculations for max loan & Tier | G19: Deal lead sheet | I19: All info for the loan
A20: Data | B20: Drop downs /inputs for calcs | D20: DIP | E20: Decision in Principle template | G20: Ext Sheets | I20: Outputs for other sheets
A21: Calcs | B21: calculations | D21: Bespoke Tier Calc | E21: which tier is best | G21: DD | I21: Direct Debit Schedule
A22: Loan Data | B22: Loan information where the hubspot info is pulled into. | D22: Holiday Let | E22: Holiday Let calculator | G22: Checklist Before deal complete | I22: Checklist Before deal complete
A23: HubSpot | B23: Hubspot export | G23: Checklist After deal complete | I23: Checklist After deal complete
G24: Completion statement | I24: Completion statement
G25: funding lines | I25: funding lines
G26: Compliance Checklists | I26: Compliance Checklists
G27: Audit Sheet | I27: Audit Sheet

Sheet ROX WORKINGS
B2: Hidden sheets | C2: Conditional Formatting | D2: Data Validation
B3: HPI | C3: N | D3: N | E3: NEW FIGURES TO BE ADDED
B4: Data | C4: N | D4: N | E4: TO LOOK THROUGH
B5: Calcs | C5: N | D5: N | E5: SORTED
B6: Loan Data | C6: N | D6: Y
B7: HubSpot | C7: N | D7: N | E7: TO LOOK THROUGH
B8: Underwriters | E8: TO LOOK THROUGH
B9: HOME PAGE | C9: N | D9: N | E9: TO LOOK THROUGH
B10: ICR Main calculator | C10: Y | D10: Y | E10: TO LOOK THROUGH
B11: DIP | C11: Y | D11: Y | E11: TO LOOK THROUGH
B12: Bespoke Tier Calc | C12: Y | D12: Y | E12: TO LOOK THROUGH
B13: Holiday Let | C13: N | D13: N | E13: TO LOOK THROUGH
B14: Loan Management | C14: N | D14: N | E14: TO LOOK THROUGH
B15: Deal lead sheet | C15: Y | D15: Y | E15: TO LOOK THROUGH
B16: Ext Sheets | C16: N | D16: N | E16: TO LOOK THROUGH
B17: DD | C17: Y | D17: N | E17: TO LOOK THROUGH
B18: Checklist Before deal complete | C18: Y | D18: Y | E18: TO LOOK THROUGH
B19: Checklist After deal complete | C19: Y | D19: Y | E19: TO LOOK THROUGH
B20: Completion statement | C20: Y | D20: Y | E20: TO LOOK THROUGH
... B23: Audit Sheet | C23: N | D23: Y | E23: TO LOOK THROUGH

Sheet HPI
J1: Future Forecasts for Case (Selected Region)
J2: 2021 | K2: 2022 | L2: 2023 | M2: 2024 | N2: 2025 | O2: 5yrs to 2025
A3: Property Value Used: | C3: =Property_Value -> 0 | E3: Front Front Sheet | I3: Predicted rental growth for region: | J3: =VLOOKUP(($C$7),HPI!$A$27:$G$36,2,FALSE) -> #N/A | K3: =VLOOKUP(($C$7),HPI!$A$27:$G$36,3,FALSE) -> #N/A | L3: =VLOOKUP(($C$7),HPI!$A$27:$G$36,4,FALSE) -> #N/A | M3: =VLOOKUP(($C$7),HPI!$A$27:$G$36,5,FALSE) -> #N/A | N3: =VLOOKUP(($C$7),HPI!$A$27:$G$36,6,FALSE) -> #N/A | O3: =VLOOKUP(($C$7),HPI!$A$27:$G$36,7,FALSE) -> #N/A | P3: =INDEX(B27:G36,MATCH($C$7,A27:A36,0),MATCH($J$2,B26:G26,0)) -> #N/A
A4: Gross Loan | C4: =Gross_Loan -> #N/A | I4: Predicted Value: | J4: =INDEX(HPI!$B$14:$B$23,MATCH($C$7,HPI!$A$14:$A$23,0)) -> #N/A | K4: =INDEX(HPI!$C$14:$C$23,MATCH($C$7,HPI!$A$14:$A$23,0)) -> #N/A | L4: =INDEX(HPI!$C$14:$C$23,MATCH($C$7,HPI!$A$14:$A$23,0)) -> #N/A | M4: =INDEX(HPI!$D$14:$D$23,MATCH($C$7,HPI!$A$14:$A$23,0)) -> #N/A | N4: =INDEX(HPI!$D$14:$D$23,MATCH($C$7,HPI!$A$14:$A$23,0)) -> #N/A | O4: =INDEX(HPI!$E$14:$E$23,MATCH($C$7,HPI!$A$14:$A$23,0)) -> #N/A
A5: Net Loan | C5: ='BTL Calculator'!M158 -> 0 | I5: Predicted LTV Net Loan: | J5: =$C$5/HPIAdjusted2021 -> #N/A | K5: =$C$5/HPIAdjusted2022 -> #N/A | L5: =$C$5/HPIAdjusted2023 -> #N/A | M5: =$C$5/HPIAdjusted2024 -> #N/A | N5: =$C$5/HPIAdjusted2025 -> #N/A | O5: =$C$5/HPIAdjusted5yrTotal -> #N/A
A6: Net Loan used | C6: =NetLoanUsed -> #N/A | I6: Predicted LTV Net Loan Used: | J6: =$C$6/HPIAdjusted2021 -> #N/A | K6: =$C$6/HPIAdjusted2022 -> #N/A | L6: =$C$6/HPIAdjusted2023 -> #N/A | M6: =$C$6/HPIAdjusted2024 -> #N/A | N6: =$C$6/HPIAdjusted2025 -> #N/A | O6: =$C$6/HPIAdjusted5yrTotal -> #N/A
A7: Region Selected | C7: ='KB_CRITERIA AND CALCULATION '!D21 -> 0 | I7: Predicted LTV Gross Loan: | J7: =$C$4/HPIAdjusted2021 -> #N/A | K7: =$C$4/HPIAdjusted2022 -> #N/A | L7: =$C$4/HPIAdjusted2023 -> #N/A | M7: =$C$4/HPIAdjusted2024 -> #N/A | N7: =$C$4/HPIAdjusted2025 -> #N/A | O7: =C4/HPIAdjusted5yrTotal -> #N/A
A8: Monthly Rent | C8: ='KB_CRITERIA AND CALCULATION '!U22 -> 0 | I8: Predicted rental growth for region: | J8: =VLOOKUP(($C$7),Future_Rent_TBL,2,FALSE) -> #N/A | K8: =VLOOKUP(($C$7),Future_Rent_TBL,3,FALSE) -> #N/A | L8: =VLOOKUP(($C$7),Future_Rent_TBL,4,FALSE) -> #N/A | M8: =VLOOKUP(($C$7),Future_Rent_TBL,5,FALSE) -> #N/A | N8: =VLOOKUP(($C$7),Future_Rent_TBL,6,FALSE) -> #N/A | O8: =VLOOKUP(($C$7),Future_Rent_TBL,7,FALSE) -> #N/A
A9: ICR used in calculations | C9: ='KB_CRITERIA AND CALCULATION '!$W$90 -> - | I9: Predicted Rental Value: | J9: =INDEX(Adjusted_House_Price_TBL2[2021],MATCH($C$7,Adjusted_House_Price_TBL2[Column1],0)) -> #N/A | K9: =INDEX(Adjusted_House_Price_TBL2[2022],MATCH($C$7,Adjusted_House_Price_TBL2[Column1],0)) -> #N/A | L9: =INDEX(Adjusted_House_Price_TBL2[2022],MATCH($C$7,Adjusted_House_Price_TBL2[Column1],0)) -> #N/A | M9: =INDEX(Adjusted_House_Price_TBL2[2023],MATCH($C$7,Adjusted_House_Price_TBL2[Column1],0)) -> #N/A | N9: =INDEX(Adjusted_House_Price_TBL2[2023],MATCH($C$7,Adjusted_House_Price_TBL2[Column1],0)) -> #N/A | O9: =INDEX(Adjusted_House_Price_TBL2[2024],MATCH($C$7,Adjusted_House_Price_TBL2[Column1],0)) -> #N/A
I10: Predicted Rent Change (Total ICR) | J10: ='KB_CRITERIA AND CALCULATION '!$W$90 -> - | K10: =J10*(100%+K$8) -> #VALUE! | L10: =K10*(100%+L$8) -> #VALUE! | M10: =L10*(100%+M$8) -> #VALUE! | N10: =M10*(100%+N$8) -> #VALUE! | O10: =N10*(100%+O$8) -> #VALUE!
A11: HPI Data | I11: RENT DATA
A12: Outputs: impact on inputted house price in future years | I12: Outputs: impact on estmated monthly rent in future years
A13: Column1 | B13: 2021 | C13: 2022 | D13: 2023 | E13: 2024 | F13: 2025 | G13: 5yrs to 2025 | I13: Column1 | J13: 2021 | K13: 2022 | L13: 2023 | M13: 2024 | N13: 2025 | O13: 5yrs to 2025
A14: London | B14: =$C$3 -> 0 | C14: =B14*(100%+C27) -> 0 | D14: =C14*(100%+D27) -> 0 | E14: =D14*(100%+E27) -> 0 | F14: =E14*(100%+F27) -> 0 | G14: =B14*(100%+G27) -> 0 | I14: London | J14: =$C$8 -> 0 | K14: =J14*(100%+K27) -> 0 | L14: =K14*(100%+L27) -> 0 | M14: =L14*(100%+M27) -> 0 | N14: =M14*(100%+N27) -> 0 | O14: =J14*(100%+O27) -> 0
A15: South East | B15: =$C$3 -> 0 | C15: =B15*(100%+C28) -> 0 | D15: =C15*(100%+D28) -> 0 | E15: =D15*(100%+E28) -> 0 | F15: =E15*(100%+F28) -> 0 | G15: =B15*(100%+G28) -> 0 | I15: South East | J15: =$C$8 -> 0 | K15: =J15*(100%+K28) -> 0 | L15: =K15*(100%+L28) -> 0 | M15: =L15*(100%+M28) -> 0 | N15: =M15*(100%+N28) -> 0 | O15: =J15*(100%+O28) -> 0
A16: East | B16: =$C$3 -> 0 | C16: =B16*(100%+C29) -> 0 | D16: =C16*(100%+D29) -> 0 | E16: =D16*(100%+E29) -> 0 | F16: =E16*(100%+F29) -> 0 | G16: =B16*(100%+G29) -> 0 | I16: East | J16: =$C$8 -> 0 | K16: =J16*(100%+K29) -> 0 | L16: =K16*(100%+L29) -> 0 | M16: =L16*(100%+M29) -> 0 | N16: =M16*(100%+N29) -> 0 | O16: =J16*(100%+O29) -> 0
A17: South West | B17: =$C$3 -> 0 | C17: =B17*(100%+C30) -> 0 | D17: =C17*(100%+D30) -> 0 | E17: =D17*(100%+E30) -> 0 | F17: =E17*(100%+F30) -> 0 | G17: =B17*(100%+G30) -> 0 | I17: South West | J17: =$C$8 -> 0 | K17: =J17*(100%+K30) -> 0 | L17: =K17*(100%+L30) -> 0 | M17: =L17*(100%+M30) -> 0 | N17: =M17*(100%+N30) -> 0 | O17: =J17*(100%+O30) -> 0
A18: East Midlands | B18: =$C$3 -> 0 | C18: =B18*(100%+C31) -> 0 | D18: =C18*(100%+D31) -> 0 | E18: =D18*(100%+E31) -> 0 | F18: =E18*(100%+F31) -> 0 | G18: =B18*(100%+G31) -> 0 | I18: East Midlands | J18: =$C$8 -> 0 | K18: =J18*(100%+K31) -> 0 | L18: =K18*(100%+L31) -> 0 | M18: =L18*(100%+M31) -> 0 | N18: =M18*(100%+N31) -> 0 | O18: =J18*(100%+O31) -> 0
A19: West Midlands | B19: =$C$3 -> 0 | C19: =B19*(100%+C32) -> 0 | D19: =C19*(100%+D32) -> 0 | E19: =D19*(100%+E32) -> 0 | F19: =E19*(100%+F32) -> 0 | G19: =B19*(100%+G32) -> 0 | I19: West Midlands | J19: =$C$8 -> 0 | K19: =J19*(100%+K32) -> 0 | L19: =K19*(100%+L32) -> 0 | M19: =L19*(100%+M32) -> 0 | N19: =M19*(100%+N32) -> 0 | O19: =J19*(100%+O32) -> 0
A20: North East | B20: =$C$3 -> 0 | C20: =B20*(100%+C33) -> 0 | D20: =C20*(100%+D33) -> 0 | E20: =D20*(100%+E33) -> 0 | F20: =E20*(100%+F33) -> 0 | G20: =B20*(100%+G33) -> 0 | I20: North East | J20: =$C$8 -> 0 | K20: =J20*(100%+K33) -> 0 | L20: =K20*(100%+L33) -> 0 | M20: =L20*(100%+M33) -> 0 | N20: =M20*(100%+N33) -> 0 | O20: =J20*(100%+O33) -> 0
A21: Yorks & Humber | B21: =$C$3 -> 0 | C21: =B21*(100%+C34) -> 0 | D21: =C21*(100%+D34) -> 0 | E21: =D21*(100%+E34) -> 0 | F21: =E21*(100%+F34) -> 0 | G21: =B21*(100%+G34) -> 0 | I21: Yorks & Humber | J21: =$C$8 -> 0 | K21: =J21*(100%+K34) -> 0 | L21: =K21*(100%+L34) -> 0 | M21: =L21*(100%+M34) -> 0 | N21: =M21*(100%+N34) -> 0 | O21: =J21*(100%+O34) -> 0
A22: North West | B22: =$C$3 -> 0 | C22: =B22*(100%+C35) -> 0 | D22: =C22*(100%+D35) -> 0 | E22: =D22*(100%+E35) -> 0 | F22: =E22*(100%+F35) -> 0 | G22: =B22*(100%+G35) -> 0 | I22: North West | J22: =$C$8 -> 0 | K22: =J22*(100%+K35) -> 0 | L22: =K22*(100%+L35) -> 0 | M22: =L22*(100%+M35) -> 0 | N22: =M22*(100%+N35) -> 0 | O22: =J22*(100%+O35) -> 0
A23: Wales | B23: =$C$3 -> 0 | C23: =B23*(100%+C36) -> 0 | D23: =C23*(100%+D36) -> 0 | E23: =D23*(100%+E36) -> 0 | F23: =E23*(100%+F36) -> 0 | G23: =B23*(100%+G36) -> 0 | I23: Wales | J23: =$C$8 -> 0 | K23: =J23*(100%+K36) -> 0 | L23: =K23*(100%+L36) -> 0 | M23: =L23*(100%+M36) -> 0 | N23: =M23*(100%+N36) -> 0 | O23: =J23*(100%+O36) -> 0
A25: Source Taken: | I25: Source Data: Savills Forecast Rent Changes Feb 2021 - CAPPED TO: | O25: 0.02
A26: Column1 | B26: 2021 | C26: 2022 | D26: 2023 | E26: 2024 | F26: 2025 | G26: 5yrs to 2025 | I26: Column1 | J26: 2021 | K26: 2022 | L26: 2023 | M26: 2024 | N26: 2025 | O26: 5yrs to 2025
A27: London | B27: 0.07 | C27: 0.02 | D27: 0.015 | E27: 0.01 | F27: 0.005 | G27: 0.124 | I27: London | J27: =MIN(J41,$O$25) -> 0.015 | K27: =MIN(K41,$O$25) -> 0.02 | L27: =MIN(L41,$O$25) -> 0.02 | M27: =MIN(M41,$O$25) -> 0.02 | N27: =MIN(N41,$O$25) -> 0.02 | O27: 0.193
A28: South East | B28: 0.09 | C28: 0.03 | D28: 0.025 | E28: 0.02 | F28: 0.015 | G28: 0.191 | I28: Outside London | J28: =MIN(J42,$O$25) -> 0.005 | K28: =MIN(K42,$O$25) -> 0.02 | L28: =MIN(L42,$O$25) -> 0.02 | M28: =MIN(M42,$O$25) -> 0.02 | N28: =MIN(N42,$O$25) -> 0.02 | O28: 0.159
A29: East | B29: 0.08 | C29: 0.03 | D29: 0.025 | E29: 0.02 | F29: 0.015 | G29: 0.18 | I29: South East | J29: =MIN(J43,$O$25) -> 0.005 | K29: =MIN(K43,$O$25) -> 0.02 | L29: =MIN(L43,$O$25) -> 0.02 | M29: =MIN(M43,$O$25) -> 0.02 | N29: =MIN(N43,$O$25) -> 0.02 | O29: =$O$28 -> 0.159
A30: South West | B30: 0.085 | C30: 0.035 | D30: 0.03 | E30: 0.025 | F30: 0.02 | G30: 0.209 | I30: East | J30: =MIN(J44,$O$25) -> 0.005 | K30: =MIN(K44,$O$25) -> 0.02 | L30: =MIN(L44,$O$25) -> 0.02 | M30: =MIN(M44,$O$25) -> 0.02 | N30: =MIN(N44,$O$25) -> 0.02 | O30: =$O$28 -> 0.159
A31: East Midlands | B31: 0.09 | C31: 0.04 | D31: 0.035 | E31: 0.03 | F31: 0.025 | G31: 0.239 | I31: South West | J31: =MIN(J45,$O$25) -> 0.005 | K31: =MIN(K45,$O$25) -> 0.02 | L31: =MIN(L45,$O$25) -> 0.02 | M31: =MIN(M45,$O$25) -> 0.02 | N31: =MIN(N45,$O$25) -> 0.02 | O31: =$O$28 -> 0.159
A32: West Midlands | B32: 0.09 | C32: 0.04 | D32: 0.035 | E32: 0.03 | F32: 0.025 | G32: 0.239 | I32: East Midlands | J32: =MIN(J46,$O$25) -> 0.005 | K32: =MIN(K46,$O$25) -> 0.02 | L32: =MIN(L46,$O$25) -> 0.02 | M32: =MIN(M46,$O$25) -> 0.02 | N32: =MIN(N46,$O$25) -> 0.02 | O32: =$O$28 -> 0.159
A33: North East | B33: 0.08 | C33: 0.04 | D33: 0.035 | E33: 0.035 | F33: 0.03 | G33: 0.239 | I33: West Midlands | J33: =MIN(J47,$O$25) -> 0.005 | K33: =MIN(K47,$O$25) -> 0.02 | L33: =MIN(L47,$O$25) -> 0.02 | M33: =MIN(M47,$O$25) -> 0.02 | N33: =MIN(N47,$O$25) -> 0.02 | O33: =$O$28 -> 0.159
A34: Yorks & Humber | B34: 0.105 | C34: 0.045 | D34: 0.04 | E34: 0.035 | F34: 0.03 | G34: 0.28 | I34: North East | J34: =MIN(J48,$O$25) -> 0.005 | K34: =MIN(K48,$O$25) -> 0.02 | L34: =MIN(L48,$O$25) -> 0.02 | M34: =MIN(M48,$O$25) -> 0.02 | N34: =MIN(N48,$O$25) -> 0.02 | O34: =$O$28 -> 0.159
A35: North West | B35: 0.105 | C35: 0.045 | D35: 0.04 | E35: 0.035 | F35: 0.03 | G35: 0.28 | I35: Yorks & Humber | J35: =MIN(J49,$O$25) -> 0.005 | K35: =MIN(K49,$O$25) -> 0.02 | L35: =MIN(L49,$O$25) -> 0.02 | M35: =MIN(M49,$O$25) -> 0.02 | N35: =MIN(N49,$O$25) -> 0.02 | O35: =$O$28 -> 0.159
A36: Wales | B36: 0.1 | C36: 0.04 | D36: 0.04 | E36: 0.035 | F36: 0.03 | G36: 0.268 | I36: North West | J36: =MIN(J50,$O$25) -> 0.005 | K36: =MIN(K50,$O$25) -> 0.02 | L36: =MIN(L50,$O$25) -> 0.02 | M36: =MIN(M50,$O$25) -> 0.02 | N36: =MIN(N50,$O$25) -> 0.02 | O36: =$O$28 -> 0.159
I37: Wales | J37: =MIN(J51,$O$25) -> 0.005 | K37: =MIN(K51,$O$25) -> 0.02 | L37: =MIN(L51,$O$25) -> 0.02 | M37: =MIN(M51,$O$25) -> 0.02 | N37: =MIN(N51,$O$25) -> 0.02 | O37: =$O$28 -> 0.159
A39: Source Data: Savills Forecast HPI Changes August 2021 | I39: Source Data: Savills Forecast Rent Changes Feb 2021
A40: Column1 | B40: 2021 | C40: 2022 | D40: 2023 | E40: 2024 | F40: 2025 | G40: 5yrs to 2025 | I40: Column1 | J40: 2021 | K40: 2022 | L40: 2023 | M40: 2024 | N40: 2025 | O40: 5yrs to 2025
A41: London | B41: 0.07 | C41: 0.02 | D41: 0.015 | E41: 0.01 | F41: 0.005 | G41: 0.124 | I41: London | J41: 0.015 | K41: 0.055 | L41: 0.04 | M41: 0.035 | N41: 0.035 | O41: 0.193
A42: South East | B42: 0.09 | C42: 0.03 | D42: 0.025 | E42: 0.02 | F42: 0.015 | G42: 0.191 | I42: Outside London | J42: 0.005 | K42: 0.04 | L42: 0.035 | M42: 0.035 | N42: 0.035 | O42: 0.159
A43: East | B43: 0.08 | C43: 0.03 | D43: 0.025 | E43: 0.02 | F43: 0.015 | G43: 0.18 | I43: South East | J43: 0.005 | K43: 0.04 | L43: 0.035 | M43: 0.035 | N43: 0.035 | O43: 0.159
A44: South West | B44: 0.085 | C44: 0.035 | D44: 0.03 | E44: 0.025 | F44: 0.02 | G44: 0.209 | I44: East | J44: 0.005 | K44: 0.04 | L44: 0.035 | M44: 0.035 | N44: 0.035 | O44: 0.159
A45: East Midlands | B45: 0.09 | C45: 0.04 | D45: 0.035 | E45: 0.03 | F45: 0.025 | G45: 0.239 | I45: South West | J45: 0.005 | K45: 0.04 | L45: 0.035 | M45: 0.035 | N45: 0.035 | O45: 0.159
A46: West Midlands | B46: 0.09 | C46: 0.04 | D46: 0.035 | E46: 0.03 | F46: 0.025 | G46: 0.239 | I46: East Midlands | J46: 0.005 | K46: 0.04 | L46: 0.035 | M46: 0.035 | N46: 0.035 | O46: 0.159
A47: North East | B47: 0.08 | C47: 0.04 | D47: 0.035 | E47: 0.035 | F47: 0.03 | G47: 0.239 | I47: West Midlands | J47: 0.005 | K47: 0.04 | L47: 0.035 | M47: 0.035 | N47: 0.035 | O47: 0.159
A48: Yorks & Humber | B48: 0.105 | C48: 0.045 | D48: 0.04 | E48: 0.035 | F48: 0.03 | G48: 0.28 | I48: North East | J48: 0.005 | K48: 0.04 | L48: 0.035 | M48: 0.035 | N48: 0.035 | O48: 0.159
A49: North West | B49: 0.105 | C49: 0.045 | D49: 0.04 | E49: 0.035 | F49: 0.03 | G49: 0.28 | I49: Yorks & Humber | J49: 0.005 | K49: 0.04 | L49: 0.035 | M49: 0.035 | N49: 0.035 | O49: 0.159
A50: Wales | B50: 0.1 | C50: 0.04 | D50: 0.04 | E50: 0.035 | F50: 0.03 | G50: 0.268 | I50: North West | J50: 0.005 | K50: 0.04 | L50: 0.035 | M50: 0.035 | N50: 0.035 | O50: 0.159
I51: Wales | J51: 0.005 | K51: 0.04 | L51: 0.035 | M51: 0.035 | N51: 0.035 | O51: 0.159
A53: Source Data: Savills Forecast HPI Changes August 2021
A54: Column1 | B54: 2021 | C54: 2022 | D54: 2023 | E54: 2024 | F54: 2025 | G54: 5yrs to 2025
A55: London | B55: 0.07 | C55: 0.02 | D55: 0.015 | E55: 0.01 | F55: 0.005 | G55: 0.124
A56: South East | B56: 0.09 | C56: 0.03 | D56: 0.025 | E56: 0.02 | F56: 0.015 | G56: 0.191
A57: East | B57: 0.08 | C57: 0.03 | D57: 0.025 | E57: 0.02 | F57: 0.015 | G57: 0.18
A58: South West | B58: 0.085 | C58: 0.035 | D58: 0.03 | E58: 0.025 | F58: 0.02 | G58: 0.209
A59: East Midlands | B59: 0.09 | C59: 0.04 | D59: 0.035 | E59: 0.03 | F59: 0.025 | G59: 0.239
A60: West Midlands | B60: 0.09 | C60: 0.04 | D60: 0.035 | E60: 0.03 | F60: 0.025 | G60: 0.239
A61: North East | B61: 0.08 | C61: 0.04 | D61: 0.035 | E61: 0.035 | F61: 0.03 | G61: 0.239
A62: Yorks & Humber | B62: 0.105 | C62: 0.045 | D62: 0.04 | E62: 0.035 | F62: 0.03 | G62: 0.28 | Y62: HPI Sources
A63: North West | B63: 0.105 | C63: 0.045 | D63: 0.04 | E63: 0.035 | F63: 0.03 | G63: 0.28
A64: Wales | B64: 0.1 | C64: 0.04 | D64: 0.04 | E64: 0.035 | F64: 0.03 | G64: 0.268

Sheet Fusion Calc
B3: BBR | C3: 0.04
A4: Standard | B4: Rate | C4: Rate with BBR | D4: Product Fee | E4: Monthly Interest rate | F4: Pay rate | G4: Revert rate | H4: LTV | I4: Max Loan | J4: Min Loan | K4: Max Loan for Property | L4: Max Gross Loan Capped | M4: Max Gross Loan | N4: Max Net Loan | O4: Rolled Month Interest | P4: Rent with Top Slicing | Q4: Defer Int £ | R4: Serviced Interest | S4: Initial Pay rate ICR | T4: Stressed ICR | U4: Product Fee | V4: Total Payrate Interest | W4: Actual ICR | X4: Total Product Fee | Y4: NPB Net Loan + max 2% fee | Z4: Monthly DD | AA4: Cost of Borrowing | AB4: Monthy Interest Cost | AC4: Revert Rate | AD4: Revert Period DD & ICR
A5: Residentials | B5: 0.0479 | C5: =SUM($C$3,B5) -> 0.0879 | D5: 0.02 | E5: =C5/12 -> 0.007325 | F5: 0.007325 | H5: 0.75 | I5: 3000000 | J5: 100000 | K5: =MIN(H5*Property_Value,I5) -> 0 | L5: =ROUND(MIN(M5,K5),0) -> 0 | M5: =P5/(F5*(24-'BTL Calculator'!$R$81)*'Fusion Calc'!S5) -> 0 | N5: =L5-U5-Q5-O5 -> 0 | O5: =L5*'BTL Calculator'!$R$81*(F5) -> 0 | P5: =('BTL Calculator'!$V$9+'BTL Calculator'!$R$80)*24 -> 0 | Q5: =(L5*'BTL Calculator'!$S$81/12)*24 -> 0 | R5: =L5*C5*(24-'BTL Calculator'!$R$81)/12 -> 0 | S5: 1.1 | T5: NA | U5: =L5*D5 -> 0 | V5: =M5*F5*24 -> 0 | W5: =P5/(((F5*12)*L5*2)-O5) -> #DIV/0!
A6: Semi and Comm | B6: 0.0529 | C6: =SUM($C$3,B6) -> 0.0929 | D6: 0.02 | E6: =C6/12 -> 0.0077416667 | F6: 0.0077416667 | H6: 0.7 | I6: 3000000 | J6: 100000 | K6: =MIN(H6*Property_Value,I6) -> 0 | L6: =MIN(M6,K6) -> 0 | M6: =P6/(F6*(24-'BTL Calculator'!$R$81)*'Fusion Calc'!S6) -> 0 | N6: =L6-U6-Q6-O6 -> 0 | O6: =L6*'BTL Calculator'!$R$81*(F6) -> 0 | P6: =('BTL Calculator'!$V$9+'BTL Calculator'!$R$80)*24 -> 0 | Q6: =(L6*'BTL Calculator'!$S$81/12)*24 -> 0 | R6: =L6*C6*(24-'BTL Calculator'!$R$81)/12 -> 0 | S6: 1.1 | T6: NA | U6: =L6*D6 -> 0 | V6: =M6*F6*24 -> 0 | W6: =P6/(((F6*12)*L6*2)-O6) -> #DIV/0!
A8: Large Loans | B8: Rate | C8: Rate with BBR | D8: Product Fee | G8: Revert Rate | H8: LTV | I8: Max Loan | J8: Min Loan
A9: Residentials | B9: 0.0599 | C9: =SUM($C$3,B9) -> 0.0999 | D9: 0.02 | E9: =C9/12 -> 0.008325 | F9: 0.008325 | H9: 0.75 | I9: 20000000 | J9: 3000000 | K9: =MIN(H9*Property_Value,I9) -> 0 | L9: =MIN(M9,K9) -> 0 | M9: =P9/(F9*(24-'BTL Calculator'!$R$81)*'Fusion Calc'!S9) -> 0 | N9: =L9-U9-Q9-O9 -> 0 | O9: =L9*'BTL Calculator'!$R$81*(F9) -> 0 | P9: =('BTL Calculator'!$V$9+'BTL Calculator'!$R$80)*24 -> 0 | Q9: =(L9*'BTL Calculator'!$S$81/12)*24 -> 0 | R9: =L9*C9*(24-'BTL Calculator'!$R$81)/12 -> 0 | S9: 1.1 | T9: NA | U9: =L9*D9 -> 0 | V9: =M9*F9*24 -> 0 | W9: =P9/(((F9*12)*L9*2)-O9) -> #DIV/0!
A10: Semi and Comm | B10: 0.0649 | C10: =SUM($C$3,B10) -> 0.1049 | D10: 0.02 | E10: =C10/12 -> 0.0087416667 | F10: 0.0087416667 | H10: 0.7 | I10: 20000000 | J10: 3000000 | K10: =MIN(H10*Property_Value,I10) -> 0 | L10: =MIN(M10,K10) -> 0 | M10: =P10/(F10*(24-'BTL Calculator'!$R$81)*'Fusion Calc'!S10) -> 0 | N10: =L10-U10-Q10-O10 -> 0 | O10: =L10*'BTL Calculator'!$R$81*(F10) -> 0 | P10: =('BTL Calculator'!$V$9+'BTL Calculator'!$R$80)*24 -> 0 | Q10: =(L10*'BTL Calculator'!$S$81/12)*24 -> 0 | R10: =L10*C10*(24-'BTL Calculator'!$R$81)/12 -> 0 | S10: 1.1 | T10: NA | U10: =L10*D10 -> 0 | V10: =M10*F10*24 -> 0 | W10: =P10/(((F10*12)*L10*2)-O10) -> #DIV/0!

Sheet KB_CRITERIA AND CALCULATION 
B1: Funding Lines
D2: Loan Chosen | E2: Zircon Limit | H2: Pearl Limit | K2: =_xlfn.TEXTJOIN(" or ",TRUE,F3,I3) -> Zircon or Pearl | L2: =IF(K2="","No Funding lines available","Available Funding lines are: "&K2) -> Available Funding lines are: Zircon or Pearl | M2: Notes
E3: Zircon | F3: =IF(COUNTIF(F4:F12,0)=0,E3,"") -> Zircon | G3: =IF(_xlfn.TEXTJOIN(", ",TRUE,G4:G12)="","",E3&" not available due to - "&_xlfn.TEXTJOIN(", ",TRUE,G4:G12)) -> #N/A | H3: Pearl | I3: =IF(COUNTIF(I4:I12,0)=0,H3,"") -> Pearl | J3: =IF(_xlfn.TEXTJOIN(", ",TRUE,J4:J12)="","",H3&" not available due to - "&_xlfn.TEXTJOIN(", ",TRUE,J4:J12)) -> #N/A | K3: =_xlfn.TEXTJOIN(" ",TRUE,G3,J3) -> #N/A | L3: =IF(K3="","",IF(L2="",""," ")&K3) -> #N/A
C4: deferred interest | D4: =J90 -> #N/A | E4: 0.01 | F4: =IF($D4>E4,0,1) -> #N/A | G4: =IF(F4=0,"Deferred Interest too High","") -> #N/A | H4: ='Product Data'!$P$9 -> 0.02 | I4: =IF($D4>H4,0,1) -> #N/A | J4: =IF(I4=0,"Deferred Interest too High","") -> #N/A | M4: IF deferred interest > 1%, only PBL YES | V4: PBL terms are:
C5: Rolled Months | D5: =K90 -> #N/A | E5: 6 | F5: =IF($D5>E5,0,1) -> #N/A | G5: =IF(F5=0,"Rolled Months too High","") -> #N/A | H5: ='BTL Calculator'!#REF! -> #REF! | I5: =IF($D5>H5,0,1) -> #N/A | J5: =IF(I5=0,"Rolled Months too High","") -> #N/A | M5: IF rolled up months > 6, only PBL YES | V5: 2yr: 24+up to 12m servicer permitted extension (at the 24m stage, and only once) YES
C6: Term | D6: =Term -> 24 | E6: 36 | F6: =IF($D6>E6,0,1) -> 1 | G6: =IF(F6=0,"Term too High","") | H6: 36 | I6: =IF($D6>H6,0,1) -> 1 | J6: =IF(I6=0,"Term too High","") | M6: IF initial term > 24 months, PBL only (as their loan facility is a proper 3yr term, not a 2+1) YES | V6: 3yr: 36m + 3m servicer extension YES
C7: Interest Rate | D7: ='BTL Calculator'!M141 -> #N/A | E7: 0.0499 | F7: =IF($D7<E7,0,1) -> #N/A | G7: =IF(F7=0,"Interest Rate too low","") -> #N/A | H7: 0 | I7: =IF($D7<H7,0,1) -> #N/A | J7: =IF(I7=0,"Interest Rate too low","") -> #N/A | M7: IF initial interest rate is < 4.99%, then PBL only (ZBL have min 4.99%) YES currently we are funding loans at 4.79% which is outside ZBL criteria | U7: Do you agree, or are there more? I have to check what’s the minimum interest rate to be charged per month on PBL as currently ZBL is 0.41% with 4.79% this become 0.399% per month | V7: During the extension, interest is due at the FULL interest rate, not the pay rate YES
C8: ICR | D8: ='BTL Calculator'!M155 -> - | E8: 1 | F8: =IF($D8<E8,0,1) -> 1 | G8: =IF(F8=0,"ICR too Low","") | H8: 1 | I8: =IF($D8<H8,0,1) -> 1 | J8: =IF(I8=0,"ICR too Low","") | M8: IF ICR, on an exception, goes below 100%, then ZBL only (old methodology, 80%+ where other income/wealth can support) Agreed – we must ensure ICR is 100% or above on all loans, PBL To be finalised | V8: ZBL terms are:
C9: Country | D9: ='BTL Calculator'!V16 -> No | F9: =IF(D9="No",1,0) -> 1 | G9: =IF(F9=0,"Restricted Country","") | H9: ANY | I9: 1 | J9: =IF(I9=0,"Restricted Country","") | M9: IF country on the excluded list for ZBL (below), then PBL only YES ,for PBL as long is not a restricted country Afghanistan, Bosnia Herzegovina, Burundi, Central African Republic, Cuba, Democratic People's Republic of Korea, Democratic Republic of the Congo, Eritrea, Ethiopia, Iran (Islamic Republic of), Iraq, Laos People's Democratic Republic, Libyan Arab Jamahiriya, Myanmar, Pakistan, Somalia, South Sudan, Sudan, Syrian Arab Republic, Uganda, Vanuatu, Venezuela, Yemen. | U9: FYI – the ERC is basically waived after 60 days (3+ yr loan) and 30 days for 2yr loan. Agreed Even during the extension. This is fine – you only really extend when a small delay in exit, and it’s at full interest rate so can be penal compared to a 3yr (to avoid gaming). We will also have retention products then to try to lock them in again | V9: 2yr: 24+up to 3m servicer permitted extension. During the extension, interest is due at the FULL interest rate, not the pay rate serviceable on full IR, however ZBL allows extension upto 12months
C10: Max Loan | D10: =Gross_Loan -> #N/A | E10: 3000000 | F10: =IF($D10>E10,0,1) -> #N/A | G10: =IF(F10=0,"Loan too big","") -> #N/A | H10: 3000000 | I10: =IF($D10>H10,0,1) -> #N/A | J10: =IF(I10=0,"Loan too big","") -> #N/A | M10: QUESTION: is the max individual loan on PBL £3m, TBD , await lender confirmation like it is on ZBL? ZBL specifically calls it out, but PBL just has standard ‘£4m’ for single property loan there will be some covenant set by PBL Lender which we are finalising terms on max amount | U10: · An early repayment charge (ERC) is payable if the Borrower redeems the loan before the contractual maturity date of the loan. ERC is waived for any early redemptions that occur within a grace period starting from a maximum of 60 days prior to the original contractual maturity date and continuing thereafter (including during any Servicer Extension). Does this cover if redeemed on month 22? | V10: 3yr: 24+up to 12m servicer permitted extension. We grant this automatically subject to conditions. Whilst the contract states interest due at full rate, we’ve done the upfront calculations that the deferred interest/net loan means reduced payments to not impact LTV adversely , pls discuss as currently UW are deferring interest upto 36m by issuing 24m term +12m (extension ), hence the issue we had today, with this the serviceable interest from 24m to 36m become serviceable on pay rate, 4.79% rate deferred 0.50% for 36m with 2 month rolled up , the borrow is serving interest on deferred rate for 34m at 4.29% -
C11: Holiday Let | D11: =D40 -> No | F11: 1 | G11: =IF(F11=0,"Term too High","") | H11: No | I11: =IF($D11=H11,1,0) -> 1 | J11: =IF(I11=0,C11,"")
F12: =IF($D12>E12,0,1) -> 1 | G12: =IF(F12=0,"Term too High","") | I12: =IF($D12>H12,0,1) -> 1
B18: Loan Calculations & Summary | F18: Linked/taken from main ICR calculator
B19: Property Details | S19: ='BTL Calculator'!V8 -> 0 | U19: ='BTL Calculator'!V9 -> 0 | W19: ='BTL Calculator'!V11 -> 0 | X19: ='BTL Calculator'!V9+'BTL Calculator'!V11 -> 0
C20: Property postcode | D20: ='BTL Calculator'!V14 -> 0 | F20: =LEFT(D20,2-(--ISNUMBER(MID(D20,2,1)*1))) -> 0 | K20: Proc Fee | L20: =D28*Gross_Loan -> #N/A | S20: Rent charge | U20: Rent charge | V20: Top Slice
C21: Property Region: | D21: ='BTL Calculator'!V15 -> 0 | F21: =INDEX('Product Data'!$I$220:$I$326,MATCH(F20,'Product Data'!$B$220:$B$334,0)) -> #N/A | I21: APRC Calculator after Rolled | S21: Weekly | U21: =IF($S$19=$S$21,$U$19,U23/52) -> 0 | V21: =V23/52 -> 0 | W21: =IF($S$19=$S$21,$W$19,W23/52) -> 0
C22: APRC Calculator before Rolled | I22: Gross Loan Amount | L22: =(IF(RoundDown,R90,Q90)) -> #N/A | S22: Monthly | U22: =IF($S$19=$S$22,U19,U23/12) -> 0 | V22: ='BTL Calculator'!$L$80 -> 0 | W22: =IF($S$19=$S$22,W19,W23/12) -> 0 | X22: =IF($S$19=$S$22,X19,X23/12)+'BTL Calculator'!H14 -> 0 | AB22: APRC Calculator after Rolled | AI22: APRC Calculator after Rolled | AN22: APRC Calculator after Rolled
C23: Gross Loan Amount | D23: =(IF(RoundDown,R90,Q90)) -> #N/A | I23: Duration (Months) | L23: =Term -> 24 | S23: Annual | U23: =IF($S$19=$S$23,U19,IF($S$19=$S$21,U19*52,U19*12)) -> 0 | V23: =V22*12 -> 0 | W23: =IF($S$19=$S$23,$W$19,IF($S$19=$S$21,W19*52,W19*12)) -> 0 | X23: =IF($S$19=$S$23,X19,IF($S$19=$S$21,X19*52,X19*12)) -> 0 | AB23: Gross Loan Amount | AC23: =(IF(RoundDown,R108,Q108)) -> #N/A | AI23: Gross Loan Amount | AJ23: =(IF(RoundDown,R126,Q126)) -> #N/A | AN23: Gross Loan Amount | AO23: =(IF(RoundDown,R144,Q144)) -> #N/A
C24: Duration (Months) | D24: =Term -> 24 | I24: Rolled | L24: =RollupMonths -> #N/A | M24: =$AE$90 -> #N/A | S24: Term rent | U24: =Monthly_Rent*Term -> 0 | V24: =V22*Term -> 0 | W24: =W22*24 -> 0 | AB24: Duration (Months) | AC24: =Term -> 24 | AI24: Duration (Months) | AJ24: =Term -> 24 | AN24: Duration (Months) | AO24: =Term -> 24
C25: Rolled | D25: 0 | I25: Monthly Int Rate | L25: =IFERROR((Tier_Standard_rate-DeferedIntPercent)/12,"-") -> - | M25: =IFERROR(L22*L25,"-") -> - | AB25: Rolled | AC25: =K108 -> #N/A | AI25: Rolled | AJ25: =K126 -> #N/A | AN25: Rolled | AO25: =K144 -> #N/A
C26: Monthly Int Rate | D26: =IFERROR(Tier_Standard_rate/12,"-") -> - | F26: =IFERROR(D23*D26,"-") -> - | I26: Defered interest | L26: =DeferedIntPercent/12 -> #N/A | M26: =L22*L26*Term -> #N/A | AB26: Monthly Int Rate | AC26: =IFERROR((H108-J108)/12,"-") -> - | AE26: =AE108 -> #N/A | AI26: Monthly Int Rate | AJ26: =IFERROR((H126-J126)/12,"-") -> - | AL26: =AE126 -> #N/A | AN26: Monthly Int Rate | AO26: =IFERROR((H144-J144)/12,"-") -> - | AQ26: =AE144 -> #N/A
C27: Product fee % | D27: =Prod_Fee_Chosen -> #N/A | F27: =D23*D27 -> #N/A | I27: Product fee % | L27: =Prod_Fee_Chosen -> #N/A | M27: =L22*L27 -> #N/A | AB27: Defered interest | AC27: =J108/12 -> #N/A | AE27: =IFERROR(AC23*AC26,"-") -> - | AI27: Defered interest | AJ27: =J126/12 -> #N/A | AL27: =IFERROR(AJ23*AJ26,"-") -> - | AN27: Defered interest | AO27: =J144/12 -> #N/A | AQ27: =IFERROR(AO23*AO26,"-") -> -
C28: Proc Fee | D28: =IFERROR(IF('BTL Calculator'!H37>=0,'BTL Calculator'!H37,'BTL Calculator'!H36)+('BTL Calculator'!H38/D23),0) -> 0 | F28: =D23*D28 -> #N/A | G28: Core Net Loan LTV | I28: Proc Fee | L28: =D28 -> 0 | M28: =L22*L28 -> #N/A | AB28: Product fee % | AC28: =I108 -> #N/A | AE28: =AC23*AC27*Term -> #N/A | AI28: Product fee % | AJ28: =I126 -> #N/A | AL28: =AJ23*AJ27*Term -> #N/A | AN28: Product fee % | AO28: 0.03 | AQ28: =AO23*AO27*Term -> #N/A
C29: Net loan Amount | D29: =IFERROR(D23-(D23*D26*D25)-(D23*D27),"-") -> - | G29: =IFERROR(Core_Net_loan/Property_Value,"-") -> - | I29: Net loan Amount | L29: =IFERROR(L22-M27-M26-M24,"-") -> - | AB29: Proc Fee | AC29: =D28 -> 0 | AE29: =AC23*AC28 -> #N/A | AI29: Proc Fee | AJ29: =D28 -> 0 | AL29: =AJ23*AJ28 -> #N/A | AN29: Proc Fee | AO29: =D28 -> 0 | AQ29: =AO23*AO28 -> #N/A
C30: Total Int£ over term | D30: =IFERROR(D24*F26,"-") -> - | I30: Total Int£ over term | L30: =IFERROR(L23*M25+M26,"-") -> - | AB30: Net loan Amount | AC30: =IFERROR(AC23-AE29-AE28-AE26,"-") -> - | AE30: =AC23*AC29 -> #N/A | AI30: Net loan Amount | AJ30: =IFERROR(AJ23-AL29-AL28-AL26,"-") -> - | AL30: =AJ23*AJ29 -> #N/A | AN30: Net loan Amount | AO30: =IFERROR(AO23-AQ29-AQ28-AQ26,"-") -> -
C31: Total Int£ + Prodfee£ | D31: =IFERROR(D30+F27,"-") -> - | I31: Total Int£ + Prodfee£ | L31: =IFERROR(L30+M27,"-") -> - | AB31: Total Int£ over term | AC31: =IFERROR(AC24*AE27+AE28,"-") -> - | AI31: Total Int£ over term | AJ31: =IFERROR(AJ24*AL27+AL28,"-") -> - | AN31: Total Int£ over term | AO31: =IFERROR(AO24*AQ27+AQ28,"-") -> -
C32: APR | D32: =IFERROR(D31/D29/D24*12,"-") -> - | I32: APR | L32: =IFERROR(L31/L29/L23*12,"-") -> - | AB32: Total Int£ + Prodfee£ | AC32: =IFERROR(AC31+AE29,"-") -> - | AI32: Total Int£ + Prodfee£ | AJ32: =IFERROR(AJ31+AL29,"-") -> - | AN32: Total Int£ + Prodfee£ | AO32: =IFERROR(AO31+AQ29,"-") -> -
C33: Monthly APR | D33: =IFERROR(D32/12,"-") -> - | I33: Monthly APR | L33: =IFERROR(L32/12,"-") -> - | AB33: APR | AC33: =IFERROR(AC32/AC30/AC24*12,"-") -> - | AI33: APR | AJ33: =IFERROR(AJ32/AJ30/AJ24*12,"-") -> - | AN33: APR | AO33: =IFERROR(AO32/AO30/AO24*12,"-") -> -
AB34: Monthly APR | AC34: =IFERROR(AC33/12,"-") -> - | AI34: Monthly APR | AJ34: =IFERROR(AJ33/12,"-") -> - | AN34: Monthly APR | AO34: =IFERROR(AO33/12,"-") -> -
B35: Tier Selector & LTV | G35: Tier
A36: CRITERIA RESI | B36: Property | D36: =IFERROR(INDEX('Product Data'!B9:B12,MATCH(TEXT(F36&"*",),'Product Data'!B9:B12,0)),"N/A") -> 1) Standard BTL | E36: =VLOOKUP(D36,'Product Data'!B8:N12,13,0) -> Tier 1 | F36: =MAX(F37:F55,IF(AND(F44=3,F37+F38>2),4,0)) -> 1 | G36: 0 | H36: 1 | I36: 2 | J36: 3 | K36: 3 | L36: 3 | M36: 4 | N36: MAX LTV | O36: =MIN(O37:O42) -> 0.75 | P36: =MIN(P37:P42) -> 0.75 | Q36: =MIN(Q37:Q42) -> 0.75 | R36: =MIN(R37:R42) -> 0.7 | S36: =MIN(S37:S42) -> 0.75 | T36: CRITERIA FOR COMMERCIAL & SEMI COMMERCIAL | U36: Property | W36: =IFERROR(INDEX('Product Data'!B34:B35,MATCH(TEXT(Y36&"*",),'Product Data'!B34:B35,0)),"N/A") -> 1) Standard | X36: =VLOOKUP(W36,'Product Data'!B34:N35,13,0) -> Tier 1 | Y36: =MAX(Y37:Y52) -> 1 | Z36: 0 | AA36: 1 | AB36: 1 | AC36: 1 | AD36: 1 | AE36: 2 | AF36: 2
C37: HMO | D37: ='BTL Calculator'!$V$17 -> No | F37: =INDEX($G$36:$M$36,MATCH(D37,G37:M37,0)) -> 1 | H37: No | I37: =IF(ISNUMBER(SEARCH("Commercial",'BTL Calculator'!V3)),"<= 12 beds","<= 6 beds") -> <= 6 beds | L37: =IF(ISNUMBER(SEARCH("commercial",'BTL Calculator'!V3)),"> 12 beds","> 6 beds") -> > 6 beds | N37: LTV Tier Cap | O37: 0.75 | P37: 0.75 | Q37: 0.75 | R37: 0.7 | S37: =INDEX(O37:R37,MATCH($F$36,$O$38:$R$38,0)) -> 0.75 | V37: HMO | W37: ='BTL Calculator'!$V$17 -> No | Y37: =INDEX($Z$36:$AE$36,MATCH(W37,Z37:AE37,0)) -> 1 | AA37: No | AB37: =IF(Rate_Type="Tracker","<= 6 beds","No") -> No | AC37: <= 12 beds | AE37: > 12 beds
C38: Multi-Unit Freehold Block | D38: ='BTL Calculator'!$V$18 -> No | F38: =INDEX($G$36:$M$36,MATCH(D38,G38:M38,0)) -> 1 | H38: No | I38: =IF(ISNUMBER(SEARCH("Commercial",'BTL Calculator'!V3)),"<= 12 units","<= 6 units") -> <= 6 units | K38: <= 30 units | L38: =IF(ISNUMBER(SEARCH("commercial",'BTL Calculator'!V3)),"> 12 units",IF(Rate_Type="Tracker","<= 30 units","<= 10 units")) -> <= 10 units | M38: > 30 Units | O38: 1 | P38: 2 | Q38: 3 | R38: 4 | S38: Chosen | V38: Multi-Unit Freehold Block | W38: ='BTL Calculator'!$V$18 -> No | Y38: =INDEX($Z$36:$AF$36,MATCH(W38,Z38:AF38,0)) -> 1 | AA38: No | AB38: =IF(Rate_Type="Tracker","<= 6 units","No") -> No | AC38: <= 12 units | AE38: > 12 units
C39: Flats above Restricted commercial | D39: ='BTL Calculator'!$V$19 -> No | F39: =INDEX($G$36:$M$36,MATCH(D39,G39:M39,0)) -> 1 | H39: No | I39: Yes | O39: =O$37 -> 0.75 | P39: =P$37 -> 0.75 | Q39: =Q$37 -> 0.75 | R39: =R$37 -> 0.7 | S39: =INDEX(O39:R39,MATCH($F$36,$O$38:$R$38,0)) -> 0.75 | V39: Development Exit | W39: ='BTL Calculator'!$V$21 -> No | Y39: =INDEX($Z$36:$AF$36,MATCH(W39,Z39:AF39,0)) -> 1 | AA39: No | AE39: Yes
C40: Holiday/ Short term Let | D40: ='BTL Calculator'!$V$20 -> No | F40: =INDEX($G$36:$M$36,MATCH(D40,G40:M40,0)) -> 1 | H40: No | I40: No | L40: =IF('BTL Calculator'!V2="Core","","Yes") -> Yes | V40: PBSA/Serviced Accommodation? | W40: ='BTL Calculator'!$V$23 -> No | Y40: =INDEX($Z$36:$AF$36,MATCH(W40,Z40:AF40,0)) -> 1 | AA40: No | AB40: No | AC40: Yes | AE40: Yes
C41: Development Exit | D41: ='BTL Calculator'!$V$21 -> No | F41: =INDEX($G$36:$M$36,MATCH(D41,G41:M41,0)) -> 1 | H41: No | I41: Yes
C42: PBSA/Serviced Accommodation? | D42: ='BTL Calculator'!$V$23 -> No | F42: =INDEX($G$36:$M$36,MATCH(D42,G42:M42,0)) -> 1 | H42: No | I42: No | O42: =O$37 -> 0.75 | P42: =IF($D$39=$H$39,P37,60%) -> 0.75 | Q42: =IF($D$39=$I$39,70%,Q37) -> 0.75 | R42: =R$37 -> 0.7 | S42: =INDEX(O42:R42,MATCH($F$36,$O$38:$R$38,0)) -> 0.75 | U42: Customer
B43: Customer | V43: Commercial Owner Occuppied | W43: ='BTL Calculator'!H13 -> No | Y43: =INDEX($Z$36:$AF$36,MATCH(W43,Z43:AF43,0)) -> 1 | AA43: No | AE43: Yes
C44: First time Landlord | D44: ='BTL Calculator'!$H$12 -> No | F44: =INDEX($G$36:$M$36,MATCH(D44,G44:M44,0)) -> 1 | H44: No | I44: Yes | L44: =IF('BTL Calculator'!V2="Core","","Yes") -> Yes | V44: First time commercial Landlord | W44: ='BTL Calculator'!$H$12 -> No | Y44: =INDEX($Z$36:$AF$36,MATCH(W44,Z44:AF44,0)) -> 1 | AA44: No | AE44: Yes
C45: Expat/ Foreign National | D45: =IF(AND('BTL Calculator'!$H$15="Yes",'BTL Calculator'!$H$16="Yes"),"No",'BTL Calculator'!$H$15) -> No | F45: =INDEX($G$36:$M$36,MATCH(D45,G45:M45,0))+IF('BTL Calculator'!V2="Core",0,F46) -> 1 | G45: No | H45: No | I45: Yes | L45: =IF('BTL Calculator'!V2="Core","","Yes") -> Yes | V45: Expat/ Foreign National | W45: =IF(AND('BTL Calculator'!$H$15="Yes",'BTL Calculator'!$H$16="Yes"),"No",'BTL Calculator'!$H$15) -> No | Y45: =INDEX($Z$36:$AF$36,MATCH(W45,Z45:AF45,0)) -> 1 | AA45: No | AE45: Yes
C46: Have a UK Footprint? | D46: ='BTL Calculator'!$H$17 -> No | F46: =INDEX($G$36:$M$36,MATCH(D46,G46:M46,0)) -> 1 | G46: Yes | H46: No | I46: Yes | V46: Have a UK Footprint?
C47: Offshore Company | D47: ='BTL Calculator'!$H$18 -> No | F47: =INDEX($G$36:$M$36,MATCH(D47,G47:M47,0)) -> 1 | H47: No | I47: No | L47: =IF('BTL Calculator'!V2="Core","","Yes") -> Yes | V47: Offshore Company | W47: ='BTL Calculator'!$H$18 -> No | Y47: =INDEX($Z$36:$AF$36,MATCH(W47,Z47:AF47,0)) -> 1 | AA47: No | AE47: Yes
C48: Any adverse credit? | D48: ='BTL Calculator'!$H$19 -> No | F48: =IF(D48="No",1,0) -> 1 | O48: Build Commercial / Semi-commercial criteria table | V48: Any adverse credit? | W48: ='BTL Calculator'!$H$19 -> No | Y48: =IF(W48="No",1,0) -> 1
C49: Missed Mortgage Payments | D49: ='BTL Calculator'!$H$20 -> 0 | F49: =IFERROR(IF($F$48=1,1,INDEX($G$36:$M$36,MATCH(D49,G49:M49,0))),0) -> 1 | H49: 0 missed last 24m | I49: 0 missed in last 18m | L49: =IF('BTL Calculator'!V2="Core","","Other, more recent") -> Other, more recent | O49: Owner-occupier methodology - use 2yrs EBITDA (1m x24) | V49: Missed Mortgage Payments | W49: ='BTL Calculator'!$H$20 -> 0 | Y49: =IFERROR(IF($F$48=1,1,INDEX($Z$36:$AF$36,MATCH(W49,Z49:AF49,0))),0) -> 1 | AA49: 2 missed last 18 months, 0 in last 6 | AE49: Considered upon referral
C50: Unsecured Card/Loan Payments | D50: ='BTL Calculator'!$H$21 -> 0 | F50: =IFERROR(IF($F$48=1,1,INDEX($G$36:$M$36,MATCH(D50,G50:M50,0))),0) -> 1 | H50: 0 missed last 24m | I50: 0 missed last 12m | L50: =IF('BTL Calculator'!V2="Core","","Other, more recent") -> Other, more recent | V50: Unsecured Card/Loan Payments | W50: ='BTL Calculator'!$H$21 -> 0 | Y50: =IFERROR(IF($F$48=1,1,INDEX($Z$36:$AF$36,MATCH(W50,Z50:AF50,0))),0) -> 1 | AA50: 2 missed last 18 months | AE50: Considered upon referral
C51: CCJs & Defaults | D51: ='BTL Calculator'!$H$22 -> 0 | F51: =IFERROR(IF($F$48=1,1,INDEX($G$36:$M$36,MATCH(D51,G51:M51,0))),0) -> 1 | H51: 0 in last 24m | I51: 0 in last 18m | L51: =IF('BTL Calculator'!V2="Core","","Other, more recent") -> Other, more recent | V51: CCJs & Defaults | W51: ='BTL Calculator'!$H$22 -> 0 | Y51: =IFERROR(IF($F$48=1,1,INDEX($Z$36:$AF$36,MATCH(W51,Z51:AF51,0))),0) -> 1 | AA51: 2 missed last 18 months, 0 in last 6 | AE51: Considered upon referral
C52: Bankruptcy/IVA/DRO | D52: ='BTL Calculator'!$H$23 -> 0 | F52: =IFERROR(IF($F$48=1,1,INDEX($G$36:$M$36,MATCH(D52,G52:M52,0))),0) -> 1 | H52: Never | I52: Never | L52: =IF('BTL Calculator'!V2="Core","","Other, more recent") -> Other, more recent | V52: Bankruptcy/IVA/DRO | W52: ='BTL Calculator'!$H$23 -> 0 | Y52: =IFERROR(IF($F$48=1,1,INDEX($Z$36:$AF$36,MATCH(W52,Z52:AF52,0))),0) -> 1 | AA52: Discharged > 3 years | AE52: Considered upon referral
H53: =IF($F37>H$36,$C37,"") | I53: =IF($F37>I$36,$C37,"") | J53: =IF($F37>J$36,$C37,"") | K53: =IF($F37>K$36,$C37,"") | L53: =IF($F37>L$36,$C37,"") | M53: =IF($F37>M$36,$C37,"") | AA53: =IF($Y37>AA$36,$V37,"") | AB53: =IF($Y37>AB$36,$V37,"") | AC53: =IF($Y37>AC$36,$V37,"") | AD53: =IF($Y37>AD$36,$V37,"") | AE53: =IF($Y37>AE$36,$V37,"")
H54: =IF($F38>H$36,$C38,"") | I54: =IF($F38>I$36,$C38,"") | J54: =IF($F38>J$36,$C38,"") | K54: =IF($F38>K$36,$C38,"") | L54: =IF($F38>L$36,$C38,"") | M54: =IF($F38>M$36,$C38,"") | AA54: =IF($Y38>AA$36,$V38,"") | AB54: =IF($Y38>AB$36,$V38,"") | AC54: =IF($Y38>AC$36,$V38,"") | AD54: =IF($Y38>AD$36,$V38,"") | AE54: =IF($Y38>AE$36,$V38,"")
H55: =IF($F39>H$36,$C39,"") | I55: =IF($F39>I$36,$C39,"") | J55: =IF($F39>J$36,$C39,"") | K55: =IF($F39>K$36,$C39,"") | L55: =IF($F39>L$36,$C39,"") | M55: =IF($F39>M$36,$C39,"") | AA55: =IF($Y39>AA$36,$V39,"") | AB55: =IF($Y39>AB$36,$V39,"") | AC55: =IF($Y39>AC$36,$V39,"") | AD55: =IF($Y39>AD$36,$V39,"") | AE55: =IF($Y39>AE$36,$V39,"")
H56: =IF($F40>H$36,$C40,"") | I56: =IF($F40>I$36,$C40,"") | J56: =IF($F40>K$36,$C40,"") | K56: =IF($F40>L$36,$C40,"") | L56: =IF($F40>M$36,$C40,"") | AA56: =IF($Y40>AA$36,$V40,"") | AB56: =IF($Y40>AB$36,$V40,"") | AC56: =IF($Y40>AD$36,$V40,"") | AD56: =IF($Y40>AE$36,$V40,"") | AE56: =IF($Y40>AF$36,$V40,"")
H57: =IF($F44>H$36,$C44,"") | I57: =IF($F44>I$36,$C44,"") | J57: =IF($F44>K$36,$C44,"") | K57: =IF($F44>L$36,$C44,"") | L57: =IF($F44>M$36,$C44,"") | AA57: =IF($Y44>AA$36,$V44,"") | AB57: =IF($Y44>AB$36,$V44,"") | AC57: =IF($Y44>AD$36,$V44,"") | AD57: =IF($Y44>AE$36,$V44,"") | AE57: =IF($Y44>AF$36,$V44,"")
H58: =IF($F45>H$36,$C45,"") | I58: =IF($F45>I$36,$C45,"") | J58: =IF($F45>K$36,$C45,"") | K58: =IF($F45>L$36,$C45,"") | L58: =IF($F45>M$36,$C45,"") | AA58: =IF($Y45>AA$36,$V45,"") | AB58: =IF($Y45>AB$36,$V45,"") | AC58: =IF($Y45>AD$36,$V45,"") | AD58: =IF($Y45>AE$36,$V45,"") | AE58: =IF($Y45>AF$36,$V45,"")
H59: =IF($F46>H$36,$C46,"") | I59: =IF($F46>I$36,$C46,"") | J59: =IF($F46>K$36,$C46,"") | K59: =IF($F46>L$36,$C46,"") | L59: =IF($F46>M$36,$C46,"") | AA59: =IF($Y46>AA$36,$V46,"") | AB59: =IF($Y46>AB$36,$V46,"") | AC59: =IF($Y46>AD$36,$V46,"") | AD59: =IF($Y46>AE$36,$V46,"") | AE59: =IF($Y46>AF$36,$V46,"")
H60: =IF($F47>H$36,$C47,"") | I60: =IF($F47>I$36,$C47,"") | J60: =IF($F47>K$36,$C47,"") | K60: =IF($F47>L$36,$C47,"") | L60: =IF($F47>M$36,$C47,"") | AA60: =IF($Y47>AA$36,$V47,"") | AB60: =IF($Y47>AB$36,$V47,"") | AC60: =IF($Y47>AD$36,$V47,"") | AD60: =IF($Y47>AE$36,$V47,"") | AE60: =IF($Y47>AF$36,$V47,"")
H61: =IF($F48>H$36,$C48,"") | I61: =IF($F48>I$36,$C48,"") | J61: =IF($F48>K$36,$C48,"") | K61: =IF($F48>L$36,$C48,"") | L61: =IF($F48>M$36,$C48,"") | AA61: =IF($Y48>AA$36,$V48,"") | AB61: =IF($Y48>AB$36,$V48,"") | AC61: =IF($Y48>AD$36,$V48,"") | AD61: =IF($Y48>AE$36,$V48,"") | AE61: =IF($Y48>AF$36,$V48,"")
H62: =IF($F49>H$36,$B49,"") | I62: =IF($F49>I$36,$B49,"") | J62: =IF($F49>K$36,$B49,"") | K62: =IF($F49>L$36,$B49,"") | L62: =IF($F49>M$36,$B49,"") | AA62: =IF($Y49>AA$36,$B49,"") | AB62: =IF($Y49>AB$36,$B49,"") | AC62: =IF($Y49>AD$36,$B49,"") | AD62: =IF($Y49>AE$36,$B49,"") | AE62: =IF($Y49>AF$36,$B49,"")
H63: =IF($F50>H$36,$B50,"") | I63: =IF($F50>I$36,$B50,"") | J63: =IF($F50>K$36,$B50,"") | K63: =IF($F50>L$36,$B50,"") | L63: =IF($F50>M$36,$B50,"") | AA63: =IF($Y50>AA$36,$B50,"") | AB63: =IF($Y50>AB$36,$B50,"") | AC63: =IF($Y50>AD$36,$B50,"") | AD63: =IF($Y50>AE$36,$B50,"") | AE63: =IF($Y50>AF$36,$B50,"")
H64: =IF($F51>H$36,$B51,"") | I64: =IF($F51>I$36,$B51,"") | J64: =IF($F51>K$36,$B51,"") | K64: =IF($F51>L$36,$B51,"") | L64: =IF($F51>M$36,$B51,"") | AA64: =IF($Y51>AA$36,$B51,"") | AB64: =IF($Y51>AB$36,$B51,"") | AC64: =IF($Y51>AD$36,$B51,"") | AD64: =IF($Y51>AE$36,$B51,"") | AE64: =IF($Y51>AF$36,$B51,"")
H65: =IF($F52>H$36,$B52,"") | I65: =IF($F52>I$36,$B52,"") | J65: =IF($F52>K$36,$B52,"") | K65: =IF($F52>L$36,$B52,"") | L65: =IF($F52>M$36,$B52,"") | AA65: =IF($Y52>AA$36,$B52,"") | AB65: =IF($Y52>AB$36,$B52,"") | AC65: =IF($Y52>AD$36,$B52,"") | AD65: =IF($Y52>AE$36,$B52,"") | AE65: =IF($Y52>AF$36,$B52,"")
H66: =_xlfn.TEXTJOIN(", ",,H53:H65) | I66: =_xlfn.TEXTJOIN(", ",,I53:I65) | J66: =_xlfn.TEXTJOIN(", ",,J53:J65) | K66: =_xlfn.TEXTJOIN(", ",,K53:K65) | L66: =_xlfn.TEXTJOIN(", ",,L53:L65) | AA66: =_xlfn.TEXTJOIN(", ",,AA53:AA65) | AB66: =_xlfn.TEXTJOIN(", ",,AB53:AB65) | AC66: =_xlfn.TEXTJOIN(", ",,AC53:AC65) | AD66: =_xlfn.TEXTJOIN(", ",,AD53:AD65) | AE66: =_xlfn.TEXTJOIN(", ",,AE53:AE65)
B68: MAX LOAN CALCS
C69: 2% Fee Product | D69: 2% fee | E69: 4% fee | F69: 6% fee | G69: 3% fee
C70: Max Gross Loan: | D70: {=IF('BTL Calculator'!V2="Core", IF(OR($H$70="Residential BTL", $H$70="Retention"), IF(RoundDown=FALSE, MAX(_xlfn._xlws.FILTER(CHOOSE({1,2,3,4,5,6}, $Q$76, $Q$77, $Q$79, $Q$80, $Q$85, $Q$86), CHOOSE({1,2,3,4,5,6}, $E$76, $E$77, $E$79, $E$80, $E$85, $E$86) >= $F$36)), MAX(_xlfn._xlws.FILTER(CHOOSE({1,2,3,4,5,6}, $R$76, $R$77, $R$79, $R$80, $R$85, $R$86), CHOOSE({1,2,3,4,5,6}, $E$76, $E$77, $E$79, $E$80, $E$85, $E$86) >= $F$36)) ), IF(RoundDown=FALSE, MAX(_xlfn._xlws.FILTER(CHOOSE({1,2,3,4,5,6}, $Q$76, $Q$77, $Q$79, $Q$80, $Q$85, $Q$86), CHOOSE({1,2,3,4,5,6}, $E$76, $E$77, $E$79, $E$80, $E$85, $E$86) >= $Y$36)), MAX(_xlfn._xlws.FILTER(CHOOSE({1,2,3,4,5,6}, $R$76, $R$77, $R$79, $R$80, $R$85, $R$86), CHOOSE({1,2,3,4,5,6}, $E$76, $E$77, $E$79, $E$80, $E$85, $E$86) >= $Y$36)) ) ), IF(OR($H$70="Residential BTL", $H$70="Retention"), IF(RoundDown=FALSE, _xlfn.MAXIFS($Q$76:$Q$87, $E$76:$E$87, ">="&$F$36), _xlfn.MAXIFS($R$76:$R$87, $E$76:$E$87, ">="&$F$36) ), IF(RoundDown=FALSE, _xlfn.MAXIFS($Q$76:$Q$87, $E$76:$E$87, ">="&$Y$36), _xlfn.MAXIFS($R$76:$R$87, $E$76:$E$87, ">="&$Y$36) ) ) )} -> 0 | E70: {=IF('BTL Calculator'!V2="Core", IF(OR($H$70="Residential BTL", $H$70="Retention"), IF(RoundDown=FALSE, MAX(_xlfn._xlws.FILTER(CHOOSE({1,2,3,4,5,6}, $Q$94, $Q$95, $Q$97, $Q$98, $Q$103, $Q$104), CHOOSE({1,2,3,4,5,6}, $E$94, $E$95, $E$97, $E$98, $E$103, $E$104) >= $F$36)), MAX(_xlfn._xlws.FILTER(CHOOSE({1,2,3,4,5,6}, $R$94, $R$95, $R$97, $R$98, $R$103, $R$104), CHOOSE({1,2,3,4,5,6}, $E$94, $E$95, $E$97, $E$98, $E$103, $E$104) >= $F$36)) ), IF(RoundDown=FALSE, MAX(_xlfn._xlws.FILTER(CHOOSE({1,2,3,4,5,6}, $Q$94, $Q$95, $Q$97, $Q$98, $Q$103, $Q$104), CHOOSE({1,2,3,4,5,6}, $E$94, $E$95, $E$97, $E$98, $E$103, $E$104) >= $Y$36)), MAX(_xlfn._xlws.FILTER(CHOOSE({1,2,3,4,5,6}, $R$94, $R$95, $R$97, $R$98, $R$103, $R$104), CHOOSE({1,2,3,4,5,6}, $E$94, $E$95, $E$97, $E$98, $E$103, $E$104) >= $Y$36)) ) ), IF(OR($H$70="Residential BTL", $H$70="Retention"), IF(RoundDown=FALSE, _xlfn.MAXIFS($Q$94:$Q$105, $E$94:$E$105, ">="&$F$36), _xlfn.MAXIFS($R$94:$R$105, $E$94:$E$105, ">="&$F$36) ), IF(RoundDown=FALSE, _xlfn.MAXIFS($Q$94:$Q$105, $E$94:$E$105, ">="&$Y$36), _xlfn.MAXIFS($R$94:$R$105, $E$94:$E$105, ">="&$Y$36) ) ) )} -> 0 | F70: {=IF('BTL Calculator'!V2="Core", IF(OR($H$70="Residential BTL", $H$70="Retention"), IF(RoundDown=FALSE, MAX(_xlfn._xlws.FILTER(CHOOSE({1,2,3,4,5,6}, $Q$112, $Q$113, $Q$115, $Q$116, $Q$121, $Q$122), CHOOSE({1,2,3,4,5,6}, $E$112, $E$113, $E$115, $E$116, $E$121, $E$122) >= $F$36)), MAX(_xlfn._xlws.FILTER(CHOOSE({1,2,3,4,5,6}, $R$112, $R$113, $R$115, $R$116, $R$121, $R$122), CHOOSE({1,2,3,4,5,6}, $E$112, $E$113, $E$115, $E$116, $E$121, $E$122) >= $F$36)) ), IF(RoundDown=FALSE, MAX(_xlfn._xlws.FILTER(CHOOSE({1,2,3,4,5,6}, $Q$112, $Q$113, $Q$115, $Q$116, $Q$121, $Q$122), CHOOSE({1,2,3,4,5,6}, $E$112, $E$113, $E$115, $E$116, $E$121, $E$122) >= $Y$36)), MAX(_xlfn._xlws.FILTER(CHOOSE({1,2,3,4,5,6}, $R$112, $R$113, $R$115, $R$116, $R$121, $R$122), CHOOSE({1,2,3,4,5,6}, $E$112, $E$113, $E$115, $E$116, $E$121, $E$122) >= $Y$36)) ) ), IF(OR($H$70="Residential BTL", $H$70="Retention"), IF(RoundDown=FALSE, _xlfn.MAXIFS($Q$112:$Q$123, $E$112:$E$123, ">="&$F$36), _xlfn.MAXIFS($R$112:$R$123, $E$112:$E$123, ">="&$F$36) ), IF(RoundDown=FALSE, _xlfn.MAXIFS($Q$112:$Q$123, $E$112:$E$123, ">="&$Y$36), _xlfn.MAXIFS($R$112:$R$123, $E$112:$E$123, ">="&$Y$36) ) ) )} -> 0 | G70: {=IF('BTL Calculator'!V2="Core", IF(OR($H$70="Residential BTL", $H$70="Retention"), IF(RoundDown=FALSE, MAX(_xlfn._xlws.FILTER(CHOOSE({1,2,3,4,5,6}, $Q$130, $Q$131, $Q$133, $Q$134, $Q$139, $Q$140), CHOOSE({1,2,3,4,5,6}, $E$130, $E$131, $E$133, $E$134, $E$139, $E$140) >= $F$36)), MAX(_xlfn._xlws.FILTER(CHOOSE({1,2,3,4,5,6}, $R$130, $R$131, $R$133, $R$134, $R$139, $R$140), CHOOSE({1,2,3,4,5,6}, $E$130, $E$131, $E$133, $E$134, $E$139, $E$140) >= $F$36)) ), IF(RoundDown=FALSE, MAX(_xlfn._xlws.FILTER(CHOOSE({1,2,3,4,5,6}, $Q$130, $Q$131, $Q$133, $Q$134, $Q$139, $Q$140), CHOOSE({1,2,3,4,5,6}, $E$130, $E$131, $E$133, $E$134, $E$139, $E$140) >= $F$36)), MAX(_xlfn._xlws.FILTER(CHOOSE({1,2,3,4,5,6}, $R$130, $R$131, $R$133, $R$134, $R$139, $R$140), CHOOSE({1,2,3,4,5,6}, $E$130, $E$131, $E$133, $E$134, $E$139, $E$140) >= $F$36)) ) ), IF(OR($H$70="Residential BTL", $H$70="Retention"), IF(RoundDown=FALSE, _xlfn.MAXIFS($Q$130:$Q$141, $E$130:$E$141, ">="&$F$36), _xlfn.MAXIFS($R$130:$R$141, $E$130:$E$141, ">="&$F$36) ), IF(RoundDown=FALSE, _xlfn.MAXIFS($Q$130:$Q$141, $E$130:$E$141, ">="&$Y$36), _xlfn.MAXIFS($R$130:$R$141, $E$130:$E$141, ">="&$Y$36) ) ) )} -> 0 | H70: ='BTL Calculator'!V3 -> 0
C71: Max Net Loan: | D71: =NetLoanUsed -> #N/A | E71: =AL108 -> #N/A | F71: =AL126 -> #N/A | G71: =AL144 -> #N/A
C72: Round Down? | D72: FALSE | H72: ='BTL Calculator'!V5 -> 0 | L72: =+'BTL Calculator'!X3 -> 0.75 | AO72: Top Slice Calcs
U73: ='Product Data'!I3 -> 0.005
D74: Product_Num | E74: Tier | F74: Tier Name | G74: Standard Rate | H74: Standard Rate | I74: Product fee | J74: Deferred Interest | K74: Rolled months | L74: Pay Rate / Rate to apply | M74: Max LTV | N74: Max loan /LTV CAP | O74: Max Loan @ ICR | P74: Max Loan @ Stress tested ICR | Q74: Max Loan (capped/ used) | R74: Max Loan used - Rounded down | S74: Total Interest Due For Max Loan @ full rate | T74: Monthly Int £ @ Standard rate | U74: ="Monthly Int £ @ pay rate if BBR goes up by "&TEXT(U73,"#.#0%") -> Monthly Int £ @ pay rate if BBR goes up by .50% | V74: Monthly Int £ @ pay rate | W74: ICR | X74: ICR (Tracker with Stressed BBR) | Y74: Monthly Int DD | Z74: Total Interest Paid in Term | AA74: Stressed Interest Paid in Term | AB74: Rent Earned Over Term | AC74: Monthly shortfall or surplus from rent | AD74: Deferred Int Owed | AE74: Rolled Months Owed | AF74: Deferred Int Owed at redmptn | AG74: Investor Funds | AH74: Product fee % | AI74: Standard Product Fee (Max 2%) | AJ74: Enhanced Product Fee (>2%) | AK74: Prod Fee Text | AL74: Net Loan | AM74: Net loan LTV | AN74: Max loan LTV | AO74: Rent with Top slice | AP74: SC & C Rent & Top Slice | AQ74: Top Slice in term | AR74: Bespoke Row? | AS74: MAX GROSS | AT74: MAX NET
A75: BTL PRODUCT FEE 2%
B76: =IF(AND('BTL Calculator'!$G$60=C85,F76='BTL Calculator'!$G$62,'BTL Calculator'!$V$2="Core"),1,IF(AND('BTL Calculator'!$G$60=C76,F76='BTL Calculator'!$G$62),1,0)) -> 0 | C76: Basic Loan | D76: 1 | E76: =VALUE(LEFT(F76,1)) -> 0 | F76: =IF($H$70='Product Data'!$BT2,'Product Data'!$B9,IF($H$70='Product Data'!$BT5,'Product Data'!$B190,IF($H$70='Product Data'!BT3,'Product Data'!B34,IF(H70='Product Data'!BT4,'Product Data'!B47,0)))) -> 0 | G76: =IF(AND($H$70='Product Data'!$BT$5,$H$72='Product Data'!$CA$5,L72=0.75),'Product Data'!C190,IF(AND($H$70='Product Data'!$BT$5,$H$72='Product Data'!$CA$5,L72=0.65),'Product Data'!C212, IF(AND($H$70='Product Data'!$BT$5,$H$72='Product Data'!$CA$4,L72=0.75),'Product Data'!G190,IF(AND($H$70='Product Data'!$BT$5,$H$72='Product Data'!$CA$4,L72=0.65),'Product Data'!G212, IF(AND($H$70='Product Data'!$BT$5,$H$72='Product Data'!$CA$3,L72=0.75),'Product Data'!K190,IF(AND($H$70='Product Data'!$BT$5,$H$72='Product Data'!$CA$3,L72=0.65),'Product Data'!K212, IF(AND($H$70='Product Data'!$BT$5,$H$72='Product Data'!$CA$2,L72=0.75),'Product Data'!O190,IF(AND($H$70='Product Data'!$BT$5,$H$72='Product Data'!$CA$2,L72=0.65),'Product Data'!O212, IF(AND($H$70='Product Data'!$BT$4,$H$72='Product Data'!$CA$4),'Product Data'!C124,IF(AND($H$70='Product Data'!$BT$4,$H$72='Product Data'!$CA$3),'Product Data'!C111,IF(AND($H$70='Product Data'!$BT$4,$H$72='Product Data'!$CA$2),'Product Data'!C47,IF(AND($H$70='Product Data'!$BT$2,$H$72='Product Data'!$CA$4),'Product Data'!C85,IF(AND($H$70='Product Data'!$BT$2,$H$72='Product Data'!$CA$3),'Product Data'!C60,IF(AND($H$70='Product Data'!$BT$2,$H$72='Product Data'!$CA$2),'Product Data'!C9,IF(AND($H$70='Product Data'!$BT$3,$H$72='Product Data'!$CA$4),'Product Data'!C150,IF(AND($H$70='Product Data'!$BT$3,$H$72='Product Data'!$CA$3),'Product Data'!C137,IF(AND($H$70='Product Data'!$BT$3,$H$72='Product Data'!$CA$2),'Product Data'!C34, IF(AND($H$70='Product Data'!$BT$2,$H$72='Product Data'!$CA$5),'Product Data'!C164)))))))))))))))))) -> FALSE | H76: =IF(AND(F76=Product_Selected,Rate_Override<>0, Rate_Override<>""),Rate_Override+G76,G76) -> FALSE | I76: =IF(H70= "Retention ", IF('BTL Calculator'!$H$33<>"",1.5%-'BTL Calculator'!$H$33,1.5%),IF('BTL Calculator'!$H$33<>"",2%-'BTL Calculator'!$H$33,2%)) -> 0.02 | L76: =IFERROR(H76-J76,"-") -> 0 | M76: =IF(AND(H70="Retention ",L72=0.65),0.65, IF(AND(H70="Retention ",L72=0.75),0.75, IF(OR($H$70="Residential BTL",$H$70="Retention "),INDEX($O$36:$R$36,MATCH(D76,$O$38:$R$38,0)),70%))) -> 0.7 | N76: =MIN(M76*Property_Value,'Product Data'!$P$16) -> 0 | O76: =IF(AND(OR(OR($H$70="Residential BTL",$H$70="Retention "),$H$70="Retention "),Rate_Type="Fixed"),IFERROR(AO76/(IF(AND('BTL Calculator'!V2="Core",L76<0.055),0.055,$L76)/12*(Term-$K76)*'Product Data'!$P$23),0), IF(AND(Rate_Type="Tracker",OR(OR($H$70="Residential BTL",$H$70="Retention "),$H$70="Retention ")),IFERROR(AO76/(IF(AND('BTL Calculator'!V2="Core",L76-BBR+'Product Data'!K2<0.055),0.055,$L76)/12*(Term-$K76)*'Product Data'!$P$17),0), IF(AND($H$70="Semi-Commercial",Rate_Type="Tracker"),IFERROR(AP76/($L76/12*(Term-$K76)*'Product Data'!$P$17),0), IF(AND($H$70="Semi-Commercial",Rate_Type="Fixed"),IFERROR(AP76/($L76/12*(Term-$K76)*'Product Data'!$P$23),0), IF(AND($H$70="Commercial",Rate_Type="Tracker"),IFERROR(AP76/($L76/12*(Term-$K76)*'Product Data'!$P$17),0), IF(AND($H$70="Commercial",Rate_Type="Fixed"),IFERROR(AP76/($L76/12*(Term-$K76)*'Product Data'!$P$23),0))))))) -> FALSE | P76: =IF('BTL Calculator'!$H$28="Fixed","",IF(OR(OR($H$70="Residential BTL",$H$70="Retention "),$H$70="Retention "),AO76/((((IF(AND('BTL Calculator'!$V$2="Core",H76-'Product Data'!$E$3+'Product Data'!$K$2-J76<0.055),0.055,H76-'Product Data'!$E$3+'Product Data'!$K$3-J76))/12*(Term-K76)))*'Product Data'!$P$18),AP76/(((((H76-'Product Data'!$E$3+'Product Data'!$K$2-J76))/12*(Term-K76)))*'Product Data'!$P$18))) | Q76: =IF('BTL Calculator'!$H$28="Tracker",MIN(N76,P76),MIN(O76,N76)) -> 0 | R76: =ROUNDDOWN(Q76,-3) -> 0 | S76: =IFERROR((IF(RoundDown,R76,Q76)*J76/12*Term)+ (IF(RoundDown,R76,Q76)*L76/12*K76)+ (IF(RoundDown,R76,Q76)*L76/12*(Term-K76)),"-") -> 0 | T76: =IFERROR(((H76)*IF(RoundDown,R76,Q76)/12),"-") -> 0 | U76: =IF('BTL Calculator'!$H$28="Fixed","",(((L76+$U$73)*IF(RoundDown,R76,Q76)/12))) | V76: =IFERROR(((L76)*IF(RoundDown,R76,Q76)/12),"-") -> 0 | W76: =IF(OR($H$70="Residential BTL",$H$70="Retention "),IFERROR(AO76/Z76,"-"),IFERROR(AP76/Z76,"-")) -> - | X76: =IF('BTL Calculator'!$H$28="Fixed","",IF(OR($H$70="Residential BTL",$H$70="Retention "),IFERROR(AO76/AA76,"-"),IFERROR(AP76/AA76,"-"))) | Y76: =TEXT(V76,"£0,0")&" @ "&TEXT(W76,"0%")&" ICR" -> £00 @ - ICR | Z76: =(IF(RoundDown,R76,Q76)*L76)/12*(Term-K76) -> 0 | AA76: =IF('BTL Calculator'!$H$28="Fixed","",(IF(RoundDown,R76,Q76)*(IF(AND('BTL Calculator'!$V$2="Core",H76-BBR+'Product Data'!$K$2<0.055),0.055,H76-'Product Data'!$E$3+'Product Data'!$K$2-J76)))/12*(Term-K76)) | AB76: =IFERROR(Monthly_Rent*Term,"-") -> 0 | AC76: =IFERROR($U$22-V76,"-") -> 0 | AD76: =((J76*IF(RoundDown,R76,Q76))/12)*Term -> 0 | AE76: =K76*IF(AND('BTL Calculator'!$V$2="Core",L76<0.055),0.055,L76)/12*IF(RoundDown,R76,Q76) -> 0 | AF76: =SUM(AD76:AE76) -> 0 | AG76: =IF(RoundDown,R76,Q76)-AF76 -> 0 | AH76: =IF(RoundDown,R76,Q76)*I76 -> 0 | AK76: =TEXT(I76,"0.00%")&" ("&TEXT(AH76,"£0,0")&")" -> 2.00% (£00) | AL76: =AG76-AH76 -> 0 | AM76: =AL76/Property_Value -> #DIV/0! | AN76: =IF(RoundDown,R76,Q76)/Property_Value -> #DIV/0! | AO76: =Rent_Over_Term+AQ76 -> 0 | AP76: =IF($H$72="3 Year Fixed",$X$22*36+AQ76, $X$22*24+AQ76) -> 0 | AQ76: ='BTL Calculator'!$L$80*Term -> 0 | AR76: =IF(ISERROR(FIND("Bespoke",F76,1)),FALSE,TRUE) -> FALSE | AS76: =IFERROR(IF(AND(IF(RoundDown,R76,Q76)=MaxGrossLoan,E76>=$F$36),1,0),"-") -> 0 | AT76: =IFERROR(IF(AND(AL76=MaxNetLoan,E76>=$F$36),1,0),"-") -> - | AU76: =SUM(AS76:AT76) -> 0 | AV76: =IF(IF(Rate_Type="Tracker",X76,W76)>'Product Data'!$P$19,"Y","N") -> Y
B77: =IF(AND('BTL Calculator'!$G$60=C85,F77='BTL Calculator'!$G$62,'BTL Calculator'!$V$2="Core"),1,IF(AND('BTL Calculator'!$G$60=C76,F77='BTL Calculator'!$G$62),1,0)) -> 0 | D77: 2 | E77: =VALUE(LEFT(F77,1)) -> 0 | F77: =IF($H$70='Product Data'!$BT5,'Product Data'!$B191,IF($H$70='Product Data'!$BT2,'Product Data'!$B10,IF($H$70='Product Data'!BT3,'Product Data'!B35,IF(H70='Product Data'!BT4,'Product Data'!B48,0)))) -> 0 | G77: =IF(AND($H$70='Product Data'!$BT$5,$H$72='Product Data'!$CA$5,L72=0.75),'Product Data'!C191,IF(AND($H$70='Product Data'!$BT$5,$H$72='Product Data'!$CA$5,L72=0.65),'Product Data'!C213, IF(AND($H$70='Product Data'!$BT$5,$H$72='Product Data'!$CA$4,L72=0.75),'Product Data'!G191,IF(AND($H$70='Product Data'!$BT$5,$H$72='Product Data'!$CA$4,L72=0.65),'Product Data'!G213, IF(AND($H$70='Product Data'!$BT$5,$H$72='Product Data'!$CA$3,L72=0.75),'Product Data'!K191,IF(AND($H$70='Product Data'!$BT$5,$H$72='Product Data'!$CA$3,L72=0.65),'Product Data'!K213, IF(AND($H$70='Product Data'!$BT$5,$H$72='Product Data'!$CA$2,L72=0.75),'Product Data'!O191,IF(AND($H$70='Product Data'!$BT$5,$H$72='Product Data'!$CA$2,L72=0.65),'Product Data'!O213, IF(AND($H$70='Product Data'!$BT$4,$H$72='Product Data'!$CA$4),'Product Data'!C125,IF(AND($H$70='Product Data'!$BT$4,$H$72='Product Data'!$CA$3),'Product Data'!C112,IF(AND($H$70='Product Data'!$BT$4,$H$72='Product Data'!$CA$2),'Product Data'!C48,IF(AND($H$70='Product Data'!$BT$2,$H$72='Product Data'!$CA$4),'Product Data'!C86,IF(AND($H$70='Product Data'!$BT$2,$H$72='Product Data'!$CA$3),'Product Data'!C61,IF(AND($H$70='Product Data'!$BT$2,$H$72='Product Data'!$CA$2),'Product Data'!C10,IF(AND($H$70='Product Data'!$BT$3,$H$72='Product Data'!$CA$4),'Product Data'!C151,IF(AND($H$70='Product Data'!$BT$3,$H$72='Product Data'!$CA$3),'Product Data'!C138,IF(AND($H$70='Product Data'!$BT$3,$H$72='Product Data'!$CA$2),'Product Data'!C35,IF(AND($H$70='Product Data'!$BT$2,$H$72='Product Data'!$CA$5),'Product Data'!C165)))))))))))))))))) -> FALSE | H77: =IF(AND(F77=Product_Selected,Rate_Override<>0, Rate_Override<>""),Rate_Override+G77,G77) -> FALSE | I77: =IF(H70= "Retention ", IF('BTL Calculator'!$H$33<>"",1.5%-'BTL Calculator'!$H$33,1.5%),IF('BTL Calculator'!$H$33<>"",2%-'BTL Calculator'!$H$33,2%)) -> 0.02 | L77: =H77-J77 -> 0 | M77: =IF(AND(H70="Retention ",L72=0.65),0.65, IF(AND(H70="Retention ",L72=0.75),0.75, IF(OR($H$70="Residential BTL",$H$70="Retention "),INDEX($O$36:$R$36,MATCH(D77,$O$38:$R$38,0)),70%))) -> 0.7 | N77: =MIN(M77*Property_Value,'Product Data'!$P$16) -> 0 | O77: =IF(AND(OR(OR($H$70="Residential BTL",$H$70="Retention "),$H$70="Retention "),Rate_Type="Fixed"),IFERROR(AO77/(IF(AND('BTL Calculator'!V2="Core",L77<0.055),0.055,$L77)/12*(Term-$K77)*'Product Data'!$P$23),0), IF(AND(Rate_Type="Tracker",OR(OR($H$70="Residential BTL",$H$70="Retention "),$H$70="Retention ")),IFERROR(AO77/(IF(AND('BTL Calculator'!V2="Core",L77-BBR+'Product Data'!K2<0.055),0.055,$L77)/12*(Term-$K77)*'Product Data'!$P$17),0), IF(AND($H$70="Semi-Commercial",Rate_Type="Tracker"),IFERROR(AP77/($L77/12*(Term-$K77)*'Product Data'!$P$17),0), IF(AND($H$70="Semi-Commercial",Rate_Type="Fixed"),IFERROR(AP77/($L77/12*(Term-$K77)*'Product Data'!$P$23),0), IF(AND($H$70="Commercial",Rate_Type="Tracker"),IFERROR(AP77/($L77/12*(Term-$K77)*'Product Data'!$P$17),0), IF(AND($H$70="Commercial",Rate_Type="Fixed"),IFERROR(AP77/($L77/12*(Term-$K77)*'Product Data'!$P$23),0))))))) -> FALSE | P77: =IF('BTL Calculator'!$H$28="Fixed","",IF(OR(OR($H$70="Residential BTL",$H$70="Retention "),$H$70="Retention "),AO77/((((IF(AND('BTL Calculator'!$V$2="Core",H77-'Product Data'!$E$3+'Product Data'!$K$2-J77<0.055),0.055,H77-'Product Data'!$E$3+'Product Data'!$K$2-J77))/12*(Term-K77)))*'Product Data'!$P$18),AP77/(((((H77-'Product Data'!$E$3+'Product Data'!$K$2-J77))/12*(Term-K77)))*'Product Data'!$P$18))) | Q77: =IF('BTL Calculator'!$H$28="Tracker",MIN(N77,P77),MIN(O77,N77)) -> 0 | R77: =ROUNDDOWN(Q77,-3) -> 0 | S77: =IFERROR((IF(RoundDown,R77,Q77)*J77/12*Term)+ (IF(RoundDown,R77,Q77)*L77/12*K77)+ (IF(RoundDown,R77,Q77)*L77/12*(Term-K77)),"-") -> 0 | T77: =IFERROR(((H77)*IF(RoundDown,R77,Q77)/12),"-") -> 0 | U77: =IF('BTL Calculator'!$H$28="Fixed","",(((L77+$U$73)*IF(RoundDown,R77,Q77)/12))) | V77: =IFERROR(((L77)*IF(RoundDown,R77,Q77)/12),"-") -> 0 | W77: =IF(OR($H$70="Residential BTL",$H$70="Retention "),IFERROR(AO77/Z77,"-"),IFERROR(AP77/Z77,"-")) -> - | X77: =IF('BTL Calculator'!$H$28="Fixed","",IF(OR($H$70="Residential BTL",$H$70="Retention "),IFERROR(AO77/AA77,"-"),IFERROR(AP77/AA77,"-"))) | Y77: =TEXT(V77,"£0,0")&" @ "&TEXT(W77,"0%")&" ICR" -> £00 @ - ICR | Z77: =(IF(RoundDown,R77,Q77)*L77)/12*(Term-K77) -> 0 | AA77: =IF('BTL Calculator'!$H$28="Fixed","",(IF(RoundDown,R77,Q77)*(IF(AND('BTL Calculator'!$V$2="Core",H77-BBR+'Product Data'!$K$2<0.055),0.055,H77-'Product Data'!$E$3+'Product Data'!$K$2-J77)))/12*(Term-K77)) | AB77: =IFERROR(Monthly_Rent*Term,"-") -> 0 | AC77: =IFERROR($U$22-V77,"-") -> 0 | AD77: =((J77*IF(RoundDown,R77,Q77))/12)*Term -> 0 | AE77: =K77*IF(AND('BTL Calculator'!$V$2="Core",L77<0.055),0.055,L77)/12*IF(RoundDown,R77,Q77) -> 0 | AF77: =SUM(AD77:AE77) -> 0 | AG77: =IF(RoundDown,R77,Q77)-AF77 -> 0 | AH77: =IF(RoundDown,R77,Q77)*I77 -> 0 | AK77: =TEXT(I77,"0.00%")&" ("&TEXT(AH77,"£0,0")&")" -> 2.00% (£00) | AL77: =AG77-AH77 -> 0 | AM77: =AL77/Property_Value -> #DIV/0! | AN77: =IF(RoundDown,R77,Q77)/Property_Value -> #DIV/0! | AO77: =Rent_Over_Term+AQ77 -> 0 | AP77: =IF($H$72="3 Year Fixed",$X$22*36+AQ77, $X$22*24+AQ77) -> 0 | AQ77: ='BTL Calculator'!$L$80*Term -> 0 | AR77: =IF(ISERROR(FIND("Bespoke",F77,1)),FALSE,TRUE) -> FALSE | AS77: =IFERROR(IF(AND(IF(RoundDown,R77,Q77)=MaxGrossLoan,E77>=$F$36),1,0),"-") -> 0 | AT77: =IFERROR(IF(AND(AL77=MaxNetLoan,E77>=$F$36),1,0),"-") -> - | AU77: =SUM(AS77:AT77) -> 0 | AV77: =IF(IF(Rate_Type="Tracker",X77,W77)>'Product Data'!$P$19,"Y","N") -> Y
B78: =IF(OR(OR($H$70="Residential BTL",$H$70="Retention "),$H$70="Retention "),IF(AND('BTL Calculator'!$G$60=C76,F78='BTL Calculator'!$G$62),1,0),"") | D78: =IF(OR(OR($H$70="Residential BTL",$H$70="Retention "),$H$70="Retention "),3,"") | E78: =IF(OR(OR($H$70="Residential BTL",$H$70="Retention "),$H$70="Retention "),VALUE(LEFT(F78,1)),"") | F78: =IF(OR(OR($H$70="Residential BTL",$H$70="Retention "),$H$70="Retention "),"3) Specialist BTL","") | G78: =IF(AND($H$70='Product Data'!$BT$5,$H$72='Product Data'!$CA$5,L72=0.75),'Product Data'!C192,IF(AND($H$70='Product Data'!$BT$5,$H$72='Product Data'!$CA$5,L72=0.65),'Product Data'!C214, IF(AND($H$70='Product Data'!$BT$5,$H$72='Product Data'!$CA$4,L72=0.75),'Product Data'!G192,IF(AND($H$70='Product Data'!$BT$5,$H$72='Product Data'!$CA$4,L72=0.65),'Product Data'!G214, IF(AND($H$70='Product Data'!$BT$5,$H$72='Product Data'!$CA$3,L72=0.75),'Product Data'!K192,IF(AND($H$70='Product Data'!$BT$5,$H$72='Product Data'!$CA$3,L72=0.65),'Product Data'!K214, IF(AND($H$70='Product Data'!$BT$5,$H$72='Product Data'!$CA$2,L72=0.75),'Product Data'!O192,IF(AND($H$70='Product Data'!$BT$5,$H$72='Product Data'!$CA$2,L72=0.65),'Product Data'!O214, IF(H70="Residential BTL",IF(H72='Product Data'!CA2,'Product Data'!C11,IF(H72='Product Data'!CA3,'Product Data'!C62,IF(H72='Product Data'!CA4,'Product Data'!C87,IF(H72='Product Data'!CA5,'Product Data'!C166)))),""))))))))) | H78: =IF(AND(F78=Product_Selected,Rate_Override<>0, Rate_Override<>""),Rate_Override+G78,G78) | I78: =IF(H70= "Retention ", IF('BTL Calculator'!$H$33<>"",1.5%-'BTL Calculator'!$H$33,1.5%),IF('BTL Calculator'!$H$33<>"",2%-'BTL Calculator'!$H$33,2%)) -> 0.02 | L78: =IF('BTL Calculator'!V2 = "Core","",(IF(OR(OR($H$70="Residential BTL",$H$70="Retention "),$H$70="Retention "),H78-J78,""))) | M78: =IF(AND(H70="Retention ",L72=0.65),0.65, IF(AND(H70="Retention ",L72=0.75),0.75, IF(OR($H$70="Residential BTL",$H$70="Retention "),INDEX($O$36:$R$36,MATCH(D78,$O$38:$R$38,0)),""))) | N78: =IF(OR(OR($H$70="Residential BTL",$H$70="Retention "),$H$70="Retention "),MIN(M78*Property_Value,'Product Data'!$P$16),"") | O78: =IF(AND(OR(OR($H$70="Residential BTL",$H$70="Retention "),$H$70="Retention "),Rate_Type="Fixed"),IFERROR(AO78/($L78/12*(Term-$K78)*'Product Data'!$P$23),0),IF(AND(Rate_Type="Tracker",OR(OR($H$70="Residential BTL",$H$70="Retention "),$H$70="Retention ")),IFERROR(AO78/($L78/12*(Term-$K78)*'Product Data'!$P$17),0),IF(AND($H$70="Semi-Commercial",Rate_Type="Tracker"),IFERROR(AP78/($L78/12*(Term-$K78)*'Product Data'!$P$17),0),IF(AND($H$70="Semi-Commercial",Rate_Type="Fixed"),IFERROR(AP78/($L78/12*(Term-$K78)*'Product Data'!$P$23),0),IF(AND($H$70="Commercial",Rate_Type="Tracker"),IFERROR(AP78/($L78/12*(Term-$K78)*'Product Data'!$P$17),0),IF(AND($H$70="Commercial",Rate_Type="Fixed"),IFERROR(AP78/($L78/12*(Term-$K78)*'Product Data'!$P$23),0))))))) -> FALSE | P78: =IF('BTL Calculator'!$H$28="Fixed","",IF(OR(OR($H$70="Residential BTL",$H$70="Retention "),$H$70="Retention "),AO78/((((IF(AND('BTL Calculator'!$V$2="Core",H78-'Product Data'!$E$3+'Product Data'!$K$2-J78<0.055),0.055,H78-'Product Data'!$E$3+'Product Data'!$K$2-J78))/12*(Term-K78)))*'Product Data'!$P$18),AP78/(((((H78-'Product Data'!$E$3+'Product Data'!$K$2-J78))/12*(Term-K78)))*'Product Data'!$P$18))) | Q78: =IF(OR($H$70="Residential BTL",$H$70="Retention "),IF('BTL Calculator'!$H$28="Tracker",MIN(N78,P78),MIN(O78,N78)),"") | R78: =IF(OR($H$70="Residential BTL",$H$70="Retention "),ROUNDDOWN(Q78,-3),"") | S78: =IFERROR((IF(RoundDown,R78,Q78)*J78/12*Term)+ (IF(RoundDown,R78,Q78)*L78/12*K78)+ (IF(RoundDown,R78,Q78)*L78/12*(Term-K78)),"-") -> - | T78: =IF('BTL Calculator'!$V$2="Core","",IF(OR($H$70="Residential BTL",$H$70="Retention "),((H78*IF(RoundDown,R78,Q78)/12)),"")) | U78: =IF('BTL Calculator'!$H$28="Fixed","",(((L78+$U$73)*IF(RoundDown,R78,Q78)/12))) | V78: =IF('BTL Calculator'!$V$2="Core","",IF(OR($H$70="Residential BTL",$H$70="Retention "),((L78*IF(RoundDown,R78,Q78)/12)),"")) | W78: =IF(OR($H$70="Residential BTL",$H$70="Retention "),IFERROR(AO78/Z78,"-"),"") | X78: =IF('BTL Calculator'!$H$28="Fixed","",IF(OR($H$70="Residential BTL",$H$70="Retention "),IFERROR(AO78/AA78,"-"),IFERROR(AP78/AA78,"-"))) | Y78: =IF('BTL Calculator'!V2="Core","",IF(OR($H$70="Residential BTL",$H$70="Retention "),TEXT(V78,"£0,0")&" @ "&TEXT(W78,"0%")&" ICR","")) | Z78: =IF('BTL Calculator'!$V$2="Core","",IF(OR($H$70="Residential BTL",$H$70="Retention "),(IF(RoundDown,R78,Q78)*L78)/12*(Term-K78),"")) | AA78: =IF('BTL Calculator'!$H$28="Fixed","",(IF(RoundDown,R78,Q78)*(H78-'Product Data'!$E$3+'Product Data'!$K$2-J78))/12*(Term-K78)) | AB78: =IF(OR($H$70="Residential BTL",$H$70="Retention "),IFERROR(Monthly_Rent*Term,"-"),"") | AC78: =IF(OR($H$70="Residential BTL",$H$70="Retention "),IFERROR($U$22-V78,"-"),"") | AD78: =((J78*IF(RoundDown,R78,Q78))/12)*Term -> #VALUE! | AE78: =IF('BTL Calculator'!$V$2="Core","",K78*L78/12*IF(RoundDown,R78,Q78)) -> #VALUE! | AF78: =IF(OR($H$70="Residential BTL",$H$70="Retention "),SUM(AD78:AE78),"") | AG78: =IF(OR($H$70="Residential BTL",$H$70="Retention "),IF(RoundDown,R78,Q78)-AF78,"") | AH78: =IF(OR($H$70="Residential BTL",$H$70="Retention "),IF(RoundDown,R78,Q78)*I78,"") | AK78: =IF(OR($H$70="Residential BTL",$H$70="Retention "),TEXT(I78,"0.00%")&" ("&TEXT(AH78,"£0,0")&")","") | AL78: =IF(OR($H$70="Residential BTL",$H$70="Retention "),AG78-AH78,"") | AM78: =IF(OR($H$70="Residential BTL",$H$70="Retention "),AL78/Property_Value,"") | AN78: =IF(OR($H$70="Residential BTL",$H$70="Retention "),IF(RoundDown,R78,Q78)/Property_Value,"") | AO78: =IF(OR($H$70="Residential BTL",$H$70="Retention "),Rent_Over_Term+AQ78,"") | AQ78: =IF(OR($H$70="Residential BTL",$H$70="Retention "),'BTL Calculator'!$L$80*Term,"") | AR78: =IF(OR($H$70="Residential BTL",$H$70="Retention "),IF(ISERROR(FIND("Bespoke",F78,1)),FALSE,TRUE),"") | AS78: =IF(OR($H$70="Residential BTL",$H$70="Retention "),IFERROR(IF(AND(IF(RoundDown,R78,Q78)=MaxGrossLoan,E78>=$F$36),1,0),"-"),"") | AT78: =IF(OR($H$70="Residential BTL",$H$70="Retention "),IFERROR(IF(AND(AL78=MaxNetLoan,E78>=$F$36),1,0),"-"),"") | AU78: =IF(OR($H$70="Residential BTL",$H$70="Retention "),SUM(AS78:AT78),"") | AV78: =IF(OR($H$70="Residential BTL",$H$70="Retention "),IF(IF(Rate_Type="Tracker",X78,W78)>'Product Data'!$P$19,"Y","N"),"")
B79: =IF(AND('BTL Calculator'!$G$60=C79,F79='BTL Calculator'!$G$62),1,0) -> 0 | C79: Use Max Rolled and Deferred | D79: 5 | E79: =VALUE(LEFT(F79,1)) -> 0 | F79: =IF($H$70='Product Data'!$BT5,'Product Data'!$B190,IF($H$70='Product Data'!$BT2,'Product Data'!$B9,IF($H$70='Product Data'!BT3,'Product Data'!B34,IF(H70='Product Data'!BT4,'Product Data'!B47,0)))) -> 0 | H79: =H76 -> FALSE | I79: =I76 -> 0.02 | J79: =IF(AND(H70="Retention ",H72="Tracker"),2%,IF(AND($H$70='Product Data'!$BT$2,$H$72='Product Data'!$CA$2),2%,IF(AND($H$70='Product Data'!$BT$3,$H$72='Product Data'!$CA$2),1.5%,IF(AND($H$70='Product Data'!$BT$4,$H$72='Product Data'!$CA$2),1.5%,IF(AND($H$70='Product Data'!$BT$2,$H$72='Product Data'!$CA$5),0.75%,1.25%))))) -> 0.0125 | K79: =IF(OR(OR($H$70="Residential BTL",$H$70="Retention "),$H$70="Retention "),IF(Term<36,'Product Data'!$P$11,'Product Data'!$P$13),6) -> 6 | L79: =IFERROR(H79-J79,"-") -> -0.0125 | M79: =M76 -> 0.7 | N79: =MIN(M79*Property_Value,'Product Data'!$P$16) -> 0 | O79: =IF(AND(OR(OR($H$70="Residential BTL",$H$70="Retention "),$H$70="Retention "),Rate_Type="Fixed"),IFERROR(AO79/($L79/12*(Term-$K79)*'Product Data'!$P$23),0),IF(AND(Rate_Type="Tracker",OR(OR($H$70="Residential BTL",$H$70="Retention "),$H$70="Retention ")),IFERROR(AO79/($L79/12*(Term-$K79)*'Product Data'!$P$17),0),IF(AND($H$70="Semi-Commercial",Rate_Type="Tracker"),IFERROR(AP79/($L79/12*(Term-$K79)*'Product Data'!$P$17),0),IF(AND($H$70="Semi-Commercial",Rate_Type="Fixed"),IFERROR(AP79/($L79/12*(Term-$K79)*'Product Data'!$P$23),0),IF(AND($H$70="Commercial",Rate_Type="Tracker"),IFERROR(AP79/($L79/12*(Term-$K79)*'Product Data'!$P$17),0),IF(AND($H$70="Commercial",Rate_Type="Fixed"),IFERROR(AP79/($L79/12*(Term-$K79)*'Product Data'!$P$23),0))))))) -> FALSE | P79: =IF('BTL Calculator'!$H$28="Fixed","",IF(OR(OR($H$70="Residential BTL",$H$70="Retention "),$H$70="Retention "),AO79/((((H79-'Product Data'!$E$3+'Product Data'!$K$2-J79)/12*(Term-K79)))*'Product Data'!$P$18),AP79/(((((H79-'Product Data'!$E$3+'Product Data'!$K$2-J79)/12*(Term-K79)))*'Product Data'!$P$18)))) | Q79: =IF('BTL Calculator'!$H$28="Tracker",MIN(N79,P79),MIN(O79,N79)) -> 0 | R79: =ROUNDDOWN(Q79,-3) -> 0 | S79: =IFERROR((IF(RoundDown,R79,Q79)*J79/12*Term)+ (IF(RoundDown,R79,Q79)*L79/12*K79)+ (IF(RoundDown,R79,Q79)*L79/12*(Term-K79)),"-") -> 0 | T79: =IFERROR(((H79*IF(RoundDown,R79,Q79)/12)),"-") -> 0 | U79: =IF('BTL Calculator'!$H$28="Fixed","",(((L79+$U$73)*IF(RoundDown,R79,Q79)/12))) | V79: =IFERROR(((L79*IF(RoundDown,R79,Q79)/12)),"-") -> 0 | W79: =IF(OR($H$70="Residential BTL",$H$70="Retention "),IFERROR(AO79/Z79,"-"),IFERROR(AP79/Z79,"-")) -> - | X79: =IF('BTL Calculator'!$H$28="Fixed","",IF(OR($H$70="Residential BTL",$H$70="Retention "),IFERROR(AO79/AA79,"-"),IFERROR(AP79/AA79,"-"))) | Y79: =TEXT(V79,"£0,0")&" @ "&TEXT(W79,"0%")&" ICR" -> £00 @ - ICR | Z79: =(IF(RoundDown,R79,Q79)*L79)/12*(Term-K79) -> 0 | AA79: =IF('BTL Calculator'!$H$28="Fixed","",(IF(RoundDown,R79,Q79)*(H79-'Product Data'!$E$3+'Product Data'!$K$2-J79))/12*(Term-K79)) | AB79: =IFERROR(Monthly_Rent*Term,"-") -> 0 | AC79: =IFERROR($U$22-V79,"-") -> 0 | AD79: =((J79*IF(RoundDown,R79,Q79))/12)*Term -> 0 | AE79: =K79*L79/12*IF(RoundDown,R79,Q79) -> 0 | AF79: =SUM(AD79:AE79) -> 0 | AG79: =IF(RoundDown,R79,Q79)-AF79 -> 0 | AH79: =IF(RoundDown,R79,Q79)*I79 -> 0 | AK79: =TEXT(I79,"0.00%")&" ("&TEXT(AH79,"£0,0")&")" -> 2.00% (£00) | AL79: =AG79-AH79 -> 0 | AM79: =AL79/Property_Value -> #DIV/0! | AN79: =IF(RoundDown,R79,Q79)/Property_Value -> #DIV/0! | AO79: =Rent_Over_Term+AQ79 -> 0 | AP79: =IF($H$72="3 Year Fixed",$X$22*36+AQ79, $X$22*24+AQ79) -> 0 | AQ79: ='BTL Calculator'!$L$80*Term -> 0 | AR79: =IF(ISERROR(FIND("Bespoke",F79,1)),FALSE,TRUE) -> FALSE | AS79: =IFERROR(IF(AND(IF(RoundDown,R79,Q79)=MaxGrossLoan,E79>=$F$36),1,0),"-") -> 0 | AT79: =IFERROR(IF(AND(AL79=MaxNetLoan,E79>=$F$36),1,0),"-") -> - | AU79: =SUM(AS79:AT79) -> 0 | AV79: =IF(IF(Rate_Type="Tracker",X79,W79)>'Product Data'!$P$19,"Y","N") -> Y
B80: =IF(AND('BTL Calculator'!$G$60=C79,F80='BTL Calculator'!$G$62),1,0) -> 0 | D80: 6 | E80: =VALUE(LEFT(F80,1)) -> 0 | F80: =IF($H$70='Product Data'!$BT5,'Product Data'!$B191,IF($H$70='Product Data'!$BT2,'Product Data'!$B10,IF($H$70='Product Data'!BT3,'Product Data'!B35,IF(H70='Product Data'!BT4,'Product Data'!B48,0)))) -> 0 | H80: =H77 -> FALSE | I80: =I77 -> 0.02 | J80: =IF(AND(H70="Retention ",H72="Tracker"),2%,IF(AND($H$70='Product Data'!$BT$2,$H$72='Product Data'!$CA$2),2%,IF(AND($H$70='Product Data'!$BT$3,$H$72='Product Data'!$CA$2),1.5%,IF(AND($H$70='Product Data'!$BT$4,$H$72='Product Data'!$CA$2),1.5%,IF(AND($H$70='Product Data'!$BT$2,$H$72='Product Data'!$CA$5),0.75%,1.25%))))) -> 0.0125 | K80: =IF(OR(OR($H$70="Residential BTL",$H$70="Retention "),$H$70="Retention "),IF(Term<36,'Product Data'!$P$11,'Product Data'!$P$13),6) -> 6 | L80: =H80-J80 -> -0.0125 | M80: =M77 -> 0.7 | N80: =MIN(M80*Property_Value,'Product Data'!$P$16) -> 0 | O80: =IF(AND(OR(OR($H$70="Residential BTL",$H$70="Retention "),$H$70="Retention "),Rate_Type="Fixed"),IFERROR(AO80/($L80/12*(Term-$K80)*'Product Data'!$P$23),0),IF(AND(Rate_Type="Tracker",OR(OR($H$70="Residential BTL",$H$70="Retention "),$H$70="Retention ")),IFERROR(AO80/($L80/12*(Term-$K80)*'Product Data'!$P$17),0),IF(AND($H$70="Semi-Commercial",Rate_Type="Tracker"),IFERROR(AP80/($L80/12*(Term-$K80)*'Product Data'!$P$17),0),IF(AND($H$70="Semi-Commercial",Rate_Type="Fixed"),IFERROR(AP80/($L80/12*(Term-$K80)*'Product Data'!$P$23),0),IF(AND($H$70="Commercial",Rate_Type="Tracker"),IFERROR(AP80/($L80/12*(Term-$K80)*'Product Data'!$P$17),0),IF(AND($H$70="Commercial",Rate_Type="Fixed"),IFERROR(AP80/($L80/12*(Term-$K80)*'Product Data'!$P$23),0))))))) -> FALSE | P80: =IF('BTL Calculator'!$H$28="Fixed","",IF(OR(OR($H$70="Residential BTL",$H$70="Retention "),$H$70="Retention "),AO80/((((H80-'Product Data'!$E$3+'Product Data'!$K$2-J80)/12*(Term-K80)))*'Product Data'!$P$18),AP80/(((((H80-'Product Data'!$E$3+'Product Data'!$K$2-J80)/12*(Term-K80)))*'Product Data'!$P$18)))) | Q80: =IF('BTL Calculator'!$H$28="Tracker",MIN(N80,P80),MIN(O80,N80)) -> 0 | R80: =ROUNDDOWN(Q80,-3) -> 0 | S80: =IFERROR((IF(RoundDown,R80,Q80)*J80/12*Term)+ (IF(RoundDown,R80,Q80)*L80/12*K80)+ (IF(RoundDown,R80,Q80)*L80/12*(Term-K80)),"-") -> 0 | T80: =IFERROR(((H80*IF(RoundDown,R80,Q80)/12)),"-") -> 0 | U80: =IF('BTL Calculator'!$H$28="Fixed","",(((L80+$U$73)*IF(RoundDown,R80,Q80)/12))) | V80: =((L80*IF(RoundDown,R80,Q80)/12))-IF('BTL Calculator'!$CY$11='Product Data'!$AG$9,AE80/Term,0) -> 0 | W80: =IF(OR($H$70="Residential BTL",$H$70="Retention "),IFERROR(AO80/Z80,"-"),IFERROR(AP80/Z80,"-")) -> - | X80: =IF('BTL Calculator'!$H$28="Fixed","",IF(OR($H$70="Residential BTL",$H$70="Retention "),IFERROR(AO80/AA80,"-"),IFERROR(AP80/AA80,"-"))) | Y80: =TEXT(V80,"£0,0")&" @ "&TEXT(W80,"0%")&" ICR" -> £00 @ - ICR | Z80: =(IF(RoundDown,R80,Q80)*L80)/12*(Term-K80) -> 0 | AA80: =IF('BTL Calculator'!$H$28="Fixed","",(IF(RoundDown,R80,Q80)*(H80-'Product Data'!$E$3+'Product Data'!$K$2-J80))/12*(Term-K80)) | AB80: =IFERROR(Monthly_Rent*Term,"-") -> 0 | AC80: =IFERROR($U$22-V80,"-") -> 0 | AD80: =((J80*IF(RoundDown,R80,Q80))/12)*Term -> 0 | AE80: =K80*L80/12*IF(RoundDown,R80,Q80) -> 0 | AF80: =SUM(AD80:AE80) -> 0 | AG80: =IF(RoundDown,R80,Q80)-AF80 -> 0 | AH80: =IF(RoundDown,R80,Q80)*I80 -> 0 | AK80: =TEXT(I80,"0.00%")&" ("&TEXT(AH80,"£0,0")&")" -> 2.00% (£00) | AL80: =AG80-AH80 -> 0 | AM80: =AL80/Property_Value -> #DIV/0! | AN80: =IF(RoundDown,R80,Q80)/Property_Value -> #DIV/0! | AO80: =Rent_Over_Term+AQ80 -> 0 | AP80: =IF($H$72="3 Year Fixed",$X$22*36+AQ80, $X$22*24+AQ80) -> 0 | AQ80: ='BTL Calculator'!$L$80*Term -> 0 | AR80: =IF(ISERROR(FIND("Bespoke",F80,1)),FALSE,TRUE) -> FALSE | AS80: =IFERROR(IF(AND(IF(RoundDown,R80,Q80)=MaxGrossLoan,E80>=$F$36),1,0),"-") -> 0 | AT80: =IFERROR(IF(AND(AL80=MaxNetLoan,E80>=$F$36),1,0),"-") -> - | AU80: =SUM(AS80:AT80) -> 0 | AV80: =IF(IF(Rate_Type="Tracker",X80,W80)>'Product Data'!$P$19,"Y","N") -> Y
B81: =IF(OR(OR($H$70="Residential BTL",$H$70="Retention "),$H$70="Retention "),IF(AND('BTL Calculator'!$G$60=C79,F81='BTL Calculator'!$G$62),1,0),"") | D81: =IF(OR(OR($H$70="Residential BTL",$H$70="Retention "),$H$70="Retention "),7,"") | E81: =IF(OR(OR($H$70="Residential BTL",$H$70="Retention "),$H$70="Retention "),VALUE(LEFT(F81,1)),"") | F81: =IF(OR(OR($H$70="Residential BTL",$H$70="Retention "),$H$70="Retention "),"3) Specialist BTL","") | H81: =H78 | I81: =I78 -> 0.02 | J81: =IF(AND(H70="Retention ",H72="Tracker"),2%,IF(AND($H$70='Product Data'!$BT$2,$H$72='Product Data'!$CA$2),2%,IF(AND($H$70='Product Data'!$BT$3,$H$72='Product Data'!$CA$2),1.5%,IF(AND($H$70='Product Data'!$BT$4,$H$72='Product Data'!$CA$2),1.5%,IF(AND($H$70='Product Data'!$BT$2,$H$72='Product Data'!$CA$5),0.75%,1.25%))))) -> 0.0125 | K81: =IF(OR(OR($H$70="Residential BTL",$H$70="Retention "),$H$70="Retention "),IF(Term<36,'Product Data'!$P$11,'Product Data'!$P$13),"") | L81: =IF('BTL Calculator'!V2="Core","",IF(OR(OR($H$70="Residential BTL",$H$70="Retention "),$H$70="Retention "),H81-J81,"")) | M81: =M78 | N81: =IF(OR(OR($H$70="Residential BTL",$H$70="Retention "),$H$70="Retention "),MIN(M81*Property_Value,'Product Data'!$P$16),"") | O81: =IF(AND(OR(OR($H$70="Residential BTL",$H$70="Retention "),$H$70="Retention "),Rate_Type="Fixed"),IFERROR(AO81/($L81/12*(Term-$K81)*'Product Data'!$P$23),0),IF(AND(Rate_Type="Tracker",OR(OR($H$70="Residential BTL",$H$70="Retention "),$H$70="Retention ")),IFERROR(AO81/($L81/12*(Term-$K81)*'Product Data'!$P$17),0),IF(AND($H$70="Semi-Commercial",Rate_Type="Tracker"),IFERROR(AP81/($L81/12*(Term-$K81)*'Product Data'!$P$17),0),IF(AND($H$70="Semi-Commercial",Rate_Type="Fixed"),IFERROR(AP81/($L81/12*(Term-$K81)*'Product Data'!$P$23),0),IF(AND($H$70="Commercial",Rate_Type="Tracker"),IFERROR(AP81/($L81/12*(Term-$K81)*'Product Data'!$P$17),0),IF(AND($H$70="Commercial",Rate_Type="Fixed"),IFERROR(AP81/($L81/12*(Term-$K81)*'Product Data'!$P$23),0))))))) -> FALSE | P81: =IF('BTL Calculator'!$H$28="Fixed","",IF(OR(OR($H$70="Residential BTL",$H$70="Retention "),$H$70="Retention "),AO81/((((H81-'Product Data'!$E$3+'Product Data'!$K$2-J81)/12*(Term-K81)))*'Product Data'!$P$18),AP81/((((H81-'Product Data'!$E$3+'Product Data'!$K$2-J81)/12*(Term-K81)))*'Product Data'!$P$18))) | Q81: =IF(OR($H$70="Residential BTL",$H$70="Retention "),IF('BTL Calculator'!$H$28="Tracker",MIN(N81,P81),MIN(O81,N81)),"") | R81: =IF(OR($H$70="Residential BTL",$H$70="Retention "),ROUNDDOWN(Q81,-3),"") | S81: =IFERROR((IF(RoundDown,R81,Q81)*J81/12*Term)+ (IF(RoundDown,R81,Q81)*L81/12*K81)+ (IF(RoundDown,R81,Q81)*L81/12*(Term-K81)),"-") -> - | T81: =IFERROR(((H81*IF(RoundDown,R81,Q81)/12)),"-") -> - | U81: =IF('BTL Calculator'!$H$28="Fixed","",(((L81+$U$73)*IF(RoundDown,R81,Q81)/12))) | V81: =IF('BTL Calculator'!$V$2="Core","",IF(OR($H$70="Residential BTL",$H$70="Retention "),((L81*IF(RoundDown,R81,Q81)/12))-IF('BTL Calculator'!$CY$11='Product Data'!$AG$9,AE81/Term,0),"")) | W81: =IF(OR($H$70="Residential BTL",$H$70="Retention "),IFERROR(AO81/Z81,"-"),"") | X81: =IF('BTL Calculator'!$H$28="Fixed","",IF(OR($H$70="Residential BTL",$H$70="Retention "),IFERROR(AO81/AA81,"-"),IFERROR(AP81/AA81,"-"))) | Y81: =IF('BTL Calculator'!V2="Core","",IF(OR($H$70="Residential BTL",$H$70="Retention "),TEXT(V81,"£0,0")&" @ "&TEXT(W81,"0%")&" ICR","")) | Z81: =IF('BTL Calculator'!$V$2="Core","",IF(OR($H$70="Residential BTL",$H$70="Retention "),(IF(RoundDown,R81,Q81)*L81)/12*(Term-K81),"")) | AA81: =IF('BTL Calculator'!$H$28="Fixed","",(IF(RoundDown,R81,Q81)*(H81-'Product Data'!$E$3+'Product Data'!$K$2-J81))/12*(Term-K81)) | AB81: =IF(OR($H$70="Residential BTL",$H$70="Retention "),IFERROR(Monthly_Rent*Term,"-"),"") | AC81: =IF(OR($H$70="Residential BTL",$H$70="Retention "),IFERROR($U$22-V81,"-"),"") | AD81: =((J81*IF(RoundDown,R81,Q81))/12)*Term -> #VALUE! | AE81: =IF('BTL Calculator'!$V$2="Core","",K81*L81/12*IF(RoundDown,R81,Q81)) -> #VALUE! | AF81: =IF(OR($H$70="Residential BTL",$H$70="Retention "),SUM(AD81:AE81),"") | AG81: =IF(OR($H$70="Residential BTL",$H$70="Retention "),IF(RoundDown,R81,Q81)-AF81,"") | AH81: =IF(OR($H$70="Residential BTL",$H$70="Retention "),IF(RoundDown,R81,Q81)*I81,"") | AK81: =IF(OR($H$70="Residential BTL",$H$70="Retention "),TEXT(I81,"0.00%")&" ("&TEXT(AH81,"£0,0")&")","") | AL81: =IF(OR($H$70="Residential BTL",$H$70="Retention "),AG81-AH81,"") | AM81: =IF(OR($H$70="Residential BTL",$H$70="Retention "),AL81/Property_Value,"") | AN81: =IF(OR($H$70="Residential BTL",$H$70="Retention "),IF(RoundDown,R81,Q81)/Property_Value,"") | AO81: =IF(OR($H$70="Residential BTL",$H$70="Retention "),Rent_Over_Term+AQ81,"") | AQ81: =IF(OR($H$70="Residential BTL",$H$70="Retention "),'BTL Calculator'!$L$80*Term,"") | AR81: =IF(OR($H$70="Residential BTL",$H$70="Retention "),IF(ISERROR(FIND("Bespoke",F81,1)),FALSE,TRUE),"") | AS81: =IF(OR($H$70="Residential BTL",$H$70="Retention "),IFERROR(IF(AND(IF(RoundDown,R81,Q81)=MaxGrossLoan,E81>=$F$36),1,0),"-"),"") | AT81: =IF(OR($H$70="Residential BTL",$H$70="Retention "),IFERROR(IF(AND(AL81=MaxNetLoan,E81>=$F$36),1,0),"-"),"") | AU81: =IF(OR($H$70="Residential BTL",$H$70="Retention "),SUM(AS81:AT81),"") | AV81: =IF(OR($H$70="Residential BTL",$H$70="Retention "),IF(IF(Rate_Type="Tracker",X81,W81)>'Product Data'!$P$19,"Y","N"),"")
B82: =IF(AND('BTL Calculator'!$G$60=C82,F82='BTL Calculator'!$G$62),1,0) -> 0 | C82: Fully Rolled and Deferred underwriter | D82: 9 | E82: =VALUE(LEFT(F82,1)) -> 1 | F82: 1) Standard BTL | H82: =H79 -> FALSE | I82: =I79 -> 0.02 | J82: ='Product Data'!$P$10 -> 0.02 | K82: =IF(Term<36,'Product Data'!$P$12,'Product Data'!$P$14) -> 9 | L82: =IFERROR(H82-J82,"-") -> -0.02 | M82: =M79 -> 0.7 | N82: =MIN(M82*Property_Value,'Product Data'!$P$16) -> 0 | O82: =IF(AND(OR($H$70="Residential BTL",$H$70="Retention "),Rate_Type="Fixed"),IFERROR(AO82/($L82/12*(Term-$K82)*'Product Data'!$P$23),0),IF(AND(Rate_Type="Tracker",OR($H$70="Residential BTL",$H$70="Retention ")),IFERROR(AO82/($L82/12*(Term-$K82)*'Product Data'!$P$17),0),IF(AND($H$70="Semi-Commercial",Rate_Type="Tracker"),IFERROR(AP82/($L82/12*(Term-$K82)*'Product Data'!$P$17),0),IF(AND($H$70="Semi-Commercial",Rate_Type="Fixed"),IFERROR(AP82/($L82/12*(Term-$K82)*'Product Data'!$P$23),0),IF(AND($H$70="Commercial",Rate_Type="Tracker"),IFERROR(AP82/($L82/12*(Term-$K82)*'Product Data'!$P$17),0),IF(AND($H$70="Commercial",Rate_Type="Fixed"),IFERROR(AP82/($L82/12*(Term-$K82)*'Product Data'!$P$23),0))))))) -> FALSE | P82: =IF('BTL Calculator'!$H$28="Fixed","",IF(OR(OR($H$70="Residential BTL",$H$70="Retention "),$H$70="Retention "),AO82/((((IF(AND('BTL Calculator'!$V$2="Core",H82-'Product Data'!$E$3+'Product Data'!$K$2-J82<0.055),0.055,H82-'Product Data'!$E$3+'Product Data'!$K$2-J82))/12*(Term-K82)))*'Product Data'!$P$18),AP82/((((IF(AND('BTL Calculator'!$V$2="Core",H82-'Product Data'!$E$3+'Product Data'!$K$2-J82<0.055),0.055,H82-'Product Data'!$E$3+'Product Data'!$K$2-J82))/12*(Term-K82)))*'Product Data'!$P$18))) | Q82: =IF('BTL Calculator'!$H$28="Tracker",MIN(N82,P82),MIN(O82,N82)) -> 0 | R82: =ROUNDDOWN(Q82,-3) -> 0 | S82: =IFERROR((IF(RoundDown,R82,Q82)*J82/12*Term)+ (IF(RoundDown,R82,Q82)*L82/12*K82)+ (IF(RoundDown,R82,Q82)*L82/12*(Term-K82)),"-") -> 0 | T82: =IFERROR(((H82*IF(RoundDown,R82,Q82)/12)),"-") -> 0 | U82: =IF('BTL Calculator'!$H$28="Fixed","",(((L82+$U$73)*IF(RoundDown,R82,Q82)/12))) | V82: =IFERROR(((L82*IF(RoundDown,R82,Q82)/12)),"-") -> 0 | W82: =IFERROR(AO82/Z82,"-") -> - | X82: =IF('BTL Calculator'!$H$28="Fixed","",IF(OR($H$70="Residential BTL",$H$70="Retention "),IFERROR(AO82/AA82,"-"),IFERROR(AP82/AA82,"-"))) | Y82: =TEXT(V82,"£0,0")&" @ "&TEXT(W82,"0%")&" ICR" -> £00 @ - ICR | Z82: =(IF(RoundDown,R82,Q82)*L82)/12*(Term-K82) -> 0 | AA82: =IF('BTL Calculator'!$H$28="Fixed","",(IF(RoundDown,R82,Q82)*(H82-'Product Data'!$E$3+'Product Data'!$K$2-J82))/12*(Term-K82)) | AB82: =IFERROR(Monthly_Rent*Term,"-") -> 0 | AC82: =IFERROR($U$22-V82,"-") -> 0 | AD82: =((J82*IF(RoundDown,R82,Q82))/12)*Term -> 0 | AE82: =K82*L82/12*IF(RoundDown,R82,Q82) -> 0 | AF82: =SUM(AD82:AE82) -> 0 | AG82: =IF(RoundDown,R82,Q82)-AF82 -> 0 | AH82: =IF(RoundDown,R82,Q82)*I82 -> 0 | AK82: =TEXT(I82,"0.00%")&" ("&TEXT(AH82,"£0,0")&")" -> 2.00% (£00) | AL82: =AG82-AH82 -> 0 | AM82: =AL82/Property_Value -> #DIV/0! | AN82: =IF(RoundDown,R82,Q82)/Property_Value -> #DIV/0! | AO82: =Rent_Over_Term+AQ82 -> 0 | AQ82: ='BTL Calculator'!$L$80*Term -> 0 | AR82: =IF(ISERROR(FIND("Bespoke",F82,1)),FALSE,TRUE) -> FALSE | AS82: =IFERROR(IF(AND(IF(RoundDown,R82,Q82)=MaxGrossLoan,E82>=$F$36),1,0),"-") -> 1 | AT82: =IFERROR(IF(AND(AL82=MaxNetLoan,E82>=$F$36),1,0),"-") -> - | AU82: =SUM(AS82:AT82) -> 1 | AV82: =IF(IF(Rate_Type="Tracker",X82,W82)>'Product Data'!$P$19,"Y","N") -> Y
B83: =IF(AND('BTL Calculator'!$G$60=C82,F83='BTL Calculator'!$G$62),1,0) -> 0 | D83: 10 | E83: =VALUE(LEFT(F83,1)) -> 2 | F83: 2) Solutions BTL | H83: =H80 -> FALSE | I83: =I80 -> 0.02 | J83: ='Product Data'!$P$10 -> 0.02 | K83: =IF(Term<36,'Product Data'!$P$12,'Product Data'!$P$14) -> 9 | L83: =H83-J83 -> -0.02 | M83: =M80 -> 0.7 | N83: =MIN(M83*Property_Value,'Product Data'!$P$16) -> 0 | O83: =IF(AND(OR($H$70="Residential BTL",$H$70="Retention "),Rate_Type="Fixed"),IFERROR(AO83/($L83/12*(Term-$K83)*'Product Data'!$P$23),0),IF(AND(Rate_Type="Tracker",OR($H$70="Residential BTL",$H$70="Retention ")),IFERROR(AO83/($L83/12*(Term-$K83)*'Product Data'!$P$17),0),IF(AND($H$70="Semi-Commercial",Rate_Type="Tracker"),IFERROR(AP83/($L83/12*(Term-$K83)*'Product Data'!$P$17),0),IF(AND($H$70="Semi-Commercial",Rate_Type="Fixed"),IFERROR(AP83/($L83/12*(Term-$K83)*'Product Data'!$P$23),0),IF(AND($H$70="Commercial",Rate_Type="Tracker"),IFERROR(AP83/($L83/12*(Term-$K83)*'Product Data'!$P$17),0),IF(AND($H$70="Commercial",Rate_Type="Fixed"),IFERROR(AP83/($L83/12*(Term-$K83)*'Product Data'!$P$23),0))))))) -> FALSE | P83: =IF('BTL Calculator'!$H$28="Fixed","",IF(OR(OR($H$70="Residential BTL",$H$70="Retention "),$H$70="Retention "),AO83/((((IF(AND('BTL Calculator'!$V$2="Core",H83-'Product Data'!$E$3+'Product Data'!$K$2-J83<0.055),0.055,H83-'Product Data'!$E$3+'Product Data'!$K$2-J83))/12*(Term-K83)))*'Product Data'!$P$18),AP83/((((IF(AND('BTL Calculator'!$V$2="Core",H83-'Product Data'!$E$3+'Product Data'!$K$2-J83<0.055),0.055,H83-'Product Data'!$E$3+'Product Data'!$K$2-J83))/12*(Term-K83)))*'Product Data'!$P$18))) | Q83: =IF('BTL Calculator'!$H$28="Tracker",MIN(N83,P83),MIN(O83,N83)) -> 0 | R83: =ROUNDDOWN(Q83,-3) -> 0 | S83: =IFERROR((IF(RoundDown,R83,Q83)*J83/12*Term)+ (IF(RoundDown,R83,Q83)*L83/12*K83)+ (IF(RoundDown,R83,Q83)*L83/12*(Term-K83)),"-") -> 0 | T83: =((H83*IF(RoundDown,R83,Q83)/12)) -> 0 | U83: =IF('BTL Calculator'!$H$28="Fixed","",(((L83+$U$73)*IF(RoundDown,R83,Q83)/12))) | V83: =((L83*IF(RoundDown,R83,Q83)/12))-IF('BTL Calculator'!$CY$11='Product Data'!$AG$9,AE83/Term,0) -> 0 | W83: =IFERROR(AO83/Z83,"-") -> - | X83: =IF('BTL Calculator'!$H$28="Fixed","",IF(OR($H$70="Residential BTL",$H$70="Retention "),IFERROR(AO83/AA83,"-"),IFERROR(AP83/AA83,"-"))) | Y83: =TEXT(V83,"£0,0")&" @ "&TEXT(W83,"0%")&" ICR" -> £00 @ - ICR | Z83: =(IF(RoundDown,R83,Q83)*L83)/12*(Term-K83) -> 0 | AA83: =IF('BTL Calculator'!$H$28="Fixed","",(IF(RoundDown,R83,Q83)*(H83-'Product Data'!$E$3+'Product Data'!$K$2-J83))/12*(Term-K83)) | AB83: =IFERROR(Monthly_Rent*Term,"-") -> 0 | AC83: =IFERROR($U$22-V83,"-") -> 0 | AD83: =((J83*IF(RoundDown,R83,Q83))/12)*Term -> 0 | AE83: =K83*L83/12*IF(RoundDown,R83,Q83) -> 0 | AF83: =SUM(AD83:AE83) -> 0 | AG83: =IF(RoundDown,R83,Q83)-AF83 -> 0 | AH83: =IF(RoundDown,R83,Q83)*I83 -> 0 | AK83: =TEXT(I83,"0.00%")&" ("&TEXT(AH83,"£0,0")&")" -> 2.00% (£00) | AL83: =AG83-AH83 -> 0 | AM83: =AL83/Property_Value -> #DIV/0! | AN83: =IF(RoundDown,R83,Q83)/Property_Value -> #DIV/0! | AO83: =Rent_Over_Term+AQ83 -> 0 | AQ83: ='BTL Calculator'!$L$80*Term -> 0 | AR83: =IF(ISERROR(FIND("Bespoke",F83,1)),FALSE,TRUE) -> FALSE | AS83: =IFERROR(IF(AND(IF(RoundDown,R83,Q83)=MaxGrossLoan,E83>=$F$36),1,0),"-") -> 1 | AT83: =IFERROR(IF(AND(AL83=MaxNetLoan,E83>=$F$36),1,0),"-") -> - | AU83: =SUM(AS83:AT83) -> 1 | AV83: =IF(IF(Rate_Type="Tracker",X83,W83)>'Product Data'!$P$19,"Y","N") -> Y
B84: =IF(OR($H$70="Residential BTL",$H$70="Retention "),IF(AND('BTL Calculator'!$G$60=C82,F84='BTL Calculator'!$G$62),1,0),"") | D84: =IF(OR($H$70="Residential BTL",$H$70="Retention "),11,"") | E84: =IF(OR($H$70="Residential BTL",$H$70="Retention "),VALUE(LEFT(F84,1)),"") | F84: =IF(OR($H$70="Residential BTL",$H$70="Retention "),"3) Specialist BTL","") | H84: =H81 | I84: =I81 -> 0.02 | J84: =IF(OR($H$70="Residential BTL",$H$70="Retention "),'Product Data'!$P$10,"") | K84: =IF(OR($H$70="Residential BTL",$H$70="Retention "),IF(Term<36,'Product Data'!$P$12,'Product Data'!$P$14),"") | L84: =IF(OR($H$70="Residential BTL",$H$70="Retention "),H84-J84,"") | M84: =M81 | N84: =IF(OR($H$70="Residential BTL",$H$70="Retention "),MIN(M84*Property_Value,'Product Data'!$P$16),"") | O84: =IF(AND(OR($H$70="Residential BTL",$H$70="Retention "),Rate_Type="Fixed"),IFERROR(AO84/($L84/12*(Term-$K84)*'Product Data'!$P$23),0),IF(AND(Rate_Type="Tracker",OR($H$70="Residential BTL",$H$70="Retention ")),IFERROR(AO84/($L84/12*(Term-$K84)*'Product Data'!$P$17),0),IF(AND($H$70="Semi-Commercial",Rate_Type="Tracker"),IFERROR(AP84/($L84/12*(Term-$K84)*'Product Data'!$P$17),0),IF(AND($H$70="Semi-Commercial",Rate_Type="Fixed"),IFERROR(AP84/($L84/12*(Term-$K84)*'Product Data'!$P$23),0),IF(AND($H$70="Commercial",Rate_Type="Tracker"),IFERROR(AP84/($L84/12*(Term-$K84)*'Product Data'!$P$17),0),IF(AND($H$70="Commercial",Rate_Type="Fixed"),IFERROR(AP84/($L84/12*(Term-$K84)*'Product Data'!$P$23),0))))))) -> FALSE | P84: =IF('BTL Calculator'!$H$28="Fixed","",IF(OR(OR($H$70="Residential BTL",$H$70="Retention "),$H$70="Retention "),AO84/((((IF(AND('BTL Calculator'!$V$2="Core",H84-'Product Data'!$E$3+'Product Data'!$K$2-J84<0.055),0.055,H84-'Product Data'!$E$3+'Product Data'!$K$2-J84))/12*(Term-K84)))*'Product Data'!$P$18),AP84/((((IF(AND('BTL Calculator'!$V$2="Core",H84-'Product Data'!$E$3+'Product Data'!$K$2-J84<0.055),0.055,H84-'Product Data'!$E$3+'Product Data'!$K$2-J84))/12*(Term-K84)))*'Product Data'!$P$18))) | Q84: =IF(OR($H$70="Residential BTL",$H$70="Retention "),IF('BTL Calculator'!$H$28="Tracker",MIN(N84,P84),MIN(O84,N84)),"") | R84: =IF(OR($H$70="Residential BTL",$H$70="Retention "),ROUNDDOWN(Q84,-3),"") | S84: =IFERROR((IF(RoundDown,R84,Q84)*J84/12*Term)+ (IF(RoundDown,R84,Q84)*L84/12*K84)+ (IF(RoundDown,R84,Q84)*L84/12*(Term-K84)),"-") -> - | T84: =IF(OR($H$70="Residential BTL",$H$70="Retention "),((H84*IF(RoundDown,R84,Q84)/12)),"") | U84: =IF('BTL Calculator'!$H$28="Fixed","",(((L84+$U$73)*IF(RoundDown,R84,Q84)/12))) | V84: =IF(OR($H$70="Residential BTL",$H$70="Retention "),((L84*IF(RoundDown,R84,Q84)/12))-IF('BTL Calculator'!$CY$11='Product Data'!$AG$9,AE84/Term,0),"") | W84: =IF(OR($H$70="Residential BTL",$H$70="Retention "),IFERROR(AO84/Z84,"-"),"") | X84: =IF('BTL Calculator'!$H$28="Fixed","",IF(OR($H$70="Residential BTL",$H$70="Retention "),IFERROR(AO84/AA84,"-"),IFERROR(AP84/AA84,"-"))) | Y84: =IF(OR($H$70="Residential BTL",$H$70="Retention "),TEXT(V84,"£0,0")&" @ "&TEXT(W84,"0%")&" ICR","") | Z84: =IF(OR($H$70="Residential BTL",$H$70="Retention "),(IF(RoundDown,R84,Q84)*L84)/12*(Term-K84),"") | AA84: =IF('BTL Calculator'!$H$28="Fixed","",(IF(RoundDown,R84,Q84)*(H84-'Product Data'!$E$3+'Product Data'!$K$2-J84))/12*(Term-K84)) | AB84: =IF(OR($H$70="Residential BTL",$H$70="Retention "),IFERROR(Monthly_Rent*Term,"-"),"") | AC84: =IF(OR($H$70="Residential BTL",$H$70="Retention "),IFERROR($U$22-V84,"-"),"") | AD84: =((J84*IF(RoundDown,R84,Q84))/12)*Term -> #VALUE! | AE84: =K84*L84/12*IF(RoundDown,R84,Q84) -> #VALUE! | AF84: =IF(OR($H$70="Residential BTL",$H$70="Retention "),SUM(AD84:AE84),"") | AG84: =IF(OR($H$70="Residential BTL",$H$70="Retention "),IF(RoundDown,R84,Q84)-AF84,"") | AH84: =IF(OR($H$70="Residential BTL",$H$70="Retention "),IF(RoundDown,R84,Q84)*I84,"") | AK84: =IF(OR($H$70="Residential BTL",$H$70="Retention "),TEXT(I84,"0.00%")&" ("&TEXT(AH84,"£0,0")&")","") | AL84: =IF(OR($H$70="Residential BTL",$H$70="Retention "),IF(OR($H$70="Residential BTL",$H$70="Retention "),AG84-AH84,""),"") | AM84: =IF(OR($H$70="Residential BTL",$H$70="Retention "),IF(OR($H$70="Residential BTL",$H$70="Retention "),AL84/Property_Value,""),"") | AN84: =IF(OR($H$70="Residential BTL",$H$70="Retention "),IF(OR($H$70="Residential BTL",$H$70="Retention "),IF(RoundDown,R84,Q84)/Property_Value,""),"") | AO84: =IF(OR($H$70="Residential BTL",$H$70="Retention "),Rent_Over_Term+AQ84,"") | AQ84: =IF(OR($H$70="Residential BTL",$H$70="Retention "),'BTL Calculator'!$L$80*Term,"") | AR84: =IF(OR($H$70="Residential BTL",$H$70="Retention "),IF(ISERROR(FIND("Bespoke",F84,1)),FALSE,TRUE),"") | AS84: =IF(OR($H$70="Residential BTL",$H$70="Retention "),IFERROR(IF(AND(IF(RoundDown,R84,Q84)=MaxGrossLoan,E84>=$F$36),1,0),"-"),"") | AT84: =IF(OR($H$70="Residential BTL",$H$70="Retention "),IFERROR(IF(AND(AL84=MaxNetLoan,E84>=$F$36),1,0),"-"),"") | AU84: =IF(OR($H$70="Residential BTL",$H$70="Retention "),SUM(AS84:AT84),"") | AV84: =IF(OR($H$70="Residential BTL",$H$70="Retention "),IF(IF(Rate_Type="Tracker",X84,W84)>'Product Data'!$P$19,"Y","N"),"")
B85: =IF('BTL Calculator'!$V$2="Core",0,IF(AND('BTL Calculator'!$G$60=C85,F85='BTL Calculator'!$G$62),1,0)) -> 0 | C85: Custom - adjust roll/defer/top slice | D85: 13 | E85: =VALUE(LEFT(F85,1)) -> 0 | F85: =IF($H$70='Product Data'!$BT5,'Product Data'!$B190,IF($H$70='Product Data'!$BT2,'Product Data'!$B9,IF($H$70='Product Data'!BT3,'Product Data'!B34,IF(H70='Product Data'!BT4,'Product Data'!B47,0)))) -> 0 | H85: =H79 -> FALSE | I85: =I79 -> 0.02 | J85: =IF(AND(Rate_Type="Fixed",H72="3 Year Fixed"),IF(Defer2>'Product Data'!$P$24,'Product Data'!$P$24,Defer2),IF(AND(Rate_Type="Fixed",H72="2 Year Fixed"),IF(Defer2>'Product Data'!$P$24,'Product Data'!$P$24,Defer2),IF(AND(Rate_Type="Fixed",H72="5 Year Fixed"),IF(Defer2>'Product Data'!$P$33,'Product Data'!$P$33,Defer2),IF(AND(Rate_Type="Tracker",$H$70="Commercial"),IF(Defer2>0.015,0.015,Defer2),IF(AND(Rate_Type="Tracker",$H$70="Semi-Commercial"),IF(Defer2>0.015,0.015,Defer2),IF(AND(Rate_Type="Tracker",OR($H$70="Residential BTL",$H$70="Retention ")),IF(Defer2>0.02,0.02,Defer2))))))) -> FALSE | K85: =IF(Roll2="",0,IF(OR(OR($H$70="Residential BTL",$H$70="Retention "),$H$70="Retention "),MAX(MIN(Roll2,'Product Data'!$P$12),0),MAX(MIN(Roll2,6),0))) -> 0 | L85: =IFERROR(H85-J85,"-") -> 0 | M85: =M79 -> 0.7 | N85: =MIN(M85*Property_Value,'Product Data'!$P$16) -> 0 | O85: =IF(AND(OR(OR($H$70="Residential BTL",$H$70="Retention "),$H$70="Retention "),Rate_Type="Fixed"),IFERROR(AO85/($L85/12*(Term-$K85)*'Product Data'!$P$23),0),IF(AND(Rate_Type="Tracker",OR(OR($H$70="Residential BTL",$H$70="Retention "),$H$70="Retention ")),IFERROR(AO85/($L85/12*(Term-$K85)*'Product Data'!$P$17),0),IF(AND($H$70="Semi-Commercial",Rate_Type="Tracker"),IFERROR(AP85/($L85/12*(Term-$K85)*'Product Data'!$P$17),0),IF(AND($H$70="Semi-Commercial",Rate_Type="Fixed"),IFERROR(AP85/($L85/12*(Term-$K85)*'Product Data'!$P$23),0),IF(AND($H$70="Commercial",Rate_Type="Tracker"),IFERROR(AP85/($L85/12*(Term-$K85)*'Product Data'!$P$17),0),IF(AND($H$70="Commercial",Rate_Type="Fixed"),IFERROR(AP85/($L85/12*(Term-$K85)*'Product Data'!$P$23),0))))))) -> FALSE | P85: =IF('BTL Calculator'!$H$28="Fixed","",IF(OR(OR($H$70="Residential BTL",$H$70="Retention "),$H$70="Retention "),AO85/((((H85-'Product Data'!$E$3+'Product Data'!$K$2-J85)/12*(Term-K85)))*'Product Data'!$P$18),AP85/((((H85-'Product Data'!$E$3+'Product Data'!$K$2-J85)/12*(Term-K85)))*'Product Data'!$P$18))) | Q85: =IF('BTL Calculator'!$H$28="Tracker",MIN(N85,P85),MIN(O85,N85)) -> 0 | R85: =ROUNDDOWN(Q85,-3) -> 0 | S85: =IFERROR((IF(RoundDown,R85,Q85)*J85/12*Term)+ (IF(RoundDown,R85,Q85)*L85/12*K85)+ (IF(RoundDown,R85,Q85)*L85/12*(Term-K85)),"-") -> 0 | T85: =IFERROR(((H85*IF(RoundDown,R85,Q85)/12)),"-") -> 0 | U85: =IF('BTL Calculator'!$H$28="Fixed","",(((L85+$U$73)*IF(RoundDown,R85,Q85)/12))) | V85: =IFERROR(((L85*IF(RoundDown,R85,Q85)/12)),"-") -> 0 | W85: =IF(OR($H$70="Residential BTL",$H$70="Retention "),IFERROR(AO85/Z85,"-"),IFERROR(AP85/Z85,"-")) -> - | X85: =IF('BTL Calculator'!$H$28="Fixed","",IF(OR($H$70="Residential BTL",$H$70="Retention "),IFERROR(AO85/AA85,"-"),IFERROR(AP85/AA85,"-"))) | Y85: =TEXT(V85,"£0,0")&" @ "&TEXT(W85,"0%")&" ICR" -> £00 @ - ICR | Z85: =(IF(RoundDown,R85,Q85)*L85)/12*(Term-K85) -> 0 | AA85: =IF('BTL Calculator'!$H$28="Fixed","",(IF(RoundDown,R85,Q85)*(H85-'Product Data'!$E$3+'Product Data'!$K$2-J85))/12*(Term-K85)) | AB85: =IFERROR(Monthly_Rent*Term,"-") -> 0 | AC85: =IFERROR($U$22-V85,"-") -> 0 | AD85: =((J85*IF(RoundDown,R85,Q85))/12)*Term -> 0 | AE85: =K85*L85/12*IF(RoundDown,R85,Q85) -> 0 | AF85: =SUM(AD85:AE85) -> 0 | AG85: =IF(RoundDown,R85,Q85)-AF85 -> 0 | AH85: =IF(RoundDown,R85,Q85)*I85 -> 0 | AK85: =TEXT(I85,"0.00%")&" ("&TEXT(AH85,"£0,0")&")" -> 2.00% (£00) | AL85: =AG85-AH85 -> 0 | AM85: =AL85/Property_Value -> #DIV/0! | AN85: =IF(RoundDown,R85,Q85)/Property_Value -> #DIV/0! | AO85: =Rent_Over_Term+AQ85 -> 0 | AP85: =IF($H$72="3 Year Fixed",$X$22*36+AQ85, $X$22*24+AQ85) -> 0 | AQ85: ='BTL Calculator'!$L$80*Term -> 0 | AR85: =IF(ISERROR(FIND("Bespoke",F85,1)),FALSE,TRUE) -> FALSE | AS85: =IFERROR(IF(AND(IF(RoundDown,R85,Q85)=MaxGrossLoan,E85>=$F$36),1,0),"-") -> 0 | AT85: =IFERROR(IF(AND(AL85=MaxNetLoan,E85>=$F$36),1,0),"-") -> - | AU85: =SUM(AS85:AT85) -> 0 | AV85: =IF(IF(Rate_Type="Tracker",X85,W85)>'Product Data'!$P$19,"Y","N") -> Y
B86: =IF('BTL Calculator'!$V$2="Core",0,IF(AND('BTL Calculator'!$G$60=C85,F86='BTL Calculator'!$G$62),1,0)) -> 0 | D86: 14 | E86: =VALUE(LEFT(F86,1)) -> 0 | F86: =IF($H$70='Product Data'!$BT5,'Product Data'!$B191,IF($H$70='Product Data'!$BT2,'Product Data'!$B10,IF($H$70='Product Data'!BT3,'Product Data'!B35,IF(H70='Product Data'!BT4,'Product Data'!B48,0)))) -> 0 | H86: =H80 -> FALSE | I86: =I80 -> 0.02 | J86: =IF(AND(Rate_Type="Fixed",H72="3 Year Fixed"),IF(Defer2>'Product Data'!$P$24,'Product Data'!$P$24,Defer2),IF(AND(Rate_Type="Fixed",H72="2 Year Fixed"),IF(Defer2>'Product Data'!$P$24,'Product Data'!$P$24,Defer2),IF(AND(Rate_Type="Fixed",H72="5 Year Fixed"),IF(Defer2>'Product Data'!$P$33,'Product Data'!$P$33,Defer2),IF(AND(Rate_Type="Tracker",$H$70="Commercial"),IF(Defer2>0.015,0.015,Defer2),IF(AND(Rate_Type="Tracker",$H$70="Semi-Commercial"),IF(Defer2>0.015,0.015,Defer2),IF(AND(Rate_Type="Tracker",OR($H$70="Residential BTL",$H$70="Retention ")),IF(Defer2>0.02,0.02,Defer2))))))) -> FALSE | K86: =IF(Roll2="",0,IF(OR(OR($H$70="Residential BTL",$H$70="Retention "),$H$70="Retention "),MAX(MIN(Roll2,'Product Data'!$P$12),0),MAX(MIN(Roll2,6),0))) -> 0 | L86: =H86-J86 -> 0 | M86: =M80 -> 0.7 | N86: =MIN(M86*Property_Value,'Product Data'!$P$16) -> 0 | O86: =IF(AND(OR(OR($H$70="Residential BTL",$H$70="Retention "),$H$70="Retention "),Rate_Type="Fixed"),IFERROR(AO86/($L86/12*(Term-$K86)*'Product Data'!$P$23),0),IF(AND(Rate_Type="Tracker",OR(OR($H$70="Residential BTL",$H$70="Retention "),$H$70="Retention ")),IFERROR(AO86/($L86/12*(Term-$K86)*'Product Data'!$P$17),0),IF(AND($H$70="Semi-Commercial",Rate_Type="Tracker"),IFERROR(AP86/($L86/12*(Term-$K86)*'Product Data'!$P$17),0),IF(AND($H$70="Semi-Commercial",Rate_Type="Fixed"),IFERROR(AP86/($L86/12*(Term-$K86)*'Product Data'!$P$23),0),IF(AND($H$70="Commercial",Rate_Type="Tracker"),IFERROR(AP86/($L86/12*(Term-$K86)*'Product Data'!$P$17),0),IF(AND($H$70="Commercial",Rate_Type="Fixed"),IFERROR(AP86/($L86/12*(Term-$K86)*'Product Data'!$P$23),0))))))) -> FALSE | P86: =IF('BTL Calculator'!$H$28="Fixed","",IF(OR(OR($H$70="Residential BTL",$H$70="Retention "),$H$70="Retention "),AO86/((((H86-'Product Data'!$E$3+'Product Data'!$K$2-J86)/12*(Term-K86)))*'Product Data'!$P$18),AP86/((((H86-'Product Data'!$E$3+'Product Data'!$K$2-J86)/12*(Term-K86)))*'Product Data'!$P$18))) | Q86: =IF('BTL Calculator'!$H$28="Tracker",MIN(N86,P86),MIN(O86,N86)) -> 0 | R86: =ROUNDDOWN(Q86,-3) -> 0 | S86: =IFERROR((IF(RoundDown,R86,Q86)*J86/12*Term)+ (IF(RoundDown,R86,Q86)*L86/12*K86)+ (IF(RoundDown,R86,Q86)*L86/12*(Term-K86)),"-") -> 0 | T86: =((H86*IF(RoundDown,R86,Q86)/12)) -> 0 | U86: =IF('BTL Calculator'!$H$28="Fixed","",(((L86+$U$73)*IF(RoundDown,R86,Q86)/12))) | V86: =((L86*IF(RoundDown,R86,Q86)/12))-IF('BTL Calculator'!$CY$11='Product Data'!$AG$9,AE86/Term,0) -> 0 | W86: =IF(OR($H$70="Residential BTL",$H$70="Retention "),IFERROR(AO86/Z86,"-"),IFERROR(AP86/Z86,"-")) -> - | X86: =IF('BTL Calculator'!$H$28="Fixed","",IF(OR($H$70="Residential BTL",$H$70="Retention "),IFERROR(AO86/AA86,"-"),IFERROR(AP86/AA86,"-"))) | Y86: =TEXT(V86,"£0,0")&" @ "&TEXT(W86,"0%")&" ICR" -> £00 @ - ICR | Z86: =(IF(RoundDown,R86,Q86)*L86)/12*(Term-K86) -> 0 | AA86: =IF('BTL Calculator'!$H$28="Fixed","",(IF(RoundDown,R86,Q86)*(H86-'Product Data'!$E$3+'Product Data'!$K$2-J86))/12*(Term-K86)) | AB86: =IFERROR(Monthly_Rent*Term,"-") -> 0 | AC86: =IFERROR($U$22-V86,"-") -> 0 | AD86: =((J86*IF(RoundDown,R86,Q86))/12)*Term -> 0 | AE86: =K86*L86/12*IF(RoundDown,R86,Q86) -> 0 | AF86: =SUM(AD86:AE86) -> 0 | AG86: =IF(RoundDown,R86,Q86)-AF86 -> 0 | AH86: =IF(RoundDown,R86,Q86)*I86 -> 0 | AK86: =TEXT(I86,"0.00%")&" ("&TEXT(AH86,"£0,0")&")" -> 2.00% (£00) | AL86: =AG86-AH86 -> 0 | AM86: =AL86/Property_Value -> #DIV/0! | AN86: =IF(RoundDown,R86,Q86)/Property_Value -> #DIV/0! | AO86: =Rent_Over_Term+AQ86 -> 0 | AP86: =IF($H$72="3 Year Fixed",$X$22*36+AQ86, $X$22*24+AQ86) -> 0 | AQ86: ='BTL Calculator'!$L$80*Term -> 0 | AR86: =IF(ISERROR(FIND("Bespoke",F86,1)),FALSE,TRUE) -> FALSE | AS86: =IFERROR(IF(AND(IF(RoundDown,R86,Q86)=MaxGrossLoan,E86>=$F$36),1,0),"-") -> 0 | AT86: =IFERROR(IF(AND(AL86=MaxNetLoan,E86>=$F$36),1,0),"-") -> - | AU86: =SUM(AS86:AT86) -> 0 | AV86: =IF(IF(Rate_Type="Tracker",X86,W86)>'Product Data'!$P$19,"Y","N") -> Y
B87: =IF('BTL Calculator'!$V$2="Core",0,IF(OR($H$70="Residential BTL",$H$70="Retention "),IF(AND('BTL Calculator'!$G$60=C85,F87='BTL Calculator'!$G$62),1,0),"")) | D87: =IF(OR(OR($H$70="Residential BTL",$H$70="Retention "),$H$70="Retention "),15,"") | E87: =IF(OR(OR($H$70="Residential BTL",$H$70="Retention "),$H$70="Retention "),VALUE(LEFT(F87,1)),"") | F87: =IF(OR(OR($H$70="Residential BTL",$H$70="Retention "),$H$70="Retention "),"3) Specialist BTL","") | H87: =H81 | I87: =I81 -> 0.02 | J87: =IF(AND(Rate_Type="Fixed",H72="3 Year Fixed"),IF(Defer2>'Product Data'!$P$24,'Product Data'!$P$24,Defer2),IF(AND(Rate_Type="Fixed",H72="2 Year Fixed"),IF(Defer2>'Product Data'!$P$24,'Product Data'!$P$24,Defer2),IF(AND(Rate_Type="Fixed",H72="5 Year Fixed"),IF(Defer2>'Product Data'!$P$33,'Product Data'!$P$33,Defer2),IF(AND(Rate_Type="Tracker",$H$70="Commercial"),IF(Defer2>0.015,0.015,Defer2),IF(AND(Rate_Type="Tracker",$H$70="Semi-Commercial"),IF(Defer2>0.015,0.015,Defer2),IF(AND(Rate_Type="Tracker",OR($H$70="Residential BTL",$H$70="Retention ")),IF(Defer2>0.02,0.02,Defer2))))))) -> FALSE | K87: =IF(OR(OR($H$70="Residential BTL",$H$70="Retention "),$H$70="Retention "),IF(Roll2="",0,IF(OR($H$70="Residential BTL",$H$70="Retention "),MAX(MIN(Roll2,'Product Data'!$P$12),0),"")),"") | L87: =IF('BTL Calculator'!V2="Core","",IF(OR(OR($H$70="Residential BTL",$H$70="Retention "),$H$70="Retention "),H87-J87,"")) | M87: =M81 | N87: =IF(OR(OR($H$70="Residential BTL",$H$70="Retention "),$H$70="Retention "),MIN(M87*Property_Value,'Product Data'!$P$16),"") | O87: =IF(AND(OR(OR($H$70="Residential BTL",$H$70="Retention "),$H$70="Retention "),Rate_Type="Fixed"),IFERROR(AO87/($L87/12*(Term-$K87)*'Product Data'!$P$23),0),IF(AND(Rate_Type="Tracker",OR(OR($H$70="Residential BTL",$H$70="Retention "),$H$70="Retention ")),IFERROR(AO87/($L87/12*(Term-$K87)*'Product Data'!$P$17),0),IF(AND($H$70="Semi-Commercial",Rate_Type="Tracker"),IFERROR(AP87/($L87/12*(Term-$K87)*'Product Data'!$P$17),0),IF(AND($H$70="Semi-Commercial",Rate_Type="Fixed"),IFERROR(AP87/($L87/12*(Term-$K87)*'Product Data'!$P$23),0),IF(AND($H$70="Commercial",Rate_Type="Tracker"),IFERROR(AP87/($L87/12*(Term-$K87)*'Product Data'!$P$17),0),IF(AND($H$70="Commercial",Rate_Type="Fixed"),IFERROR(AP87/($L87/12*(Term-$K87)*'Product Data'!$P$23),0))))))) -> FALSE | P87: =IF('BTL Calculator'!$H$28="Fixed","",IF(OR(OR($H$70="Residential BTL",$H$70="Retention "),$H$70="Retention "),AO87/((((H87-'Product Data'!$E$3+'Product Data'!$K$2-J87)/12*(Term-K87)))*'Product Data'!$P$18),AP87/((((H87-'Product Data'!$E$3+'Product Data'!$K$2-J87)/12*(Term-K87)))*'Product Data'!$P$18))) | Q87: =IF(OR($H$70="Residential BTL",$H$70="Retention "),IF('BTL Calculator'!$H$28="Tracker",MIN(N87,P87),MIN(O87,N87)),"") | R87: =IF(OR($H$70="Residential BTL",$H$70="Retention "),ROUNDDOWN(Q87,-3),"") | S87: =IFERROR((IF(RoundDown,R87,Q87)*J87/12*Term)+ (IF(RoundDown,R87,Q87)*L87/12*K87)+ (IF(RoundDown,R87,Q87)*L87/12*(Term-K87)),"-") -> - | T87: =IFERROR(((H87*IF(RoundDown,R87,Q87)/12)),"-") -> - | U87: =IF('BTL Calculator'!$H$28="Fixed","",(((L87+$U$73)*IF(RoundDown,R87,Q87)/12))) | V87: =IF('BTL Calculator'!$V$2="Core","",IF(OR($H$70="Residential BTL",$H$70="Retention "),((L87*IF(RoundDown,R87,Q87)/12))-IF('BTL Calculator'!$CY$11='Product Data'!$AG$9,AE87/Term,0),"")) | W87: =IF(OR($H$70="Residential BTL",$H$70="Retention "),IFERROR(AO87/Z87,"-"),"") | X87: =IF('BTL Calculator'!$H$28="Fixed","",IF(OR($H$70="Residential BTL",$H$70="Retention "),IFERROR(AO87/AA87,"-"),IFERROR(AP87/AA87,"-"))) | Y87: =IF('BTL Calculator'!V2="Core","",IF(OR($H$70="Residential BTL",$H$70="Retention "),TEXT(V87,"£0,0")&" @ "&TEXT(W87,"0%")&" ICR","")) | Z87: =IF('BTL Calculator'!$V$2="Core","",IF(OR($H$70="Residential BTL",$H$70="Retention "),(IF(RoundDown,R87,Q87)*L87)/12*(Term-K87),"")) | AA87: =IF('BTL Calculator'!$H$28="Fixed","",(IF(RoundDown,R87,Q87)*(H87-'Product Data'!$E$3+'Product Data'!$K$2-J87))/12*(Term-K87)) | AB87: =IF(OR($H$70="Residential BTL",$H$70="Retention "),IFERROR(Monthly_Rent*Term,"-"),"") | AC87: =IF(OR($H$70="Residential BTL",$H$70="Retention "),IFERROR($U$22-V87,"-"),"") | AD87: =((J87*IF(RoundDown,R87,Q87))/12)*Term -> #VALUE! | AE87: =IF('BTL Calculator'!$V$2="Core","",K87*L87/12*IF(RoundDown,R87,Q87)) -> #VALUE! | AF87: =IF(OR($H$70="Residential BTL",$H$70="Retention "),SUM(AD87:AE87),"") | AG87: =IF(OR($H$70="Residential BTL",$H$70="Retention "),IF(RoundDown,R87,Q87)-AF87,"") | AH87: =IF(OR($H$70="Residential BTL",$H$70="Retention "),IF(RoundDown,R87,Q87)*I87,"") | AK87: =IF(OR($H$70="Residential BTL",$H$70="Retention "),TEXT(I87,"0.00%")&" ("&TEXT(AH87,"£0,0")&")","") | AL87: =IF(OR($H$70="Residential BTL",$H$70="Retention "),AG87-AH87,"") | AM87: =IF(OR($H$70="Residential BTL",$H$70="Retention "),AL87/Property_Value,"") | AN87: =IF(OR($H$70="Residential BTL",$H$70="Retention "),IF(RoundDown,R87,Q87)/Property_Value,"") | AO87: =IF(OR($H$70="Residential BTL",$H$70="Retention "),Rent_Over_Term+AQ87,"") | AQ87: =IF(OR($H$70="Residential BTL",$H$70="Retention "),'BTL Calculator'!$L$80*Term,"") | AR87: =IF(OR($H$70="Residential BTL",$H$70="Retention "),IF(ISERROR(FIND("Bespoke",F87,1)),FALSE,TRUE),"") | AS87: =IF(OR($H$70="Residential BTL",$H$70="Retention "),IFERROR(IF(AND(IF(RoundDown,R87,Q87)=MaxGrossLoan,E87>=$F$36),1,0),"-"),"") | AT87: =IF(OR($H$70="Residential BTL",$H$70="Retention "),IFERROR(IF(AND(AL87=MaxNetLoan,E87>=$F$36),1,0),"-"),"") | AU87: =IF(OR($H$70="Residential BTL",$H$70="Retention "),SUM(AS87:AT87),"") | AV87: =IF(OR($H$70="Residential BTL",$H$70="Retention "),IF(IF(Rate_Type="Tracker",X87,W87)>'Product Data'!$P$19,"Y","N"),"")
B88: =IF(AND('BTL Calculator'!$G$60=C88,F88='BTL Calculator'!$G$62),1,0) -> 0 | C88: Specific Gross Loan | D88: 17 | E88: =VALUE(LEFT(F88,1)) -> 1 | F88: ='BTL Calculator'!$G$62 -> 1) Standard | H88: =INDEX(H$76:H$78,MATCH($F$88,$F$76:$F$78,0)) -> #N/A | I88: =INDEX(I$76:I$78,MATCH($F$88,$F$76:$F$78,0)) -> #N/A | J88: =IF('BTL Calculator'!V2="Core",0,IF(AND(Rate_Type="Fixed",H72="3 Year Fixed"),IF(Defer2>'Product Data'!$P$24,'Product Data'!$P$24,Defer2),IF(AND(Rate_Type="Fixed",H72="2 Year Fixed"),IF(Defer2>'Product Data'!$P$24,'Product Data'!$P$24,Defer2),IF(AND(Rate_Type="Fixed",H72="5 Year Fixed"),IF(Defer2>'Product Data'!$P$33,'Product Data'!$P$33,Defer2),IF(AND(Rate_Type="Tracker",$H$70="Commercial"),IF(Defer2>0.015,0.015,Defer2),IF(AND(Rate_Type="Tracker",$H$70="Semi-Commercial"),IF(Defer2>0.015,0.015,Defer2),IF(AND(Rate_Type="Tracker",OR($H$70="Residential BTL",$H$70="Retention ")),IF(Defer2>0.02,0.02,Defer2)))))))) -> FALSE | K88: =IF('BTL Calculator'!V2="Core",0,INDEX(K$85:K$87,MATCH($F$88,$F$85:$F$87,0))) -> #N/A | L88: =IFERROR(H88-J88,"-") -> - | M88: =INDEX(M$76:M$78,MATCH($F$88,$F$76:$F$78,0)) -> #N/A | N88: =MIN(M88*Property_Value,'Product Data'!$P$16) -> #N/A | O88: =IF(AND(OR(OR($H$70="Residential BTL",$H$70="Retention "),$H$70="Retention "),Rate_Type="Fixed"),IFERROR(AO88/(IF(AND('BTL Calculator'!V2="Core",L88<0.055),0.055,$L88)/12*(Term-$K88)*'Product Data'!$P$23),0),IF(AND(Rate_Type="Tracker",OR(OR($H$70="Residential BTL",$H$70="Retention "),$H$70="Retention ")),IFERROR(AO88/(IF(AND('BTL Calculator'!V2="Core",L88-BBR+'Product Data'!K2<0.055),0.055,$L88)/12*(Term-$K88)*'Product Data'!$P$17),0),IF(AND($H$70="Semi-Commercial",Rate_Type="Tracker"),IFERROR(AP88/($L88/12*(Term-$K88)*'Product Data'!$P$17),0),IF(AND($H$70="Semi-Commercial",Rate_Type="Fixed"),IFERROR(AP88/($L88/12*(Term-$K88)*'Product Data'!$P$23),0),IF(AND($H$70="Commercial",Rate_Type="Tracker"),IFERROR(AP88/($L88/12*(Term-$K88)*'Product Data'!$P$17),0),IF(AND($H$70="Commercial",Rate_Type="Fixed"),IFERROR(AP88/($L88/12*(Term-$K88)*'Product Data'!$P$23),0))))))) -> FALSE | P88: =IF('BTL Calculator'!$H$28="Fixed","",IF(OR(OR($H$70="Residential BTL",$H$70="Retention "),$H$70="Retention "),AO88/((((IF(AND('BTL Calculator'!V2="Core",H88-'Product Data'!$E$3+'Product Data'!$K$2-J88<0.055),0.055,H88-'Product Data'!$E$3+'Product Data'!$K$2-J88))/12*(Term-K88)))*'Product Data'!$P$18),AP88/(((((H88-'Product Data'!$E$3+'Product Data'!$K$2-J88))/12*(Term-K88)))*'Product Data'!$P$18))) | Q88: =IF('BTL Calculator'!$H$28="Tracker",MIN(N88,P88,'BTL Calculator'!L83),MIN(O88,N88,'BTL Calculator'!L83)) -> #N/A | R88: =ROUNDDOWN(Q88,-3) -> #N/A | S88: =IFERROR((IF(RoundDown,R88,Q88)*J88/12*Term)+ (IF(RoundDown,R88,Q88)*L88/12*K88)+ (IF(RoundDown,R88,Q88)*L88/12*(Term-K88)),"-") -> - | T88: =IFERROR(((IF(AND('BTL Calculator'!$V$2="Core",H88<0.055),0.055,H88)*IF(RoundDown,R88,Q88)/12)),"-") -> - | U88: =IF('BTL Calculator'!$H$28="Fixed","",(((L88+$U$73)*IF(RoundDown,R88,Q88)/12))) | V88: =IFERROR(((IF(AND('BTL Calculator'!$V$2="Core",L88<0.055),0.055,L88)*IF(RoundDown,R88,Q88)/12)),"-") -> - | W88: =IF(OR($H$70="Residential BTL",$H$70="Retention "),IFERROR(AO88/Z88,"-"),IFERROR(AP88/Z88,"-")) -> - | X88: =IF('BTL Calculator'!$H$28="Fixed","",IF(OR($H$70="Residential BTL",$H$70="Retention "),IFERROR(AO88/AA88,"-"),IFERROR(AP88/AA88,"-"))) | Y88: =TEXT(V88,"£0,0")&" @ "&TEXT(W88,"0%")&" ICR" -> - @ - ICR | Z88: =(IF(RoundDown,R88,Q88)*L88)/12*(Term-K88) -> #N/A | AA88: =IF('BTL Calculator'!$H$28="Fixed","",(IF(RoundDown,R88,Q88)*(IF(AND('BTL Calculator'!$V$2="Core",H88-BBR+'Product Data'!$K$2<0.055),0.055,H88-'Product Data'!$E$3+'Product Data'!$K$2-J88)))/12*(Term-K88)) | AB88: =IFERROR(Monthly_Rent*Term,"-") -> 0 | AC88: =IFERROR($U$22-V88,"-") -> - | AD88: =((J88*IF(RoundDown,R88,Q88))/12)*Term -> #N/A | AE88: =K88*IF(AND('BTL Calculator'!$V$2="Core",L88<0.055),0.055,L88)/12*IF(RoundDown,R88,Q88) -> #N/A | AF88: =SUM(AD88:AE88) -> #N/A | AG88: =IF(RoundDown,R88,Q88)-AF88 -> #N/A | AH88: =IF(RoundDown,R88,Q88)*I88 -> #N/A | AK88: =TEXT(I88,"0.00%")&" ("&TEXT(AH88,"£0,0")&")" -> #N/A | AL88: =AG88-AH88 -> #N/A | AM88: =AL88/Property_Value -> #N/A | AN88: =IF(RoundDown,R88,Q88)/Property_Value -> #N/A | AO88: =Rent_Over_Term+AQ88 -> 0 | AP88: =IF($H$72="3 Year Fixed",$X$22*36+AQ88, $X$22*24+AQ88) -> 0 | AQ88: ='BTL Calculator'!$L$80*Term -> 0 | AS88: =IFERROR(IF(AND(IF(RoundDown,R88,Q88)=MaxGrossLoan,E88>=$F$36),1,0),"-") -> - | AT88: =IFERROR(IF(AND(AL88=MaxNetLoan,E88>=$F$36),1,0),"-") -> - | AU88: =SUM(AS88:AT88) -> 0 | AV88: =IF(IF(Rate_Type="Tracker",X88,W88)>'Product Data'!$P$19,"Y","N") -> Y
B89: =IF(AND('BTL Calculator'!$G$60=C89,F89='BTL Calculator'!$G$62),1,0) -> 0 | C89: Specific Net Loan | D89: 18 | E89: =VALUE(LEFT(F89,1)) -> 1 | F89: =F88 -> 1) Standard | H89: =H88 -> #N/A | I89: =I88 -> #N/A | J89: =IF('BTL Calculator'!V2="Core",0,IF(AND(Rate_Type="Fixed",H72="3 Year Fixed"),IF(Defer2>'Product Data'!$P$24,'Product Data'!$P$24,Defer2),IF(AND(Rate_Type="Fixed",H72="2 Year Fixed"),IF(Defer2>'Product Data'!$P$24,'Product Data'!$P$24,Defer2),IF(AND(Rate_Type="Fixed",H72="5 Year Fixed"),IF(Defer2>'Product Data'!$P$33,'Product Data'!$P$33,Defer2),IF(AND(Rate_Type="Tracker",$H$70="Commercial"),IF(Defer2>0.015,0.015,Defer2),IF(AND(Rate_Type="Tracker",$H$70="Semi-Commercial"),IF(Defer2>0.015,0.015,Defer2),IF(AND(Rate_Type="Tracker",OR($H$70="Residential BTL",$H$70="Retention ")),IF(Defer2>0.02,0.02,Defer2)))))))) -> FALSE | K89: =IF('BTL Calculator'!V2="Core",0,INDEX(K$85:K$87,MATCH($F$88,$F$85:$F$87,0))) -> #N/A | L89: =IFERROR(H89-J89,"-") -> - | M89: =M88 -> #N/A | N89: =N88 -> #N/A | O89: =IF(AND(OR(OR($H$70="Residential BTL",$H$70="Retention "),$H$70="Retention "),Rate_Type="Fixed"),IFERROR(AO89/(IF(AND('BTL Calculator'!V2="Core",L89<0.055),0.055,$L89)/12*(Term-$K89)*'Product Data'!$P$23),0),IF(AND(Rate_Type="Tracker",OR(OR($H$70="Residential BTL",$H$70="Retention "),$H$70="Retention ")),IFERROR(AO89/(IF(AND('BTL Calculator'!V2="Core",L89-BBR+'Product Data'!K3<0.055),0.055,$L89)/12*(Term-$K89)*'Product Data'!$P$17),0),IF(AND($H$70="Semi-Commercial",Rate_Type="Tracker"),IFERROR(AP89/($L89/12*(Term-$K89)*'Product Data'!$P$17),0),IF(AND($H$70="Semi-Commercial",Rate_Type="Fixed"),IFERROR(AP89/($L89/12*(Term-$K89)*'Product Data'!$P$23),0),IF(AND($H$70="Commercial",Rate_Type="Tracker"),IFERROR(AP89/($L89/12*(Term-$K89)*'Product Data'!$P$17),0),IF(AND($H$70="Commercial",Rate_Type="Fixed"),IFERROR(AP89/($L89/12*(Term-$K89)*'Product Data'!$P$23),0))))))) -> FALSE | P89: =IF('BTL Calculator'!$H$28="Fixed","",IF(OR(OR($H$70="Residential BTL",$H$70="Retention "),$H$70="Retention "),AO89/((((IF(AND('BTL Calculator'!V2="Core",H89-'Product Data'!$E$3+'Product Data'!$K$2-J89<0.055),0.055,H89-'Product Data'!$E$3+'Product Data'!$K$2-J89))/12*(Term-K89)))*'Product Data'!$P$18),AP89/(((((H89-'Product Data'!$E$3+'Product Data'!$K$2-J89))/12*(Term-K89)))*'Product Data'!$P$18))) | Q89: =MIN(N89,P89,O89,AR89/(1-(J89/12*IF((Defer_Term_Override="No")*(Rate_Type="Tracker"),Term-K89,Term))-I89-(IF(('BTL Calculator'!H28="Tracker")*(Rolled_Rate_Override="Full Rate"),H89,L89)/12*K89))) -> #N/A | R89: =ROUNDDOWN(Q89,-3) -> #N/A | S89: =IFERROR((IF(RoundDown,R89,Q89)*J89/12*Term)+ (IF(RoundDown,R89,Q89)*L89/12*K89)+ (IF(RoundDown,R89,Q89)*L89/12*(Term-K89)),"-") -> - | T89: =IFERROR(((IF(AND('BTL Calculator'!$V$2="Core",H89<0.055),0.055,H89)*IF(RoundDown,R89,Q89)/12)),"-") -> - | U89: =IF('BTL Calculator'!$H$28="Fixed","",(((L89+$U$73)*IF(RoundDown,R89,Q89)/12))) | V89: =IFERROR(((IF(AND('BTL Calculator'!$V$2="Core",L89<0.055),0.055,L89)*IF(RoundDown,R89,Q89)/12)),"-") -> - | W89: =IF(OR($H$70="Residential BTL",$H$70="Retention "),IFERROR(AO89/Z89,"-"),IFERROR(AP89/Z89,"-")) -> - | X89: =IF('BTL Calculator'!$H$28="Fixed","",IF(OR($H$70="Residential BTL",$H$70="Retention "),IFERROR(AO89/AA89,"-"),IFERROR(AP89/AA89,"-"))) | Y89: =TEXT(V89,"£0,0")&" @ "&TEXT(W89,"0%")&" ICR" -> - @ - ICR | Z89: =(IF(RoundDown,R89,Q89)*L89)/12*(Term-K89) -> #N/A | AA89: =IF('BTL Calculator'!$H$28="Fixed","",(IF(RoundDown,R89,Q89)*(IF(AND('BTL Calculator'!$V$2="Core",H89-BBR+'Product Data'!$K$2<0.055),0.055,H89-'Product Data'!$E$3+'Product Data'!$K$2-J89)))/12*(Term-K89)) | AB89: =IFERROR(Monthly_Rent*Term,"-") -> 0 | AC89: =IFERROR($U$22-V89,"-") -> - | AD89: =((J89*IF(RoundDown,R89,Q89))/12)*Term -> #N/A | AE89: =K89*IF(AND('BTL Calculator'!$V$2="Core",L89<0.055),0.055,L89)/12*IF(RoundDown,R89,Q89) -> #N/A | AF89: =SUM(AD89:AE89) -> #N/A | AG89: =IF(RoundDown,R89,Q89)-AF89 -> #N/A | AH89: =IF(RoundDown,R89,Q89)*I89 -> #N/A | AK89: =TEXT(I89,"0.00%")&" ("&TEXT(AH89,"£0,0")&")" -> #N/A | AL89: =AG89-AH89 -> #N/A | AM89: =AL89/Property_Value -> #N/A | AN89: =IF(RoundDown,R89,Q89)/Property_Value -> #N/A | AO89: =Rent_Over_Term+AQ89 -> 0 | AP89: =IF($H$72="3 Year Fixed",$X$22*36+AQ89, $X$22*24+AQ89) -> 0 | AQ89: ='BTL Calculator'!$L$80*Term -> 0 | AR89: ='BTL Calculator'!L83 -> 350000 | AS89: =IFERROR(IF(AND(IF(RoundDown,R89,Q89)=MaxGrossLoan,E89>=$F$36),1,0),"-") -> - | AT89: =IFERROR(IF(AND(AL89=MaxNetLoan,E89>=$F$36),1,0),"-") -> - | AU89: =SUM(AS89:AT89) -> 0 | AV89: =IF(IF(Rate_Type="Tracker",X89,W89)>'Product Data'!$P$19,"Y","N") -> Y
C90: CHOSEN | D90: =INDEX(D76:D89,MATCH(1,$B$76:$B$89,0)) -> #N/A | E90: =LEFT(F90,1) -> #N/A | F90: =INDEX(F76:F89,MATCH(1,$B$76:$B$89,0)) -> #N/A | H90: =INDEX(H76:H89,MATCH(1,$B$76:$B$89,0)) -> #N/A | I90: =INDEX(I76:I89,MATCH(1,$B$76:$B$89,0)) -> #N/A | J90: =INDEX(J76:J89,MATCH(1,$B$76:$B$89,0)) -> #N/A | K90: =INDEX(K76:K89,MATCH(1,$B$76:$B$89,0)) -> #N/A | L90: =INDEX(L76:L89,MATCH(1,$B$76:$B$89,0)) -> #N/A | M90: =INDEX(M76:M89,MATCH(1,$B$76:$B$89,0)) -> #N/A | N90: =INDEX(N76:N89,MATCH(1,$B$76:$B$89,0)) -> #N/A | O90: =IF(AND(OR(OR($H$70="Residential BTL",$H$70="Retention "),$H$70="Retention "),Rate_Type="Fixed"),IFERROR(AO90/(IF(AND('BTL Calculator'!V2="Core",L90<0.055),0.055,$L90)/12*(Term-$K90)*'Product Data'!$P$23),0),IF(AND(Rate_Type="Tracker",OR(OR($H$70="Residential BTL",$H$70="Retention "),$H$70="Retention ")),IFERROR(AO90/(IF(AND('BTL Calculator'!V2="Core",L90-BBR+'Product Data'!K2<0.055),0.055,$L90)/12*(Term-$K90)*'Product Data'!$P$17),0),IF(AND($H$70="Semi-Commercial",Rate_Type="Tracker"),IFERROR(AP90/($L90/12*(Term-$K90)*'Product Data'!$P$17),0),IF(AND($H$70="Semi-Commercial",Rate_Type="Fixed"),IFERROR(AP90/($L90/12*(Term-$K90)*'Product Data'!$P$23),0),IF(AND($H$70="Commercial",Rate_Type="Tracker"),IFERROR(AP90/($L90/12*(Term-$K90)*'Product Data'!$P$17),0),IF(AND($H$70="Commercial",Rate_Type="Fixed"),IFERROR(AP90/($L90/12*(Term-$K90)*'Product Data'!$P$23),0))))))) -> FALSE | P90: =IF('BTL Calculator'!$H$28="Fixed","",IF(OR(OR($H$70="Residential BTL",$H$70="Retention "),$H$70="Retention "),AO90/((((IF(AND('BTL Calculator'!V2="Core",H90-'Product Data'!$E$3+'Product Data'!$K$2-J90<0.055),0.055,H90-'Product Data'!$E$3+'Product Data'!$K$2-J90))/12*(Term-K90)))*'Product Data'!$P$18),AP90/(((((H90-'Product Data'!$E$3+'Product Data'!$K$2-J90))/12*(Term-K90)))*'Product Data'!$P$18))) | Q90: =INDEX(Q76:Q89,MATCH(1,$B$76:$B$89,0)) -> #N/A | R90: =ROUNDDOWN(Q90,-3) -> #N/A | S90: =IFERROR((IF(RoundDown,R90,Q90)*J90/12*Term)+ (IF(RoundDown,R90,Q90)*L90/12*K90)+ (IF(RoundDown,R90,Q90)*L90/12*(Term-K90)),"-") -> - | T90: =IFERROR(((H90)*IF(RoundDown,R90,Q90)/12),"-") -> - | U90: =IF('BTL Calculator'!$H$28="Fixed","",(((L90+$U$73)*IF(RoundDown,R90,Q90)/12))) | V90: =IFERROR(((L90)*IF(RoundDown,R90,Q90)/12),"-") -> - | W90: =IF(OR($H$70="Residential BTL",$H$70="Retention "),IFERROR(AO90/Z90,"-"),IFERROR(AP90/Z90,"-")) -> - | X90: =IF('BTL Calculator'!$H$28="Fixed","",IF(OR($H$70="Residential BTL",$H$70="Retention "),IFERROR(AO90/AA90,"-"),IFERROR(AP90/AA90,"-"))) | Y90: =TEXT(V90,"£0,0")&" @ "&TEXT(W90,"0%")&" ICR" -> - @ - ICR | Z90: =(IF(RoundDown,R90,Q90)*L90)/12*(Term-K90) -> #N/A | AA90: =IF('BTL Calculator'!$H$28="Fixed","",(IF(RoundDown,R90,Q90)*(IF(AND('BTL Calculator'!$V$2="Core",H90-BBR+'Product Data'!$K$2<0.055),0.055,H90-'Product Data'!$E$3+'Product Data'!$K$2-J90)))/12*(Term-K90)) | AB90: =IFERROR(Monthly_Rent*Term,"-") -> 0 | AC90: =INDEX(AC76:AC89,MATCH(1,$B$76:$B$89,0)) -> #N/A | AD90: =((J90*IF(RoundDown,R90,Q90))/12)*Term -> #N/A | AE90: =K90*IF(AND('BTL Calculator'!$V$2="Core",L90<0.055),0.055,L90)/12*IF(RoundDown,R90,Q90) -> #N/A | AF90: =INDEX(AF76:AF89,MATCH(1,$B$76:$B$89,0)) -> #N/A | AG90: =ROUND(INDEX(AG76:AG89,MATCH(1,$B$76:$B$89,0)),0) -> #N/A | AH90: =ROUND(INDEX(AH76:AH89,MATCH(1,$B$76:$B$89,0)),0) -> #N/A | AK90: =INDEX(AK76:AK89,MATCH(1,$B$76:$B$89,0)) -> #N/A | AL90: =IF(AG90-AH90<0,0,AG90-AH90) -> #N/A | AM90: =AL90/Property_Value -> #N/A | AN90: =INDEX(AN76:AN89,MATCH(1,$B$76:$B$89,0)) -> #N/A | AO90: =Rent_Over_Term+AQ90 -> 0 | AP90: =IF($H$72="3 Year Fixed",$X$22*36+AQ90, $X$22*24+AQ90) -> 0 | AQ90: ='BTL Calculator'!$L$80*Term -> 0 | AS90: =IFERROR(IF(AND(IF(RoundDown,R90,Q90)=MaxGrossLoan,E90>=$F$36),1,0),"-") -> - | AT90: =IFERROR(IF(AND(AL90=MaxNetLoan,E90>=$F$36),1,0),"-") -> - | AU90: =SUM(AS90:AT90) -> 0 | AV90: =INDEX(AV76:AV89,MATCH(1,$B$76:$B$89,0)) -> #N/A
A93: BTL PRODUCT FEE 4%
B94: =IF(AND('BTL Calculator'!$G$60=C103,F94='BTL Calculator'!$G$62,'BTL Calculator'!V2="Core"),1,IF(AND('BTL Calculator'!$G$60=C94,F94='BTL Calculator'!$G$62),1,0)) -> 0 | C94: Basic Loan | D94: 1 | E94: =VALUE(LEFT(F94,1)) -> 0 | F94: =IF($H$70='Product Data'!$BT5,'Product Data'!$B190,IF($H$70='Product Data'!$BT2,'Product Data'!$B9,IF($H$70='Product Data'!BT3,'Product Data'!B34,IF(H70='Product Data'!BT4,'Product Data'!B47,0)))) -> 0 | G94: =IF(AND($H$70='Product Data'!$BT$5,$H$72='Product Data'!$CA$5,L72=0.75),'Product Data'!C195,IF(AND($H$70='Product Data'!$BT$5,$H$72='Product Data'!$CA$5,L72=0.65),'Product Data'!C217, IF(AND($H$70='Product Data'!$BT$5,$H$72='Product Data'!$CA$4,L72=0.75),'Product Data'!G195,IF(AND($H$70='Product Data'!$BT$5,$H$72='Product Data'!$CA$4,L72=0.65),'Product Data'!G217, IF(AND($H$70='Product Data'!$BT$5,$H$72='Product Data'!$CA$3,L72=0.75),'Product Data'!K195,IF(AND($H$70='Product Data'!$BT$5,$H$72='Product Data'!$CA$3,L72=0.65),'Product Data'!K217, IF(AND($H$70='Product Data'!$BT$5,$H$72='Product Data'!$CA$2,L72=0.75),'Product Data'!O195,IF(AND($H$70='Product Data'!$BT$5,$H$72='Product Data'!$CA$2,L72=0.65),'Product Data'!O217, IF(AND($H$70='Product Data'!$BT$4,$H$72='Product Data'!$CA$4),'Product Data'!C128,IF(AND($H$70='Product Data'!$BT$4,$H$72='Product Data'!$CA$3),'Product Data'!C115,IF(AND($H$70='Product Data'!$BT$4,$H$72='Product Data'!$CA$2),'Product Data'!C51,IF(AND($H$70='Product Data'!$BT$2,$H$72='Product Data'!$CA$4),'Product Data'!C91,IF(AND($H$70='Product Data'!$BT$2,$H$72='Product Data'!$CA$3),'Product Data'!C66,IF(AND($H$70='Product Data'!$BT$2,$H$72='Product Data'!$CA$2),'Product Data'!C15,IF(AND($H$70='Product Data'!$BT$3,$H$72='Product Data'!$CA$4),'Product Data'!C154,IF(AND($H$70='Product Data'!$BT$3,$H$72='Product Data'!$CA$3),'Product Data'!C141,IF(AND($H$70='Product Data'!$BT$3,$H$72='Product Data'!$CA$2),'Product Data'!C38, IF(AND($H$70='Product Data'!$BT$2,$H$72='Product Data'!$CA$5),'Product Data'!C170)))))))))))))))))) -> FALSE | H94: =IF(AND(F94=Product_Selected,Rate_Override<>0, Rate_Override<>""),Rate_Override+G94,G94) -> FALSE | I94: =IF(H70= "Retention ", IF('BTL Calculator'!$H$33<>"",3.5%-'BTL Calculator'!$H$33,3.5%),IF('BTL Calculator'!$H$33<>"",4%-'BTL Calculator'!$H$33,4%)) -> 0.04 | L94: =IFERROR(H94-J94,"-") -> 0 | M94: =IF(AND(H70="Retention ",L72=0.65),0.65, IF(AND(H70="Retention ",L72=0.75),0.75, IF(OR($H$70="Residential BTL",$H$70="Retention "),INDEX($O$36:$R$36,MATCH(D94,$O$38:$R$38,0)),70%))) -> 0.7 | N94: =MIN(M94*Property_Value,'Product Data'!$P$16) -> 0 | O94: =IF(AND(OR(OR($H$70="Residential BTL",$H$70="Retention "),$H$70="Retention "),Rate_Type="Fixed"),IFERROR(AO94/(IF(AND('BTL Calculator'!V2="Core",L94<0.055),0.055,$L94)/12*(Term-$K94)*'Product Data'!$P$23),0), IF(AND(Rate_Type="Tracker",OR(OR($H$70="Residential BTL",$H$70="Retention "),$H$70="Retention ")),IFERROR(AO94/(IF(AND('BTL Calculator'!V2="Core",L94-BBR+'Product Data'!K2<0.055),0.055,$L94)/12*(Term-$K94)*'Product Data'!$P$17),0), IF(AND($H$70="Semi-Commercial",Rate_Type="Tracker"),IFERROR(AP94/($L94/12*(Term-$K94)*'Product Data'!$P$17),0), IF(AND($H$70="Semi-Commercial",Rate_Type="Fixed"),IFERROR(AP94/($L94/12*(Term-$K94)*'Product Data'!$P$23),0), IF(AND($H$70="Commercial",Rate_Type="Tracker"),IFERROR(AP94/($L94/12*(Term-$K94)*'Product Data'!$P$17),0), IF(AND($H$70="Commercial",Rate_Type="Fixed"),IFERROR(AP94/($L94/12*(Term-$K94)*'Product Data'!$P$23),0))))))) -> FALSE | P94: =IF('BTL Calculator'!$H$28="Fixed","",IF(OR(OR($H$70="Residential BTL",$H$70="Retention "),$H$70="Retention "),AO94/((((IF(AND('BTL Calculator'!V2="Core",H94-'Product Data'!$E$3+'Product Data'!$K$2-J94<0.055),0.055,H94-'Product Data'!$E$3+'Product Data'!$K$3-J94))/12*(Term-K94)))*'Product Data'!$P$18),AP94/(((((H94-'Product Data'!$E$3+'Product Data'!$K$2-J94))/12*(Term-K94)))*'Product Data'!$P$18))) | Q94: =IF('BTL Calculator'!$H$28="Tracker",MIN(N94,P94),MIN(O94,N94)) -> 0 | R94: =ROUNDDOWN(Q94,-3) -> 0 | S94: =IFERROR((IF(RoundDown,R94,Q94)*J94/12*Term)+ (IF(RoundDown,R94,Q94)*L94/12*K94)+ (IF(RoundDown,R94,Q94)*L94/12*(Term-K94)),"-") -> 0 | T94: =IFERROR(((H94)*IF(RoundDown,R94,Q94)/12),"-") -> 0 | U94: =IF('BTL Calculator'!$H$28="Fixed","",(((L94+$U$73)*IF(RoundDown,R94,Q94)/12))) | V94: =IFERROR(((L94)*IF(RoundDown,R94,Q94)/12),"-") -> 0 | W94: =IF(OR($H$70="Residential BTL",$H$70="Retention "),IFERROR(AO94/Z94,"-"),IFERROR(AP94/Z94,"-")) -> - | X94: =IF('BTL Calculator'!$H$28="Fixed","",IF(OR($H$70="Residential BTL",$H$70="Retention "),IFERROR(AO94/AA94,"-"),IFERROR(AP94/AA94,"-"))) | Y94: =TEXT(V94,"£0,0")&" @ "&TEXT(W94,"0%")&" ICR" -> £00 @ - ICR | Z94: =(IF(RoundDown,R94,Q94)*L94)/12*(Term-K94) -> 0 | AA94: =IF('BTL Calculator'!$H$28="Fixed","",(IF(RoundDown,R94,Q94)*(IF(AND('BTL Calculator'!$V$2="Core",H94-BBR+'Product Data'!$K$2<0.055),0.055,H94-'Product Data'!$E$3+'Product Data'!$K$2-J94)))/12*(Term-K94)) | AB94: =IFERROR(Monthly_Rent*Term,"-") -> 0 | AC94: =IFERROR($U$22-V94,"-") -> 0 | AD94: =((J94*IF(RoundDown,R94,Q94))/12)*Term -> 0 | AE94: =K94*IF(AND('BTL Calculator'!$V$2="Core",L94<0.055),0.055,L94)/12*IF(RoundDown,R94,Q94) -> 0 | AF94: =SUM(AD94:AE94) -> 0 | AG94: =AL94+AI94 -> 0 | AH94: =+AI94+AJ94 -> 0 | AI94: =+IF(RoundDown,R94,Q94)*0.02 -> 0 | AJ94: =+IF(RoundDown,R94,Q94)*I94-AI94 -> 0 | AK94: =TEXT(I94,"0.00%")&" ("&TEXT(AH94,"£0,0")&")" -> 4.00% (£00) | AL94: =IF(RoundDown,R94,Q94)-AD94-AE94-AH94 -> 0 | AM94: =AL94/Property_Value -> #DIV/0! | AN94: =IF(RoundDown,R94,Q94)/Property_Value -> #DIV/0! | AO94: =Rent_Over_Term+AQ94 -> 0 | AP94: =IF($H$72="3 Year Fixed",$X$22*36+AQ94, $X$22*24+AQ94) -> 0 | AQ94: ='BTL Calculator'!$I$80*Term -> 0 | AR94: =IF(ISERROR(FIND("Bespoke",F76,1)),FALSE,TRUE) -> FALSE | AS94: =IFERROR(IF(AND(IF(RoundDown,R94,Q94)=$E$70,E94>=$F$36),1,0),"-") -> 0 | AT94: =IFERROR(IF(AND(AL94=$E$71,E94>=$F$36),1,0),"-") -> - | AU94: =SUM(AS94:AT94) -> 0 | AV94: =IF(IF(Rate_Type="Tracker",X94,W94)>'Product Data'!$P$19,"Y","N") -> Y | AY94: =+IF(RoundDown,AH94,AG94)*Y94-AZ94 -> #VALUE! | AZ94: =+IF(RoundDown,AH94,AG94)*0.02 -> 0
B95: =IF(AND('BTL Calculator'!$G$60=C103,F95='BTL Calculator'!$G$62,'BTL Calculator'!$V$2="Core"),1,IF(AND('BTL Calculator'!$G$60=C94,F95='BTL Calculator'!$G$62),1,0)) -> 0 | D95: 2 | E95: =VALUE(LEFT(F95,1)) -> 0 | F95: =IF($H$70='Product Data'!$BT5,'Product Data'!$B191,IF($H$70='Product Data'!$BT2,'Product Data'!$B10,IF($H$70='Product Data'!BT3,'Product Data'!B35,IF(H70='Product Data'!BT4,'Product Data'!B48,0)))) -> 0 | G95: =IF(AND($H$70='Product Data'!$BT$5,$H$72='Product Data'!$CA$5,L72=0.75),'Product Data'!C196,IF(AND($H$70='Product Data'!$BT$5,$H$72='Product Data'!$CA$5,L72=0.65),'Product Data'!C218, IF(AND($H$70='Product Data'!$BT$5,$H$72='Product Data'!$CA$4,L72=0.75),'Product Data'!G196,IF(AND($H$70='Product Data'!$BT$5,$H$72='Product Data'!$CA$4,L72=0.65),'Product Data'!G218, IF(AND($H$70='Product Data'!$BT$5,$H$72='Product Data'!$CA$3,L72=0.75),'Product Data'!K196,IF(AND($H$70='Product Data'!$BT$5,$H$72='Product Data'!$CA$3,L72=0.65),'Product Data'!K218, IF(AND($H$70='Product Data'!$BT$5,$H$72='Product Data'!$CA$2,L72=0.75),'Product Data'!O196,IF(AND($H$70='Product Data'!$BT$5,$H$72='Product Data'!$CA$2,L72=0.65),'Product Data'!O218, IF(AND($H$70='Product Data'!$BT$4,$H$72='Product Data'!$CA$4),'Product Data'!C129,IF(AND($H$70='Product Data'!$BT$4,$H$72='Product Data'!$CA$3),'Product Data'!C116,IF(AND($H$70='Product Data'!$BT$4,$H$72='Product Data'!$CA$2),'Product Data'!C52,IF(AND($H$70='Product Data'!$BT$2,$H$72='Product Data'!$CA$4),'Product Data'!C92,IF(AND($H$70='Product Data'!$BT$2,$H$72='Product Data'!$CA$3),'Product Data'!C67,IF(AND($H$70='Product Data'!$BT$2,$H$72='Product Data'!$CA$2),'Product Data'!C16,IF(AND($H$70='Product Data'!$BT$3,$H$72='Product Data'!$CA$4),'Product Data'!C155,IF(AND($H$70='Product Data'!$BT$3,$H$72='Product Data'!$CA$3),'Product Data'!C142,IF(AND($H$70='Product Data'!$BT$3,$H$72='Product Data'!$CA$2),'Product Data'!C39, IF(AND($H$70='Product Data'!$BT$2,$H$72='Product Data'!$CA$5),'Product Data'!C171)))))))))))))))))) -> FALSE | H95: =IF(AND(F95=Product_Selected,Rate_Override<>0, Rate_Override<>""),Rate_Override+G95,G95) -> FALSE | I95: =IF(H70= "Retention ", IF('BTL Calculator'!$H$33<>"",3.5%-'BTL Calculator'!$H$33,3.5%),IF('BTL Calculator'!$H$33<>"",4%-'BTL Calculator'!$H$33,4%)) -> 0.04 | L95: =H95-J95 -> 0 | M95: =IF(AND(H70="Retention ",L72=0.65),0.65, IF(AND(H70="Retention ",L72=0.75),0.75, IF(OR($H$70="Residential BTL",$H$70="Retention "),INDEX($O$36:$R$36,MATCH(D95,$O$38:$R$38,0)),70%))) -> 0.7 | N95: =MIN(M95*Property_Value,'Product Data'!$P$16) -> 0 | O95: =IF(AND(OR(OR($H$70="Residential BTL",$H$70="Retention "),$H$70="Retention "),Rate_Type="Fixed"),IFERROR(AO95/(IF(AND('BTL Calculator'!V2="Core",L95<0.055),0.055,$L95)/12*(Term-$K95)*'Product Data'!$P$23),0),IF(AND(Rate_Type="Tracker",OR(OR($H$70="Residential BTL",$H$70="Retention "),$H$70="Retention ")),IFERROR(AO95/(IF(AND('BTL Calculator'!V2="Core",L95-BBR+'Product Data'!K2<0.055),0.055,$L95)/12*(Term-$K95)*'Product Data'!$P$17),0),IF(AND($H$70="Semi-Commercial",Rate_Type="Tracker"),IFERROR(AP95/($L95/12*(Term-$K95)*'Product Data'!$P$17),0),IF(AND($H$70="Semi-Commercial",Rate_Type="Fixed"),IFERROR(AP95/($L95/12*(Term-$K95)*'Product Data'!$P$23),0),IF(AND($H$70="Commercial",Rate_Type="Tracker"),IFERROR(AP95/($L95/12*(Term-$K95)*'Product Data'!$P$17),0),IF(AND($H$70="Commercial",Rate_Type="Fixed"),IFERROR(AP95/($L95/12*(Term-$K95)*'Product Data'!$P$23),0))))))) -> FALSE | P95: =IF('BTL Calculator'!$H$28="Fixed","",IF(OR(OR($H$70="Residential BTL",$H$70="Retention "),$H$70="Retention "),AO95/((((IF(AND('BTL Calculator'!V2="Core",H95-'Product Data'!$E$3+'Product Data'!$K$2-J95<0.055),0.055,H95-'Product Data'!$E$3+'Product Data'!$K$3-J95))/12*(Term-K95)))*'Product Data'!$P$18),AP95/(((((H95-'Product Data'!$E$3+'Product Data'!$K$2-J95))/12*(Term-K95)))*'Product Data'!$P$18))) | Q95: =IF('BTL Calculator'!$H$28="Tracker",MIN(N95,P95),MIN(O95,N95)) -> 0 | R95: =ROUNDDOWN(Q95,-3) -> 0 | S95: =IFERROR((IF(RoundDown,R95,Q95)*J95/12*Term)+ (IF(RoundDown,R95,Q95)*L95/12*K95)+ (IF(RoundDown,R95,Q95)*L95/12*(Term-K95)),"-") -> 0 | T95: =IFERROR(((H95)*IF(RoundDown,R95,Q95)/12),"-") -> 0 | U95: =IF('BTL Calculator'!$H$28="Fixed","",(((L95+$U$73)*IF(RoundDown,R95,Q95)/12))) | V95: =IFERROR(((L95)*IF(RoundDown,R95,Q95)/12),"-") -> 0 | W95: =IF(OR($H$70="Residential BTL",$H$70="Retention "),IFERROR(AO95/Z95,"-"),IFERROR(AP95/Z95,"-")) -> - | X95: =IF('BTL Calculator'!$H$28="Fixed","",IF(OR($H$70="Residential BTL",$H$70="Retention "),IFERROR(AO95/AA95,"-"),IFERROR(AP95/AA95,"-"))) | Y95: =TEXT(V95,"£0,0")&" @ "&TEXT(W95,"0%")&" ICR" -> £00 @ - ICR | Z95: =(IF(RoundDown,R95,Q95)*L95)/12*(Term-K95) -> 0 | AA95: =IF('BTL Calculator'!$H$28="Fixed","",(IF(RoundDown,R95,Q95)*(IF(AND('BTL Calculator'!$V$2="Core",H95-BBR+'Product Data'!$K$2<0.055),0.055,H95-'Product Data'!$E$3+'Product Data'!$K$2-J95)))/12*(Term-K95)) | AB95: =IFERROR(Monthly_Rent*Term,"-") -> 0 | AC95: =IFERROR($U$22-V95,"-") -> 0 | AD95: =((J95*IF(RoundDown,R95,Q95))/12)*Term -> 0 | AE95: =K95*IF(AND('BTL Calculator'!$V$2="Core",L95<0.055),0.055,L95)/12*IF(RoundDown,R95,Q95) -> 0 | AF95: =SUM(AD95:AE95) -> 0 | AG95: =AL95+AI95 -> 0 | AH95: =+AI95+AJ95 -> 0 | AI95: =+IF(RoundDown,R95,Q95)*0.02 -> 0 | AJ95: =+IF(RoundDown,R95,Q95)*I95-AI95 -> 0 | AK95: =TEXT(I95,"0.00%")&" ("&TEXT(AH95,"£0,0")&")" -> 4.00% (£00) | AL95: =IF(RoundDown,R95,Q95)-AD95-AE95-AH95 -> 0 | AM95: =AL95/Property_Value -> #DIV/0! | AN95: =IF(RoundDown,R95,Q95)/Property_Value -> #DIV/0! | AO95: =Rent_Over_Term+AQ95 -> 0 | AP95: =IF($H$72="3 Year Fixed",$X$22*36+AQ95, $X$22*24+AQ95) -> 0 | AQ95: ='BTL Calculator'!$I$80*Term -> 0 | AR95: =IF(ISERROR(FIND("Bespoke",F77,1)),FALSE,TRUE) -> FALSE | AS95: =IFERROR(IF(AND(IF(RoundDown,R95,Q95)=$E$70,E95>=$F$36),1,0),"-") -> 0 | AT95: =IFERROR(IF(AND(AL95=$E$71,E95>=$F$36),1,0),"-") -> - | AU95: =SUM(AS95:AT95) -> 0 | AV95: =IF(IF(Rate_Type="Tracker",X95,W95)>'Product Data'!$P$19,"Y","N") -> Y | AY95: =+IF(RoundDown,AH95,AG95)*Y95-AZ95 -> #VALUE! | AZ95: =+IF(RoundDown,AH95,AG95)*0.02 -> 0
B96: =IF(OR($H$70="Residential BTL",$H$70="Retention "),IF(AND('BTL Calculator'!$G$60=C94,F96='BTL Calculator'!$G$62),1,0),"") | D96: =IF(OR(OR($H$70="Residential BTL",$H$70="Retention "),$H$70="Retention "),3,"") | E96: =IF(OR(OR($H$70="Residential BTL",$H$70="Retention "),$H$70="Retention "),VALUE(LEFT(F96,1)),"") | F96: =IF(OR(OR($H$70="Residential BTL",$H$70="Retention "),$H$70="Retention "),"3) Specialist BTL","") | G96: =IF(AND($H$70='Product Data'!$BT$5,$H$72='Product Data'!$CA$5,L72=0.75),'Product Data'!C197,IF(AND($H$70='Product Data'!$BT$5,$H$72='Product Data'!$CA$5,L72=0.65),'Product Data'!C219, IF(AND($H$70='Product Data'!$BT$5,$H$72='Product Data'!$CA$4,L72=0.75),'Product Data'!G197,IF(AND($H$70='Product Data'!$BT$5,$H$72='Product Data'!$CA$4,L72=0.65),'Product Data'!G219, IF(AND($H$70='Product Data'!$BT$5,$H$72='Product Data'!$CA$3,L72=0.75),'Product Data'!K197,IF(AND($H$70='Product Data'!$BT$5,$H$72='Product Data'!$CA$3,L72=0.65),'Product Data'!K219, IF(AND($H$70='Product Data'!$BT$5,$H$72='Product Data'!$CA$2,L72=0.75),'Product Data'!O197,IF(AND($H$70='Product Data'!$BT$5,$H$72='Product Data'!$CA$2,L72=0.65),'Product Data'!O219, IF(H70="Residential BTL",IF(H72='Product Data'!CA2,'Product Data'!C17,IF(H72='Product Data'!CA3,'Product Data'!C68,IF(H72='Product Data'!CA4,'Product Data'!C93,IF(H72='Product Data'!CA5,'Product Data'!C172)))),""))))))))) | H96: =IF(AND(F96=Product_Selected,Rate_Override<>0, Rate_Override<>""),Rate_Override+G96,G96) | I96: =I95 -> 0.04 | L96: =IF('BTL Calculator'!V2="Core","",IF(OR(OR($H$70="Residential BTL",$H$70="Retention "),$H$70="Retention "),H96-J96,"")) | M96: =IF(AND(H70="Retention ",L72=0.65),0.65, IF(AND(H70="Retention ",L72=0.75),0.75, IF(OR($H$70="Residential BTL",$H$70="Retention "),INDEX($O$36:$R$36,MATCH(D96,$O$38:$R$38,0)),""))) | N96: =IF(OR(OR($H$70="Residential BTL",$H$70="Retention "),$H$70="Retention "),MIN(M96*Property_Value,'Product Data'!$P$16),"") | O96: =IF(AND(OR(OR($H$70="Residential BTL",$H$70="Retention "),$H$70="Retention "),Rate_Type="Fixed"),IFERROR(AO96/($L96/12*(Term-$K96)*'Product Data'!$P$23),0),IF(AND(Rate_Type="Tracker",OR(OR($H$70="Residential BTL",$H$70="Retention "),$H$70="Retention ")),IFERROR(AO96/($L96/12*(Term-$K96)*'Product Data'!$P$17),0),IF(AND($H$70="Semi-Commercial",Rate_Type="Tracker"),IFERROR(AP96/($L96/12*(Term-$K96)*'Product Data'!$P$17),0),IF(AND($H$70="Semi-Commercial",Rate_Type="Fixed"),IFERROR(AP96/($L96/12*(Term-$K96)*'Product Data'!$P$23),0),IF(AND($H$70="Commercial",Rate_Type="Tracker"),IFERROR(AP96/($L96/12*(Term-$K96)*'Product Data'!$P$17),0),IF(AND($H$70="Commercial",Rate_Type="Fixed"),IFERROR(AP96/($L96/12*(Term-$K96)*'Product Data'!$P$23),0))))))) -> FALSE | P96: =IF('BTL Calculator'!$H$28="Fixed","",IF(OR(OR($H$70="Residential BTL",$H$70="Retention "),$H$70="Retention "),AO96/((((IF(AND('BTL Calculator'!V2="Core",H96-'Product Data'!$E$3+'Product Data'!$K$2-J96<0.055),0.055,H96-'Product Data'!$E$3+'Product Data'!$K$3-J96))/12*(Term-K96)))*'Product Data'!$P$18),AP96/(((((H96-'Product Data'!$E$3+'Product Data'!$K$2-J96))/12*(Term-K96)))*'Product Data'!$P$18))) | Q96: =IF(OR($H$70="Residential BTL",$H$70="Retention "),IF('BTL Calculator'!$H$28="Tracker",MIN(N96,P96),MIN(O96,N96)),"") | R96: =IF(OR($H$70="Residential BTL",$H$70="Retention "),ROUNDDOWN(Q96,-3),"") | S96: =IFERROR((IF(RoundDown,R96,Q96)*J96/12*Term)+ (IF(RoundDown,R96,Q96)*L96/12*K96)+ (IF(RoundDown,R96,Q96)*L96/12*(Term-K96)),"-") -> - | T96: =IF('BTL Calculator'!$V$2="Core","",IF(OR($H$70="Residential BTL",$H$70="Retention "),((H96*IF(RoundDown,R96,Q96)/12)),"")) | U96: =IF('BTL Calculator'!$H$28="Fixed","",(((L96+$U$73)*IF(RoundDown,R96,Q96)/12))) | V96: =IF('BTL Calculator'!$V$2="Core","",IF(OR($H$70="Residential BTL",$H$70="Retention "),((L96*IF(RoundDown,R96,Q96)/12)),"")) | W96: =IF(OR($H$70="Residential BTL",$H$70="Retention "),IFERROR(AO96/Z96,"-"),"") | X96: =IF('BTL Calculator'!$H$28="Fixed","",IF(OR($H$70="Residential BTL",$H$70="Retention "),IFERROR(AO96/AA96,"-"),IFERROR(AP96/AA96,"-"))) | Y96: =IF(OR($H$70="Residential BTL",$H$70="Retention "),TEXT(V96,"£0,0")&" @ "&TEXT(W96,"0%")&" ICR","") | Z96: =IF('BTL Calculator'!$V$2="Core","",IF(OR($H$70="Residential BTL",$H$70="Retention "),(IF(RoundDown,R96,Q96)*L96)/12*(Term-K96),"")) | AA96: =IF('BTL Calculator'!$H$28="Fixed","",(IF(RoundDown,R96,Q96)*(H96-'Product Data'!$E$3+'Product Data'!$K$2-J96))/12*(Term-K96)) | AB96: =IF(OR($H$70="Residential BTL",$H$70="Retention "),IFERROR(Monthly_Rent*Term,"-"),"") | AC96: =IF(OR($H$70="Residential BTL",$H$70="Retention "),IFERROR($U$22-V96,"-"),"") | AD96: =((J96*IF(RoundDown,R96,Q96))/12)*Term -> #VALUE! | AE96: =IF('BTL Calculator'!$V$2="Core","",K96*L96/12*IF(RoundDown,R96,Q96)) -> #VALUE! | AF96: =IF(OR($H$70="Residential BTL",$H$70="Retention "),SUM(AD96:AE96),"") | AG96: =IF('BTL Calculator'!V2="Core","",IF(OR($H$70="Residential BTL",$H$70="Retention "),AL96+AI96,"")) | AH96: =+AI96+AJ96 -> #VALUE! | AI96: =+IF(RoundDown,R96,Q96)*0.02 -> #VALUE! | AJ96: =+IF(RoundDown,R96,Q96)*I96-AI96 -> #VALUE! | AK96: =IF(OR($H$70="Residential BTL",$H$70="Retention "),TEXT(I96,"0.00%")&" ("&TEXT(AH96,"£0,0")&")","") | AL96: =IF('BTL Calculator'!V2="Core","",IF(OR($H$70="Residential BTL",$H$70="Retention "),IF(RoundDown,R96,Q96)-AD96-AE96-AH96,"")) | AM96: =IF(OR($H$70="Residential BTL",$H$70="Retention "),AL96/Property_Value,"") | AN96: =IF(OR($H$70="Residential BTL",$H$70="Retention "),IF(RoundDown,R96,Q96)/Property_Value,"") | AO96: =IF(OR($H$70="Residential BTL",$H$70="Retention "),Rent_Over_Term+AQ96,"") | AQ96: =IF(OR($H$70="Residential BTL",$H$70="Retention "),'BTL Calculator'!$I$80*Term,"") | AR96: =IF(OR($H$70="Residential BTL",$H$70="Retention "),IF(ISERROR(FIND("Bespoke",F78,1)),FALSE,TRUE),"") | AS96: =IF(OR($H$70="Residential BTL",$H$70="Retention "),IFERROR(IF(AND(IF(RoundDown,R96,Q96)=$E$70,E96>=$F$36),1,0),"-"),"") | AT96: =IF(OR($H$70="Residential BTL",$H$70="Retention "),IFERROR(IF(AND(AL96=$E$71,E96>=$F$36),1,0),"-"),"") | AU96: =IF(OR($H$70="Residential BTL",$H$70="Retention "),SUM(AS96:AT96),"") | AV96: =IF(OR($H$70="Residential BTL",$H$70="Retention "),IF(IF(Rate_Type="Tracker",X96,W96)>'Product Data'!$P$19,"Y","N"),"") | AY96: =+IF(RoundDown,AH96,AG96)*Y96-AZ96 -> #VALUE! | AZ96: =+IF(RoundDown,AH96,AG96)*0.02 -> #VALUE!
B97: =IF(AND('BTL Calculator'!$G$60=C97,F97='BTL Calculator'!$G$62),1,0) -> 0 | C97: Use Max Rolled and Deferred | D97: 5 | E97: =VALUE(LEFT(F97,1)) -> 0 | F97: =IF($H$70='Product Data'!$BT5,'Product Data'!$B190,IF($H$70='Product Data'!$BT2,'Product Data'!$B9,IF($H$70='Product Data'!BT3,'Product Data'!B34,IF(H70='Product Data'!BT4,'Product Data'!B47,0)))) -> 0 | H97: =H94 -> FALSE | I97: =I94 -> 0.04 | J97: =IF(AND(H70="Retention ",H72="Tracker"),2%,IF(AND($H$70='Product Data'!$BT$2,$H$72='Product Data'!$CA$2),2%,IF(AND($H$70='Product Data'!$BT$3,$H$72='Product Data'!$CA$2),1.5%,IF(AND($H$70='Product Data'!$BT$4,$H$72='Product Data'!$CA$2),1.5%,IF(AND($H$70='Product Data'!$BT$2,$H$72='Product Data'!$CA$5),0.75%,1.25%))))) -> 0.0125 | K97: =IF(OR(OR($H$70="Residential BTL",$H$70="Retention "),$H$70="Retention "),IF(Term<36,'Product Data'!$P$11,'Product Data'!$P$13),6) -> 6 | L97: =IFERROR(H97-J97,"-") -> -0.0125 | M97: =M94 -> 0.7 | N97: =MIN(M97*Property_Value,'Product Data'!$P$16) -> 0 | O97: =IF(AND(OR(OR($H$70="Residential BTL",$H$70="Retention "),$H$70="Retention "),Rate_Type="Fixed"),IFERROR(AO97/($L97/12*(Term-$K97)*'Product Data'!$P$23),0),IF(AND(Rate_Type="Tracker",OR(OR($H$70="Residential BTL",$H$70="Retention "),$H$70="Retention ")),IFERROR(AO97/($L97/12*(Term-$K97)*'Product Data'!$P$17),0),IF(AND($H$70="Semi-Commercial",Rate_Type="Tracker"),IFERROR(AP97/($L97/12*(Term-$K97)*'Product Data'!$P$17),0),IF(AND($H$70="Semi-Commercial",Rate_Type="Fixed"),IFERROR(AP97/($L97/12*(Term-$K97)*'Product Data'!$P$23),0),IF(AND($H$70="Commercial",Rate_Type="Tracker"),IFERROR(AP97/($L97/12*(Term-$K97)*'Product Data'!$P$17),0),IF(AND($H$70="Commercial",Rate_Type="Fixed"),IFERROR(AP97/($L97/12*(Term-$K97)*'Product Data'!$P$23),0))))))) -> FALSE | P97: =IF('BTL Calculator'!$H$28="Fixed","",IF(OR(OR($H$70="Residential BTL",$H$70="Retention "),$H$70="Retention "),AO97/((((H97-'Product Data'!$E$3+'Product Data'!$K$3-J97)/12*(Term-K97)))*'Product Data'!$P$18),AP97/((((H97-'Product Data'!$E$3+'Product Data'!$K$3-J97)/12*(Term-K97)))*'Product Data'!$P$18))) | Q97: =IF('BTL Calculator'!$H$28="Tracker",MIN(N97,P97),MIN(O97,N97)) -> 0 | R97: =ROUNDDOWN(Q97,-3) -> 0 | S97: =IFERROR((IF(RoundDown,R97,Q97)*J97/12*Term)+ (IF(RoundDown,R97,Q97)*L97/12*K97)+ (IF(RoundDown,R97,Q97)*L97/12*(Term-K97)),"-") -> 0 | T97: =IFERROR(((H97*IF(RoundDown,R97,Q97)/12)),"-") -> 0 | U97: =IF('BTL Calculator'!$H$28="Fixed","",(((L97+$U$73)*IF(RoundDown,R97,Q97)/12))) | V97: =IFERROR(((L97*IF(RoundDown,R97,Q97)/12)),"-") -> 0 | W97: =IF(OR($H$70="Residential BTL",$H$70="Retention "),IFERROR(AO97/Z97,"-"),IFERROR(AP97/Z97,"-")) -> - | X97: =IF('BTL Calculator'!$H$28="Fixed","",IF(OR($H$70="Residential BTL",$H$70="Retention "),IFERROR(AO97/AA97,"-"),IFERROR(AP97/AA97,"-"))) | Y97: =TEXT(V97,"£0,0")&" @ "&TEXT(W97,"0%")&" ICR" -> £00 @ - ICR | Z97: =(IF(RoundDown,R97,Q97)*L97)/12*(Term-K97) -> 0 | AA97: =IF('BTL Calculator'!$H$28="Fixed","",(IF(RoundDown,R97,Q97)*(H97-'Product Data'!$E$3+'Product Data'!$K$2-J97))/12*(Term-K97)) | AB97: =IFERROR(Monthly_Rent*Term,"-") -> 0 | AC97: =IFERROR($U$22-V97,"-") -> 0 | AD97: =((J97*IF(RoundDown,R97,Q97))/12)*Term -> 0 | AE97: =K97*L97/12*IF(RoundDown,R97,Q97) -> 0 | AF97: =SUM(AD97:AE97) -> 0 | AG97: =AL97+AI97 -> 0 | AH97: =+AI97+AJ97 -> 0 | AI97: =+IF(RoundDown,R97,Q97)*0.02 -> 0 | AJ97: =+IF(RoundDown,R97,Q97)*I97-AI97 -> 0 | AK97: =TEXT(I97,"0.00%")&" ("&TEXT(AH97,"£0,0")&")" -> 4.00% (£00) | AL97: =IF(RoundDown,R97,Q97)-AD97-AE97-AH97 -> 0 | AM97: =AL97/Property_Value -> #DIV/0! | AN97: =IF(RoundDown,R97,Q97)/Property_Value -> #DIV/0! | AO97: =Rent_Over_Term+AQ97 -> 0 | AP97: =IF($H$72="3 Year Fixed",$X$22*36+AQ97, $X$22*24+AQ97) -> 0 | AQ97: ='BTL Calculator'!$I$80*Term -> 0 | AR97: =IF(ISERROR(FIND("Bespoke",F79,1)),FALSE,TRUE) -> FALSE | AS97: =IFERROR(IF(AND(IF(RoundDown,R97,Q97)=$E$70,E97>=$F$36),1,0),"-") -> 0 | AT97: =IFERROR(IF(AND(AL97=$E$71,E97>=$F$36),1,0),"-") -> - | AU97: =SUM(AS97:AT97) -> 0 | AV97: =IF(IF(Rate_Type="Tracker",X97,W97)>'Product Data'!$P$19,"Y","N") -> Y | AY97: =+IF(RoundDown,AH97,AG97)*Y97-AZ97 -> #VALUE! | AZ97: =+IF(RoundDown,AH97,AG97)*0.02 -> 0
B98: =IF(AND('BTL Calculator'!$G$60=C97,F98='BTL Calculator'!$G$62),1,0) -> 0 | D98: 6 | E98: =VALUE(LEFT(F98,1)) -> 0 | F98: =IF($H$70='Product Data'!$BT5,'Product Data'!$B191,IF($H$70='Product Data'!$BT2,'Product Data'!$B10,IF($H$70='Product Data'!BT3,'Product Data'!B35,IF(H70='Product Data'!BT4,'Product Data'!B48,0)))) -> 0 | H98: =H95 -> FALSE | I98: =I95 -> 0.04 | J98: =IF(AND(H70="Retention ",H72="Tracker"),2%,IF(AND($H$70='Product Data'!$BT$2,$H$72='Product Data'!$CA$2),2%,IF(AND($H$70='Product Data'!$BT$3,$H$72='Product Data'!$CA$2),1.5%,IF(AND($H$70='Product Data'!$BT$4,$H$72='Product Data'!$CA$2),1.5%,IF(AND($H$70='Product Data'!$BT$2,$H$72='Product Data'!$CA$5),0.75%,1.25%))))) -> 0.0125 | K98: =IF(OR(OR($H$70="Residential BTL",$H$70="Retention "),$H$70="Retention "),IF(Term<36,'Product Data'!$P$11,'Product Data'!$P$13),6) -> 6 | L98: =H98-J98 -> -0.0125 | M98: =M95 -> 0.7 | N98: =MIN(M98*Property_Value,'Product Data'!$P$16) -> 0 | O98: =IF(AND(OR(OR($H$70="Residential BTL",$H$70="Retention "),$H$70="Retention "),Rate_Type="Fixed"),IFERROR(AO98/($L98/12*(Term-$K98)*'Product Data'!$P$23),0),IF(AND(Rate_Type="Tracker",OR(OR($H$70="Residential BTL",$H$70="Retention "),$H$70="Retention ")),IFERROR(AO98/($L98/12*(Term-$K98)*'Product Data'!$P$17),0),IF(AND($H$70="Semi-Commercial",Rate_Type="Tracker"),IFERROR(AP98/($L98/12*(Term-$K98)*'Product Data'!$P$17),0),IF(AND($H$70="Semi-Commercial",Rate_Type="Fixed"),IFERROR(AP98/($L98/12*(Term-$K98)*'Product Data'!$P$23),0),IF(AND($H$70="Commercial",Rate_Type="Tracker"),IFERROR(AP98/($L98/12*(Term-$K98)*'Product Data'!$P$17),0),IF(AND($H$70="Commercial",Rate_Type="Fixed"),IFERROR(AP98/($L98/12*(Term-$K98)*'Product Data'!$P$23),0))))))) -> FALSE | P98: =IF('BTL Calculator'!$H$28="Fixed","",IF(OR(OR($H$70="Residential BTL",$H$70="Retention "),$H$70="Retention "),AO98/((((H98-'Product Data'!$E$3+'Product Data'!$K$3-J98)/12*(Term-K98)))*'Product Data'!$P$18),AP98/((((H98-'Product Data'!$E$3+'Product Data'!$K$3-J98)/12*(Term-K98)))*'Product Data'!$P$18))) | Q98: =IF('BTL Calculator'!$H$28="Tracker",MIN(N98,P98),MIN(O98,N98)) -> 0 | R98: =ROUNDDOWN(Q98,-3) -> 0 | S98: =IFERROR((IF(RoundDown,R98,Q98)*J98/12*Term)+ (IF(RoundDown,R98,Q98)*L98/12*K98)+ (IF(RoundDown,R98,Q98)*L98/12*(Term-K98)),"-") -> 0 | T98: =IFERROR(((H98*IF(RoundDown,R98,Q98)/12)),"-") -> 0 | U98: =IF('BTL Calculator'!$H$28="Fixed","",(((L98+$U$73)*IF(RoundDown,R98,Q98)/12))) | V98: =((L98*IF(RoundDown,R98,Q98)/12))-IF('BTL Calculator'!$CY$11='Product Data'!$AG$9,AE98/Term,0) -> 0 | W98: =IF(OR($H$70="Residential BTL",$H$70="Retention "),IFERROR(AO98/Z98,"-"),IFERROR(AP98/Z98,"-")) -> - | X98: =IF('BTL Calculator'!$H$28="Fixed","",IF(OR($H$70="Residential BTL",$H$70="Retention "),IFERROR(AO98/AA98,"-"),IFERROR(AP98/AA98,"-"))) | Y98: =TEXT(V98,"£0,0")&" @ "&TEXT(W98,"0%")&" ICR" -> £00 @ - ICR | Z98: =(IF(RoundDown,R98,Q98)*L98)/12*(Term-K98) -> 0 | AA98: =IF('BTL Calculator'!$H$28="Fixed","",(IF(RoundDown,R98,Q98)*(H98-'Product Data'!$E$3+'Product Data'!$K$2-J98))/12*(Term-K98)) | AB98: =IFERROR(Monthly_Rent*Term,"-") -> 0 | AC98: =IFERROR($U$22-V98,"-") -> 0 | AD98: =((J98*IF(RoundDown,R98,Q98))/12)*Term -> 0 | AE98: =K98*L98/12*IF(RoundDown,R98,Q98) -> 0 | AF98: =SUM(AD98:AE98) -> 0 | AG98: =AL98+AI98 -> 0 | AH98: =+AI98+AJ98 -> 0 | AI98: =+IF(RoundDown,R98,Q98)*0.02 -> 0 | AJ98: =+IF(RoundDown,R98,Q98)*I98-AI98 -> 0 | AK98: =TEXT(I98,"0.00%")&" ("&TEXT(AH98,"£0,0")&")" -> 4.00% (£00) | AL98: =IF(RoundDown,R98,Q98)-AD98-AE98-AH98 -> 0 | AM98: =AL98/Property_Value -> #DIV/0! | AN98: =IF(RoundDown,R98,Q98)/Property_Value -> #DIV/0! | AO98: =Rent_Over_Term+AQ98 -> 0 | AP98: =IF($H$72="3 Year Fixed",$X$22*36+AQ98, $X$22*24+AQ98) -> 0 | AQ98: ='BTL Calculator'!$I$80*Term -> 0 | AR98: =IF(ISERROR(FIND("Bespoke",F80,1)),FALSE,TRUE) -> FALSE | AS98: =IFERROR(IF(AND(IF(RoundDown,R98,Q98)=$E$70,E98>=$F$36),1,0),"-") -> 0 | AT98: =IFERROR(IF(AND(AL98=$E$71,E98>=$F$36),1,0),"-") -> - | AU98: =SUM(AS98:AT98) -> 0 | AV98: =IF(IF(Rate_Type="Tracker",X98,W98)>'Product Data'!$P$19,"Y","N") -> Y | AY98: =+IF(RoundDown,AH98,AG98)*Y98-AZ98 -> #VALUE! | AZ98: =+IF(RoundDown,AH98,AG98)*0.02 -> 0
B99: =IF(OR($H$70="Residential BTL",$H$70="Retention "),IF(AND('BTL Calculator'!$G$60=C97,F99='BTL Calculator'!$G$62),1,0),"") | D99: =IF(OR(OR($H$70="Residential BTL",$H$70="Retention "),$H$70="Retention "),7,"") | E99: =IF(OR(OR($H$70="Residential BTL",$H$70="Retention "),$H$70="Retention "),VALUE(LEFT(F99,1)),"") | F99: =IF(OR(OR($H$70="Residential BTL",$H$70="Retention "),$H$70="Retention "),"3) Specialist BTL","") | H99: =H96 | I99: =I96 -> 0.04 | J99: =IF(AND(H70="Retention ",H72="Tracker"),2%,IF(AND($H$70='Product Data'!$BT$2,$H$72='Product Data'!$CA$2),2%,IF(AND($H$70='Product Data'!$BT$3,$H$72='Product Data'!$CA$2),1.5%,IF(AND($H$70='Product Data'!$BT$4,$H$72='Product Data'!$CA$2),1.5%,IF(AND($H$70='Product Data'!$BT$2,$H$72='Product Data'!$CA$5),0.75%,1.25%))))) -> 0.0125 | K99: =IF(OR(OR($H$70="Residential BTL",$H$70="Retention "),$H$70="Retention "),IF(Term<36,'Product Data'!$P$11,'Product Data'!$P$13),"") | L99: =IF('BTL Calculator'!V2="Core","",IF(OR(OR($H$70="Residential BTL",$H$70="Retention "),$H$70="Retention "),H99-J99,"")) | M99: =M96 | N99: =IF(OR(OR($H$70="Residential BTL",$H$70="Retention "),$H$70="Retention "),MIN(M99*Property_Value,'Product Data'!$P$16),"") | O99: =IF(AND(OR(OR($H$70="Residential BTL",$H$70="Retention "),$H$70="Retention "),Rate_Type="Fixed"),IFERROR(AO99/($L99/12*(Term-$K99)*'Product Data'!$P$23),0),IF(AND(Rate_Type="Tracker",OR(OR($H$70="Residential BTL",$H$70="Retention "),$H$70="Retention ")),IFERROR(AO99/($L99/12*(Term-$K99)*'Product Data'!$P$17),0),IF(AND($H$70="Semi-Commercial",Rate_Type="Tracker"),IFERROR(AP99/($L99/12*(Term-$K99)*'Product Data'!$P$17),0),IF(AND($H$70="Semi-Commercial",Rate_Type="Fixed"),IFERROR(AP99/($L99/12*(Term-$K99)*'Product Data'!$P$23),0),IF(AND($H$70="Commercial",Rate_Type="Tracker"),IFERROR(AP99/($L99/12*(Term-$K99)*'Product Data'!$P$17),0),IF(AND($H$70="Commercial",Rate_Type="Fixed"),IFERROR(AP99/($L99/12*(Term-$K99)*'Product Data'!$P$23),0))))))) -> FALSE | P99: =IF('BTL Calculator'!$H$28="Fixed","",IF(OR(OR($H$70="Residential BTL",$H$70="Retention "),$H$70="Retention "),AO99/((((H99-'Product Data'!$E$3+'Product Data'!$K$3-J99)/12*(Term-K99)))*'Product Data'!$P$18),AP99/((((H99-'Product Data'!$E$3+'Product Data'!$K$3-J99)/12*(Term-K99)))*'Product Data'!$P$18))) | Q99: =IF(OR($H$70="Residential BTL",$H$70="Retention "),IF('BTL Calculator'!$H$28="Tracker",MIN(N99,P99),MIN(O99,N99)),"") | R99: =IF(OR($H$70="Residential BTL",$H$70="Retention "),ROUNDDOWN(Q99,-3),"") | S99: =IFERROR((IF(RoundDown,R99,Q99)*J99/12*Term)+ (IF(RoundDown,R99,Q99)*L99/12*K99)+ (IF(RoundDown,R99,Q99)*L99/12*(Term-K99)),"-") -> - | T99: =IFERROR(((H99*IF(RoundDown,R99,Q99)/12)),"-") -> - | U99: =IF('BTL Calculator'!$H$28="Fixed","",(((L99+$U$73)*IF(RoundDown,R99,Q99)/12))) | V99: =IF('BTL Calculator'!$V$2="Core","",IF(OR($H$70="Residential BTL",$H$70="Retention "),((L99*IF(RoundDown,R99,Q99)/12))-IF('BTL Calculator'!$CY$11='Product Data'!$AG$9,AE99/Term,0),"")) | W99: =IF(OR($H$70="Residential BTL",$H$70="Retention "),IFERROR(AO99/Z99,"-"),"") | X99: =IF('BTL Calculator'!$H$28="Fixed","",IF(OR($H$70="Residential BTL",$H$70="Retention "),IFERROR(AO99/AA99,"-"),IFERROR(AP99/AA99,"-"))) | Y99: =IF(OR($H$70="Residential BTL",$H$70="Retention "),TEXT(V99,"£0,0")&" @ "&TEXT(W99,"0%")&" ICR","") | Z99: =IF('BTL Calculator'!$V$2="Core","",IF(OR($H$70="Residential BTL",$H$70="Retention "),(IF(RoundDown,R99,Q99)*L99)/12*(Term-K99),"")) | AA99: =IF('BTL Calculator'!$H$28="Fixed","",(IF(RoundDown,R99,Q99)*(H99-'Product Data'!$E$3+'Product Data'!$K$2-J99))/12*(Term-K99)) | AB99: =IF(OR($H$70="Residential BTL",$H$70="Retention "),IFERROR(Monthly_Rent*Term,"-"),"") | AC99: =IF(OR($H$70="Residential BTL",$H$70="Retention "),IFERROR($U$22-V99,"-"),"") | AD99: =((J99*IF(RoundDown,R99,Q99))/12)*Term -> #VALUE! | AE99: =IF('BTL Calculator'!$V$2="Core","",K99*L99/12*IF(RoundDown,R99,Q99)) -> #VALUE! | AF99: =IF(OR($H$70="Residential BTL",$H$70="Retention "),SUM(AD99:AE99),"") | AG99: =IF('BTL Calculator'!V2="Core","",IF(OR($H$70="Residential BTL",$H$70="Retention "),AL99+AI99,"")) | AH99: =+AI99+AJ99 -> #VALUE! | AI99: =+IF(RoundDown,R99,Q99)*0.02 -> #VALUE! | AJ99: =+IF(RoundDown,R99,Q99)*I99-AI99 -> #VALUE! | AK99: =IF(OR($H$70="Residential BTL",$H$70="Retention "),TEXT(I99,"0.00%")&" ("&TEXT(AH99,"£0,0")&")","") | AL99: =IF('BTL Calculator'!V2="Core","",IF(OR($H$70="Residential BTL",$H$70="Retention "),IF(RoundDown,R99,Q99)-AD99-AE99-AH99,"")) | AM99: =IF(OR($H$70="Residential BTL",$H$70="Retention "),AL99/Property_Value,"") | AN99: =IF(OR($H$70="Residential BTL",$H$70="Retention "),IF(RoundDown,R99,Q99)/Property_Value,"") | AO99: =IF(OR($H$70="Residential BTL",$H$70="Retention "),Rent_Over_Term+AQ99,"") | AQ99: =IF(OR($H$70="Residential BTL",$H$70="Retention "),'BTL Calculator'!$I$80*Term,"") | AR99: =IF(OR($H$70="Residential BTL",$H$70="Retention "),IF(ISERROR(FIND("Bespoke",F81,1)),FALSE,TRUE),"") | AS99: =IF(OR($H$70="Residential BTL",$H$70="Retention "),IFERROR(IF(AND(IF(RoundDown,R99,Q99)=$E$70,E99>=$F$36),1,0),"-"),"") | AT99: =IF(OR($H$70="Residential BTL",$H$70="Retention "),IFERROR(IF(AND(AL99=$E$71,E99>=$F$36),1,0),"-"),"") | AU99: =IF(OR($H$70="Residential BTL",$H$70="Retention "),SUM(AS99:AT99),"") | AV99: =IF(OR($H$70="Residential BTL",$H$70="Retention "),IF(IF(Rate_Type="Tracker",X99,W99)>'Product Data'!$P$19,"Y","N"),"") | AY99: =+IF(RoundDown,AH99,AG99)*Y99-AZ99 -> #VALUE! | AZ99: =+IF(RoundDown,AH99,AG99)*0.02 -> #VALUE!
B100: =IF(AND('BTL Calculator'!$G$60=C100,F100='BTL Calculator'!$G$62),1,0) -> 0 | C100: Fully Rolled and Deferred underwriter | D100: 9 | E100: =VALUE(LEFT(F100,1)) -> 1 | F100: 1) Standard BTL | H100: =H97 -> FALSE | I100: =I97 -> 0.04 | J100: ='Product Data'!$P$10 -> 0.02 | K100: =IF(Term<36,'Product Data'!$P$12,'Product Data'!$P$14) -> 9 | L100: =IFERROR(H100-J100,"-") -> -0.02 | M100: =M97 -> 0.7 | N100: =MIN(M100*Property_Value,'Product Data'!$P$16) -> 0 | O100: =IF(AND(OR(OR($H$70="Residential BTL",$H$70="Retention "),$H$70="Retention "),Rate_Type="Fixed"),IFERROR(AO100/($L100/12*(Term-$K100)*'Product Data'!$P$23),0),IF(AND(Rate_Type="Tracker",OR(OR($H$70="Residential BTL",$H$70="Retention "),$H$70="Retention ")),IFERROR(AO100/($L100/12*(Term-$K100)*'Product Data'!$P$17),0),IF(AND($H$70="Semi-Commercial",Rate_Type="Tracker"),IFERROR(AP100/($L100/12*(Term-$K100)*'Product Data'!$P$17),0),IF(AND($H$70="Semi-Commercial",Rate_Type="Fixed"),IFERROR(AP100/($L100/12*(Term-$K100)*'Product Data'!$P$23),0),IF(AND($H$70="Commercial",Rate_Type="Tracker"),IFERROR(AP100/($L100/12*(Term-$K100)*'Product Data'!$P$17),0),IF(AND($H$70="Commercial",Rate_Type="Fixed"),IFERROR(AP100/($L100/12*(Term-$K100)*'Product Data'!$P$23),0))))))) -> FALSE | P100: =IF('BTL Calculator'!$H$28="Fixed","",IF(OR(OR($H$70="Residential BTL",$H$70="Retention "),$H$70="Retention "),AO100/((((H100-'Product Data'!$E$3+'Product Data'!$K$3-J100)/12*(Term-K100)))*'Product Data'!$P$18),AP100/((((H100-'Product Data'!$E$3+'Product Data'!$K$3-J100)/12*(Term-K100)))*'Product Data'!$P$18))) | Q100: =IF('BTL Calculator'!$H$28="Tracker",MIN(N100,P100),MIN(O100,N100)) -> 0 | R100: =ROUNDDOWN(Q100,-3) -> 0 | S100: =IFERROR((IF(RoundDown,R100,Q100)*J100/12*Term)+ (IF(RoundDown,R100,Q100)*L100/12*K100)+ (IF(RoundDown,R100,Q100)*L100/12*(Term-K100)),"-") -> 0 | T100: =IFERROR(((H100*IF(RoundDown,R100,Q100)/12)),"-") -> 0 | U100: =IF('BTL Calculator'!$H$28="Fixed","",(((L100+$U$73)*IF(RoundDown,R100,Q100)/12))) | V100: =IFERROR(((L100*IF(RoundDown,R100,Q100)/12)),"-") -> 0 | W100: =IFERROR(AO100/Z100,"-") -> - | X100: =IF('BTL Calculator'!$H$28="Fixed","",IF(OR($H$70="Residential BTL",$H$70="Retention "),IFERROR(AO100/AA100,"-"),IFERROR(AP100/AA100,"-"))) | Y100: =TEXT(V100,"£0,0")&" @ "&TEXT(W100,"0%")&" ICR" -> £00 @ - ICR | Z100: =(IF(RoundDown,R100,Q100)*L100)/12*(Term-K100) -> 0 | AA100: =IF('BTL Calculator'!$H$28="Fixed","",(IF(RoundDown,R100,Q100)*(H100-'Product Data'!$E$3+'Product Data'!$K$2-J100))/12*(Term-K100)) | AB100: =IFERROR(Monthly_Rent*Term,"-") -> 0 | AC100: =IFERROR($U$22-V100,"-") -> 0 | AD100: =((J100*IF(RoundDown,R100,Q100))/12)*Term -> 0 | AE100: =K100*L100/12*IF(RoundDown,R100,Q100) -> 0 | AF100: =SUM(AD100:AE100) -> 0 | AG100: =AL100+AI100 -> 0 | AH100: =IF(RoundDown,R100,Q100)*I100 -> 0 | AI100: =+IF(RoundDown,R100,Q100)*0.02 -> 0 | AJ100: =+IF(RoundDown,R100,Q100)*I100-AI100 -> 0 | AK100: =TEXT(I100,"0.00%")&" ("&TEXT(AH100,"£0,0")&")" -> 4.00% (£00) | AL100: =IF(RoundDown,R100,Q100)-AD100-AE100-AH100 -> 0 | AM100: =AL100/Property_Value -> #DIV/0! | AN100: =IF(RoundDown,R100,Q100)/Property_Value -> #DIV/0! | AO100: =Rent_Over_Term+AQ100 -> 0 | AQ100: ='BTL Calculator'!$I$80*Term -> 0 | AR100: =IF(ISERROR(FIND("Bespoke",F82,1)),FALSE,TRUE) -> FALSE | AS100: =IFERROR(IF(AND(IF(RoundDown,R100,Q100)=$E$70,E100>=$F$36),1,0),"-") -> 1 | AT100: =IFERROR(IF(AND(AL100=$E$71,E100>=$F$36),1,0),"-") -> - | AU100: =SUM(AS100:AT100) -> 1 | AV100: =IF(IF(Rate_Type="Tracker",X100,W100)>'Product Data'!$P$19,"Y","N") -> Y | AY100: =AX100/2 -> 0 | AZ100: =AX100-AY100 -> 0
B101: =IF(AND('BTL Calculator'!$G$60=C100,F101='BTL Calculator'!$G$62),1,0) -> 0 | D101: 10 | E101: =VALUE(LEFT(F101,1)) -> 2 | F101: 2) Solutions BTL | H101: =H98 -> FALSE | I101: =I98 -> 0.04 | J101: ='Product Data'!$P$10 -> 0.02 | K101: =IF(Term<36,'Product Data'!$P$12,'Product Data'!$P$14) -> 9 | L101: =H101-J101 -> -0.02 | M101: =M98 -> 0.7 | N101: =MIN(M101*Property_Value,'Product Data'!$P$16) -> 0 | O101: =IF(AND(OR(OR($H$70="Residential BTL",$H$70="Retention "),$H$70="Retention "),Rate_Type="Fixed"),IFERROR(AO101/($L101/12*(Term-$K101)*'Product Data'!$P$23),0),IF(AND(Rate_Type="Tracker",OR(OR($H$70="Residential BTL",$H$70="Retention "),$H$70="Retention ")),IFERROR(AO101/($L101/12*(Term-$K101)*'Product Data'!$P$17),0),IF(AND($H$70="Semi-Commercial",Rate_Type="Tracker"),IFERROR(AP101/($L101/12*(Term-$K101)*'Product Data'!$P$17),0),IF(AND($H$70="Semi-Commercial",Rate_Type="Fixed"),IFERROR(AP101/($L101/12*(Term-$K101)*'Product Data'!$P$23),0),IF(AND($H$70="Commercial",Rate_Type="Tracker"),IFERROR(AP101/($L101/12*(Term-$K101)*'Product Data'!$P$17),0),IF(AND($H$70="Commercial",Rate_Type="Fixed"),IFERROR(AP101/($L101/12*(Term-$K101)*'Product Data'!$P$23),0))))))) -> FALSE | P101: =IF('BTL Calculator'!$H$28="Fixed","",IF(OR(OR($H$70="Residential BTL",$H$70="Retention "),$H$70="Retention "),AO101/((((H101-'Product Data'!$E$3+'Product Data'!$K$3-J101)/12*(Term-K101)))*'Product Data'!$P$18),AP101/((((H101-'Product Data'!$E$3+'Product Data'!$K$3-J101)/12*(Term-K101)))*'Product Data'!$P$18))) | Q101: =IF('BTL Calculator'!$H$28="Tracker",MIN(N101,P101),MIN(O101,N101)) -> 0 | R101: =ROUNDDOWN(Q101,-3) -> 0 | S101: =IFERROR((IF(RoundDown,R101,Q101)*J101/12*Term)+ (IF(RoundDown,R101,Q101)*L101/12*K101)+ (IF(RoundDown,R101,Q101)*L101/12*(Term-K101)),"-") -> 0 | T101: =((H101*IF(RoundDown,R101,Q101)/12)) -> 0 | U101: =IF('BTL Calculator'!$H$28="Fixed","",(((L101+$U$73)*IF(RoundDown,R101,Q101)/12))) | V101: =((L101*IF(RoundDown,R101,Q101)/12))-IF('BTL Calculator'!$CY$11='Product Data'!$AG$9,AE101/Term,0) -> 0 | W101: =IFERROR(AO101/Z101,"-") -> - | X101: =IF('BTL Calculator'!$H$28="Fixed","",IF(OR($H$70="Residential BTL",$H$70="Retention "),IFERROR(AO101/AA101,"-"),IFERROR(AP101/AA101,"-"))) | Y101: =TEXT(V101,"£0,0")&" @ "&TEXT(W101,"0%")&" ICR" -> £00 @ - ICR | Z101: =(IF(RoundDown,R101,Q101)*L101)/12*(Term-K101) -> 0 | AA101: =IF('BTL Calculator'!$H$28="Fixed","",(IF(RoundDown,R101,Q101)*(H101-'Product Data'!$E$3+'Product Data'!$K$2-J101))/12*(Term-K101)) | AB101: =IFERROR(Monthly_Rent*Term,"-") -> 0 | AC101: =IFERROR($U$22-V101,"-") -> 0 | AD101: =((J101*IF(RoundDown,R101,Q101))/12)*Term -> 0 | AE101: =K101*L101/12*IF(RoundDown,R101,Q101) -> 0 | AF101: =SUM(AD101:AE101) -> 0 | AG101: =AL101+AI101 -> 0 | AH101: =IF(RoundDown,R101,Q101)*I101 -> 0 | AI101: =+IF(RoundDown,R101,Q101)*0.02 -> 0 | AJ101: =+IF(RoundDown,R101,Q101)*I101-AI101 -> 0 | AK101: =TEXT(I101,"0.00%")&" ("&TEXT(AH101,"£0,0")&")" -> 4.00% (£00) | AL101: =IF(RoundDown,R101,Q101)-AD101-AE101-AH101 -> 0 | AM101: =AL101/Property_Value -> #DIV/0! | AN101: =IF(RoundDown,R101,Q101)/Property_Value -> #DIV/0! | AO101: =Rent_Over_Term+AQ101 -> 0 | AQ101: ='BTL Calculator'!$I$80*Term -> 0 | AR101: =IF(ISERROR(FIND("Bespoke",F83,1)),FALSE,TRUE) -> FALSE | AS101: =IFERROR(IF(AND(IF(RoundDown,R101,Q101)=$E$70,E101>=$F$36),1,0),"-") -> 1 | AT101: =IFERROR(IF(AND(AL101=$E$71,E101>=$F$36),1,0),"-") -> - | AU101: =SUM(AS101:AT101) -> 1 | AV101: =IF(IF(Rate_Type="Tracker",X101,W101)>'Product Data'!$P$19,"Y","N") -> Y | AY101: =AX101/2 -> 0 | AZ101: =AX101-AY101 -> 0
B102: =IF(OR($H$70="Residential BTL",$H$70="Retention "),IF(AND('BTL Calculator'!$G$60=C100,F102='BTL Calculator'!$G$62),1,0),"") | D102: =IF(OR($H$70="Residential BTL",$H$70="Retention "),11,"") | E102: =IF(OR($H$70="Residential BTL",$H$70="Retention "),VALUE(LEFT(F102,1)),"") | F102: =IF(OR($H$70="Residential BTL",$H$70="Retention "),"3) Specialist BTL","") | H102: =H99 | I102: =I99 -> 0.04 | J102: =IF(OR($H$70="Residential BTL",$H$70="Retention "),'Product Data'!$P$10,"") | K102: =IF(OR($H$70="Residential BTL",$H$70="Retention "),IF(Term<36,'Product Data'!$P$12,'Product Data'!$P$14),"") | L102: =IF(OR($H$70="Residential BTL",$H$70="Retention "),H102-J102,"") | M102: =M99 | N102: =IF(OR($H$70="Residential BTL",$H$70="Retention "),MIN(M102*Property_Value,'Product Data'!$P$16),"") | O102: =IF(AND(OR(OR($H$70="Residential BTL",$H$70="Retention "),$H$70="Retention "),Rate_Type="Fixed"),IFERROR(AO102/($L102/12*(Term-$K102)*'Product Data'!$P$23),0),IF(AND(Rate_Type="Tracker",OR(OR($H$70="Residential BTL",$H$70="Retention "),$H$70="Retention ")),IFERROR(AO102/($L102/12*(Term-$K102)*'Product Data'!$P$17),0),IF(AND($H$70="Semi-Commercial",Rate_Type="Tracker"),IFERROR(AP102/($L102/12*(Term-$K102)*'Product Data'!$P$17),0),IF(AND($H$70="Semi-Commercial",Rate_Type="Fixed"),IFERROR(AP102/($L102/12*(Term-$K102)*'Product Data'!$P$23),0),IF(AND($H$70="Commercial",Rate_Type="Tracker"),IFERROR(AP102/($L102/12*(Term-$K102)*'Product Data'!$P$17),0),IF(AND($H$70="Commercial",Rate_Type="Fixed"),IFERROR(AP102/($L102/12*(Term-$K102)*'Product Data'!$P$23),0))))))) -> FALSE | P102: =IF('BTL Calculator'!$H$28="Fixed","",IF(OR(OR($H$70="Residential BTL",$H$70="Retention "),$H$70="Retention "),AO102/((((H102-'Product Data'!$E$3+'Product Data'!$K$3-J102)/12*(Term-K102)))*'Product Data'!$P$18),AP102/((((H102-'Product Data'!$E$3+'Product Data'!$K$3-J102)/12*(Term-K102)))*'Product Data'!$P$18))) | Q102: =IF(OR($H$70="Residential BTL",$H$70="Retention "),IF('BTL Calculator'!$H$28="Tracker",MIN(N102,P102),MIN(O102,N102)),"") | R102: =IF(OR($H$70="Residential BTL",$H$70="Retention "),ROUNDDOWN(Q102,-3),"") | S102: =IFERROR((IF(RoundDown,R102,Q102)*J102/12*Term)+ (IF(RoundDown,R102,Q102)*L102/12*K102)+ (IF(RoundDown,R102,Q102)*L102/12*(Term-K102)),"-") -> - | T102: =IF(OR($H$70="Residential BTL",$H$70="Retention "),((H102*IF(RoundDown,R102,Q102)/12)),"") | U102: =IF('BTL Calculator'!$H$28="Fixed","",(((L102+$U$73)*IF(RoundDown,R102,Q102)/12))) | V102: =IF(OR($H$70="Residential BTL",$H$70="Retention "),((L102*IF(RoundDown,R102,Q102)/12))-IF('BTL Calculator'!$CY$11='Product Data'!$AG$9,AE102/Term,0),"") | W102: =IF(OR($H$70="Residential BTL",$H$70="Retention "),IFERROR(AO102/Z102,"-"),"") | X102: =IF('BTL Calculator'!$H$28="Fixed","",IF(OR($H$70="Residential BTL",$H$70="Retention "),IFERROR(AO102/AA102,"-"),IFERROR(AP102/AA102,"-"))) | Y102: =IF(OR($H$70="Residential BTL",$H$70="Retention "),TEXT(V102,"£0,0")&" @ "&TEXT(W102,"0%")&" ICR","") | Z102: =IF(OR($H$70="Residential BTL",$H$70="Retention "),(IF(RoundDown,R102,Q102)*L102)/12*(Term-K102),"") | AA102: =IF('BTL Calculator'!$H$28="Fixed","",(IF(RoundDown,R102,Q102)*(H102-'Product Data'!$E$3+'Product Data'!$K$2-J102))/12*(Term-K102)) | AB102: =IF(OR($H$70="Residential BTL",$H$70="Retention "),IFERROR(Monthly_Rent*Term,"-"),"") | AC102: =IF(OR($H$70="Residential BTL",$H$70="Retention "),IFERROR($U$22-V102,"-"),"") | AD102: =((J102*IF(RoundDown,R102,Q102))/12)*Term -> #VALUE! | AE102: =K102*L102/12*IF(RoundDown,R102,Q102) -> #VALUE! | AF102: =IF(OR($H$70="Residential BTL",$H$70="Retention "),SUM(AD102:AE102),"") | AG102: =IF(OR($H$70="Residential BTL",$H$70="Retention "),AL102+AI102,"") | AH102: =IF(OR($H$70="Residential BTL",$H$70="Retention "),IF(RoundDown,R102,Q102)*I102,"") | AI102: =+IF(RoundDown,R102,Q102)*0.02 -> #VALUE! | AJ102: =+IF(RoundDown,R102,Q102)*I102-AI102 -> #VALUE! | AK102: =IF(OR($H$70="Residential BTL",$H$70="Retention "),TEXT(I102,"0.00%")&" ("&TEXT(AH102,"£0,0")&")","") | AL102: =IF(OR($H$70="Residential BTL",$H$70="Retention "),IF(RoundDown,R102,Q102)-AD102-AE102-AH102,"") | AM102: =IF(OR($H$70="Residential BTL",$H$70="Retention "),AL102/Property_Value,"") | AN102: =IF(OR($H$70="Residential BTL",$H$70="Retention "),IF(RoundDown,R102,Q102)/Property_Value,"") | AO102: =IF(OR($H$70="Residential BTL",$H$70="Retention "),Rent_Over_Term+AQ102,"") | AQ102: =IF(OR($H$70="Residential BTL",$H$70="Retention "),'BTL Calculator'!$I$80*Term,"") | AR102: =IF(OR($H$70="Residential BTL",$H$70="Retention "),IF(ISERROR(FIND("Bespoke",F84,1)),FALSE,TRUE),"") | AS102: =IF(OR($H$70="Residential BTL",$H$70="Retention "),IFERROR(IF(AND(IF(RoundDown,R102,Q102)=$E$70,E102>=$F$36),1,0),"-"),"") | AT102: =IF(OR($H$70="Residential BTL",$H$70="Retention "),IFERROR(IF(AND(AL102=$E$71,E102>=$F$36),1,0),"-"),"") | AU102: =IF(OR($H$70="Residential BTL",$H$70="Retention "),SUM(AS102:AT102),"") | AV102: =IF(OR($H$70="Residential BTL",$H$70="Retention "),IF(IF(Rate_Type="Tracker",X102,W102)>'Product Data'!$P$19,"Y","N"),"") | AY102: =IF(OR($H$70="Residential BTL",$H$70="Retention "),AX102/2,"") | AZ102: =IF(OR($H$70="Residential BTL",$H$70="Retention "),AX102-AY102,"")
B103: =IF('BTL Calculator'!$V$2="Core",0,IF(AND('BTL Calculator'!$G$60=C103,F103='BTL Calculator'!$G$62),1,0)) -> 0 | C103: Custom - adjust roll/defer/top slice | D103: 13 | E103: =VALUE(LEFT(F103,1)) -> 0 | F103: =IF($H$70='Product Data'!$BT5,'Product Data'!$B190,IF($H$70='Product Data'!$BT2,'Product Data'!$B9,IF($H$70='Product Data'!BT3,'Product Data'!B34,IF(H70='Product Data'!BT4,'Product Data'!B47,0)))) -> 0 | H103: =H97 -> FALSE | I103: =I97 -> 0.04 | J103: =IF(AND(Rate_Type="Fixed",H72="3 Year Fixed"),IF(Defer4>'Product Data'!$P$24,'Product Data'!$P$24,Defer4),IF(AND(Rate_Type="Fixed",H72="2 Year Fixed"),IF(Defer4>'Product Data'!$P$24,'Product Data'!$P$24,Defer4),IF(AND(Rate_Type="Fixed",H72="5 Year Fixed"),IF(Defer4>'Product Data'!$P$33,'Product Data'!$P$33,Defer4),IF(AND(Rate_Type="Tracker",$H$70="Commercial"),IF(Defer4>0.015,0.015,Defer4),IF(AND(Rate_Type="Tracker",$H$70="Semi-Commercial"),IF(Defer4>0.015,0.015,Defer4),IF(AND(Rate_Type="Tracker",OR($H$70="Residential BTL",$H$70="Retention ")),IF(Defer4>0.02,0.02,Defer4))))))) -> FALSE | K103: =IF(Roll4="",0,IF(OR(OR($H$70="Residential BTL",$H$70="Retention "),$H$70="Retention "),MAX(MIN(Roll4,'Product Data'!$P$12),0),MAX(MIN(Roll4,6),0))) -> 0 | L103: =IFERROR(H103-J103,"-") -> 0 | M103: =M97 -> 0.7 | N103: =MIN(M103*Property_Value,'Product Data'!$P$16) -> 0 | O103: =IF(AND(OR(OR($H$70="Residential BTL",$H$70="Retention "),$H$70="Retention "),Rate_Type="Fixed"),IFERROR(AO103/($L103/12*(Term-$K103)*'Product Data'!$P$23),0),IF(AND(Rate_Type="Tracker",OR(OR($H$70="Residential BTL",$H$70="Retention "),$H$70="Retention ")),IFERROR(AO103/($L103/12*(Term-$K103)*'Product Data'!$P$17),0),IF(AND($H$70="Semi-Commercial",Rate_Type="Tracker"),IFERROR(AP103/($L103/12*(Term-$K103)*'Product Data'!$P$17),0),IF(AND($H$70="Semi-Commercial",Rate_Type="Fixed"),IFERROR(AP103/($L103/12*(Term-$K103)*'Product Data'!$P$23),0),IF(AND($H$70="Commercial",Rate_Type="Tracker"),IFERROR(AP103/($L103/12*(Term-$K103)*'Product Data'!$P$17),0),IF(AND($H$70="Commercial",Rate_Type="Fixed"),IFERROR(AP103/($L103/12*(Term-$K103)*'Product Data'!$P$23),0))))))) -> FALSE | P103: =IF('BTL Calculator'!$H$28="Fixed","",IF(OR(OR($H$70="Residential BTL",$H$70="Retention "),$H$70="Retention "),AO103/((((H103-'Product Data'!$E$3+'Product Data'!$K$3-J103)/12*(Term-K103)))*'Product Data'!$P$18),AP103/((((H103-'Product Data'!$E$3+'Product Data'!$K$3-J103)/12*(Term-K103)))*'Product Data'!$P$18))) | Q103: =IF('BTL Calculator'!$H$28="Tracker",MIN(N103,P103),MIN(O103,N103)) -> 0 | R103: =ROUNDDOWN(Q103,-3) -> 0 | S103: =IFERROR((IF(RoundDown,R103,Q103)*J103/12*Term)+ (IF(RoundDown,R103,Q103)*L103/12*K103)+ (IF(RoundDown,R103,Q103)*L103/12*(Term-K103)),"-") -> 0 | T103: =IFERROR(((H103*IF(RoundDown,R103,Q103)/12)),"-") -> 0 | U103: =IF('BTL Calculator'!$H$28="Fixed","",(((L103+$U$73)*IF(RoundDown,R103,Q103)/12))) | V103: =IFERROR(((L103*IF(RoundDown,R103,Q103)/12)),"-") -> 0 | W103: =IF(OR($H$70="Residential BTL",$H$70="Retention "),IFERROR(AO103/Z103,"-"),IFERROR(AP103/Z103,"-")) -> - | X103: =IF('BTL Calculator'!$H$28="Fixed","",IF(OR($H$70="Residential BTL",$H$70="Retention "),IFERROR(AO103/AA103,"-"),IFERROR(AP103/AA103,"-"))) | Y103: =TEXT(V103,"£0,0")&" @ "&TEXT(W103,"0%")&" ICR" -> £00 @ - ICR | Z103: =(IF(RoundDown,R103,Q103)*L103)/12*(Term-K103) -> 0 | AA103: =IF('BTL Calculator'!$H$28="Fixed","",(IF(RoundDown,R103,Q103)*(H103-'Product Data'!$E$3+'Product Data'!$K$2-J103))/12*(Term-K103)) | AB103: =IFERROR(Monthly_Rent*Term,"-") -> 0 | AC103: =IFERROR($U$22-V103,"-") -> 0 | AD103: =((J103*IF(RoundDown,R103,Q103))/12)*Term -> 0 | AE103: =K103*L103/12*IF(RoundDown,R103,Q103) -> 0 | AF103: =SUM(AD103:AE103) -> 0 | AG103: =AL103+AI103 -> 0 | AH103: =+AI103+AJ103 -> 0 | AI103: =+IF(RoundDown,R103,Q103)*0.02 -> 0 | AJ103: =+IF(RoundDown,R103,Q103)*I103-AI103 -> 0 | AK103: =TEXT(I103,"0.00%")&" ("&TEXT(AH103,"£0,0")&")" -> 4.00% (£00) | AL103: =IF(RoundDown,R103,Q103)-AD103-AE103-AH103 -> 0 | AM103: =AL103/Property_Value -> #DIV/0! | AN103: =IF(RoundDown,R103,Q103)/Property_Value -> #DIV/0! | AO103: =Rent_Over_Term+AQ103 -> 0 | AP103: =IF($H$72="3 Year Fixed",$X$22*36+AQ103, $X$22*24+AQ103) -> 0 | AQ103: ='BTL Calculator'!$I$80*Term -> 0 | AR103: =IF(ISERROR(FIND("Bespoke",F85,1)),FALSE,TRUE) -> FALSE | AS103: =IFERROR(IF(AND(IF(RoundDown,R103,Q103)=$E$70,E103>=$F$36),1,0),"-") -> 0 | AT103: =IFERROR(IF(AND(AL103=$E$71,E103>=$F$36),1,0),"-") -> - | AU103: =SUM(AS103:AT103) -> 0 | AV103: =IF(IF(Rate_Type="Tracker",X103,W103)>'Product Data'!$P$19,"Y","N") -> Y | AY103: =+IF(RoundDown,AH103,AG103)*Y103-AZ103 -> #VALUE! | AZ103: =+IF(RoundDown,AH103,AG103)*0.02 -> 0
B104: =IF('BTL Calculator'!$V$2="Core",0,IF(AND('BTL Calculator'!$G$60=C103,F104='BTL Calculator'!$G$62),1,0)) -> 0 | D104: 14 | E104: =VALUE(LEFT(F104,1)) -> 0 | F104: =IF($H$70='Product Data'!$BT5,'Product Data'!$B191,IF($H$70='Product Data'!$BT2,'Product Data'!$B10,IF($H$70='Product Data'!BT3,'Product Data'!B35,IF(H70='Product Data'!BT4,'Product Data'!B48,0)))) -> 0 | H104: =H98 -> FALSE | I104: =I98 -> 0.04 | J104: =IF(AND(Rate_Type="Fixed",H72="3 Year Fixed"),IF(Defer4>'Product Data'!$P$24,'Product Data'!$P$24,Defer4),IF(AND(Rate_Type="Fixed",H72="2 Year Fixed"),IF(Defer4>'Product Data'!$P$24,'Product Data'!$P$24,Defer4),IF(AND(Rate_Type="Fixed",H72="5 Year Fixed"),IF(Defer4>'Product Data'!$P$33,'Product Data'!$P$33,Defer4),IF(AND(Rate_Type="Tracker",$H$70="Commercial"),IF(Defer4>0.015,0.015,Defer4),IF(AND(Rate_Type="Tracker",$H$70="Semi-Commercial"),IF(Defer4>0.015,0.015,Defer4),IF(AND(Rate_Type="Tracker",OR($H$70="Residential BTL",$H$70="Retention ")),IF(Defer4>0.02,0.02,Defer4))))))) -> FALSE | K104: =IF(Roll4="",0,IF(OR(OR($H$70="Residential BTL",$H$70="Retention "),$H$70="Retention "),MAX(MIN(Roll4,'Product Data'!$P$12),0),MAX(MIN(Roll4,6),0))) -> 0 | L104: =H104-J104 -> 0 | M104: =M98 -> 0.7 | N104: =MIN(M104*Property_Value,'Product Data'!$P$16) -> 0 | O104: =IF(AND(OR(OR($H$70="Residential BTL",$H$70="Retention "),$H$70="Retention "),Rate_Type="Fixed"),IFERROR(AO104/($L104/12*(Term-$K104)*'Product Data'!$P$23),0),IF(AND(Rate_Type="Tracker",OR(OR($H$70="Residential BTL",$H$70="Retention "),$H$70="Retention ")),IFERROR(AO104/($L104/12*(Term-$K104)*'Product Data'!$P$17),0),IF(AND($H$70="Semi-Commercial",Rate_Type="Tracker"),IFERROR(AP104/($L104/12*(Term-$K104)*'Product Data'!$P$17),0),IF(AND($H$70="Semi-Commercial",Rate_Type="Fixed"),IFERROR(AP104/($L104/12*(Term-$K104)*'Product Data'!$P$23),0),IF(AND($H$70="Commercial",Rate_Type="Tracker"),IFERROR(AP104/($L104/12*(Term-$K104)*'Product Data'!$P$17),0),IF(AND($H$70="Commercial",Rate_Type="Fixed"),IFERROR(AP104/($L104/12*(Term-$K104)*'Product Data'!$P$23),0))))))) -> FALSE | P104: =IF('BTL Calculator'!$H$28="Fixed","",IF(OR(OR($H$70="Residential BTL",$H$70="Retention "),$H$70="Retention "),AO104/((((H104-'Product Data'!$E$3+'Product Data'!$K$3-J104)/12*(Term-K104)))*'Product Data'!$P$18),AP104/((((H104-'Product Data'!$E$3+'Product Data'!$K$3-J104)/12*(Term-K104)))*'Product Data'!$P$18))) | Q104: =IF('BTL Calculator'!$H$28="Tracker",MIN(N104,P104),MIN(O104,N104)) -> 0 | R104: =ROUNDDOWN(Q104,-3) -> 0 | S104: =IFERROR((IF(RoundDown,R104,Q104)*J104/12*Term)+ (IF(RoundDown,R104,Q104)*L104/12*K104)+ (IF(RoundDown,R104,Q104)*L104/12*(Term-K104)),"-") -> 0 | T104: =((H104*IF(RoundDown,R104,Q104)/12)) -> 0 | U104: =IF('BTL Calculator'!$H$28="Fixed","",(((L104+$U$73)*IF(RoundDown,R104,Q104)/12))) | V104: =((L104*IF(RoundDown,R104,Q104)/12))-IF('BTL Calculator'!$CY$11='Product Data'!$AG$9,AE104/Term,0) -> 0 | W104: =IF(OR($H$70="Residential BTL",$H$70="Retention "),IFERROR(AO104/Z104,"-"),IFERROR(AP104/Z104,"-")) -> - | X104: =IF('BTL Calculator'!$H$28="Fixed","",IF(OR($H$70="Residential BTL",$H$70="Retention "),IFERROR(AO104/AA104,"-"),IFERROR(AP104/AA104,"-"))) | Y104: =TEXT(V104,"£0,0")&" @ "&TEXT(W104,"0%")&" ICR" -> £00 @ - ICR | Z104: =(IF(RoundDown,R104,Q104)*L104)/12*(Term-K104) -> 0 | AA104: =IF('BTL Calculator'!$H$28="Fixed","",(IF(RoundDown,R104,Q104)*(H104-'Product Data'!$E$3+'Product Data'!$K$2-J104))/12*(Term-K104)) | AB104: =IFERROR(Monthly_Rent*Term,"-") -> 0 | AC104: =IFERROR($U$22-V104,"-") -> 0 | AD104: =((J104*IF(RoundDown,R104,Q104))/12)*Term -> 0 | AE104: =K104*L104/12*IF(RoundDown,R104,Q104) -> 0 | AF104: =SUM(AD104:AE104) -> 0 | AG104: =AL104+AI104 -> 0 | AH104: =+AI104+AJ104 -> 0 | AI104: =+IF(RoundDown,R104,Q104)*0.02 -> 0 | AJ104: =+IF(RoundDown,R104,Q104)*I104-AI104 -> 0 | AK104: =TEXT(I104,"0.00%")&" ("&TEXT(AH104,"£0,0")&")" -> 4.00% (£00) | AL104: =IF(RoundDown,R104,Q104)-AD104-AE104-AH104 -> 0 | AM104: =AL104/Property_Value -> #DIV/0! | AN104: =IF(RoundDown,R104,Q104)/Property_Value -> #DIV/0! | AO104: =Rent_Over_Term+AQ104 -> 0 | AP104: =IF($H$72="3 Year Fixed",$X$22*36+AQ104, $X$22*24+AQ104) -> 0 | AQ104: ='BTL Calculator'!$I$80*Term -> 0 | AR104: =IF(ISERROR(FIND("Bespoke",F86,1)),FALSE,TRUE) -> FALSE | AS104: =IFERROR(IF(AND(IF(RoundDown,R104,Q104)=$E$70,E104>=$F$36),1,0),"-") -> 0 | AT104: =IFERROR(IF(AND(AL104=$E$71,E104>=$F$36),1,0),"-") -> - | AU104: =SUM(AS104:AT104) -> 0 | AV104: =IF(IF(Rate_Type="Tracker",X104,W104)>'Product Data'!$P$19,"Y","N") -> Y | AY104: =+IF(RoundDown,AH104,AG104)*Y104-AZ104 -> #VALUE! | AZ104: =+IF(RoundDown,AH104,AG104)*0.02 -> 0
