Workbook
Name _ftn1: DIP!#REF!
Name _ftn1: 'DIP Fusion'!$O$20
Name _ftn2: DIP!#REF!
Name _ftn2: 'DIP Fusion'!#REF!
Name _ftn3: DIP!#REF!
Name _ftn3: 'DIP Fusion'!$O$21
Name _Hlk83203796: DIP!$A$73
Name _Hlk83203796: 'DIP Fusion'!$A$87
Name _Hlk84245425: DIP!$A$56
Name _Hlk84245425: 'DIP Fusion'!$A$61
Name _Hlk98754409: DIP!$M$59
Name _Hlk98754409: 'DIP Fusion'!$M$63
Name Amber_P: #REF!
Name Application_Type: #REF!
Name Application_Type: #REF!
Name Application_Type: 'Input Sheet'!$C$12
Name APR: #REF!
Name APR: #REF!
Name Bank_Rate: 'EBITDA calc_'!#REF!
Name Bank_Rate: #REF!
Name BankBase: #REF!
Name BBR: #REF!
Name BBR: #REF!
Name BBR: #REF!
Name BBR: #REF!
Name BBR: 'Input Sheet'!$C$41
Name BBR_Override: #REF!
Name BBR_Override: #REF!
Name Core_Net_loan: #REF!
Name Core_Net_loan: #REF!
Name DD_In_Month1: #REF!
Name DD_In_Month1: #REF!
Name Defer_Term_Override: #REF!
Name Defer_Term_Override: #REF!
Name Defer2: #REF!
Name Defer2: #REF!
Name Defer4: #REF!
Name Defer4: #REF!
Name Defer6: #REF!
Name Defer6: #REF!
Name DeferedIntPercent: #REF!
Name DeferedIntPercent: #REF!
Name Deferred_Int_Owed: #REF!
Name Deferred_Int_Owed: #REF!
Name Deferred_Owed: #REF!
Name Deferred_Owed: #REF!
Name DIP_Selection: #REF!
Name DIP_Selection: #REF!
Name DIP_Selection: 'Input Sheet'!$P$2
Name EarthAve_P: #REF!
Name End_Date: #REF!
Name ERC_Rate: #REF!
Name Existing_Customer: #REF!
Name Existing_Customer: #REF!
Name Final_Month_DD_Req: #REF!
Name Final_Month_DD_Req: #REF!
Name Funder_Pic: INDIRECT(#REF!)
Name Funding_Line: #REF!
Name FusionP: 'Input Sheet'!$C$15
Name Future_Rent_TBL: #REF!

Sheet Main Calculations
XEV1: Yes | XEW1: No | XEX1: Please Choose
E3: Main Calculations
D7: Fusion | F7: Variable Bridge | H7: Fixed Bridge
D8: Specific Net Loan | E8: Normal Calc | F8: Specific Net Loan | G8: Normal Calc | H8: Specific Net Loan | I8: Normal Calc
C9: Gross Loan | D9: =CEILING(MIN(D36/(1-D13-(D30/12*24)-(D56*(D29-D41))),'Input Sheet'!$C$28,1000000000),1000) -> #VALUE! | F9: =CEILING(MIN((F36/(1-F13-(F30/12*24)-(F56*(F29-F41)))),F10),1000) -> #N/A | H9: =CEILING(MIN((H36/(1-H13-(H30/12*24)-(H56*(H29-H41)))),H10),1000) -> #N/A
C10: ='Input Sheet'!$B$27 -> Purchase Price | D10: ='Input Sheet'!$C$28 -> 0 | E10: ='Input Sheet'!$C$28 -> 0 | F10: ='Input Sheet'!$C$28 -> 0 | G10: ='Input Sheet'!$C$28 -> 0 | H10: ='Input Sheet'!$C$28 -> 0 | I10: ='Input Sheet'!$C$28 -> 0
C11: Rent (£ pm) | D11: ='Input Sheet'!$C$29 -> 0 | E11: ='Input Sheet'!$C$29 -> 0
C12: Top Slicing (£ pm) | D12: ='Input Sheet'!$C$31 -> 0 | E12: ='Input Sheet'!$C$31 -> 0
C13: Arrangement Fee (%) | D13: =IF('Input Sheet'!$C$34="",Rates!$E$37,'Input Sheet'!$C$34) -> 0.02 | E13: =IF('Input Sheet'!$C$34="",Rates!$E$37,'Input Sheet'!$C$34) -> 0.02 | F13: =IF('Input Sheet'!C34>0,'Input Sheet'!C34,CHOOSE(MATCH('Input Sheet'!I4,Rates!C7:J7,0),Rates!C13,Rates!D13,Rates!E13,Rates!G13,Rates!H13,Rates!I13,Rates!J13)) -> #N/A | G13: =IF('Input Sheet'!C34>0,'Input Sheet'!C34,CHOOSE(MATCH('Input Sheet'!I4,Rates!C7:J7,0),Rates!C13,Rates!D13,Rates!E13,Rates!G13,Rates!H13,Rates!I13,Rates!J13)) -> #N/A | H13: =IF('Input Sheet'!C34>0,'Input Sheet'!C34,CHOOSE(MATCH('Input Sheet'!I4,Rates!C21:J21,0),Rates!C27,Rates!D27,Rates!E27,Rates!G27,Rates!H27,Rates!I27,Rates!J27)) -> #N/A | I13: =IF('Input Sheet'!C34>0,'Input Sheet'!C34,CHOOSE(MATCH('Input Sheet'!I4,Rates!C21:J21,0),Rates!C27,Rates!D27,Rates!E27,Rates!G27,Rates!H27,Rates!I27,Rates!J27)) -> #N/A
C14: Broker Fee (%) | D14: ='Input Sheet'!$C$35 -> 0 | E14: ='Input Sheet'!$C$35 -> 0 | F14: ='Input Sheet'!$C$35 -> 0 | G14: ='Input Sheet'!$C$35 -> 0 | H14: ='Input Sheet'!$C$35 -> 0 | I14: ='Input Sheet'!$C$35 -> 0
C15: Additional Broker Fee (%) | D15: ='Input Sheet'!$C$36 -> 0 | E15: ='Input Sheet'!$C$36 -> 0 | F15: ='Input Sheet'!$C$36 -> 0 | G15: ='Input Sheet'!$C$36 -> 0 | H15: ='Input Sheet'!$C$36 -> 0 | I15: ='Input Sheet'!$C$36 -> 0
C16: Additional Broker Fee (£) | D16: ='Input Sheet'!$C$37 -> 0 | E16: ='Input Sheet'!$C$37 -> 0 | F16: ='Input Sheet'!$C$37 -> 0 | G16: ='Input Sheet'!$C$37 -> 0 | H16: ='Input Sheet'!$C$37 -> 0 | I16: ='Input Sheet'!$C$37 -> 0
C17: Exit Fee (%) Bridge Only | F17: ='Input Sheet'!$C$38 -> 0 | G17: ='Input Sheet'!$C$38 -> 0 | H17: ='Input Sheet'!$C$38 -> 0 | I17: ='Input Sheet'!$C$38 -> 0
C18: Commitment Fee (£) | D18: ='Input Sheet'!$C$39 -> 0 | E18: ='Input Sheet'!$C$39 -> 0 | F18: ='Input Sheet'!$C$39 -> 0 | G18: ='Input Sheet'!$C$39 -> 0 | H18: ='Input Sheet'!$C$39 -> 0 | I18: ='Input Sheet'!$C$39 -> 0
C19: 1st Charge Outstanding (£) | D19: ='Input Sheet'!$D$17 -> 0 | E19: ='Input Sheet'!$D$17 -> 0 | F19: ='Input Sheet'!$D$17 -> 0 | G19: ='Input Sheet'!$D$17 -> 0 | H19: ='Input Sheet'!$D$17 -> 0 | I19: ='Input Sheet'!$D$17 -> 0
C20: BBR | D20: ='Input Sheet'!$C$41 -> 0.04 | E20: ='Input Sheet'!$C$41 -> 0.04 | F20: ='Input Sheet'!$C$41 -> 0.04 | G20: ='Input Sheet'!$C$41 -> 0.04 | H20: ='Input Sheet'!$C$41 -> 0.04 | I20: ='Input Sheet'!$C$41 -> 0.04
C21: BBR (pm) % | D21: =$D$20/12 -> 0.0033333333 | E21: =$D$20/12 -> 0.0033333333 | F21: =$D$20/12 -> 0.0033333333 | G21: =$D$20/12 -> 0.0033333333 | H21: =$D$20/12 -> 0.0033333333 | I21: =$D$20/12 -> 0.0033333333
C22: BBR Cost £ | D22: =D20*D9*'Input Sheet'!$F$8/12 -> #VALUE! | E22: =E20*E32*'Input Sheet'!$F$8/12 -> 0 | F22: =F20*F9*'Input Sheet'!$I$8/12 -> #N/A | G22: =G20*G32*'Input Sheet'!$I$8/12 -> 0
C23: Product Type | D23: ='Input Sheet'!$C$13 -> 0 | E23: ='Input Sheet'!$C$13 -> 0 | F23: ='Input Sheet'!$C$13 -> 0 | G23: ='Input Sheet'!$C$13 -> 0 | H23: ='Input Sheet'!$C$13 -> 0 | I23: ='Input Sheet'!$C$13 -> 0
C24: Sub Product | D24: ='Input Sheet'!$F$5 | E24: ='Input Sheet'!$F$5 | F24: ='Input Sheet'!$C$14 -> 0 | G24: ='Input Sheet'!$C$14 -> 0 | H24: ='Input Sheet'!$C$14 -> 0 | I24: ='Input Sheet'!$C$14 -> 0
C25: Rate Override (Optional) | D25: {=IF('Input Sheet'!$F$6>0,'Input Sheet'!$F$6+BBR,"")} | E25: {=IF('Input Sheet'!$F$6>0,'Input Sheet'!$F$6+BBR,"")} | F25: ='Input Sheet'!I6 -> 0 | G25: ='Input Sheet'!I6 -> 0 | H25: ='Input Sheet'!L6 -> 0 | I25: ='Input Sheet'!L6 -> 0
C26: Coupon / Fixed rate % | D26: =IF($D$25<>"",$D$25, IF(AND('Input Sheet'!$C$15="Yes",'Input Sheet'!$C$13="Residential"),Rates!$E$42, IF($D$23="Residential", IF($D$9<=Rates!E36,Rates!E33, IF($D$9<=Rates!F36,Rates!F33, Rates!G33)), IF($D$23="Semi & Full Commercial", IF($D$9<=Rates!E36,Rates!E34, IF($D$9<=Rates!F36,Rates!F34, Rates!G34)), "")))) | E26: =IF($E$25<>"",$E$25, IF(AND('Input Sheet'!$C$15="Yes",'Input Sheet'!$C$13="Residential"),Rates!$E$42, IF($E$23="Residential", IF(E32<=Rates!E36,Rates!E33, IF(E32<=Rates!F36,Rates!F33, Rates!G33)), IF($E$23="Semi & Full Commercial", IF(E32<=Rates!E36,Rates!E34, IF(E32<=Rates!F36,Rates!F34, Rates!G34)), "")))) | F26: ='Input Sheet'!$I$5 | G26: ='Input Sheet'!$I$5 | H26: ='Input Sheet'!$L$5 | I26: ='Input Sheet'!$L$5
C27: Coupon / Fixed rate £ | D27: =D26*D9*'Input Sheet'!$F$8/12 -> #VALUE! | E27: =E26*E32*'Input Sheet'!$F$8/12 -> #VALUE! | F27: =F26*F9*'Input Sheet'!$I$8 -> #VALUE! | G27: =G26*G32*'Input Sheet'!$I$8 -> #VALUE!
C28: Rolled Months | D28: ='Input Sheet'!$F$7 -> 6 | E28: ='Input Sheet'!$F$7 -> 6 | F28: ='Input Sheet'!$I$7 -> 3 | G28: ='Input Sheet'!$I$7 -> 3 | H28: ='Input Sheet'!$L$7 -> 3 | I28: ='Input Sheet'!$L$7 -> 3
C29: Term | D29: ='Input Sheet'!$F$8 -> 24 | E29: ='Input Sheet'!$F$8 -> 24 | F29: ='Input Sheet'!$I$8 -> 12 | G29: ='Input Sheet'!$I$8 -> 12 | H29: ='Input Sheet'!$L$8 -> 12 | I29: ='Input Sheet'!$L$8 -> 12
C30: Deferred (%) | D30: ='Input Sheet'!$F$9 -> 0 | E30: ='Input Sheet'!$F$9 -> 0
C31: Full Annual / Monthly Rate (%) | D31: =IF($D$25="",D26+BBR,$D$25) -> #VALUE! | E31: =IF($E$25="",E26+BBR,$E$25) -> #VALUE! | F31: =(F26*12)+F20 -> #VALUE! | G31: =(G26*12)+G20 -> #VALUE! | H31: =H26*12 -> #VALUE! | I31: =I26*12 -> #VALUE!
C32: Gross Loan | E32: =IF('Input Sheet'!$C$11>'Input Sheet'!$C$28,'Input Sheet'!$C$28,'Input Sheet'!$C$11) -> 0 | G32: =IF('Input Sheet'!$C$11>'Input Sheet'!$C$28,'Input Sheet'!$C$28,'Input Sheet'!$C$11) -> 0 | I32: =IF('Input Sheet'!$C$11>'Input Sheet'!$C$28,'Input Sheet'!$C$28,'Input Sheet'!$C$11) -> 0
C33: Gross LTV | D33: =IFERROR((D9+D19)/D10,0) -> 0 | E33: =IFERROR((E32+E19)/E10,0) -> 0 | F33: =IFERROR((F9+F19)/F10,0) -> 0 | G33: =IFERROR((G32+G19)/G10,0) -> 0 | H33: =IFERROR((H9+H19)/H10,0) -> 0 | I33: =IFERROR((I32+I19)/I10,0) -> 0
C34: NPB | D34: =D35+D38 -> #VALUE! | E34: =E35+E38 -> #VALUE! | F34: =F35+F38 -> #N/A | G34: =G35+G38 -> #N/A | H34: =H35+H38 -> #N/A | I34: =I35+I38 -> #N/A
C35: Net Loan | D35: =D9-D44-D38-D43 -> #VALUE! | E35: =E32-E44-E38-E43 -> #VALUE! | F35: =F9-F38-F43 -> #N/A | G35: =G32-G38-G43 -> #N/A | H35: =H9-H38-H43 -> #N/A | I35: =I32-I38-I43 -> #N/A
C36: Specific Net Loan | D36: =IF('Input Sheet'!$D$15>'Input Sheet'!$C$28,'Input Sheet'!$C$28,'Input Sheet'!$D$15) -> 0 | F36: =IF('Input Sheet'!$D$15>'Input Sheet'!$C$28,'Input Sheet'!$C$28,'Input Sheet'!$D$15) -> 0 | H36: =IF('Input Sheet'!$D$15>'Input Sheet'!$C$28,'Input Sheet'!$C$28,'Input Sheet'!$D$15) -> 0
C37: Net LTV | D37: =IFERROR(D35/D10,0) -> 0 | E37: =IFERROR(E35/E10,0) -> 0 | F37: =IFERROR((F35+IF('Input Sheet'!$C$17="Yes",F19,0))/F10,0) -> 0 | G37: =IFERROR((G35+IF('Input Sheet'!$C$17="Yes",G19,0))/G10,0) -> 0 | H37: =IFERROR((H35+IF('Input Sheet'!$C$17="Yes",H19,0))/H10,0) -> 0 | I37: =IFERROR((I35+IF('Input Sheet'!$C$17="Yes",I19,0))/I10,0) -> 0
C38: Arrangement Fee (£) | D38: =D9*D13 -> #VALUE! | E38: =E32*E13 -> 0 | F38: =F9*F13 -> #N/A | G38: =G32*G13 -> #N/A | H38: =H9*H13 -> #N/A | I38: =I32*I13 -> #N/A
C39: Broker Fee (£) | D39: =D9*D14 -> #VALUE! | E39: =E32*E14 -> 0 | F39: =F9*F14 -> #N/A | G39: =G32*G14 -> 0 | H39: =H9*H14 -> #N/A | I39: =I32*I14 -> 0
C40: Additional Broker Fee (£) | D40: =IF('Input Sheet'!$C$37>0,'Input Sheet'!$C$37,D9*D15) -> #VALUE! | E40: =IF('Input Sheet'!$C$37>0,'Input Sheet'!$C$37,E32*E15) -> 0 | F40: =IF('Input Sheet'!$C$37>0,'Input Sheet'!$C$37,F9*F15) -> #N/A | G40: =IF('Input Sheet'!$C$37>0,'Input Sheet'!$C$37,G32*G15) -> 0 | H40: =IF('Input Sheet'!$C$37>0,'Input Sheet'!$C$37,H9*H15) -> #N/A | I40: =IF('Input Sheet'!$C$37>0,'Input Sheet'!$C$37,I32*I15) -> 0
C41: Serviced Months | D41: =IF(D29-D28<0,0,D29-D28) -> 18 | E41: =IF(E29-E28<0,0,E29-E28) -> 18 | F41: =IF(F29-F28<0,0,F29-F28) -> 9 | G41: =IF(G29-G28<0,0,G29-G28) -> 9 | H41: =IF(H29-H28<0,0,H29-H28) -> 9 | I41: =IF(I29-I28<0,0,I29-I28) -> 9
C42: Serviced Interest | D42: =D9*(D29-D28)*(D31-D30)/12 -> #VALUE! | E42: =E32*(E29-E28)*(E31-E30)/12 -> #VALUE! | F42: =F9*(F29-F28)*F31/12 -> #N/A | G42: =G32*(G29-G28)*G31/12 -> #VALUE! | H42: =H9*(H29-H28)*H31/12 -> #N/A | I42: =I32*(I29-I28)*I31/12 -> #VALUE!
C43: Rolled Interest (£) | D43: =D9*(D31-D30)*D28/12 -> #VALUE! | E43: =E32*(E31-E30)*E28/12 -> #VALUE! | F43: =F9*F56*F28 -> #N/A | G43: =G32*G31*G28/12 -> #VALUE! | H43: =H9*H56*H28 -> #N/A | I43: =I32*I31*I28/12 -> #VALUE!
C44: Deferred (£) | D44: =(D9*D30/12)*24 -> #VALUE! | E44: =(E32*E30/12)*24 -> 0
C45: Total Interest (defer + rolled + serviced) | D45: =SUM(D42:D44) -> #VALUE! | E45: =SUM(E42:E44) -> #VALUE! | F45: =SUM(F42:F43) -> #N/A | G45: =SUM(G42:G43) -> #VALUE! | H45: =SUM(H42:H43) -> #N/A | I45: =SUM(I42:I43) -> #VALUE!
C46: Total Interest | D46: =D9*D31*D29/12 -> #VALUE! | E46: =E32*E31*E29/12 -> #VALUE! | F46: =F9*F31*F29/12 -> #N/A | G46: =G32*G31*G29/12 -> #VALUE! | H46: =H9*H31*H29/12 -> #N/A | I46: =I32*I31*I29/12 -> #VALUE!
C47: APRC (%) | D47: =IFERROR((D40+D38+D46)/D35/D29*12,0) -> 0 | E47: =IFERROR((E40+E38+E46)/E35/E29*12,0) -> 0 | F47: =IFERROR((F40+F38+F46)/F35/F29*12,0) -> 0 | G47: =IFERROR((G40+G38+G46)/G35/G29*12,0) -> 0 | H47: =IFERROR((H40+H38+H46)/H35/H29*12,0) -> 0 | I47: =IFERROR((I40+I38+I46)/I35/I29*12,0) -> 0
C48: APRC (% pm) | D48: =IFERROR(D47/12,0) -> 0 | E48: =IFERROR(E47/12,0) -> 0 | F48: =IFERROR(F47/12,0) -> 0 | G48: =IFERROR(G47/12,0) -> 0 | H48: =IFERROR(H47/12,0) -> 0 | I48: =IFERROR(I47/12,0) -> 0
C49: Monthly Payment | D49: =D9*(D31-D30)/12 -> #VALUE! | E49: =E32*(E31-E30)/12 -> #VALUE! | F49: =IF('Input Sheet'!$I$22=0,0,F9*F56) -> #N/A | G49: =IF('Input Sheet'!$I$22=0,0,G32*G56) -> #VALUE! | H49: =IF('Input Sheet'!$L$22=0,0,H9*H56) -> #N/A | I49: =IF('Input Sheet'!$L$22=0,0,I32*I56) -> #VALUE!
C50: ERC 3% for Fusion / Exit Fee (£) | D50: =D9*75%*3% -> #VALUE! | E50: =E32*75%*3% -> 0 | F50: =F9*F17 -> #N/A | G50: =G32*G17 -> 0 | H50: =H9*H17 -> #N/A | I50: =I32*I17 -> 0
C51: ERC 1.5% for Fusion | D51: =D9*75%*1.5% -> #VALUE! | E51: =E32*75%*1.5% -> 0
C52: Roll Int Coupon (£) | D52: =D$9*D$28*((D$31-D$20-D30)/12) -> #VALUE! | E52: =E$32*E$28*((E$31-E$20-E30)/12) -> #VALUE! | F52: =F$9*F$28*((F$31-F$20)/12) -> #N/A | G52: =G$32*G$28*((G$31-G$20)/12) -> #VALUE!
C53: Roll Int BBR (£) | D53: =D9*D28*(D20)/12 -> #VALUE! | E53: =E32*E28*(E20)/12 -> 0 | F53: =F9*F28*(F20)/12 -> #N/A | G53: =G32*G28*(G20)/12 -> 0
C54: Full Rate (pm) | D54: =D31/12 -> #VALUE! | E54: =E31/12 -> #VALUE! | F54: =F31/12 -> #VALUE! | G54: =G31/12 -> #VALUE! | H54: =H31/12 -> #VALUE! | I54: =I31/12 -> #VALUE!
C55: Full Coupon Rate (pm) | D55: =(D31-D20)/12 -> #VALUE! | E55: =(E31-E20)/12 -> #VALUE! | F55: =(F31-F20)/12 -> #VALUE! | G55: =(G31-G20)/12 -> #VALUE! | H55: =(H31)/12 -> #VALUE! | I55: =(I31)/12 -> #VALUE!
C56: Pay Rate (pm) | D56: =IF(D25<>"",D25/12,IF('Input Sheet'!$F$4="Residential", IF(MIN(Rates!R36,Rates!S36)<3000000, (Rates!E33+BBR-D30)/12, IF(MIN(Rates!R36,Rates!S36)<10000000, (Rates!F33+BBR-D30)/12, (Rates!G33+BBR-D30)/12)), IF('Input Sheet'!$F$4="Semi & Full Commercial", IF(MIN(Rates!R37,Rates!S37)<3000000, (Rates!E34+BBR-D30)/12, IF(MIN(Rates!R37,Rates!S37)<10000000, (Rates!F34+BBR-D30)/12, (Rates!G34+BBR-D30)/12)), ""))) | E56: =(E31-E30)/12 -> #VALUE! | F56: =(F31)/12 -> #VALUE! | G56: =(G31)/12 -> #VALUE! | H56: =(H31)/12 -> #VALUE! | I56: =(I31)/12 -> #VALUE!
C57: ICR | D57: =IFERROR((D11+D12)*24/(((D31-D30)*D9*2)-D43),0) -> 0 | E57: =IFERROR((E11+E12)*24/(((E31-E30)*E32*2)-E43),0) -> 0

Sheet Input Sheet
E2: TRUE | G2: =IF(OR(C13="Mix Rate",C17="Yes"),FALSE,E2) -> TRUE | H2: TRUE | K2: TRUE | M2: =COUNTIF(G2:K2,TRUE) -> 3 | N2: Go to Indicatives | P2: {=_xlfn.IFS( AND(C15="Yes", E2=TRUE), "Fusion Premier", E2=TRUE, "Fusion", H2=TRUE, "Variable", K2=TRUE, "Fixed", TRUE, "None" )} -> Fusion | Q2: =IF(SUM((E2=TRUE) + (H2=TRUE) + (K2=TRUE))=0,3,SUM((E2=TRUE) + (H2=TRUE) + (K2=TRUE))) -> 3
E3: Fusion | H3: Variable Bridge | K3: Fixed Bridge | N3: Notes to the Underwriter
B4: Bridging Loan Calculator | C4: =IF(AND(D11<>"",C28>0,D11>C28),"Loan Amount is more than Property value", "") | E4: Product Type | F4: =IF(C13="","Please select product type",C13) -> Please select product type | H4: Sub Product Type | I4: =IF(AND($C$13="Mix Rate",$C$17="Yes"),"Mix Rate 2nd Charge",IF($C$17="Yes","2nd Charge",IF($C$13="Mix Rate","Mix Rate",IF($C$13="","Please select product type",IF(AND($C$13<>"",$C$14=""),"Please select sub product",IF(AND($C$17="No",$C$14=""),"",$C$14)))))) -> Please select product type | J4: =IF(I13="", "", IF(I13<=60%, INDEX(Rates!C8:J8, MATCH(I4, Rates!C7:J7, 0)), IF(I13<=70%, INDEX(Rates!C9:J9, MATCH(I4, Rates!C7:J7, 0)), IF(I13<=100%, INDEX(Rates!C10:J10, MATCH(I4, Rates!C7:J7, 0)), "Use Rate Override")))) -> #N/A | K4: Sub Product Type | L4: =IF(AND($C$13="Mix Rate",$C$17="Yes"),"Mix Rate 2nd Charge",IF($C$17="Yes","2nd Charge",IF($C$13="Mix Rate","Mix Rate",IF($C$13="","Please select product type",IF(AND($C$13<>"",$C$14=""),"Please select sub product",IF(AND($C$17="No",$C$14=""),"",$C$14)))))) -> Please select product type | M4: =IF(L13="", "", IF(L13<=60%, INDEX(Rates!C22:J22, MATCH(I4, Rates!C21:J21, 0)), IF(L13<=70%, INDEX(Rates!C23:J23, MATCH(I4, Rates!C21:J21, 0)), IF(L13<=100%, INDEX(Rates!C24:J24, MATCH(I4, Rates!C21:J21, 0)), "Use Rate Override")))) -> #N/A
B5: v.1 05 November 25 | E5: Sub Product | F5: =IF(C15="Yes","Premier",IF(C13="","", IF(F12<=Rates!E36,"Fusion S", IF(F12<=Rates!F36,"Fusion M", "Fusion L")))) | H5: Coupon Rate (%) | I5: =_xlfn.IFNA(IF(I6>0, I6, IF(C20="Yes", J5, J4)), "") | J5: =IF(I4="", "", IF(C22<=60%, INDEX(Rates!C8:J8, MATCH(I4, Rates!C7:J7, 0)), IF(C22<=70%, INDEX(Rates!C9:J9, MATCH(I4, Rates!C7:J7, 0)), IF(C22<=75%, INDEX(Rates!C10:J10, MATCH(I4, Rates!C7:J7, 0)), "Use Rate Override")))) -> #N/A | K5: Fixed Rate (%) | L5: =_xlfn.IFNA(IF(L6>0, L6, IF(C20="Yes", M5, M4)), "") | M5: =IF(L4="", "", IF(C23<=60%, INDEX(Rates!C22:J22, MATCH(I4, Rates!C21:J21, 0)), IF(C23<=70%, INDEX(Rates!C23:J23, MATCH(I4, Rates!C21:J21, 0)), IF(C23<=75%, INDEX(Rates!C24:J24, MATCH(I4, Rates!C21:J21, 0)), "Use Rate Override")))) -> #N/A | P5: Title Insurance
B6: Loan | E6: Rate Override (Optional) | H6: Rate Override (Optional) | K6: Rate Override (Optional) | N6: Please enter Mix Rate Manually | P6: Eligibility | Q6: =IF(AND(F12>3000000,I12>3000000,L12>3000000),"No",IF(AND(C17="Yes",I12>3000000,L12>3000000),"No",IF(C13<>"Residential","No",IF(AND(Q7<>"",Q8<>"No", Q8<>"No",Q8<>"",OR(Q7="Individual",AND(Q7="Corporate",Q9<>"No",Q9<>""))),"Yes",IF(OR(AND(Q7="Corporate",Q9="No"),AND(Q7="Corporate",Q9="")),"No",IF(Q8="No","No","No")))))) -> No | S6: Eligible nationalities Individual: UK national/passport holder of EEA country, Channel Islands, Switzerland, USA, Canada, Australia or New Zealand. Corporate: company, Trust and partnership incorporated in the UK, EEA, Channel Islands, Switzerland or the British Virgin Islands. UBO must meet the individual nationality criteria even if company incorporated in the permitted list.
B7: Reference | C7: HubSpot reference | E7: Rolled Months | F7: 6 | H7: Rolled Months | I7: 3 | K7: Rolled Months | L7: 3 | N7: Rolled Months exceed Total Term | P7: Applicant Type
B8: Borrower Name | C8: xxxxx | E8: Term | F8: 24 | H8: Term | I8: 12 | K8: Term | L8: 12 | P8: Eligible Nationalities
B9: Property Address | C9: xxxxx | E9: Deferred (%) | P9: Country Of Incorporation
B10: Loan Start Date
B11: Gross Loan | D11: =IF(C20="Yes","",IF(C11="","",C11)) | E11: Full Annual Rate (%) | F11: =IF(F5="","",IF($F$6>=0,IF(C20="Yes",'Main Calculations'!D31,'Main Calculations'!E31),$F$6)) | H11: Full Monthly Rate (%) | I11: =IFERROR(IF(I5="","",IF(C20="Yes",'Main Calculations'!F31/12,'Main Calculations'!G31/12)),"") | K11: Full Monthly Rate (%) | L11: =IFERROR(IF(L5="","",IF(F16="Yes",'Main Calculations'!H31/12,'Main Calculations'!I31/12)),"") | P11: Title Insurance Premium
B12: Applicant Type | E12: Gross Loan | F12: =IF(C13="Mix Rate",0,IF(C17="Yes",0,IF(C13="",0,IF(C20="Yes",IF('Main Calculations'!D9<0,0,'Main Calculations'!D9),IF(D11=0,0,IF('Main Calculations'!E32<0,0,'Main Calculations'!E32)))))) -> 0 | H12: Gross Loan | I12: =IF(I5="",0,IF($C$20="Yes",'Main Calculations'!F9,'Main Calculations'!G32)) -> 0 | K12: Gross Loan | L12: =IF(L5="",0,IF($C$20="Yes",'Main Calculations'!H9,'Main Calculations'!I32)) -> 0 | N12: =IF(OR(AND(F12<100000,F12>0),AND(I12>0,I12<100000),AND(L12>0,L12<100000)),"Less than minimum loan",IF(OR(I12>=50000000,L12>=50000000, F12>=65000000),"Maxmium Loan Achieved","")) | P12: Fusion | Q12: =IF(Q6<>"No",IF(OR(F12<=0,F12>3000000),"NA",IF(((F12*0.0013)+(F12*0.0013)*12%)<392,392,(F12*0.0013)+(F12*0.0013)*12%)),"")
B13: Product Type | E13: Gross LTV | F13: =IFERROR(IF($C$17="Yes",0,IF($C$20="Yes",'Main Calculations'!D33,'Main Calculations'!E33)),0) -> 0 | H13: Gross LTV | I13: =IFERROR(IF($C$20="Yes",'Main Calculations'!F33,'Main Calculations'!G33),0) -> 0 | K13: Gross LTV | L13: =IFERROR(IF($C$20="Yes",'Main Calculations'!H33,'Main Calculations'!I33),0) -> 0 | N13: Max LTV Achieved | P13: Variable Bridge | Q13: =IF(Q6<>"No",IF(OR(I12>3000000,I12<=0),"NA",IF(((I12*0.0013)+(I12*0.0013)*12%)<392,392,(I12*0.0013)+(I12*0.0013)*12%)),"")
B14: Sub Product Bridge only | E14: NPB | F14: =IFERROR(IF($C$20="Yes",'Main Calculations'!D34,'Main Calculations'!E34),0) -> 0 | H14: NPB | I14: =IFERROR(IF($C$20="Yes",'Main Calculations'!F34,'Main Calculations'!G34),0) -> 0 | K14: NPB | L14: =IFERROR(IF($C$20="Yes",'Main Calculations'!H34,'Main Calculations'!I34),0) -> 0 | P14: Fixed Bridge | Q14: =IF(Q6<>"No",IF(OR(L12<=0,L12>3000000),"NA",IF(((L12*0.0013)+(L12*0.0013)*12%)<392,392,(L12*0.0013)+(L12*0.0013)*12%)),"")
B15: Fusion Premier | C15: No | D15: =IF(C20="Yes",C21,0) -> 0 | E15: Net Loan | F15: =IFERROR(IF($C$20="Yes",'Main Calculations'!D35,'Main Calculations'!E35),0) -> 0 | H15: Net Loan | I15: =IFERROR(IF($C$20="Yes",'Main Calculations'!F35,'Main Calculations'!G35),0) -> 0 | K15: Net Loan | L15: =IFERROR(IF($C$20="Yes",'Main Calculations'!H35,'Main Calculations'!I35),0) -> 0
B16: Multi Property Loan ? | C16: No | E16: Net LTV | F16: =IFERROR(IF($C$20="Yes",'Main Calculations'!D37,'Main Calculations'!E37),0) -> 0 | H16: Net LTV | I16: =IFERROR(IF($C$20="Yes",'Main Calculations'!F37,'Main Calculations'!G37),0) -> 0 | K16: Net LTV | L16: =IFERROR(IF($C$20="Yes",'Main Calculations'!H37,'Main Calculations'!I37),0) -> 0
B17: 2nd Charge | C17: No | D17: =IF(C17="Yes",C19,0) -> 0
B18: 1st Charge | E18: Arrangement Fee (£) | F18: =IFERROR(IF($C$20="Yes",'Main Calculations'!D38,'Main Calculations'!E38),0) -> 0 | H18: Arrangement Fee (£) | I18: =IFERROR(IF($C$20="Yes",'Main Calculations'!F38,'Main Calculations'!G38),0) -> 0 | K18: Arrangement Fee (£) | L18: =IFERROR(IF($C$20="Yes",'Main Calculations'!H38,'Main Calculations'!I38),0) -> 0
B19: 1st Charge | C19: =IF($C$16="Yes",'Multi Property Deal'!$R$64,'Input Sheet'!$C$18) -> 0 | E19: Proc Fee (%) | F19: =IFERROR(IF($C$20="Yes",'Main Calculations'!D39,'Main Calculations'!E39),0) -> 0 | H19: Proc Fee (%) | I19: =IFERROR(IF($C$20="Yes",'Main Calculations'!F39,'Main Calculations'!G39),0) -> 0 | K19: Proc Fee (%) | L19: =IFERROR(IF($C$20="Yes",'Main Calculations'!H39,'Main Calculations'!I39),0) -> 0
B20: Specific Net Loan ? | C20: No | E20: Broker Client Fee (£) | F20: =IFERROR(IF($C$20="Yes",'Main Calculations'!D40,'Main Calculations'!E40),0) -> 0 | H20: Broker Client Fee (£) | I20: =IFERROR(IF($C$20="Yes",'Main Calculations'!F40,'Main Calculations'!G40),0) -> 0 | K20: Broker Client Fee (£) | L20: =IFERROR(IF($C$20="Yes",'Main Calculations'!H40,'Main Calculations'!I40),0) -> 0
B21: Specific Net Loan (£)
B22: LTV Rate Range Variable | C22: {=IFERROR(Rates!$S$15:$S$15,0)} -> 0 | E22: Serviced Months | F22: =IFERROR(IF($C$20="Yes",'Main Calculations'!D41,'Main Calculations'!E41),0) -> 18 | H22: Serviced Months | I22: =IFERROR(IF($C$20="Yes",'Main Calculations'!F41,'Main Calculations'!G41),0) -> 9 | K22: Serviced Months | L22: =IFERROR(IF($C$20="Yes",'Main Calculations'!H41,'Main Calculations'!I41),0) -> 9
B23: LTV Rate Range Fixed | C23: =IFERROR(Rates!$S$29,0) -> 0 | E23: Rolled Interest (£) | F23: =IFERROR(IF($C$20="Yes",'Main Calculations'!D43,'Main Calculations'!E43),0) -> 0 | H23: Rolled Interest (£) | I23: =IFERROR(IF($C$20="Yes",'Main Calculations'!F43,'Main Calculations'!G43),0) -> 0 | K23: Rolled Interest (£) | L23: =IFERROR(IF($C$20="Yes",'Main Calculations'!H43,'Main Calculations'!I43),0) -> 0
E24: Deferred (£) | F24: =IFERROR(IF($C$20="Yes",'Main Calculations'!D44,'Main Calculations'!E44),0) -> 0
B25: Property | E25: Total Interest (Defer + Rolled + Serviced) | F25: =IFERROR(IF($C$20="Yes",'Main Calculations'!D45,'Main Calculations'!E45),0) -> 0 | H25: Total Interest (Rolled + Serviced) | I25: =IFERROR(IF($C$20="Yes",'Main Calculations'!F45,'Main Calculations'!G45),0) -> 0 | K25: Total Interest (Rolled + Serviced) | L25: =IFERROR(IF($C$20="Yes",'Main Calculations'!H45,'Main Calculations'!I45),0) -> 0
B26: Lending off | C26: Purchase Price
B27: =C26 -> Purchase Price | E27: APRC (%) | F27: =IFERROR(IF($C$20="Yes",'Main Calculations'!D47,'Main Calculations'!E47),"") -> 0 | H27: APRC (%) | I27: =IFERROR(IF($C$20="Yes",'Main Calculations'!F47,'Main Calculations'!G47),0) -> 0 | K27: APRC (%) | L27: =IFERROR(IF($C$20="Yes",'Main Calculations'!H47,'Main Calculations'!I47),0) -> 0
B28: =C26 -> Purchase Price | C28: =IF(C16="Yes",'Multi Property Deal'!$M$64,IF(AND($C$13="Residential",'Input Sheet'!$C$15="Yes"),'Fusion Portfolio'!$M$4,'Input Sheet'!$C$27)) -> 0 | E28: APRC (% pm) | F28: =IFERROR(IF($C$20="Yes",'Main Calculations'!D48,'Main Calculations'!E48),"") -> 0 | H28: APRC (% pm) | I28: =IFERROR(IF($C$20="Yes",'Main Calculations'!F48,'Main Calculations'!G48),0) -> 0 | K28: APRC (% pm) | L28: =IFERROR(IF($C$20="Yes",'Main Calculations'!H48,'Main Calculations'!I48),0) -> 0
B29: Rent (£ pm) | C29: =IF($C$15="Yes",'Fusion Portfolio'!$N$4,'Input Sheet'!$C$30) -> 0 | E29: Monthly Payment | F29: =IFERROR(IF($C$20="Yes",'Main Calculations'!D49,'Main Calculations'!E49),0) -> 0 | H29: Monthly Payment | I29: =IFERROR(IF($C$20="Yes",'Main Calculations'!F49,'Main Calculations'!G49),0) -> 0 | K29: Monthly Payment | L29: =IFERROR(IF($C$20="Yes",'Main Calculations'!H49,'Main Calculations'!I49),0) -> 0
B30: Rent (£ pm) | E30: ERC (£) Yr1 | F30: =IFERROR(IF($C$20="Yes",'Main Calculations'!D50,'Main Calculations'!E50),0) -> 0 | H30: Exit Fee (£) | I30: =IFERROR(IF($C$20="Yes",'Main Calculations'!F50,'Main Calculations'!G50),0) -> 0 | K30: Exit Fee (£) | L30: =IFERROR(IF($C$20="Yes",'Main Calculations'!H50,'Main Calculations'!I50),0) -> 0
B31: Top Slicing (£ pm) | E31: ERC (£) Yr2 | F31: =IFERROR(IF($C$20="Yes",'Main Calculations'!D51,'Main Calculations'!E51),0) -> 0
B33: Fee | E33: Roll Int Coupon (£) | F33: =IFERROR(IF($C$20="Yes",'Main Calculations'!D52,'Main Calculations'!E52),0) -> 0 | H33: Roll Int Coupon (£) | I33: =IFERROR(IF($C$20="Yes",'Main Calculations'!F52,'Main Calculations'!G52),0) -> 0
B34: Arrangement Fee (%) | E34: Roll Int BBR (£) | F34: =IFERROR(IF($C$20="Yes",'Main Calculations'!D53,'Main Calculations'!E53),0) -> 0 | H34: Roll Int BBR (£) | I34: =IFERROR(IF($C$20="Yes",'Main Calculations'!F53,'Main Calculations'!G53),0) -> 0
B35: Proc Fee (%) | E35: Full Int Coupon (£) | F35: =IFERROR(IF($C$20="Yes",'Main Calculations'!D27,'Main Calculations'!E27),0) -> 0 | H35: Full Int Coupon (£) | I35: =IFERROR(IF($C$20="Yes",'Main Calculations'!F27,'Main Calculations'!G27),0) -> 0
B36: Broker Client Fee (%) | E36: Full Int BBR (£) | F36: =IFERROR(IF($C$20="Yes",'Main Calculations'!D22,'Main Calculations'!E22),0) -> 0 | H36: Full Int BBR (£) | I36: =IFERROR(IF($C$20="Yes",'Main Calculations'!F22,'Main Calculations'!G22),0) -> 0
B37: Broker Client Fee (£)
B38: Exit Fee (%) Bridge Only | E38: Full Rate (pm) | F38: =IFERROR(IF('Input Sheet'!$C$20="Yes",'Main Calculations'!D54,'Main Calculations'!E54),"")
B39: Commitment Fee (£) | E39: Full Coupon Rate (pm) | F39: =IFERROR((IF(F5="",0,IF(C20="Yes",'Main Calculations'!D55,'Main Calculations'!E55))),"") -> 0
E40: Pay Rate (pm) | F40: =IFERROR(IF(C20="Yes",'Main Calculations'!D56,'Main Calculations'!E56),"")
B41: BBR | C41: 0.04 | E41: ICR | F41: =IF(F12=0,"",IF(C20="Yes",'Main Calculations'!D57,'Main Calculations'!E57)) | H41: ICR Too Low Please Adjust Loan Amount
B42: BBR (pm) | C42: =C41/12 -> 0.0033333333
B43: Macro for Indicative | C43: =IF(AND(C13="Mix Rate", C17 = "Yes"), "Yes", IF(AND(C17 = "Yes", C13<>"Mix Rate"), "Yes", IF(AND(C17 <>"Yes", C13="Mix Rate"), "Yes", IF(AND(C17<>"Yes",C13<>"Mix Rate"),"No", "No")))) -> No
B45: Please enter data in all required fields (yellow) to generate a quote

Sheet DIP Premier
B3: Decision in Principle – Premier Fusion Loan
B6: This offer is valid for 30 days and is subject to satisfactory valuation, due diligence, documentation, and Credit Committee approval. The below terms do not constitute a commitment to provide funding by the Lender nor representation that such funding will be made available.
B7: Loan Details
B9: Application ID | C9: ='Input Sheet'!$C$7 -> HubSpot reference
B10: Properties | C10: As listed in Schedule 1 – List of Properties | D10: Name from Input page
B11: Borrower | C11: ='Input Sheet'!$C$8 -> xxxxx
B12: Guarantor | D12: Manual input
B13: Obligors | D13: Manual input
B14: Lender | C14: =$G$14 -> 0 | F14: Funding Line
B15: Loan Manager | C15: Market Financial Solutions Limited
B16: Purpose | C16: [To refinance [Properties OR [details of Properties]/Acquisition of [Properties OR [details of Properties]] | D16: Manual input
B17: Term | C17: 24 months from the date of funding, unless extended for another 12 months (at Lender’s discretion)
B18: Gross Loan Amount | C18: ="£"& TEXT('Input Sheet'!$F$12,"#,##")&" based on an assumed MV of £"&TEXT('Input Sheet'!$C$28,"#,##") -> £ based on an assumed MV of £
B19: Net Loan Amount | C19: ="£"&TEXT('Input Sheet'!$F$15+'Input Sheet'!$F$20,"#,##")&" net loan including any Broker Client Fee" -> £ net loan including any Broker Client Fee | D19: Hide if blank
B20: Advance | C20: ="£"&TEXT('Input Sheet'!$F$15,"#,##")&" net amount advanced on day 1" -> £ net amount advanced on day 1
B21: Retained Interest | C21: =TEXT('Input Sheet'!$F$23,"£#,##")&" / "&TEXT('Input Sheet'!$F$7,"##")&" months" -> £ / 6 months | D21: Hide if blank
B22: Deferred Interest | C22: =TEXT('Input Sheet'!$F$24,"£#,##")&" / "&TEXT('Input Sheet'!$F$9,"#.##%")&" of the Gross Loan Amount" -> £ / .% of the Gross Loan Amount | D22: Hide if blank
B23: Interest Rate (variable) | C23: ="Margin "&('Input Sheet'!F11-'Input Sheet'!C41)*100&"% per annum plus the applicable Bank of England Base Rate (“BBR”), equal to a total interest rate of "&'Input Sheet'!F11*100&"% per annum Any changes to BBR will be reflected in interest charged from the first day of the next calendar month. " -> #VALUE!
B24: Interest Charging Basis | C24: =TEXT('Input Sheet'!$F$22,"#,##")&" months serviced "&TEXT('Input Sheet'!$F$7,"#,##")&" months retained "&TEXT('Input Sheet'!$F$9,"0.00%")&" deferred" -> 18 months serviced 6 months retained 0.00% deferred | F24: Interest Payment | G24: monthly
B25: Interest Payments | C25: =TEXT('Input Sheet'!$F$29,"£#,##")&" based on current BBR, payable "&G24&" commencing ON "& TEXT(G25,"dd-mmm-yyyy") -> £ based on current BBR, payable monthly commencing ON 28-May-2026 | D25: <-- Check | F25: Commencing date | G25: =EDATE(TODAY(), 'Input Sheet'!$F$7) -> 46170
B26: Default Interest Rate | C26: Interest Rate plus an additional 2.00% per month
B27: Minimum Interest Period | C27: 6 months from the date of drawdown of the Advance
B30: Fees
B33: Commitment Fee | C33: =IF('Input Sheet'!$C$39>0,TEXT('Input Sheet'!$C$39,"£#,##"),"£0 ")&$G$33 -> £0 is a reasonable estimate of costs for undertaking the process necessary to prepare the Loan for completion, payable on acceptance of this Decision in Principle and is refundable upon completion Note we reserve the right to retain the commitment fee should the loan fail to complete due to matters outside of our control | E33: Can be removed as per Ildiko | G33: is a reasonable estimate of costs for undertaking the process necessary to prepare the Loan for completion, payable on acceptance of this Decision in Principle and is refundable upon completion Note we reserve the right to retain the commitment fee should the loan fail to complete due to matters outside of our control
B34: Arrangement / Product Fee | C34: ="2.00% of the Gross Loan Amount payable upon the first drawdown date "&IF(G34>0, "or, if earlier, "&TEXT(G34,"dd-mmm-yyyy"),"") -> 2.00% of the Gross Loan Amount payable upon the first drawdown date or, if earlier, 01-Jan-2022 | D34: <-- Check | F34: Earlier Date | G34: 44562
B35: Broker’s Commission | C35: ="£"&TEXT('Input Sheet'!$F$19,"#,##")&" deducted from the Arrangement Fee and payable as commission to the Borrower’s broker" -> £ deducted from the Arrangement Fee and payable as commission to the Borrower’s broker
B36: Broker Client Fee | C36: ="£"&TEXT('Input Sheet'!$F$20,"#,##")&" deducted from the Net Loan Amount and payable as commission to the Borrower’s broker" -> £ deducted from the Net Loan Amount and payable as commission to the Borrower’s broker | D36: Hide if blank
B37: Valuation Fee | C37: =TEXT($G$37,"£#,##") & " plus VAT payable to us in advance of a valuation being instructed" -> £ plus VAT payable to us in advance of a valuation being instructed | D37: <-- Check | F37: Valuation Fee
B38: Legal Fees | C38: Lender’s legal fees payable by the Borrower with amount to be confirmed at a future date
B39: Title Insurance Fee | C39: =TEXT('Input Sheet'!$Q$12,"£#,##0.00")&" plus insurance premium tax, equating to 0.13% of the Gross Loan Amount, subject to a minimum amount of £350." -> plus insurance premium tax, equating to 0.13% of the Gross Loan Amount, subject to a minimum amount of £350.
B40: Early Repayment Charge (“ERC”) | C40: 1. Any time during the Minimum Interest Period: 3.0% of the amount repaid PLUS any interest that would have been payable on the amount repaid from the date of repayment up to and including the final day of the Minimum Interest Period. 2. Following the Minimum Interest Period and subject to the ERC Threshold: a. 3.0% of the amount repaid during the first 12 months of the Term; b. 1.5% of the amount repaid during months 13 to 21 of the Term; and c. no ERC thereafter.
B41: ERC Threshold | C41: Following the Minimum Interest Period until the month 21 of the Term, the Borrower can prepay an aggregate amount of up to 25% of the Gross Loan Amount without any charge.
B42: Tariff of Charges | C42: as available on our website at [LINK]. The Loan Manager reserves its right to change the Tariff of Charges from time to time at its own discretion. | D42: No link available
B45: Security & Covenants
B48: Debenture | C48: ="A first rank debenture with fixed and floating charges over all assets and undertakings of "&G48&" , including mortgages over the Properties" -> A first rank debenture with fixed and floating charges over all assets and undertakings of ABC, EFG , including mortgages over the Properties | D48: <-- Check | F48: Company Name | G48: ABC, EFG
B49: Share Charge | C49: ="A first charge over the shares in "&G48 -> A first charge over the shares in ABC, EFG | D49: <-- Check
B50: First Legal Charge | C50: A first ranking legal charge over the Properties. If(corporate,[which is covered by the Debenture]) | D50: <-- Manual Check
B51: Guarantee | C51: ="A personal/corporate guarantee from" &G51&" for the repayment of the Gross Loan Amount plus all interest, default interest and costs and expenses." -> A personal/corporate guarantee from for the repayment of the Gross Loan Amount plus all interest, default interest and costs and expenses. | D51: <-- Check | F51: Gaurantor Name
B52: Loan to Value (“LTV”) | C52: ="Aggregate of the loan plus all fees and interest as a percentage of MV not to exceed "&TEXT('Input Sheet'!$F$13,"#.##%")&". To be tested quarterly with a compliance certificate to be provided within 30 days of the relevant period" -> Aggregate of the loan plus all fees and interest as a percentage of MV not to exceed .%. To be tested quarterly with a compliance certificate to be provided within 30 days of the relevant period
B53: Interest Cover | C53: As at any date, passing rental as a percentage of finance cost at that date; calculation period - a period of three months or, if less, the period from the date of drawdown of Advance to the date as at which the relevant calculation is made; finance costs - the aggregate amount of interest paid or payable to the Lender during any calculation period in respect of which passing rental has been calculated; and passing rental means, as at any date, the passing rental income that was received on a regular periodical basis by the Borrower during the calculation period ending that date;
B54: Interest Cover Ratio (“ICR”) | C54: =TEXT('Input Sheet'!$F$41,"#.##%")&" To be tested quarterly with a compliance certificate to be provided within 30 days of the relevant period" -> To be tested quarterly with a compliance certificate to be provided within 30 days of the relevant period
B57: Summary Terms & Conditions
B59: Due Diligence | C59: • A full red book valuation prepared by a valuer acceptable to the Lender • Full property and legal diligence undertaken by the Lender’s appointed legal advisor • Supporting documentation and other public information sources we deem necessary such as Credit Reference Agencies (“CRAs”) to conduct our anti-fraud checks and Know Your Customer (“KYC”) and Customer Due Diligence (“CDD”) checks in accordance with the requirements of The Money Laundering Regulations; • Electronic ID verification and liveness checks on the Obligors, if requested by the Lender
B60: Standard Conditions Precedent | C60: Including but not limited to: • For corporate Borrowers certified copies of all relevant constitutional documents including a resolution of the board of directors approving the transaction • For individual Guarantors or third party security providers evidence of independent legal advice • Executed facility agreement and security documents • Evidence of the Borrower's equity contribution towards purchasing and/or refinancing the Properties • All relevant KYC documents and certified identification • Receipt of clear bankruptcy or insolvency (as applicable) searches • All title documents relating to the Borrower's interests in the Properties • A clear Land Charges Registry search against the Borrower • A complete and signed SDLT certificate • Full property searches dated within 3 months prior to the date of completion • Evidence that each required insurance is in place with the lender’s interest noted • Where applicable copies of all planning permissions (including relevant plans and approvals required by planning conditions), building approvals, building regulation completion certificates, licences and consents and planning agreements relating to the prorerty and or granted in respect of the development and any previous development at the property • Evidence that on funding of the loan any existing security interest over any of the Properties and assets to be mortgaged or charged by the security documents will be immediately released • Opening of designated bank accounts such as rent account, cash trap account and cure account
B61: Transaction Specific Conditions Precedent | C61: • [List here] | D61: Manual input
B62: Representations & Warranties | C62: • Validity of incorporation of the Borrower • Power, capacity and authority of the Borrower to comply with its obligations under the finance documents • Legal authority, non-conflict and regulatory compliance • No existing or pending bankruptcy or insolvency • No existing or pending legal proceedings
B63: Valuation | C63: • AVM on all Properties on a half-yearly basis, at Borrower’s costs • Should AVM show a decrease of 5% or more on a Property, full red book valuation is required on that Property at Borrower’s cost • Any time when an Event of Default is continuing or is likely to occur as a result of obtaining that valuation and such Valuation evidences the breach of the LTV breach.
B64: Mandatory Prepayment | C64: • Illegality • Change of control • Proceeds of disposals, subject to agreed carve-outs • Proceeds of insurance, subject to agreed carve-outs • Proceeds of claims against the Property's seller or report providers, subject to agreed carve-outs • Proceeds of compulsory purchase
B65: Application of Prepayments | C65: Prepayments will be applied against amounts outstanding in line with the payment waterfall as documented in the Facility Agreement
B66: Standard Events of Default | C66: Including but not limited to: • Change of control of the Borrower • Insolvency of the Borrower or bankruptcy of any of its directors or shareholders • Appointment of a receiver or similar officer over any of the Borrower’s assets • Submission of an application for a winding up, dissolution or liquidation of the Borrower • Submission of a petition for the bankruptcy of any directors or shareholders of the Borrower • Non-payment of any sums falling due under the facility agreement • Breach of any covenant, representation or warranty contained within the facility agreement • Cross default of any other facility provided by the Lender to the Borrower • Breach of any other financial obligations of the Borrower
B67: Cure rights | C67: • If there is a breach in the LTV or ICR covenants, the Borrower will be given a cure period of 10 business days to either: • prepay in full or in part the loan to cure the financial covenants without triggering Event of Default; or • deposit in the cure account an amount not less than such amount as is required such that immediately following such deposit, if such deposit had been applied in prepayment of the loan on the relevant calculation date, the Borrower would be in compliance with its financial covenants. • No ERC up until ERC Threshold • The Borrower shall not exercise its cure rights by way of voluntary prepayment in two consecutive financial quarters or more than 4 times in aggregate during the Term
B68: Information Covenants | C68: The Borrower to provide the Lender and Loan Manager: • with a detailed rental roll within 5 days of such request and within 30 days of each quarter end, this should include: tenant names, lease terms, rental, arrears, and expiry dates; • quarterly operating statement detailing income and expenditures relating to each property within 30 days of each quarter • any material changes in tenancy, such as lease terminations, changes to the lease and new leases within 10 business days; and • predicted annual budget within 30 days prior to the start of their financial year
B71: Terms of Business
B73: The Loan will be subject to the terms and conditions of a loan agreement and security documents
B75: Variation or withdrawal | C75: We reserve the right to vary the terms or withdraw the Loan at our discretion, should enquiries, valuation or our client due diligence result in material change to the application as now presented or contradict any information disclosed by the Borrower to date. If we decide to vary terms, we will notify the Borrower of variations and provide our reasons for doing so.
B76: Payments to the broker/intermediary | C76: =E76 -> The Borrower authorises us (and/or to instruct our solicitors), to deduct any Arrangement Fees (which includes the Broker’s Commission), Legal Fees and expenses, Title Insurance (if applicable), any interest (rolled up and deferred) and any other fees, costs or expenses payable by the Borrower (which have not already been paid), from the Gross Loan Amount upon completion of the Loan. Market Financial Solutions or its investors pay a part of the Arrangement Fee to the Borrower’s intermediary/broker as Broker’s Commission in the amount as specified above. This means that the intermediary/broker may be unable to provide impartial advice about the Loan to the Borrower. | D76: <-- Check and adjust | E76: =G76& ""&IF('Input Sheet'!F20>0," "&H76," ")&" "&I76 -> The Borrower authorises us (and/or to instruct our solicitors), to deduct any Arrangement Fees (which includes the Broker’s Commission), Legal Fees and expenses, Title Insurance (if applicable), any interest (rolled up and deferred) and any other fees, costs or expenses payable by the Borrower (which have not already been paid), from the Gross Loan Amount upon completion of the Loan. Market Financial Solutions or its investors pay a part of the Arrangement Fee to the Borrower’s intermediary/broker as Broker’s Commission in the amount as specified above. This means that the intermediary/broker may be unable to provide impartial advice about the Loan to the Borrower. | G76: The Borrower authorises us (and/or to instruct our solicitors), to deduct any Arrangement Fees (which includes the Broker’s Commission), Legal Fees and expenses, Title Insurance (if applicable), any interest (rolled up and deferred) and any other fees, costs or expenses payable by the Borrower (which have not already been paid), from the Gross Loan Amount upon completion of the Loan. | H76: The Borrower authorises us to deduct the Broker Client Fee from the Net Loan Amount which is in line with the Borrower’s agreement with its intermediary/broker and payable to the intermediary/broker. No part of the Broker Client Fee is payable to us. | I76: Market Financial Solutions or its investors pay a part of the Arrangement Fee to the Borrower’s intermediary/broker as Broker’s Commission in the amount as specified above. This means that the intermediary/broker may be unable to provide impartial advice about the Loan to the Borrower.
B77: Business Purposes | C77: The Loan is being provided solely for business purposes. The Loan is therefore exempt from the provisions of and the Borrower will therefore not receive the protections afforded by the Financial Services & Markets Act 2000 and the Financial Services and Markets The Mortgage Credit Directive Order 2015 and Consumer Credit Act 1974. The Borrower confirms to us that the Properties have never been and will not be occupied by the Borrower or any spouse, unmarried partner, civil partner, parents, grandparents, siblings, children and grandchildren or any other related person whilst any amount of the Loan remains outstanding. We will rely upon the Borrower’s declarations when completing the Loan, and such declarations will be a condition of the lending.
B78: Data Protection and Privacy | C78: I / We acknowledge that the MFS Privacy Notice - https://www.mfsuk.com/privacy-gdpr/ - has been made available to me through the link provided in this document.
B80: Signed by the Borrower or Authorised signatory of the Borrower if the Borrower is a corporate entity
B83: Signature: | C83: ___________________________________
B86: (Print Name) | C86: ___________________________________
B88: Date: | C88: ___________________________________
B90: [Signed by the Guarantor/Obligors]
B92: Signature: | C92: ___________________________________
B95: (Print Name) | C95: ___________________________________
B97: Date: | C97: ___________________________________
B100: Schedule 1 – List of Properties
A101: 1 - | B101: =_xlfn.CONCAT('Fusion Portfolio'!C9,", ",'Fusion Portfolio'!D9) -> ,
A102: 2 - | B102: =_xlfn.CONCAT('Fusion Portfolio'!C10,", ",'Fusion Portfolio'!D10) -> ,
A103: 3 - | B103: =_xlfn.CONCAT('Fusion Portfolio'!C11,", ",'Fusion Portfolio'!D11) -> ,
A104: 4 - | B104: =_xlfn.CONCAT('Fusion Portfolio'!C12,", ",'Fusion Portfolio'!D12) -> ,
A105: 5 - | B105: =_xlfn.CONCAT('Fusion Portfolio'!C13,", ",'Fusion Portfolio'!D13) -> ,
A106: 6 - | B106: =_xlfn.CONCAT('Fusion Portfolio'!C14,", ",'Fusion Portfolio'!D14) -> ,
A107: 7 - | B107: =_xlfn.CONCAT('Fusion Portfolio'!C15,", ",'Fusion Portfolio'!D15) -> ,
A108: 8 - | B108: =_xlfn.CONCAT('Fusion Portfolio'!C16,", ",'Fusion Portfolio'!D16) -> ,
A109: 9 - | B109: =_xlfn.CONCAT('Fusion Portfolio'!C17,", ",'Fusion Portfolio'!D17) -> ,
A110: 10 - | B110: =_xlfn.CONCAT('Fusion Portfolio'!C18,", ",'Fusion Portfolio'!D18) -> ,
A111: 11 - | B111: =_xlfn.CONCAT('Fusion Portfolio'!C19,", ",'Fusion Portfolio'!D19) -> ,
A112: 12 - | B112: =_xlfn.CONCAT('Fusion Portfolio'!C20,", ",'Fusion Portfolio'!D20) -> ,
... A760: 660 - | B760: =_xlfn.CONCAT('Fusion Portfolio'!C668,", ",'Fusion Portfolio'!D668) -> ,

Sheet Indicative All 3
D3: Bridging Loans | F3: Summary of Terms - Indicative Illustration
D4: ='Input Sheet'!$C$8 -> xxxxx | F4: =IF('Input Sheet'!$C$16="Yes", "Multi-Property",'Input Sheet'!$C$9) -> xxxxx | H4: ='Input Sheet'!B7 -> Reference | I4: ='Input Sheet'!$C$7 -> HubSpot reference
D5: ='Input Sheet'!B27 &": "& TEXT('Input Sheet'!C28,"£#,#")&" "&" Monthly rent: "&TEXT(IF(OR('Input Sheet'!C29 ="", 'Input Sheet'!C29 =0),"N/A", 'Input Sheet'!C29),"£#,#") -> Purchase Price: £ Monthly rent: N/A
A7: Range | D7: Fusion | F7: Variable Bridge | H7: Fixed Bridge
A8: Product Name | D8: ='Input Sheet'!$F$4 & " "& 'Input Sheet'!$F$5 -> Please select product type | F8: =IF('Input Sheet'!$C$13="Mix Rate", "Mix Rate",'Input Sheet'!$I$4) -> Please select product type | H8: =IF('Input Sheet'!$C$13="Mix Rate", "Mix Rate",'Input Sheet'!$I$4) -> Please select product type
A9: Initial Rate | D9: =IF('Input Sheet'!$F$5="","",TEXT(('Input Sheet'!$F$11-BBR),"0.00%")&" + BBR (pa)") | F9: =IF('Input Sheet'!I5="","",TEXT('Input Sheet'!I5,"0.00%")&" + BBR (pm)") | H9: =IF('Input Sheet'!L5="","",TEXT('Input Sheet'!L11,"0.00%")&" (pm)")
A10: Pay Rate | D10: =IF('Input Sheet'!$F$5="","",TEXT(('Input Sheet'!$F$11-BBR-'Input Sheet'!$F$9),"0.00%")&" + BBR (pa)") | F10: =$F$9 | H10: =$H$9
A11: Gross Loan (repayable at redemption) | D11: =IFERROR(TEXT('Input Sheet'!F12,"£0,#"),0) & " @ "&TEXT('Input Sheet'!$F$13,"0%")&" LTV" -> £0 @ 0% LTV | F11: =IFERROR(TEXT('Input Sheet'!I12,"£0,#"),0)&" "&"@ "&TEXT('Input Sheet'!$I$13,"0%")&" LTV" -> £0 @ 0% LTV | H11: =IFERROR(TEXT('Input Sheet'!L12,"£0,#"),0) & " @ "&TEXT('Input Sheet'!$L$13,"0%")&" LTV" -> £0 @ 0% LTV
A12: Net Loan (day 1 advance) | D12: =TEXT('Input Sheet'!F15,"£0,#") & " " & "@ " & TEXT('Input Sheet'!F16,"0%") & " LTV" -> £0 @ 0% LTV | F12: =IFERROR(TEXT('Input Sheet'!I15,"£0,#"),0) & " " &IFERROR("@ " & TEXT('Input Sheet'!I16,"0%") & " LTV","") -> £0 @ 0% LTV | H12: =IFERROR(TEXT('Input Sheet'!L15,"£0,#"),0) & " @ " & TEXT('Input Sheet'!L16,"0%") & " LTV" -> £0 @ 0% LTV
A13: Arrangement Fee | D13: =IFERROR(TEXT('Input Sheet'!F18,"£0,#"),0) &" " &"(" & TEXT('Main Calculations'!$D$13,"0.00%") &")" -> £0 (2.00%) | F13: =IFERROR(TEXT('Input Sheet'!I18,"£0,#")&" "&"("&TEXT('Main Calculations'!$F$13,"0.00%")&")","") | H13: =IFERROR(TEXT('Input Sheet'!L18,"£0,#")& " (" & TEXT('Main Calculations'!$H$13,"0.00%") &")","")
A14: Total Loan Term | D14: 24 Months | F14: ='Input Sheet'!I8 & " Months" -> 12 Months | H14: ='Input Sheet'!L8 & " Months" -> 12 Months
A15: Rolled Months Interest | D15: =IFERROR(TEXT('Input Sheet'!F23,"£0,#"),0) & " " &"(" & 'Input Sheet'!F7 & " months"&")" -> £0 (6 months) | F15: =IFERROR(TEXT('Input Sheet'!I23,"£0,#"),0) & " " &"(" & 'Input Sheet'!I7 & IF('Input Sheet'!I7="", "0 months",IF('Input Sheet'!I7=1, " month", " months"))&")" -> £0 (3 months) | H15: =IFERROR(TEXT('Input Sheet'!L23,"£0,#"),0)& " (" & 'Input Sheet'!L7 & IF('Input Sheet'!L7="", "0 months",IF('Input Sheet'!L7 = 1, " month"," months"))&")" -> £0 (3 months)
A16: Monthly Payment | D16: =TEXT('Input Sheet'!F29,"£0,#") & " " &"from month " & 'Input Sheet'!F7+1 -> £0 from month 7 | F16: =TEXT(IF('Input Sheet'!$I$8='Input Sheet'!$I$7,"Fully Rolled",'Input Sheet'!I29), "£0,#")& " " & IF('Input Sheet'!$I$7>='Input Sheet'!$I$8, "","from month " & 'Input Sheet'!$I$7+1) -> £0 from month 4 | H16: =TEXT(IF('Input Sheet'!L8='Input Sheet'!L7,"Fully Rolled",'Input Sheet'!L29),"£0,#") &" " &IF('Input Sheet'!$L$7>='Input Sheet'!$L$8,"","from month " & 'Input Sheet'!$L$7+1) -> £0 from month 4
A17: Deferred Interest | D17: =IF('Input Sheet'!F24>0,TEXT('Input Sheet'!F24,"£0#,#") & " " &"("&TEXT('Input Sheet'!F9,"0.00%"&")"),"N/A") -> N/A | F17: N/A | H17: N/A
B18: Min Interest Period | D18: 6 Months | F18: 3 Months | H18: 3 Months
A19: ERC/Exit Fee | D19: ="3% in Yr1, 1.5% in Yr2" &" (25% capital repayment allowed from month 7, no ERC after 21 months)" -> 3% in Yr1, 1.5% in Yr2 (25% capital repayment allowed from month 7, no ERC after 21 months) | F19: =IF('Input Sheet'!$C$38<=0,"N/A",'Input Sheet'!$C$38) -> N/A | H19: =IF('Input Sheet'!$C$38<=0,"N/A",'Input Sheet'!$C$38) -> N/A
A20: Proc Fee | D20: =IFERROR(IF('Input Sheet'!$C$35="TBC", "TBC",'Input Sheet'!$F$19),0) -> 0 | F20: =IFERROR(IF('Input Sheet'!$C$35="TBC", "TBC",'Input Sheet'!$I$19),0) -> 0 | H20: =IFERROR(IF('Input Sheet'!$C$35="TBC", "TBC",'Input Sheet'!$L$19),0) -> 0
A21: Broker Client Fee (To be deducted from the net loan) | D21: =IFERROR('Input Sheet'!F20,0) -> 0 | F21: =IFERROR('Input Sheet'!I20,0) -> 0 | H21: =IFERROR('Input Sheet'!L20,0) -> 0
A23: Commitment Fee | D23: =IF('Input Sheet'!$C$39=0, "TBC by the Underwriter", 'Input Sheet'!$C$39) -> TBC by the Underwriter | F23: Payable when DIP signed, refundable on completion
A24: Valuation Fee | D24: TBC by the Underwriter | F24: Payable when DIP is signed
A25: Lender Legal Fee | D25: TBC by the Underwriter | F25: Excludes the borrower's own legal cost
B26: Title Insurance Premium | D26: ='Input Sheet'!$Q$12 | F26: ='Input Sheet'!$Q$13 | H26: ='Input Sheet'!$Q$14
D27: Please note: indicative only, subject to full underwrite, valuation, credit report and other supporting evidence. This Document is confidential to the intended recipient. If you are not the intended recipient, do not use, copy or disclose the information in any way or act in reliance on it, and notify the sender immediately, then delete it from your system. Market Financial Solutions Ltd accepts no liability (to the fullest extent permitted by law) for opinions, conclusions and other information in this message which do not relate to its official business. No contracts or official orders will be confirmed by means of this document.
B34: Property Address | G34: Property Value | H34: Our Charge | I34: Outstanding Charge | XFC34: <-- Hide if Fusion Premier
B35: =IF('Multi Property Deal'!$B$4="","",'Multi Property Deal'!$B$4) | G35: =IF('Multi Property Deal'!$M$4="","",'Multi Property Deal'!$M$4) | H35: =IF('Multi Property Deal'!$P$4="","",'Multi Property Deal'!$P$4) | I35: =IF(B35="","",IF(SUM('Multi Property Deal'!$R$4:$R$6)=0,0,SUM('Multi Property Deal'!$R$4:$R$6)))
B36: =IF('Multi Property Deal'!$B$7="","",'Multi Property Deal'!$B$7) | G36: =IF('Multi Property Deal'!$M$7="","",'Multi Property Deal'!$M$7) | H36: =IF('Multi Property Deal'!$P$7="","",'Multi Property Deal'!$P$7) | I36: =IF(B36="","",IF(SUM('Multi Property Deal'!$R$7:$R$9)=0,0,SUM('Multi Property Deal'!$R$7:$R$9)))
B37: =IF('Multi Property Deal'!$B$10="","",'Multi Property Deal'!$B$10) | G37: =IF('Multi Property Deal'!$M$10="","",'Multi Property Deal'!$M$10) | H37: =IF('Multi Property Deal'!$P$10="","",'Multi Property Deal'!$P$10) | I37: =IF(B37="","",IF(SUM('Multi Property Deal'!$R$10:$R$12)=0,0,SUM('Multi Property Deal'!$R$10:$R$12)))
B38: =IF('Multi Property Deal'!$B$13="","",'Multi Property Deal'!$B$13) | G38: =IF('Multi Property Deal'!$M$13="","",'Multi Property Deal'!$M$13) | H38: =IF('Multi Property Deal'!$P$13="","",'Multi Property Deal'!$P$13) | I38: =IF(B38="","",IF(SUM('Multi Property Deal'!$R$13:$R$15)=0,0,SUM('Multi Property Deal'!$R$13:$R$15)))
B39: =IF('Multi Property Deal'!$B$16="","",'Multi Property Deal'!$B$16) | G39: =IF('Multi Property Deal'!$M$16="","",'Multi Property Deal'!$M$16) | H39: =IF('Multi Property Deal'!$P$16="","",'Multi Property Deal'!$P$16) | I39: =IF(B39="","",IF(SUM('Multi Property Deal'!$R$16:$R$18)=0,0,SUM('Multi Property Deal'!$R$16:$R$18)))
B40: =IF('Multi Property Deal'!$B$19="","",'Multi Property Deal'!$B$19) | G40: =IF('Multi Property Deal'!$M$19="","",'Multi Property Deal'!$M$19) | H40: =IF('Multi Property Deal'!$P$19="","",'Multi Property Deal'!$P$19) | I40: =IF(B40="","",IF(SUM('Multi Property Deal'!$R$19:$R$21)=0,0,SUM('Multi Property Deal'!$R$19:$R$21)))
B41: =IF('Multi Property Deal'!$B$22="","",'Multi Property Deal'!$B$22) | G41: =IF('Multi Property Deal'!$M$22="","",'Multi Property Deal'!$M$22) | H41: =IF('Multi Property Deal'!$P$22="","",'Multi Property Deal'!$P$22) | I41: =IF(B41="","",IF(SUM('Multi Property Deal'!$R$22:$R$24)=0,0,SUM('Multi Property Deal'!$R$22:$R$24)))
B42: =IF('Multi Property Deal'!$B$25="","",'Multi Property Deal'!$B$25) | G42: =IF('Multi Property Deal'!$M$25="","",'Multi Property Deal'!$M$25) | H42: =IF('Multi Property Deal'!$P$25="","",'Multi Property Deal'!$P$25) | I42: =IF(B42="","",IF(SUM('Multi Property Deal'!$R$22:$R$24)=0,0,SUM('Multi Property Deal'!$R$22:$R$24)))
B43: =IF('Multi Property Deal'!$B$28="","",'Multi Property Deal'!$B$28) | G43: =IF('Multi Property Deal'!$M$28="","",'Multi Property Deal'!$M$28) | H43: =IF('Multi Property Deal'!$P$28="","",'Multi Property Deal'!$P$28) | I43: =IF(B43="","",IF(SUM('Multi Property Deal'!$R$28:$R$30)=0,0,SUM('Multi Property Deal'!$R$28:$R$30)))
B44: =IF('Multi Property Deal'!$B$31="","",'Multi Property Deal'!$B$31) | G44: =IF('Multi Property Deal'!$M$31="","",'Multi Property Deal'!$M$31) | H44: =IF('Multi Property Deal'!$P$31="","",'Multi Property Deal'!$P$31) | I44: =IF(B44="","",IF(SUM('Multi Property Deal'!$R$31:$R$33)=0,0,SUM('Multi Property Deal'!$R$31:$R$33)))
B45: =IF('Multi Property Deal'!$B$34="","",'Multi Property Deal'!$B$34) | G45: =IF('Multi Property Deal'!$M$34="","",'Multi Property Deal'!$M$34) | H45: =IF('Multi Property Deal'!$P$34="","",'Multi Property Deal'!$P$34) | I45: =IF(B45="","",IF(SUM('Multi Property Deal'!$R$34:$R$36)=0,0,SUM('Multi Property Deal'!$R$34:$R$36)))

Sheet Indicative 2 only
D3: Bridging Loans | F3: Summary of Terms - Indicative Illustration
D4: ='Input Sheet'!$C$8 -> xxxxx | F4: =IF('Input Sheet'!$C$16="Yes", "Multi-Property",'Input Sheet'!$C$9) -> xxxxx | H4: ='Input Sheet'!B7 -> Reference | I4: ='Input Sheet'!$C$7 -> HubSpot reference
B5: =IF(AND(D7="Variable Bridge",G7="Fixed Bridge"),1,0) -> 0 | D5: ='Input Sheet'!B27 &": "& TEXT('Input Sheet'!C28,"£#,#")&" "&" Monthly rent: "&TEXT(IF(OR('Input Sheet'!C29 ="", 'Input Sheet'!C29 =0),"N/A", 'Input Sheet'!C29),"£#,#") -> Purchase Price: £ Monthly rent: N/A
A7: Range | D7: =IF('Input Sheet'!$G$2=TRUE,'Indicative All 3'!D7,'Indicative All 3'!F7) -> Fusion | G7: =IF('Input Sheet'!$K$2=TRUE,'Indicative All 3'!H7,'Indicative All 3'!F7) -> Fixed Bridge
A8: Product Name | D8: =IF($D$7="Fusion",'Indicative All 3'!D8,'Indicative All 3'!F8) -> Please select product type | G8: =IF('Input Sheet'!$K$2=TRUE,'Indicative All 3'!H8,'Indicative All 3'!F8) -> Please select product type
A9: Initial Rate | D9: =IF($D$7="Fusion",'Indicative All 3'!D9,'Indicative All 3'!F9) | G9: =IF('Input Sheet'!$K$2=TRUE,'Indicative All 3'!H9,'Indicative All 3'!F9)
A10: Pay Rate | D10: =IF($D$7="Fusion",'Indicative All 3'!D10,'Indicative All 3'!F10) | G10: =IF('Input Sheet'!$K$2=TRUE,'Indicative All 3'!H10,'Indicative All 3'!F10)
A11: Gross Loan (repayable at redemption) | D11: =IF($D$7="Fusion",'Indicative All 3'!D11,'Indicative All 3'!F11) -> £0 @ 0% LTV | G11: =IF('Input Sheet'!$K$2=TRUE,'Indicative All 3'!H11,'Indicative All 3'!F11) -> £0 @ 0% LTV
A12: Net Loan (day 1 advance) | D12: =IF($D$7="Fusion",'Indicative All 3'!D12,'Indicative All 3'!F12) -> £0 @ 0% LTV | G12: =IF('Input Sheet'!$K$2=TRUE,'Indicative All 3'!H12,'Indicative All 3'!F12) -> £0 @ 0% LTV
A13: Arrangement Fee | D13: =IF($D$7="Fusion",'Indicative All 3'!D13,'Indicative All 3'!F13) -> £0 (2.00%) | G13: =IF('Input Sheet'!$K$2=TRUE,'Indicative All 3'!H13,'Indicative All 3'!F13)
A14: Total Loan Term | D14: =IF($D$7="Fusion",'Indicative All 3'!D14,'Indicative All 3'!F14) -> 24 Months | G14: =IF('Input Sheet'!$K$2=TRUE,'Indicative All 3'!H14,'Indicative All 3'!F14) -> 12 Months
A15: Rolled Months Interest | D15: =IF($D$7="Fusion",'Indicative All 3'!D15,'Indicative All 3'!F15) -> £0 (6 months) | G15: =IF('Input Sheet'!$K$2=TRUE,'Indicative All 3'!H15,'Indicative All 3'!F15) -> £0 (3 months)
A16: Monthly Payment | D16: =IF($D$7="Fusion",'Indicative All 3'!D16,'Indicative All 3'!F16) -> £0 from month 7 | G16: =IF('Input Sheet'!$K$2=TRUE,'Indicative All 3'!H16,'Indicative All 3'!F16) -> £0 from month 4
B17: Deferred Interest | D17: =IF($D$7="Fusion",'Indicative All 3'!D17,'Indicative All 3'!F17) -> N/A | G17: =IF('Input Sheet'!$K$2=TRUE,'Indicative All 3'!H17,'Indicative All 3'!F17) -> N/A
B18: Min Interest Period | D18: =IF($D$7="Fusion",'Indicative All 3'!D18,'Indicative All 3'!F18) -> 6 Months | G18: =IF('Input Sheet'!$K$2=TRUE,'Indicative All 3'!H18,'Indicative All 3'!F18) -> 3 Months
A19: ERC/Exit Fee | D19: =IF($D$7="Fusion",'Indicative All 3'!D19,'Indicative All 3'!F19) -> 3% in Yr1, 1.5% in Yr2 (25% capital repayment allowed from month 7, no ERC after 21 months) | G19: =IF('Input Sheet'!$K$2=TRUE,'Indicative All 3'!H19,'Indicative All 3'!F19) -> N/A
A20: Proc Fee | D20: =IF($D$7="Fusion",'Indicative All 3'!D20,'Indicative All 3'!F20) -> 0 | G20: =IF('Input Sheet'!$K$2=TRUE,'Indicative All 3'!H20,'Indicative All 3'!F20) -> 0
A21: Broker Client Fee (To be deducted from the net loan) | D21: =IF($D$7="Fusion",'Indicative All 3'!D21,'Indicative All 3'!F21) -> 0 | G21: =IF('Input Sheet'!$K$2=TRUE,'Indicative All 3'!H21,'Indicative All 3'!F21) -> 0
A23: Commitment Fee | D23: =IF('Input Sheet'!$C$39=0, "TBC by the Underwriter", 'Input Sheet'!$C$39) -> TBC by the Underwriter | F23: Payable when DIP signed, refundable on completion
A24: Valuation Fee | D24: TBC by the Underwriter | F24: Payable when DIP is signed
A25: Lender Legal Fee | D25: TBC by the Underwriter | F25: Excludes the borrower's own legal cost
B26: Title Insurance Premium | D26: =IF($D$7="Fusion",'Indicative All 3'!D26,'Indicative All 3'!F26) | G26: =IF('Input Sheet'!$K$2=TRUE,'Indicative All 3'!H26,'Indicative All 3'!F26)
D27: Please note: indicative only, subject to full underwrite, valuation, credit report and other supporting evidence. This Document is confidential to the intended recipient. If you are not the intended recipient, do not use, copy or disclose the information in any way or act in reliance on it, and notify the sender immediately, then delete it from your system. Market Financial Solutions Ltd accepts no liability (to the fullest extent permitted by law) for opinions, conclusions and other information in this message which do not relate to its official business. No contracts or official orders will be confirmed by means of this document.
B35: Property Address | G35: Property Value | H35: Our Charge | I35: Outstanding Charge | XFC35: <-- Hide if Fusion Premier
B36: =IF('Multi Property Deal'!$B$4="","",'Multi Property Deal'!$B$4) | G36: =IF('Multi Property Deal'!$M$4="","",'Multi Property Deal'!$M$4) | H36: =IF('Multi Property Deal'!$P$4="","",'Multi Property Deal'!$P$4) | I36: =IF(B36="","",IF(SUM('Multi Property Deal'!$R$4:$R$6)=0,0,SUM('Multi Property Deal'!$R$4:$R$6)))
B37: =IF('Multi Property Deal'!$B$7="","",'Multi Property Deal'!$B$7) | G37: =IF('Multi Property Deal'!$M$7="","",'Multi Property Deal'!$M$7) | H37: =IF('Multi Property Deal'!$P$7="","",'Multi Property Deal'!$P$7) | I37: =IF(B37="","",IF(SUM('Multi Property Deal'!$R$7:$R$9)=0,0,SUM('Multi Property Deal'!$R$7:$R$9)))
B38: =IF('Multi Property Deal'!$B$10="","",'Multi Property Deal'!$B$10) | G38: =IF('Multi Property Deal'!$M$10="","",'Multi Property Deal'!$M$10) | H38: =IF('Multi Property Deal'!$P$10="","",'Multi Property Deal'!$P$10) | I38: =IF(B38="","",IF(SUM('Multi Property Deal'!$R$10:$R$12)=0,0,SUM('Multi Property Deal'!$R$10:$R$12)))
B39: =IF('Multi Property Deal'!$B$13="","",'Multi Property Deal'!$B$13) | G39: =IF('Multi Property Deal'!$M$13="","",'Multi Property Deal'!$M$13) | H39: =IF('Multi Property Deal'!$P$13="","",'Multi Property Deal'!$P$13) | I39: =IF(B39="","",IF(SUM('Multi Property Deal'!$R$13:$R$15)=0,0,SUM('Multi Property Deal'!$R$13:$R$15)))
B40: =IF('Multi Property Deal'!$B$16="","",'Multi Property Deal'!$B$16) | G40: =IF('Multi Property Deal'!$M$16="","",'Multi Property Deal'!$M$16) | H40: =IF('Multi Property Deal'!$P$16="","",'Multi Property Deal'!$P$16) | I40: =IF(B40="","",IF(SUM('Multi Property Deal'!$R$16:$R$18)=0,0,SUM('Multi Property Deal'!$R$16:$R$18)))
B41: =IF('Multi Property Deal'!$B$19="","",'Multi Property Deal'!$B$19) | G41: =IF('Multi Property Deal'!$M$19="","",'Multi Property Deal'!$M$19) | H41: =IF('Multi Property Deal'!$P$19="","",'Multi Property Deal'!$P$19) | I41: =IF(B41="","",IF(SUM('Multi Property Deal'!$R$19:$R$21)=0,0,SUM('Multi Property Deal'!$R$19:$R$21)))
B42: =IF('Multi Property Deal'!$B$22="","",'Multi Property Deal'!$B$22) | G42: =IF('Multi Property Deal'!$M$22="","",'Multi Property Deal'!$M$22) | H42: =IF('Multi Property Deal'!$P$22="","",'Multi Property Deal'!$P$22) | I42: =IF(B42="","",IF(SUM('Multi Property Deal'!$R$22:$R$24)=0,0,SUM('Multi Property Deal'!$R$22:$R$24)))
B43: =IF('Multi Property Deal'!$B$25="","",'Multi Property Deal'!$B$25) | G43: =IF('Multi Property Deal'!$M$25="","",'Multi Property Deal'!$M$25) | H43: =IF('Multi Property Deal'!$P$25="","",'Multi Property Deal'!$P$25) | I43: =IF(B43="","",IF(SUM('Multi Property Deal'!$R$22:$R$24)=0,0,SUM('Multi Property Deal'!$R$22:$R$24)))
B44: =IF('Multi Property Deal'!$B$28="","",'Multi Property Deal'!$B$28) | G44: =IF('Multi Property Deal'!$M$28="","",'Multi Property Deal'!$M$28) | H44: =IF('Multi Property Deal'!$P$28="","",'Multi Property Deal'!$P$28) | I44: =IF(B44="","",IF(SUM('Multi Property Deal'!$R$28:$R$30)=0,0,SUM('Multi Property Deal'!$R$28:$R$30)))
B45: =IF('Multi Property Deal'!$B$31="","",'Multi Property Deal'!$B$31) | G45: =IF('Multi Property Deal'!$M$31="","",'Multi Property Deal'!$M$31) | H45: =IF('Multi Property Deal'!$P$31="","",'Multi Property Deal'!$P$31) | I45: =IF(B45="","",IF(SUM('Multi Property Deal'!$R$31:$R$33)=0,0,SUM('Multi Property Deal'!$R$31:$R$33)))
B46: =IF('Multi Property Deal'!$B$34="","",'Multi Property Deal'!$B$34) | G46: =IF('Multi Property Deal'!$M$34="","",'Multi Property Deal'!$M$34) | H46: =IF('Multi Property Deal'!$P$34="","",'Multi Property Deal'!$P$34) | I46: =IF(B46="","",IF(SUM('Multi Property Deal'!$R$34:$R$36)=0,0,SUM('Multi Property Deal'!$R$34:$R$36)))

Sheet Single Indicative
D3: Bridging Loans | F3: Summary of Terms - Indicative Illustration
D4: ='Input Sheet'!$C$8 -> xxxxx | F4: =IF('Input Sheet'!$C$16="Yes", "Multi-Property",'Input Sheet'!$C$9) -> xxxxx | H4: ='Input Sheet'!B7 -> Reference | I4: ='Input Sheet'!$C$7 -> HubSpot reference
B5: =IF(D7<>"Fusion",1,0) -> 0 | D5: ='Input Sheet'!B27 &": "& TEXT('Input Sheet'!C28,"£#,#")&" "&" Monthly rent: "&TEXT(IF(OR('Input Sheet'!C29 ="", 'Input Sheet'!C29 =0),"N/A", 'Input Sheet'!C29),"£#,#") -> Purchase Price: £ Monthly rent: N/A
A7: Range | D7: =IF('Input Sheet'!$G$2=TRUE,'Indicative All 3'!D7,IF('Input Sheet'!$H$2=TRUE,'Indicative All 3'!F7,IF('Input Sheet'!$K$2=TRUE,'Indicative All 3'!H7))) -> Fusion
A8: Product Name | D8: =IF($D$7="Fusion",'Indicative All 3'!D8,IF('Input Sheet'!$H$2=TRUE,'Indicative All 3'!F8,IF('Input Sheet'!$K$2=TRUE,'Indicative All 3'!H8))) -> Please select product type
A9: Initial Rate | D9: =IF($D$7="Fusion",'Indicative All 3'!D9,IF('Input Sheet'!$H$2=TRUE,'Indicative All 3'!F9,IF('Input Sheet'!$K$2=TRUE,'Indicative All 3'!H9)))
A10: Pay Rate | D10: =IF('Input Sheet'!$E$2=TRUE,'Indicative All 3'!D10,IF('Input Sheet'!$H$2=TRUE,'Indicative All 3'!F10,IF('Input Sheet'!$K$2=TRUE,'Indicative All 3'!H10)))
A11: Gross Loan (repayable at redemption) | D11: =IF($D$7="Fusion",'Indicative All 3'!D11,IF('Input Sheet'!$H$2=TRUE,'Indicative All 3'!F11,IF('Input Sheet'!$K$2=TRUE,'Indicative All 3'!H11))) -> £0 @ 0% LTV
A12: Net Loan (day 1 advance) | D12: =IF($D$7="Fusion",'Indicative All 3'!D12,IF('Input Sheet'!$H$2=TRUE,'Indicative All 3'!F12,IF('Input Sheet'!$K$2=TRUE,'Indicative All 3'!H12))) -> £0 @ 0% LTV
A13: Arrangement Fee | D13: =IF($D$7="Fusion",'Indicative All 3'!D13,IF('Input Sheet'!$H$2=TRUE,'Indicative All 3'!F13,IF('Input Sheet'!$K$2=TRUE,'Indicative All 3'!H13))) -> £0 (2.00%)
A14: Total Loan Term | D14: =IF($D$7="Fusion",'Indicative All 3'!D14,IF('Input Sheet'!$H$2=TRUE,'Indicative All 3'!F14,IF('Input Sheet'!$K$2=TRUE,'Indicative All 3'!H14))) -> 24 Months
A15: Rolled Months Interest | D15: =IF($D$7="Fusion",'Indicative All 3'!D15,IF('Input Sheet'!$H$2=TRUE,'Indicative All 3'!F15,IF('Input Sheet'!$K$2=TRUE,'Indicative All 3'!H15))) -> £0 (6 months)
A16: Monthly Payment | D16: =IF($D$7="Fusion",'Indicative All 3'!D16,IF('Input Sheet'!$H$2=TRUE,'Indicative All 3'!F16,IF('Input Sheet'!$K$2=TRUE,'Indicative All 3'!H16))) -> £0 from month 7
B17: Deferred Interest | D17: =IF('Input Sheet'!$E$2=TRUE,'Indicative All 3'!D17,IF('Input Sheet'!$H$2=TRUE,'Indicative All 3'!F17,IF('Input Sheet'!$K$2=TRUE,'Indicative All 3'!H17))) -> N/A
B18: Min Interest Period | D18: =IF($D$7="Fusion",'Indicative All 3'!D18,IF('Input Sheet'!$H$2=TRUE,'Indicative All 3'!F18,IF('Input Sheet'!$K$2=TRUE,'Indicative All 3'!H18))) -> 6 Months
A19: ERC/Exit Fee | D19: =IF($D$7="Fusion",'Indicative All 3'!D19,IF('Input Sheet'!$H$2=TRUE,'Indicative All 3'!F19,IF('Input Sheet'!$K$2=TRUE,'Indicative All 3'!H19))) -> 3% in Yr1, 1.5% in Yr2 (25% capital repayment allowed from month 7, no ERC after 21 months)
A20: Proc Fee | D20: =IF($D$7="Fusion",'Indicative All 3'!D20,IF('Input Sheet'!$H$2=TRUE,'Indicative All 3'!F20,IF('Input Sheet'!$K$2=TRUE,'Indicative All 3'!H20))) -> 0
A21: Broker Client Fee (To be deducted from the net loan) | D21: =IF($D$7="Fusion",'Indicative All 3'!D21,IF('Input Sheet'!$H$2=TRUE,'Indicative All 3'!F21,IF('Input Sheet'!$K$2=TRUE,'Indicative All 3'!H21))) -> 0
A23: Commitment Fee | D23: =IF('Input Sheet'!$C$39=0, "TBC by the Underwriter", 'Input Sheet'!$C$39) -> TBC by the Underwriter | F23: Payable when DIP signed, refundable on completion
A24: Valuation Fee | D24: TBC by the Underwriter | F24: Payable when DIP is signed
A25: Lender Legal Fee | D25: TBC by the Underwriter | F25: Excludes the borrower's own legal cost
B26: Title Insurance Premium | D26: =IF($D$7="Fusion",'Indicative All 3'!D26,IF('Input Sheet'!$H$2=TRUE,'Indicative All 3'!F26,IF('Input Sheet'!$K$2=TRUE,'Indicative All 3'!H26)))
D27: Please note: indicative only, subject to full underwrite, valuation, credit report and other supporting evidence. This Document is confidential to the intended recipient. If you are not the intended recipient, do not use, copy or disclose the information in any way or act in reliance on it, and notify the sender immediately, then delete it from your system. Market Financial Solutions Ltd accepts no liability (to the fullest extent permitted by law) for opinions, conclusions and other information in this message which do not relate to its official business. No contracts or official orders will be confirmed by means of this document.
B35: Property Address | G35: Property Value | H35: Our Charge | I35: Outstanding Charge | L35: <-- Hide if Fusion Premier
B36: =IF('Multi Property Deal'!$B$4="","",'Multi Property Deal'!$B$4) | G36: =IF('Multi Property Deal'!$M$4="","",'Multi Property Deal'!$M$4) | H36: =IF('Multi Property Deal'!$P$4="","",'Multi Property Deal'!$P$4) | I36: =IF(B36="","",IF(SUM('Multi Property Deal'!$R$4:$R$6)=0,0,SUM('Multi Property Deal'!$R$4:$R$6)))
B37: =IF('Multi Property Deal'!$B$7="","",'Multi Property Deal'!$B$7) | G37: =IF('Multi Property Deal'!$M$7="","",'Multi Property Deal'!$M$7) | H37: =IF('Multi Property Deal'!$P$7="","",'Multi Property Deal'!$P$7) | I37: =IF(B37="","",IF(SUM('Multi Property Deal'!$R$7:$R$9)=0,0,SUM('Multi Property Deal'!$R$7:$R$9)))
B38: =IF('Multi Property Deal'!$B$10="","",'Multi Property Deal'!$B$10) | G38: =IF('Multi Property Deal'!$M$10="","",'Multi Property Deal'!$M$10) | H38: =IF('Multi Property Deal'!$P$10="","",'Multi Property Deal'!$P$10) | I38: =IF(B38="","",IF(SUM('Multi Property Deal'!$R$10:$R$12)=0,0,SUM('Multi Property Deal'!$R$10:$R$12)))
B39: =IF('Multi Property Deal'!$B$13="","",'Multi Property Deal'!$B$13) | G39: =IF('Multi Property Deal'!$M$13="","",'Multi Property Deal'!$M$13) | H39: =IF('Multi Property Deal'!$P$13="","",'Multi Property Deal'!$P$13) | I39: =IF(B39="","",IF(SUM('Multi Property Deal'!$R$13:$R$15)=0,0,SUM('Multi Property Deal'!$R$13:$R$15)))
B40: =IF('Multi Property Deal'!$B$16="","",'Multi Property Deal'!$B$16) | G40: =IF('Multi Property Deal'!$M$16="","",'Multi Property Deal'!$M$16) | H40: =IF('Multi Property Deal'!$P$16="","",'Multi Property Deal'!$P$16) | I40: =IF(B40="","",IF(SUM('Multi Property Deal'!$R$16:$R$18)=0,0,SUM('Multi Property Deal'!$R$16:$R$18)))
B41: =IF('Multi Property Deal'!$B$19="","",'Multi Property Deal'!$B$19) | G41: =IF('Multi Property Deal'!$M$19="","",'Multi Property Deal'!$M$19) | H41: =IF('Multi Property Deal'!$P$19="","",'Multi Property Deal'!$P$19) | I41: =IF(B41="","",IF(SUM('Multi Property Deal'!$R$19:$R$21)=0,0,SUM('Multi Property Deal'!$R$19:$R$21)))
B42: =IF('Multi Property Deal'!$B$22="","",'Multi Property Deal'!$B$22) | G42: =IF('Multi Property Deal'!$M$22="","",'Multi Property Deal'!$M$22) | H42: =IF('Multi Property Deal'!$P$22="","",'Multi Property Deal'!$P$22) | I42: =IF(B42="","",IF(SUM('Multi Property Deal'!$R$22:$R$24)=0,0,SUM('Multi Property Deal'!$R$22:$R$24)))
B43: =IF('Multi Property Deal'!$B$25="","",'Multi Property Deal'!$B$25) | G43: =IF('Multi Property Deal'!$M$25="","",'Multi Property Deal'!$M$25) | H43: =IF('Multi Property Deal'!$P$25="","",'Multi Property Deal'!$P$25) | I43: =IF(B43="","",IF(SUM('Multi Property Deal'!$R$22:$R$24)=0,0,SUM('Multi Property Deal'!$R$22:$R$24)))
B44: =IF('Multi Property Deal'!$B$28="","",'Multi Property Deal'!$B$28) | G44: =IF('Multi Property Deal'!$M$28="","",'Multi Property Deal'!$M$28) | H44: =IF('Multi Property Deal'!$P$28="","",'Multi Property Deal'!$P$28) | I44: =IF(B44="","",IF(SUM('Multi Property Deal'!$R$28:$R$30)=0,0,SUM('Multi Property Deal'!$R$28:$R$30)))
B45: =IF('Multi Property Deal'!$B$31="","",'Multi Property Deal'!$B$31) | G45: =IF('Multi Property Deal'!$M$31="","",'Multi Property Deal'!$M$31) | H45: =IF('Multi Property Deal'!$P$31="","",'Multi Property Deal'!$P$31) | I45: =IF(B45="","",IF(SUM('Multi Property Deal'!$R$31:$R$33)=0,0,SUM('Multi Property Deal'!$R$31:$R$33)))
B46: =IF('Multi Property Deal'!$B$34="","",'Multi Property Deal'!$B$34) | G46: =IF('Multi Property Deal'!$M$34="","",'Multi Property Deal'!$M$34) | H46: =IF('Multi Property Deal'!$P$34="","",'Multi Property Deal'!$P$34) | I46: =IF(B46="","",IF(SUM('Multi Property Deal'!$R$34:$R$36)=0,0,SUM('Multi Property Deal'!$R$34:$R$36)))

Sheet DIP
A1: Automatic DIP production - choose Print to Microsft PDF for a email DIP
A2: THIS IS SET TEXT THAT WILL BE PRINTED - DO NOT AMEND COLUMNS A to D | F2: Shows rows to check | G2: Applicant Type | H2: ='Input Sheet'!C12 -> 0
F3: UW TO CHECK | G3: NOTES FOR THE UNDERWRITER | H3: Overwrite - new value? | I3: Notes for overwrite | J3: Formula pull through
A4: Decision in Principle | B4: =IF(H4="",J4,H4) -> 45989 | F4: ← Check | G4: Means variable value to the left to check or amend (amends to the right) | I4: Defaults to todays date | J4: =IF(H4="",TODAY(),H4) -> 45989
A5: Proposed Loan to: | B5: =IF(H2="Personal",IF(H5="",'Input Sheet'!C8,H5),(IF(H5="",'Input Sheet'!C8,H5)&" (Company No: "&J5&")")) -> xxxxx (Company No: XXXXXXXXX) | F5: ← Check | I5: Company Number | J5: XXXXXXXXX
A6: Security Property: | B6: =IF('Input Sheet'!$C$16="Yes",DIP!$K$6,IF(H6="",'Input Sheet'!$C$9,DIP!$H$6)) -> xxxxx | D6: =IF('Input Sheet'!$C$16="Yes",DIP!$M$6,"Title No: "&DIP!$J$6) -> Title No: XXXXXXXXX | F6: Manually Adjust Row height for Multi Property | I6: Title Number | J6: XXXXXXXXX | K6: =_xlfn.TEXTJOIN(" ",TRUE,"Address:",'Multi Property Deal'!B4:D6,'Multi Property Deal'!B7:D9,'Multi Property Deal'!B10:D12,'Multi Property Deal'!B13:D15,'Multi Property Deal'!B16:D18,'Multi Property Deal'!B19:D21,'Multi Property Deal'!B22:D24,'Multi Property Deal'!B25:D27,'Multi Property Deal'!B28:D30,'Multi Property Deal'!B31:D33,'Multi Property Deal'!B34:D36,'Multi Property Deal'!B37:D39,'Multi Property Deal'!B40:D42,'Multi Property Deal'!B43:D45,'Multi Property Deal'!B46:D48,'Multi Property Deal'!B49:D51,'Multi Property Deal'!B52:D54,'Multi Property Deal'!B55:D57,'Multi Property Deal'!B58:D60,'Multi Property Deal'!B61:D63) -> Address: | M6: =_xlfn.TEXTJOIN(" ",TRUE,"Title No:",'Multi Property Deal'!F4:F6,'Multi Property Deal'!F7:F9,'Multi Property Deal'!F10:F12,'Multi Property Deal'!F13:F15,'Multi Property Deal'!F16:F18,'Multi Property Deal'!F19:F21,'Multi Property Deal'!F22:F24,'Multi Property Deal'!F25:F27,'Multi Property Deal'!F28:F30,'Multi Property Deal'!F31:F33,'Multi Property Deal'!F34:F36,'Multi Property Deal'!F37:F39,'Multi Property Deal'!F40:F42,'Multi Property Deal'!F43:F45,'Multi Property Deal'!F46:F48,'Multi Property Deal'!F49:F51,'Multi Property Deal'!F52:F54,'Multi Property Deal'!F55:F57,'Multi Property Deal'!F58:F60,'Multi Property Deal'!F61:F63) -> Title No:
A7: Current Anticipated 180-Day Market Value: | B7: ='Input Sheet'!$C$28 -> 0
A8: We Market Financial Solutions Limited (hereinafter "MFS", “we”, “us”) propose to arrange a loan facility to you on the terms, financial particulars and conditions set out below (“the Loan”). The Loan itself will be subject to the receipt of a signed Decision in Principle (this document), payment of the Admin and Valuation Fees referred to below, a signed contract, a valuation, responses to MFS enquiries, due diligence, and will be subject to the terms and conditions of a loan agreement (Loan Agreement) which shall be secured by our standard form Security and a Guarantee (both defined in The Summary below). This Decision in Principle sets out the obligations of Market Financial Solutions regarding data protection and the rights of clients, partners, affiliate, vendor, and any third-party provider in respect of their personal data under The Data Protection Act 2018 (”GDPR”). The terms of and financial particulars of the Loan are set out in The Summary below.
A9: The Summary | F9: This main section is pulled through automatically from Loan Data Tab AND ICR Main tab - suggest value changes in original tabs rather than here
A10: Borrower (“you”): | B10: =B5 -> xxxxx (Company No: XXXXXXXXX) | F10: ← Check
A11: Product Type: | B11: ="Bridging Loan " & IF('Input Sheet'!$C$13="Residential", "Residential", H11)&IF(DIP_Selection="Variable"," with floating interest rate (as defined below) "," with fixed interest rate (as defined below)") -> Bridging Loan Semi-Commercial with fixed interest rate (as defined below) | H11: Semi-Commercial | I11: <- Select Semi or Full Commercial
A12: Loan Term: | B12: =IF(DIP_Selection="Variable",'Input Sheet'!I8,'Input Sheet'!L8)&" Months" -> 12 Months | F12: ← Check | L12: 1 | M12: 4% of loan balance in yr1, 3% of loan balance in yr2. No charge thereafter.
A13: Annual Interest Rate: | B13: =IF(DIP_Selection="Variable",M13,N13) -> #VALUE! | M13: ="An annual tracker rate equal to "&TEXT(('Input Sheet'!I11-'Input Sheet'!C42)*12, "#.00%")& " + Bank of England Base Rate (BBR) which is equal to a monthly coupon of "& TEXT(('Input Sheet'!I11-'Input Sheet'!C42), "0.00%") &" + BBR. Following any change to BBR, your mortgage rate and monthly payment will be adjusted on the 1st day of the next calendar month. " -> #VALUE! | N13: ="An annual fixed rate equal to "&TEXT(('Input Sheet'!L11)*12,"#.00%")&" which is equal to a monthly coupon of " &TEXT(('Input Sheet'!L11),"0.00%") -> #VALUE!
A14: Net Loan (advanced day 1): | B14: =TEXT(IF(DIP_Selection="Variable",'Input Sheet'!I15,'Input Sheet'!L15), "£#,##0") & " (including the Broker Client Fee, as below)" -> £0 (including the Broker Client Fee, as below)
A15: Gross Loan Amount: | B15: {=_xlfn.IFS('Input Sheet'!$P$2="Fusion",DIP!I15,'Input Sheet'!$P$2="Variable",DIP!M15,'Input Sheet'!$P$2="Fixed",DIP!N15)} -> 0 | F15: ← Check | M15: =TEXT('Input Sheet'!$I$12, "£#,##0") & " (on estimated valuation of " &TEXT('Input Sheet'!$C$28, "£#,##0") & "). The Gross Loan is the total principal owed at the end of the term, and is made up of the Net Loan Amount advanced, and the following:" -> £0 (on estimated valuation of £0). The Gross Loan is the total principal owed at the end of the term, and is made up of the Net Loan Amount advanced, and the following: | N15: =TEXT('Input Sheet'!$L$12, "£#,##0") & " (on estimated valuation of " &TEXT('Input Sheet'!$C$28, "£#,##0") & "). The Gross Loan is the total principal owed at the end of the term, and is made up of the Net Loan Amount advanced, and the following:" -> £0 (on estimated valuation of £0). The Gross Loan is the total principal owed at the end of the term, and is made up of the Net Loan Amount advanced, and the following:
B16: {=_xlfn.IFS('Input Sheet'!$P$2="Fusion",DIP!I16,'Input Sheet'!$P$2="Variable",DIP!M16,'Input Sheet'!$P$2="Fixed",DIP!N16)} -> 0 | M16: ="Arrangement Fees: "&TEXT('Input Sheet'!$I$18, "£#,##0")&" (" &TEXT('Input Sheet'!$C$34, "#.00%")&" of the Gross Loan Amount)" -> Arrangement Fees: £0 (.00% of the Gross Loan Amount) | N16: ="Arrangement Fees: "&TEXT('Input Sheet'!$L$18, "£#,##0")&" (" &TEXT('Input Sheet'!$C$34, "#.00%")&" of the Gross Loan Amount)" -> Arrangement Fees: £0 (.00% of the Gross Loan Amount)
B17: {=_xlfn.IFS('Input Sheet'!$P$2="Fusion",DIP!I17,'Input Sheet'!$P$2="Variable",DIP!M17,'Input Sheet'!$P$2="Fixed",DIP!N17)} -> 0 | M17: ="Months Interest Rolled Up: "&TEXT('Input Sheet'!$I$7, "#,##0")&" month(s), equivalent to "&TEXT('Input Sheet'!$I$23, "£#,##0") -> Months Interest Rolled Up: 3 month(s), equivalent to £0 | N17: ="Months Interest Rolled Up: "&TEXT('Input Sheet'!$L$7, "#,##0")&" month(s), equivalent to "&TEXT('Input Sheet'!$L$23, "£#,##0") -> Months Interest Rolled Up: 3 month(s), equivalent to £0
A18: Serviced Monthly Payments: | B18: =IF(DIP_Selection="Variable",M18,N18) -> 9 monthly payments of £0 will start in month 4 following drawdown of the Loan (following the months of Rolled Up interest), from a valid UK bank account. *Monthly rate is rounded to 2 decimal points; however, Interest Rate is calculated on annualised rate. | F18: =IF(H18="Show","← Check","Hide") -> ← Check | G18: =IF(H18="Show","Manually Adjust Row height","Hide if Fully Rolled") -> Manually Adjust Row height | H18: =IF(AND(DIP_Selection="Variable",'Input Sheet'!I22<1),"Hide",IF(AND(DIP_Selection="Fixed",'Input Sheet'!L22<1),"Hide","Show")) -> Show | M18: =TEXT('Input Sheet'!I22, "#,##0")&" monthly payments of "&TEXT('Input Sheet'!$I$29, "£#,##0")&" will start in month "&TEXT('Input Sheet'!I7+1, "#,##0")&" following drawdown of the Loan (following the months of Rolled Up interest), from a valid UK bank account. *Monthly rate is rounded to 2 decimal points; however, Interest Rate is calculated on annualised rate. " &O18 -> 9 monthly payments of £0 will start in month 4 following drawdown of the Loan (following the months of Rolled Up interest), from a valid UK bank account. *Monthly rate is rounded to 2 decimal points; however, Interest Rate is calculated on annualised rate. Please note, the amount stated to service the interest monthly is as of today’s date & BBR. Any increase in the BBR will require the increased interest cost to be serviced from the 1st day of the next calendar month, regardless of if you are currently in a Rolled Up initial period. Any reduction in BBR will be credited back to you upon redemption. IMPORTANT: monthly payments shown in this illustration can be considerably different if a variable rate changes. For example: for every £100,000 borrowed a 0.25% increase in BBR would raise the annual cost by £250. Rates may increase by more than this, or be significantly different on the anticipated Interest Rate so make sure you can afford the monthly payment | N18: =TEXT('Input Sheet'!$L$22, "#,##0")&" monthly payments of "&TEXT('Input Sheet'!$L$29, "£#,##0")&" will start in month "&TEXT('Input Sheet'!$L$7+1, "#,##0")&" following drawdown of the Loan (following the months of Rolled Up interest), from a valid UK bank account. *Monthly rate is rounded to 2 decimal points; however, Interest Rate is calculated on annualised rate. " -> 9 monthly payments of £0 will start in month 4 following drawdown of the Loan (following the months of Rolled Up interest), from a valid UK bank account. *Monthly rate is rounded to 2 decimal points; however, Interest Rate is calculated on annualised rate. | O18: Please note, the amount stated to service the interest monthly is as of today’s date & BBR. Any increase in the BBR will require the increased interest cost to be serviced from the 1st day of the next calendar month, regardless of if you are currently in a Rolled Up initial period. Any reduction in BBR will be credited back to you upon redemption. IMPORTANT: monthly payments shown in this illustration can be considerably different if a variable rate changes. For example: for every £100,000 borrowed a 0.25% increase in BBR would raise the annual cost by £250. Rates may increase by more than this, or be significantly different on the anticipated Interest Rate so make sure you can afford the monthly payment
A19: Broker’s Commission: | B19: =TEXT(IF(DIP_Selection="Variable",'Input Sheet'!I19,'Input Sheet'!L19), "£#,##0") & " (to be deducted from the Arrangement Fee) " -> £0 (to be deducted from the Arrangement Fee) | F19: ← Check
A20: Broker Client Fee: | B20: =TEXT(IF(DIP_Selection="Variable",'Input Sheet'!$I$20,'Input Sheet'!$L$20), "£#,##0") & " (to be deducted from the Net Loan Amount)." -> £0 (to be deducted from the Net Loan Amount). | F20: Hide if no broker client fee
A21: Minimum Interest Payment: | B21: the amount of interest payable for 3 Months
A22: Commitment Fee: | B22: =M22&N22 -> A Commitment Fee (a reasonable estimate of costs for undertaking the process necessary to prepare the Loan for completion) of £0 is to be paid to us or an associated company as directed by us prior to instructing Valuers & Solicitors and is payable on acceptance of this Decision in Principle. The Commitment Fee will be refunded to you by us on completion (drawdown) of the Loan. In circumstances where the Loan is not completed for reasons such as the property failing to meet valuation, the Loan failing to meet current underwriting criteria, you failing to satisfy customer due diligence, non-disclosure by you, misrepresentation by you, or any other matter or issue which, at our discretion deems us unable to proceed with providing you the Loan, the Commitment Fee will not be refunded. | F22: ← Check | M22: ="A Commitment Fee (a reasonable estimate of costs for undertaking the process necessary to prepare the Loan for completion) of "&TEXT('Input Sheet'!C39, "£#,##0") -> A Commitment Fee (a reasonable estimate of costs for undertaking the process necessary to prepare the Loan for completion) of £0 | N22: is to be paid to us or an associated company as directed by us prior to instructing Valuers & Solicitors and is payable on acceptance of this Decision in Principle. The Commitment Fee will be refunded to you by us on completion (drawdown) of the Loan. In circumstances where the Loan is not completed for reasons such as the property failing to meet valuation, the Loan failing to meet current underwriting criteria, you failing to satisfy customer due diligence, non-disclosure by you, misrepresentation by you, or any other matter or issue which, at our discretion deems us unable to proceed with providing you the Loan, the Commitment Fee will not be refunded.
A23: Valuation Fee: | B23: =IF(('Input Sheet'!$P$2="Variable")*('Input Sheet'!I12>4000000),M23,IF(('Input Sheet'!$P$2="Fixed")*('Input Sheet'!L12>4000000),M23,N23)) -> A non-refundable Valuation Fee of TBC by the Underwriter is to be paid to us or an associated company as directed by us prior to instructing valuers. This represents the cost incurred by us for arranging the valuation. We may also instruct third party services like National Field Agency for a review of the application and fees incurred in the event of instructing any third party services will be payable by you. | F23: ← Check | H23: TBC by the Underwriter | I23: <-only the valuation amount needed | M23: ="A non-refundable Valuation Fee of "&TEXT(IF(H23="TBC by Underwriters",100,H23),"£#,##")&" is to be paid to us or an associated company as directed by us prior to instructing valuers. "&"This represents the cost incurred by us for arranging the valuation. We may also instruct third party services like National Field Agency for a review of "&"the application and fees incurred in the event of instructing any third party services will be payable by you." -> A non-refundable Valuation Fee of TBC by the Underwriter is to be paid to us or an associated company as directed by us prior to instructing valuers. This represents the cost incurred by us for arranging the valuation. We may also instruct third party services like National Field Agency for a review of the application and fees incurred in the event of instructing any third party services will be payable by you. | N23: =M23& " "&O23 -> A non-refundable Valuation Fee of TBC by the Underwriter is to be paid to us or an associated company as directed by us prior to instructing valuers. This represents the cost incurred by us for arranging the valuation. We may also instruct third party services like National Field Agency for a review of the application and fees incurred in the event of instructing any third party services will be payable by you.
A24: Legal Fees: | B24: At the Borrower’s costs, amount to be confirmed. | F24: ← £ FEE
A25: Title Insurance: | B25: =TEXT(IF(DIP_Selection="Variable",'Input Sheet'!Q13,'Input Sheet'!Q14),"£#,##0.00")&" (made up of 0.13% of the Gross Loan amount, subject to a minimum amount of £350 plus Insurance Premium Tax, currently 12% of premium). Deducted from the Net Loan Amount at completion." -> (made up of 0.13% of the Gross Loan amount, subject to a minimum amount of £350 plus Insurance Premium Tax, currently 12% of premium). Deducted from the Net Loan Amount at completion. | F25: HIDE ROW | G25: Hide row if no title insurance
A26: Security: | B26: [A first fixed and floating Debenture (including legal charge over Security Property).] [A first charge over the shares in the Borrower.] [A first legal charge of the Security Property.] [ANY OTHER SECURITY provided by [ ] | F26: <- Free text update as needed | G26: 1- Retain if Borrower is a corporate vehicle. 2- Retain if Borrower is a corporate vehicle. 3- Retain if the Borrower is an individual.
A27: Guarantee: | B27: ="A personal guarantee from "&H27&" for the repayment of the Gross Loan Amount plus all interest, default interest and costs and expenses." -> A personal guarantee from xxxxxxxxxxx for the repayment of the Gross Loan Amount plus all interest, default interest and costs and expenses. | F27: HIDE ROW | G27: Hide row if Personal application | H27: xxxxxxxxxxx | I27: <-only the shareholder name
A28: Financial Covenants: | B28: ="Loan to Value must not exceed " & TEXT(ROUNDUP(IF(DIP_Selection="Variable",'Input Sheet'!$I$13,'Input Sheet'!$L$13), 2), "0%") & "." -> Loan to Value must not exceed 0%.
A38: TERMS OF BUSINESS
A39: Defined Terms
A40: The terms defined in The Summary above are imported with the same meaning in these Terms of Business.
A41: Offer Expiry
A42: =M42 -> Please note that the terms offered are valid for only 14 days from the date of this offer. The Loan as per the terms offered within The Summary above must be drawn down on or before 21 Days from the date on which we instruct our solicitors. Failure to complete the drawdown of the Loan on or before 21 Days from the date of which we instruct our solicitors will render the loan offer expired and you will be liable to pay our costs incurred including our solicitors’ abortive legal fees and disbursements. | H42: =B4+14 -> 46003 | I42: <- DIP expiry defaults to 14 days from todays date | M42: Please note that the terms offered are valid for only 14 days from the date of this offer. The Loan as per the terms offered within The Summary above must be drawn down on or before 21 Days from the date on which we instruct our solicitors. Failure to complete the drawdown of the Loan on or before 21 Days from the date of which we instruct our solicitors will render the loan offer expired and you will be liable to pay our costs incurred including our solicitors’ abortive legal fees and disbursements.
A43: General & Privacy
A44: Market Financial Solutions Limited is arranging this transaction for the Loan to be advanced to you. The Loan has been approved in principle by us, but remains conditional upon and subject to satisfactory due diligence, valuation and enquiries to us and our solicitors. We reserve the right to vary the terms or withdraw the Loan at our discretion, should enquiries, valuation or due diligence result in material change to the application as now presented or contradict any information disclosed by you to date. If we decide to vary terms we will notify you of variations and provide our reasons for doing so. By accepting these terms and signing this Decision in Principle, you authorise Market Financial Solutions Limited and its subsidiaries to conduct due diligence checks and data handling either to assess the viability of the application or whilst the Loan is in effect, including:
A45: • ID, AML, Credit Searches including a payment profile, and KYC (Know Your Customer) fraud checks as well as other Public Information searches we deem necessary from different Credit Reference Agencies (CRAs). • Many checks and searches use or share relevant data with third-party external companies and against any specifications on any databases available with relation to your Loan or property. A record of each search carried out will be retained on your credit file initially as a soft footprint (should have no impact on your credit score) but over time and following application it may be set as a hard, or application, footprint (which could have an impact on your credit rating). • Data and your evidence documents may also be shared with any of our loan funding providers. • If the Loan is drawn, and whilst any balance of the Loan is outstanding, MFS may exchange information and documents about you (and any Loan guarantors) with CRAs, including recording any outstanding debt if you do not repay in full and on time. CRAs may share your information with other organisations. We may also make periodic searches at CRAs to help manage your account with us. The identities of the CRAs, their role also as fraud prevention agencies, the data they hold, the ways in which they use and share personal information, their data retention periods and your data protection rights with the CRAs are explained in the Credit Reference Agency Information Notice (CRAIN), www.transunion.co.uk/CRAIN. You can also get further information via our privacy policy at www.mfsuk.com/privacy-gdpr/.
A46: • The personal information we have collected from you will be shared with fraud prevention agencies who will use it to prevent fraud and money-laundering and to verify your identity. If fraud is detected, you could be refused certain services, finance, or employment. Further details of how your information will be used by us and these fraud prevention agencies, and your data protection rights, can be found via our privacy policy at www.mfsuk.com/privacy-gdpr/ or by going to www.cifas.org.uk/fpn. • You have the right to view certain records we hold concerning you and you may request that any inaccuracies are corrected by corresponding with the relevant parties. You may contact our Data Protection Officer at privacy@mfsuk.com or by writing to the Data Protection Officer, Market Financial Solutions, 46 Hertford Street, Mayfair, London, W1J 7DP.
A47: If you carried out your own credit search at www.checkmyfile.com via the MFS link, please understand Checkmyfile may charge you as per their Terms & Conditions from a set date once the free trial expires. MFS will not be held responsible for any charges that may apply as it is not our responsibility. The link was provided as a quick access for borrowers who do not have access to their own specific credit agencies. You may see full details of our privacy notice at: www.mfsuk.com/privacy-gdpr/.
A48: Loan Purpose
A49: The Loan is being provided solely for business purposes, and by signing this Decision in Principle you declare to us that the Loan is entered into by you wholly for the purposes of your business, profession or trade carried on, or intended to be carried on by you. The Loan is therefore exempt from the provisions of the Financial Services & Markets Act 2000, The Mortgage Credit Directive Order 2015, and Consumer Credit Act 1974 and you will not get the protection afforded by those Acts. You will be required to provide and sign a declaration relating to business purposes before drawdown.
A50: You confirm to us that the property has never been occupied by you or any spouse, unmarried partner, civil partner, parents, grandparents, siblings, children and grandchildren or any other related person and will not be occupied by you or any of the above-stated persons or any other related person in the future and whilst any amount of the Loan remains outstanding. You will be required to sign a declaration certificate to this effect before completion takes place. | F50: Hide if Commercial or Main residence | H50: No | I50: <-- Commercial or Main Residence?
A51: We will rely upon your declarations when completing your Loan, and such declarations will be a condition of the lending.
A52: Do not sign this Decision in Principle or any declaration unless your declarations and confirmations are true.
A53: Loan Amount and Deduction of Fees
A54: Please note that the financial particulars in The Summary are, at this stage, estimates only, and are subject to contract. These will only be varied in circumstances where our enquiries reveal information which differs from that provided on initial application or if there is reason to do so at our discretion.
A55: You authorise us (and/or to instruct our solicitors), to deduct any Arrangement Fees (which includes the Broker’s Commission as specified in The Summary), Legal Fees and expenses, Title Insurance (if applicable), any Interest (rolled up and deferred) and any other fees, costs or expenses payable by you (which have not already been paid), from the Gross Loan Amount upon completion of the Loan. | G55: =H55&I55 -> 60 | H55: ='Input Sheet'!$F$7 -> 6 | I55: ='Input Sheet'!$F$9 -> 0 | M55: ="You authorise us to deduct (and/or to instruct our solicitor), any Product Fee (which includes the Broker’s Commission as specified in The Summary), Legal Fees and expenses, "&IF('Input Sheet'!Q6="Yes","Title Insurance fee, ","")&IF(G55>0,"any Interest (months of interest rolled and deferred until loan redemption), ","")&N55 -> You authorise us to deduct (and/or to instruct our solicitor), any Product Fee (which includes the Broker’s Commission as specified in The Summary), Legal Fees and expenses, any Interest (months of interest rolled and deferred until loan redemption), and any other fees, costs, or expenses payable by you (which have not already been paid), from the Gross Loan Amount upon completion of the Loan. | N55: and any other fees, costs, or expenses payable by you (which have not already been paid), from the Gross Loan Amount upon completion of the Loan.
A56: Payments to your Broker/Intermediary
A57: =M57 -> Market Financial Solutions or its investors pay a part of the Product Fee to your Introducer/Broker as Broker’s Commission upon drawdown of the Loan, in the amount as specified in The Summary. This means that your Broker/Intermediary may be unable to provide impartial advice about the Loan to you. | F57: ← Check | H57: =IF(AND('Input Sheet'!I20>1,DIP_Selection="Variable"),"Yes",IF(AND('Input Sheet'!L20>1,DIP_Selection="Fixed"),"Yes","No")) -> No | I57: Need to update formula | M57: =IF(H57="Yes",N57,O57) -> Market Financial Solutions or its investors pay a part of the Product Fee to your Introducer/Broker as Broker’s Commission upon drawdown of the Loan, in the amount as specified in The Summary. This means that your Broker/Intermediary may be unable to provide impartial advice about the Loan to you. | N57: You authorise us to deduct the Broker Client Fee from the Net Loan Amount which is in line with your agreement with your Broker/Intermediary and payable to your Broker/Intermediary. No part of the Broker Client Fee is payable to us. In addition to any Broker Client Fee, Market Financial Solutions or its investors pay a part of the Product Fee to your Introducer/Broker as Broker’s Commission upon drawdown of the Loan, in the amount as specified in The Summary. This means that your Broker/Intermediary may be unable to provide impartial advice about the Loan to you. | O57: Market Financial Solutions or its investors pay a part of the Product Fee to your Introducer/Broker as Broker’s Commission upon drawdown of the Loan, in the amount as specified in The Summary. This means that your Broker/Intermediary may be unable to provide impartial advice about the Loan to you.
A58: Interest Rate Applied
A59: =IF(DIP_Selection="Variable",_Hlk98754409,N59) -> The standard rate of interest payable on the Gross Loan Amount will be the Interest Rate in The Summary, which is calculated as a flat percentage rate applied monthly. In accordance with the monthly Interest Rate outlined in The Summary the applicable APRC of the loan is within the letter sent to your Introducer/Broker. Please refer to them for the same. Interest that is not deducted at source on completion is to be paid to us on a monthly basis if the Loan is serviceable after the interest retention period (if any), until the Loan Term has expired, at which date the contractual balance outstanding together with any outstanding fees, costs, and expenses (including our Legal Fees for discharge) is repayable in full. Interest payments after the interest retention period (if any) must be made on or before the due date and is payable monthly in advance. In the event of a default under the terms of the Loan, interest on the Loan outstanding will accrue at the Default Rate, which is 3% per month. Further details are included in the Loan Agreement issued later in the process if the Loan is proceeding. If the Borrower cannot redeem the loan upon or before the expiry of the Loan Term, there is a provision to extend the loan facility for another 3 months which is strictly contingent upon the Borrower notifying the Lender of their request for the extension in writing at least one month before the expiry of the Loan Term and servicing the monthly interest due in the interim. If the Borrower fails to notify the Lender in writing at least one month before the expiry of the Loan Term or fails to service, the monthly interest due whilst the Gross Loan Amount is outstanding, interest on the Loan outstanding will accrue at the Default Rate, which is 3% per month. | M59: The standard rate of interest payable on the Gross Loan Amount will be the Interest Rate in The Summary, which is calculated as a flat percentage rate applied monthly. In accordance with the monthly Interest Rate outlined in The Summary the applicable APRC of the loan is within the letter sent to your Introducer/Broker. Please refer to them for the same. Interest that is not deducted at source on completion is to be paid to us on a monthly basis if the Loan is serviceable after the interest retention period (if any), until the Loan Term has expired, at which date the contractual balance outstanding together with any outstanding fees, costs and expenses (including our Legal Fees for discharge) is repayable in full. Interest payments after the interest retention period (if any) must be made on or before the due date and is payable monthly in advance. In the event of a default under the terms of the Loan, interest on the Loan outstanding will accrue at the Default Rate, which is 3% per month. Further details are included in the Loan Agreement issued later in the process if the Loan is proceeding. If the Borrower cannot redeem the loan upon or before the expiry of the Loan Term, there is a provision to extend the loan facility for another 3 months which is strictly contingent upon the Borrower notifying the Lender of their request for the extension in writing at least one month before the expiry of the Loan Term and servicing the monthly interest due in the interim. If the Borrower fails to notify the Lender in writing at least one month before the expiry of the Loan Term or fails to service the monthly interest due whilst the Gross Loan Amount is outstanding, interest on the Loan outstanding will accrue at the Default Rate, which is 3% per month. | N59: The standard rate of interest payable on the Gross Loan Amount will be the Interest Rate in The Summary, which is calculated as a flat percentage rate applied monthly. In accordance with the monthly Interest Rate outlined in The Summary the applicable APRC of the loan is within the letter sent to your Introducer/Broker. Please refer to them for the same. Interest that is not deducted at source on completion is to be paid to us on a monthly basis if the Loan is serviceable after the interest retention period (if any), until the Loan Term has expired, at which date the contractual balance outstanding together with any outstanding fees, costs, and expenses (including our Legal Fees for discharge) is repayable in full. Interest payments after the interest retention period (if any) must be made on or before the due date and is payable monthly in advance. In the event of a default under the terms of the Loan, interest on the Loan outstanding will accrue at the Default Rate, which is 3% per month. Further details are included in the Loan Agreement issued later in the process if the Loan is proceeding. If the Borrower cannot redeem the loan upon or before the expiry of the Loan Term, there is a provision to extend the loan facility for another 3 months which is strictly contingent upon the Borrower notifying the Lender of their request for the extension in writing at least one month before the expiry of the Loan Term and servicing the monthly interest due in the interim. If the Borrower fails to notify the Lender in writing at least one month before the expiry of the Loan Term or fails to service, the monthly interest due whilst the Gross Loan Amount is outstanding, interest on the Loan outstanding will accrue at the Default Rate, which is 3% per month.
A60: Term of Loan
A61: The Loan shall be for the Loan Term, which will commence from the date of drawdown of the Loan. Please note that this is an interest only Bridge Loan facility, and you must be in a position to repay the capital in full at the end of the Term. You should not assume that the Loan Term will be extended. | M61: The Loan shall be for the Loan Term, which will commence from the date of drawdown of the Loan. Please note that this is an interest only Bridge Loan facility, and you must be in a position to repay the capital in full at the end of the Term. You should not assume that the Loan Term will be extended.
A62: Valuation Fee and Legal Fees
A63: The fees for the valuation of the Property shall be your cost and will be collected in advance upon acceptance of this Decision in Principle. You will be responsible for our Legal Fees in relation to the Loan. These are set out in the Financial Summary. You will be responsible for these fees whether the Loan proceeds to completion or not. Our solicitors will require payment in full or your solicitors' undertaking to make payment before commencing work. With regards to the Valuation report, unless Title Insurance is used, once our Solicitors have conducted their Report on Title it will need to be sent to the valuer for their comments. Any detrimental impact, or adverse comments from the Valuer may result in MFS not being able to proceed with the Loan or varying the terms offered.
A64: Tariff of Charges
A65: Fee Structure Table - Post Completion | F65: Note: standard tarrif for all cases. ONLY change for a customer case with Credit Committee Approval
A66: Fee | C66: Charges from
A67: Chaps Fee | C67: =H67 -> 0 | H67: 0
A68: Data Request | C68: =H68 -> 0 | H68: 0
A69: Building Insurance | C69: =H69 -> 250 | H69: 250
A70: Expiry/Renewal of Buildings Insurance | C70: =H70 -> 500 | H70: 500
A71: Duplicate or Interim Statement (per Statement) | C71: =H71 -> 35 | H71: 35
A72: Calculating Settlement Figures for 3rd time onwards | C72: =H72 -> 55 | H72: 55
A73: Approval of Tenancy Agreement | C73: =H73 -> 0 | H73: 0
A74: Deed of Postponement (per Deed required to be executed) | C74: =H74 -> 250 | H74: 250
A75: Unpaid Ground Rent or Service Charge | C75: =H75 -> 75 | H75: 75
A76: Repayment Administration Fee (per Property being discharged) | C76: =H76 -> 475 | H76: 475
A77: Deeds Handling | C77: =H77 -> 0 | H77: 0
A78: Part Sale / Transfer of Security (per part sale/transfer) | C78: =H78 -> 250 | H78: 250
... A88: Asset Manager Fee | C88: =H88 -> 0 | H88: 0
A89: Fees Structure Table - In event of Default
A90: Fee | C90: Charges from
A91: Letters and Calls to Customers (per letter or call) | C91: =H91 -> 35 | H91: 35
A92: Letter and Calls to Third Parties (per letter or call) | C92: =H92 -> 35 | H92: 35
A93: Instruction of Collection Agents | C93: =H93 -> 100 | H93: 100
A94: Issue of Default Notice | C94: =H94 -> 70 | H94: 70
A95: Issue of Possession Proceedings | C95: =H95 -> 150 | H95: 150
A96: Court Preparation Fee (per hearing) | C96: =H96 -> 195 | H96: 195
A97: Court Hearing Fee (per hearing) | C97: =H97 -> 250 | H97: 250
A98: Issuing a Warrant for Possession | C98: =H98 -> 175 | H98: 175
A99: Borrowers Application to Suspend our Legal Action | C99: =H99 -> 155 | H99: 155
A100: Repossession of Property (per property) | C100: =H100 -> 175 | H100: 175
A101: Administration of an Account in Possession (per month) | C101: =H101 -> 250 | H101: 250
A102: Realisation of the Sale of a Repossessed Property | C102: =H102 -> 300 | H102: 300
... A106: Monthly Arrears Management Fee | C106: =H106 -> 400 | H106: 400
A107: Please see the enclosed Appendix – Schedule 1 for the explanation of each charge outlined within the Fee structure tables.
A112: Legally Binding Agreement
A113: You acknowledge and agree that we do not, and will not, provide any financial, accounting, taxation or legal advice in relation to the Loan (and this includes any advice as to the suitability of the Loan for you).
A114: You acknowledge that this Decision in Principle is an agreement for the Loan and is intended to be legally binding, and will be governed by the laws of England and Wales. This letter may be signed in counterparts and emailed scanned versions, of which the sum of the parts shall form a legally binding agreement. You will be bound by the terms of this Decision in Principle and the payment made hereunder whether or not the Loan proceeds to completion.
A115: You should seek your own independent advice in relation to this Decision in Principle.
A116: Assignment
A117: In some instances, we may arrange to assign or transfer the Loan to such entity associated with us, as we deem fit at our discretion. The Terms will not change. If we do assign the Loan you will be notified of the change of lender and be provided with contact and payment details. You may not assign the Loan or its benefit or obligations to any other party.
A118: Agency and Conflict of Interest
A119: You acknowledge that we do not act as your agent and therefore do not owe you a duty of care in this regard. When signing this Decision in Principle you expressly waive any claim you may now or in the future seek to bring. You agree to waive any claim to a conflict of interest arising out of any assignment of the Loan or the Loan itself.
A120: Indemnity
A121: You agree to indemnify and hold us harmless (including all of our employees, and assignees and their employees agents or directors, agents and directors) against all claims, losses, damages, liabilities, costs and expenses whether consequential or not, incurred or arising out of or related to any actual or threatened claim against us (or any of its employees, agents and directors and assignees etc.), brought by any guarantor or any other party to the Loan (except for instances where such liability arises through direct gross negligence or fraud) or in relation to the Loan. Please note, your solicitor must hold sufficient professional indemnity insurance to cover the Gross Loan Amount.
A122: Data Breach Notification
... A127: Data Controller: Market Financial Solutions Limited.
A128: ="Signed by each " & IF(Application_Type="Personal", "Borrower","Director/Member") -> Signed by each Director/Member | F128: ← Check
A133: Signature: ___________________________________ | C133: Signature: ______________________________
...

Sheet DIP Fusion
A1: Automatic DIP production - choose Print to Microsft PDF for a email DIP
A2: THIS IS SET TEXT THAT WILL BE PRINTED - DO NOT AMEND COLUMNS A to D | F2: Shows rows to check | G2: Applicant Type | H2: ='Input Sheet'!C12 -> 0
F3: UW TO CHECK | G3: NOTES FOR THE UNDERWRITER | H3: Overwrite - new value? | I3: Notes for overwrite | J3: Formula pull through
A4: Decision in Principle | B4: =IF(H4="",J4,H4) -> 45989 | F4: ← Check | G4: Means variable value to the left to check or amend (amends to the right) | I4: Defaults to todays date | J4: =IF(H4="",TODAY(),H4) -> 45989
A5: Proposed Loan to: | B5: =IF(H2="Personal",IF(H5="",'Input Sheet'!C8,H5),(IF(H5="",'Input Sheet'!C8,H5)&" (Company No: "&J5&")")) -> xxxxx (Company No: xxxxxxx) | F5: ← Check | I5: Company Number | J5: xxxxxxx
A6: Security Property: | B6: =IF('Input Sheet'!$C$16="Yes",$K$6,IF(H6="",'Input Sheet'!$C$9,DIP!$H$6)) -> xxxxx | D6: =IF('Input Sheet'!$C$16="Yes",$M$6,"Title No: "&$J$6) -> Title No: xxxxxxx | F6: Manually Adjust Row height for Multi Property | I6: Title Number | J6: xxxxxxx | K6: =_xlfn.TEXTJOIN(" ",TRUE,"Address",'Multi Property Deal'!B4:D6,'Multi Property Deal'!B7:D9,'Multi Property Deal'!B10:D12,'Multi Property Deal'!B13:D15,'Multi Property Deal'!B16:D18,'Multi Property Deal'!B19:D21,'Multi Property Deal'!B22:D24,'Multi Property Deal'!B25:D27,'Multi Property Deal'!B28:D30,'Multi Property Deal'!B31:D33,'Multi Property Deal'!B34:D36,'Multi Property Deal'!B37:D39,'Multi Property Deal'!B40:D42,'Multi Property Deal'!B43:D45,'Multi Property Deal'!B46:D48,'Multi Property Deal'!B49:D51,'Multi Property Deal'!B52:D54,'Multi Property Deal'!B55:D57,'Multi Property Deal'!B58:D60,'Multi Property Deal'!B61:D63) -> Address | M6: =_xlfn.TEXTJOIN(" ",TRUE,"Title No",'Multi Property Deal'!F4:F6,'Multi Property Deal'!F7:F9,'Multi Property Deal'!F10:F12,'Multi Property Deal'!F13:F15,'Multi Property Deal'!F16:F18,'Multi Property Deal'!F19:F21,'Multi Property Deal'!F22:F24,'Multi Property Deal'!F25:F27,'Multi Property Deal'!F28:F30,'Multi Property Deal'!F31:F33,'Multi Property Deal'!F34:F36,'Multi Property Deal'!F37:F39,'Multi Property Deal'!F40:F42,'Multi Property Deal'!F43:F45,'Multi Property Deal'!F46:F48,'Multi Property Deal'!F49:F51,'Multi Property Deal'!F52:F54,'Multi Property Deal'!F55:F57,'Multi Property Deal'!F58:F60,'Multi Property Deal'!F61:F63) -> Title No
A7: Current Anticipated 180-Day Market Value: | B7: ='Input Sheet'!$C$28 -> 0
A8: We Market Financial Solutions Limited (hereinafter "MFS", “we”, “us”) propose to arrange a loan facility to you on the terms, financial particulars and conditions set out below (“the Loan”). The Loan itself will be subject to the receipt of a signed Decision in Principle (this document), payment of the Admin and Valuation Fees referred to below, a signed contract, a valuation, responses to MFS enquiries, due diligence, and will be subject to the terms and conditions of a loan agreement (Loan Agreement) which shall be secured by our standard form Security and a Guarantee (both defined in The Summary below). This Decision in Principle sets out the obligations of Market Financial Solutions regarding data protection and the rights of clients, partners, affiliate, vendor, and any third-party provider in respect of their personal data under The Data Protection Act 2018 (”GDPR”). The terms of and financial particulars of the Loan are set out in The Summary below.
A9: The Summary | F9: This main section is pulled through automatically from Loan Data Tab AND ICR Main tab - suggest value changes in original tabs rather than here
A10: Borrower (“you”): | B10: =B5 -> xxxxx (Company No: xxxxxxx) | F10: ← Check
A11: Product Type: | B11: ="Bridge 'Fusion' " & IF('Input Sheet'!$C$13="Residential", "Residential", H11) -> Bridge 'Fusion' Semi-Commercial | H11: Semi-Commercial | I11: <- Select Semi or Full Commercial
A12: Loan Term: | B12: 24 months. The Loan Term may be extended by up to 12 months at the Lender’s discretion. Further details are set out below.
A13: Annual Interest Rate: | B13: ="an annual tracker rate of " &('Input Sheet'!F11-'Input Sheet'!C41)*100&"% + Bank of England Base Rate (BBR) which is equal to a monthly coupon of " &TEXT(('Input Sheet'!F11 - 'Input Sheet'!C41)/ 12, "0.00%")&" + BBR. Following any change to BBR, your mortgage rate and monthly payment will be adjusted on the 1st day of the next calendar month." -> #VALUE!
A14: Net Loan Amount (advanced day 1): | B14: =TEXT('Input Sheet'!$F$15, "£#,##0") & " (including the Broker Client Fee, as below) " -> £0 (including the Broker Client Fee, as below)
A15: Gross Loan Amount: | B15: =TEXT('Input Sheet'!$F$12, "£#,##0") & " (on estimated valuation of " &TEXT('Input Sheet'!$C$27, "£#,##0") & "). LTV must be maintained throughout the life of the Loan. An increase in Bank of England Base Rate (BBR) will result in an increased interest payment to maintain the initial LTV." -> £0 (on estimated valuation of £0). LTV must be maintained throughout the life of the Loan. An increase in Bank of England Base Rate (BBR) will result in an increased interest payment to maintain the initial LTV. | F15: ← Check
A16: Arrangement Fees: | B16: =TEXT('Input Sheet'!$F$18, "£#,##0") & " ("&TEXT('Input Sheet'!C34, "#.00%")& " of the Gross Loan Amount)" -> £0 (.00% of the Gross Loan Amount)
A17: Months Interest Rolled Up: | B17: ='Input Sheet'!$F$7& " month(s), equivalent to " &TEXT('Input Sheet'!$F$23, "£#,##0") -> 6 month(s), equivalent to £0
A18: Deferred Interest & Pay Rate: | B18: =TEXT('Input Sheet'!$F$9, "0.00%")&" deferred, equivalent to "&TEXT('Input Sheet'!$F$24,"£#,##0")&" over 24 months. Pay Rate now "&TEXT('Input Sheet'!F11-'Input Sheet'!$F$9, "0.00%")&" for 24 months" -> #VALUE! | F18: =IF('Input Sheet'!F9<0.00001,"HIDE ROW","") -> HIDE ROW | G18: Hide row if no deffered interest
A19: Serviced Monthly Payments: | B19: ='Input Sheet'!F22&" monthly payments of "&TEXT('Input Sheet'!$F$29, "£#,##0") & " will start in month "&'Input Sheet'!$F$7+1&" following drawdown of the Loan (following the months of Rolled Up interest), from a valid UK bank account. "&'DIP Fusion'!M19 -> 18 monthly payments of £0 will start in month 7 following drawdown of the Loan (following the months of Rolled Up interest), from a valid UK bank account. *Monthly rate is rounded to 2 decimal points; however, Interest Rate is calculated on annualised rate. Please note, the amount stated to service the interest monthly is as of today’s date & BBR. Any increase in the BBR will require the increased interest cost to be serviced from the 1st day of the next calendar month, regardless of if you are currently in a Rolled Up initial period. Any reduction in BBR will be credited back to you upon redemption. IMPORTANT: monthly payments shown in this illustration can be considerably different if a variable rate changes. For example: for every £100,000 borrowed a 0.25% increase in BBR would raise the annual cost by £250. Rates may increase by more than this, or be significantly different on the anticipated Interest Rate so make sure you can afford the monthly payment | M19: *Monthly rate is rounded to 2 decimal points; however, Interest Rate is calculated on annualised rate. Please note, the amount stated to service the interest monthly is as of today’s date & BBR. Any increase in the BBR will require the increased interest cost to be serviced from the 1st day of the next calendar month, regardless of if you are currently in a Rolled Up initial period. Any reduction in BBR will be credited back to you upon redemption. IMPORTANT: monthly payments shown in this illustration can be considerably different if a variable rate changes. For example: for every £100,000 borrowed a 0.25% increase in BBR would raise the annual cost by £250. Rates may increase by more than this, or be significantly different on the anticipated Interest Rate so make sure you can afford the monthly payment
A20: Minimum Interest Period: | B20: 6 Months from the date of completion
A21: Minimum Interest Period Fee: | B21: If any part of the Loan is prepaid during the Minimum Interest Period, the Borrower will pay the Lender an aggregate amount equal to: 1- the Annual Interest Rate that would have been payable on the amount prepaid from the date of prepayment and up to and including the date falling 6 months after completion; and 2- 3.0% on the amount repaid. | F21: ← Check
A22: Broker’s Commission: | B22: =TEXT('Input Sheet'!$F$19, "£#,##0") &" (to be deducted from the Arrangement Fee) " -> £0 (to be deducted from the Arrangement Fee) | F22: ← Check
A23: Broker Client Fee: | B23: =TEXT('Input Sheet'!$F$20, "£#,##") &" (to be deducted from the Net Loan Amount)." -> £ (to be deducted from the Net Loan Amount). | F23: Hide if no broker client fee
A24: Early Repayment Charge (ERC): | B24: 1. Any time during the Minimum Interest Period: 3.0% of the amount repaid plus any interest that would have been payable on the amount repaid from the date of repayment up to and including the final day of the Minimum Interest Period. 2. Following the Minimum Interest Period and subject to the ERC Threshold: a. 3.0% of the amount repaid during the first 12 months of the Loan Term; b. 1.5% of the amount repaid months 13 to 21 of the Loan Term; and c. no ERC thereafter.
A25: ERC Threshold: | B25: Following the Minimum Interest Period until month 21, the Borrower can prepay an aggregate amount of up to 25% of the Gross Loan Amount without any charge.
A26: Commitment Fee: | B26: ="A Commitment Fee (a reasonable estimate of costs for undertaking the process necessary to prepare the Loan for completion) of " &TEXT('Input Sheet'!$C$39, "£#,##0")&'DIP Fusion'!N26 -> A Commitment Fee (a reasonable estimate of costs for undertaking the process necessary to prepare the Loan for completion) of £0 is to be paid to us or an associated company as directed by us prior to instructing Valuers & Solicitors and is payable on acceptance of this Decision in Principle. The Commitment Fee will be refunded to you by us on completion (drawdown) of the Loan. In circumstances where the Loan is not completed for reasons such as the property failing to meet valuation, the Loan failing to meet current underwriting criteria, you failing to satisfy customer due diligence, non-disclosure by you, misrepresentation by you, or any other matter or issue which, at our discretion deems us unable to proceed with providing you the Loan, the Commitment Fee will not be refunded. | F26: ← Check | N26: is to be paid to us or an associated company as directed by us prior to instructing Valuers & Solicitors and is payable on acceptance of this Decision in Principle. The Commitment Fee will be refunded to you by us on completion (drawdown) of the Loan. In circumstances where the Loan is not completed for reasons such as the property failing to meet valuation, the Loan failing to meet current underwriting criteria, you failing to satisfy customer due diligence, non-disclosure by you, misrepresentation by you, or any other matter or issue which, at our discretion deems us unable to proceed with providing you the Loan, the Commitment Fee will not be refunded.
A27: Valuation Fee: | B27: =IF('Input Sheet'!F12<=4000000,N27,M27) -> A non-refundable Valuation Fee of TBC by the Underwriter is to be paid to us or an associated company as directed by us prior to instructing valuers. This represents the cost incurred by us for arranging the valuation. We may also instruct third party services like National Field Agency for a review of the application and fees incurred in the event of instructing any third party services will be payable by you. | F27: ← Check | H27: TBC by the Underwriter | I27: <-only the valuation amount needed | M27: ="A non-refundable Valuation Fee of "&TEXT(IF(H27="TBC by Underwriters",100,H27),"£#,##")&" is to be paid to us or an associated company as directed by us prior to instructing valuers. "&"This represents the cost incurred by us for arranging the valuation. We may also instruct third party services like National Field Agency for a review of "&"the application and fees incurred in the event of instructing any third party services will be payable by you." -> A non-refundable Valuation Fee of TBC by the Underwriter is to be paid to us or an associated company as directed by us prior to instructing valuers. This represents the cost incurred by us for arranging the valuation. We may also instruct third party services like National Field Agency for a review of the application and fees incurred in the event of instructing any third party services will be payable by you. | N27: =M27& " "&O27 -> A non-refundable Valuation Fee of TBC by the Underwriter is to be paid to us or an associated company as directed by us prior to instructing valuers. This represents the cost incurred by us for arranging the valuation. We may also instruct third party services like National Field Agency for a review of the application and fees incurred in the event of instructing any third party services will be payable by you.
A28: Legal Fees: | B28: At the Borrower’s costs, amount to be confirmed.
A29: Title Insurance: | B29: =TEXT('Input Sheet'!$Q$12,"£#,##0.00")&" (made up of 0.13% of the Gross Loan amount, subject to a minimum amount of £350 plus Insurance Premium Tax, currently 12% of premium). Deducted from the Net Loan Amount at completion." -> (made up of 0.13% of the Gross Loan amount, subject to a minimum amount of £350 plus Insurance Premium Tax, currently 12% of premium). Deducted from the Net Loan Amount at completion. | F29: =IF('Input Sheet'!$Q$12="","HIDE ROW","") -> HIDE ROW | G29: Hide row if no title insurance (e.g. purchase)
A30: Security: | B30: [A first fixed and floating Debenture (including legal charge over Security Property).] [A first charge over the shares in the Borrower.] [A first legal charge of the Security Property.] [ANY OTHER SECURITY provided by [ ] | F30: <- Free text update as needed | G30: 1- Retain if Borrower is a corporate vehicle. 2- Retain if Borrower is a corporate vehicle. 3- Retain if the Borrower is an individual.
A31: Guarantee: | B31: ="a personal guarantee from "&H31&" for the repayment of the Gross Loan Amount plus all interest, default interest and costs and expenses." -> a personal guarantee from xxxxxxxxxxx for the repayment of the Gross Loan Amount plus all interest, default interest and costs and expenses. | F31: HIDE ROW | G31: Hide row if Personal application | H31: xxxxxxxxxxx | I31: <-only the shareholder name
A32: Financial Covenants: | B32: ="Loan to Value must not exceed " & TEXT(ROUNDUP('Input Sheet'!$F$13, 2), "0%") & "." -> Loan to Value must not exceed 0%.
B33: Interest Cover (received passing rental as a percentage of finance costs) to be at least 110% at all times.
H34: £199 | I34: <-only the admin fee amount needed | M34: ="A non-refundable fee of "&TEXT(IF(H34="TBC by Underwriters",199,H34),"£#,##")&" per property payable to MFS along with the Valuation Fee. " -> A non-refundable fee of £199 per property payable to MFS along with the Valuation Fee.
H35: TBC by the Underwriter | I35: <-only the valuation amount needed | M35: ="A non-refundable Valuation Fee of "&TEXT(IF(H35="TBC by Underwriters",100,H35),"£#,##")&" is to be paid to us or an associated company as directed by us prior to instructing valuers. "&"This represents the cost incurred by us for arranging the valuation. We may also instruct third party services like National Field Agency for a review of "&"the application and fees incurred in the event of instructing any third party services will be payable by you." -> A non-refundable Valuation Fee of TBC by the Underwriter is to be paid to us or an associated company as directed by us prior to instructing valuers. This represents the cost incurred by us for arranging the valuation. We may also instruct third party services like National Field Agency for a review of the application and fees incurred in the event of instructing any third party services will be payable by you.
H36: TBC by the Underwriter | I36: <- legal fees and any clause | M36: =TEXT(H36, "£#,##0") & ", to be payable by you." -> TBC by the Underwriter, to be payable by you.
M38: A first legal charge over the Security Property.
H39: xxxxxxxxxxx
A40: TERMS OF BUSINESS
A41: Defined Terms
A42: The terms defined in The Summary above are imported with the same meaning in these Terms of Business.
A43: Offer Expiry
A44: =M44 -> Please note that the terms offered are valid for only 14 days from the date of this offer. The Loan as per the terms offered within The Summary above must be drawn down on or before 21 Days from the date on which we instruct our solicitors. Failure to complete the drawdown of the Loan on or before 21 Days from the date of which we instruct our solicitors will render the loan offer expired and you will be liable to pay our costs incurred including our solicitors’ abortive legal fees and disbursements. | F44: ← Check Date | H44: =B4+14 -> 46003 | I44: <-- DIP expiry defaults to 14 days from todays date | M44: Please note that the terms offered are valid for only 14 days from the date of this offer. The Loan as per the terms offered within The Summary above must be drawn down on or before 21 Days from the date on which we instruct our solicitors. Failure to complete the drawdown of the Loan on or before 21 Days from the date of which we instruct our solicitors will render the loan offer expired and you will be liable to pay our costs incurred including our solicitors’ abortive legal fees and disbursements.
A45: General & Privacy
A46: Market Financial Solutions Limited is arranging this transaction for the Loan to be advanced to you. The Loan has been approved in principle by us, but remains conditional upon and subject to satisfactory due diligence, valuation and enquiries to us and our solicitors. We reserve the right to vary the terms or withdraw the Loan at our discretion, should enquiries, valuation or due diligence result in material change to the application as now presented or contradict any information disclosed by you to date. If we decide to vary terms we will notify you of variations and provide our reasons for doing so. By accepting these terms and signing this Decision in Principle, you authorise Market Financial Solutions Limited and its subsidiaries to conduct due diligence checks and data handling either to assess the viability of the application or whilst the Loan is in effect, including:
A47: • ID, AML, Credit Searches including a payment profile, and KYC (Know Your Customer) fraud checks as well as other Public Information searches we deem necessary from different Credit Reference Agencies (CRAs). • Many checks and searches use or share relevant data with third-party external companies and against any specifications on any databases available with relation to your Loan or property. A record of each search carried out will be retained on your credit file initially as a soft footprint (should have no impact on your credit score) but over time and following application it may be set as a hard, or application, footprint (which could have an impact on your credit rating). • Data and your evidence documents may also be shared with any of our loan funding providers. • If the Loan is drawn, and whilst any balance of the Loan is outstanding, MFS may exchange information and documents about you (and any Loan guarantors) with CRAs, including recording any outstanding debt if you do not repay in full and on time. CRAs may share your information with other organisations. We may also make periodic searches at CRAs to help manage your account with us. The identities of the CRAs, their role also as fraud prevention agencies, the data they hold, the ways in which they use and share personal information, their data retention periods and your data protection rights with the CRAs are explained in the Credit Reference Agency Information Notice (CRAIN), www.transunion.co.uk/CRAIN. You can also get further information via our privacy policy at www.mfsuk.com/privacy-gdpr/.
A48: • The personal information we have collected from you will be shared with fraud prevention agencies who will use it to prevent fraud and money-laundering and to verify your identity. If fraud is detected, you could be refused certain services, finance, or employment. Further details of how your information will be used by us and these fraud prevention agencies, and your data protection rights, can be found via our privacy policy at www.mfsuk.com/privacy-gdpr/ or by going to www.cifas.org.uk/fpn. • You have the right to view certain records we hold concerning you and you may request that any inaccuracies are corrected by corresponding with the relevant parties. You may contact our Data Protection Officer at privacy@mfsuk.com or by writing to the Data Protection Officer, Market Financial Solutions, 46 Hertford Street, Mayfair, London, W1J 7DP.
A49: If you carried out your own credit search at www.checkmyfile.com via the MFS link, please understand Checkmyfile may charge you as per their Terms & Conditions from a set date once the free trial expires. MFS will not be held responsible for any charges that may apply as it is not our responsibility. The link was provided as a quick access for borrowers who do not have access to their own specific credit agencies. You may see full details of our privacy notice at: www.mfsuk.com/privacy-gdpr/.
A50: Loan Purpose
A51: The Loan is being provided solely for business purposes, and by signing this Decision in Principle you declare to us that the Loan is entered into by you wholly for the purposes of your business, profession or trade carried on, or intended to be carried on by you. The Loan is therefore exempt from the provisions of the Financial Services & Markets Act 2000, The Mortgage Credit Directive Order 2015, and Consumer Credit Act 1974 and you will not get the protection afforded by those Acts. You will be required to provide and sign a declaration relating to business purposes before drawdown.
A52: You confirm to us that the property has never been occupied by you or any spouse, unmarried partner, civil partner, parents, grandparents, siblings, children and grandchildren or any other related person and will not be occupied by you or any of the above-stated persons or any other related person in the future and whilst any amount of the Loan remains outstanding. You will be required to sign a declaration certificate to this effect before completion takes place. | F52: Hide if Commercial or Main residence | H52: No | I52: <-- Commercial or Main Residence?
A53: We will rely upon your declarations when completing your Loan, and such declarations will be a condition of the lending.
A54: Do not sign this Decision in Principle or any declaration unless the above paragraphs are true.
A55: Loan Amount and Deduction of Fees
A56: Please note that the financial particulars in The Summary are, at this stage, estimates only, and are subject to contract. These will only be varied in circumstances where our enquiries reveal information which differs from that provided on initial application or if there is reason to do so at our discretion.
A57: You authorise us (and/or to instruct our solicitors), to deduct any Arrangement Fees (which includes the Broker’s Commission as specified in The Summary), Legal Fees and expenses, any Rolled Up and Deferred Interest and any other fees, costs or expenses payable by you (which have not already been paid), from the Gross Loan Amount upon completion of the Loan. | G57: =H57&I57 -> 60 | H57: ='Input Sheet'!$F$7 -> 6 | I57: ='Input Sheet'!$F$9 -> 0 | M57: ="You authorise us to deduct (and/or to instruct our solicitor), any Product Fee (which includes the Broker’s Commission as specified in The Summary), Legal Fees and expenses, "&IF('Input Sheet'!Q6="Yes","Title Insurance fee, ","")&IF(G57>0,"any Interest (months of interest rolled and deferred until loan redemption), ","")&N57 -> You authorise us to deduct (and/or to instruct our solicitor), any Product Fee (which includes the Broker’s Commission as specified in The Summary), Legal Fees and expenses, any Interest (months of interest rolled and deferred until loan redemption), and any other fees, costs, or expenses payable by you (which have not already been paid), from the Gross Loan Amount upon completion of the Loan. | N57: and any other fees, costs, or expenses payable by you (which have not already been paid), from the Gross Loan Amount upon completion of the Loan.
A58: Payments to your Broker/Intermediary
A59: =M59 -> Market Financial Solutions or its investors pay a part of the Product Fee to your Introducer/Broker as Broker’s Commission upon drawdown of the Loan, in the amount as specified in The Summary. This means that your Broker/Intermediary may be unable to provide impartial advice about the Loan to you. | F59: ← Check | H59: =IF('Input Sheet'!F20>1, "Yes","No") -> No | M59: =IF(H59="Yes",N59,O59) -> Market Financial Solutions or its investors pay a part of the Product Fee to your Introducer/Broker as Broker’s Commission upon drawdown of the Loan, in the amount as specified in The Summary. This means that your Broker/Intermediary may be unable to provide impartial advice about the Loan to you. | N59: You authorise us to deduct the Broker Client Fee from the Net Loan Amount which is in line with your agreement with your Broker/Intermediary and payable to your Broker/Intermediary. No part of the Broker Client Fee is payable to us. In addition to any Broker Client Fee, Market Financial Solutions or its investors pay a part of the Product Fee to your Introducer/Broker as Broker’s Commission upon drawdown of the Loan, in the amount as specified in The Summary. This means that your Broker/Intermediary may be unable to provide impartial advice about the Loan to you. | O59: Market Financial Solutions or its investors pay a part of the Product Fee to your Introducer/Broker as Broker’s Commission upon drawdown of the Loan, in the amount as specified in The Summary. This means that your Broker/Intermediary may be unable to provide impartial advice about the Loan to you.
A60: Interest Rate Applied
A61: The standard rate of interest payable on the Gross Loan Amount will be the Interest Rate in The Summary, which is calculated as a flat percentage rate applied monthly. In accordance with the Interest Rate outlined in The Summary the applicable APRC of the loan is within the letter sent to your Introducer/Broker. Please refer to them for the same. Interest that is not deducted at source on completion is to be paid to us monthly until the Loan Term has expired, at which date the contractual balance outstanding together with any outstanding fees, costs and expenses (including our legal fees for discharge) is repayable in full. Interest payments after the interest retention period must be made on or before the due date and is payable monthly in advance. In the event of a default under the terms of the Loan, interest on the Loan outstanding will accrue at the Default Rate, which is 3% per month. Further details are included in the Loan Agreement issued later in the process if the Loan is proceeding. If the Borrower cannot redeem the loan upon or before the expiry of the Loan Term, they can request an extension no later than 4 weeks before the loan term expiry. The Lender may in its absolute discretion extend the Loan Term by up to 12 months. Any extension will be subject to ‘fit and proper’ covenant test (e.g. involving income, valuation, payment profile checks and any other checks the Lender deems necessary) and the payment by the Borrower to the Lender of an amount equal to 1% of the outstanding principal balance at the point of extension. If the Borrower fails to notify the Lender in writing at least one month before the expiry of the Loan Term or fails to service, the monthly interest due whilst the Gross Loan Amount is outstanding the interest rate will increase to 3% and be applicable on the total amount outstanding
A62: Term of Loan
A63: The Loan shall be for the Loan Term, which will commence from the date of drawdown of the Loan. Please note that this is an interest only Bridge Loan facility, and you must be in a position to repay the capital in full at the end of the Term. You should not assume that the Loan Term will be extended. | M63: The Loan shall be for the Loan Term, which will commence from the date of drawdown of the Loan. Please note that this is an interest only Bridge Loan facility, and you must be in a position to repay the capital in full at the end of the Term. You should not assume that the Loan Term will be extended.
A64: Valuation Fee and Legal Fees
A65: The fees for the valuation of the Property shall be your cost and will be collected in advance upon acceptance of this Decision in Principle. You will be responsible for our Legal Fees in relation to the Loan. These are set out in the Financial Summary. You will be responsible for these fees whether the Loan proceeds to completion or not. Our solicitors will require payment in full or your solicitors' undertaking to make payment before commencing work. With regards to the Valuation report, unless Title Insurance is used, once our Solicitors have conducted their Report on Title it will need to be sent to the valuer for their comments. Any detrimental impact, or adverse comments from the Valuer may result in MFS not being able to proceed with the Loan or varying the terms offered.
A66: Tariff of Charges
A67: Fee Structure Table - Post Completion | F67: Note: standard tarrif for all cases. ONLY change for a customer case with Credit Committee Approval
A68: Fee | C68: Charges from
A69: Chaps Fee | C69: =H69 -> 0 | H69: 0
A70: Data Request | C70: =H70 -> 0 | H70: 0
A71: Building Insurance | C71: =H71 -> 250 | H71: 250
A72: Expiry/Renewal of Buildings Insurance | C72: =H72 -> 500 | H72: 500
A73: Duplicate or Interim Statement (per Statement) | C73: =H73 -> 35 | H73: 35
A74: Calculating Settlement Figures for 3rd time onwards | C74: =H74 -> 55 | H74: 55
A75: Approval of Tenancy Agreement | C75: =H75 -> 0 | H75: 0
A76: Deed of Postponement (per Deed required to be executed) | C76: =H76 -> 250 | H76: 250
A77: Unpaid Ground Rent or Service Charge | C77: =H77 -> 75 | H77: 75
A78: Repayment Administration Fee (per Property being discharged) | C78: =H78 -> 475 | H78: 475
A79: Deeds Handling | C79: =H79 -> 0 | H79: 0
A80: Part Sale / Transfer of Security (per part sale/transfer) | C80: =H80 -> 250 | H80: 250
... A90: Asset Manager Fee | C90: =H90 -> 0 | H90: 0
A91: Fees Structure Table - In event of Default
A92: Fee | C92: Charges from
A93: Letters and Calls to Customers (per letter or call) | C93: =H93 -> 35 | H93: 35
A94: Letter and Calls to Third Parties (per letter or call) | C94: =H94 -> 35 | H94: 35
A95: Instruction of Collection Agents | C95: =H95 -> 100 | H95: 100
A96: Issue of Default Notice | C96: =H96 -> 70 | H96: 70
A97: Issue of Possession Proceedings | C97: =H97 -> 150 | H97: 150
A98: Court Preparation Fee (per hearing) | C98: =H98 -> 195 | H98: 195
A99: Court Hearing Fee (per hearing) | C99: =H99 -> 250 | H99: 250
A100: Issuing a Warrant for Possession | C100: =H100 -> 175 | H100: 175
A101: Borrowers Application to Suspend our Legal Action | C101: =H101 -> 155 | H101: 155
A102: Repossession of Property (per property) | C102: =H102 -> 175 | H102: 175
A103: Administration of an Account in Possession (per month) | C103: =H103 -> 250 | H103: 250
A104: Realisation of the Sale of a Repossessed Property | C104: =H104 -> 300 | H104: 300
... A108: Monthly Arrears Management Fee | C108: =H108 -> 400 | H108: 400
A109: Please see the enclosed Appendix – Schedule 1 for the explanation of each charge outlined within the Fee structure tables.
A110: Legally Binding Agreement
A111: You acknowledge and agree that we do not, and will not, provide any financial, accounting, taxation or legal advice in relation to the Loan (and this includes any advice as to the suitability of the Loan for you).
A112: You acknowledge that this Decision in Principle is an agreement for the Loan and is intended to be legally binding, and will be governed by the laws of England and Wales. This letter may be signed in counterparts and emailed scanned versions, of which the sum of the parts shall form a legally binding agreement. You will be bound by the terms of this Decision in Principle and the payment made hereunder whether or not the Loan proceeds to completion.
A113: You should seek your own independent advice in relation to this Decision in Principle.
...

Sheet Multi Property Deal
XEI1: Yes | XEJ1: No | XEK1: Please Choose
L2: Property Value
B3: Property Address | E3: Postcode | F3: Title Number | G3: Proprietor | H3: Age | I3: Nationality | J3: Property type | K3: Purchase Date | L3: Purchase Price | M3: Client (Mandatory) | N3: Actual | O3: Actual Vs Client | P3: Our Charge | Q3: Existing Charge | R3: Existing Outstanding | S3: Current LTV | T3: Current lender | W3: Current LTV | X3: To be Discharged | AD3: =SUM(AB4:AB61) -> 0
O4: =M4-N4 -> 0 | S4: =IFERROR((R4+R6+R5)/N4,0) -> 0 | U4: 0.7 | V4: =U4/$O$64*O4 -> #DIV/0! | W4: =IFERROR((R4+R6+R5)/O4,0) -> 0 | X4: =IF(P4="1st","Yes",IF(R4>0,"No","")) | AB4: =IFERROR(AC4*AD4,0) -> 0 | AC4: =O4/$O$64 -> #DIV/0! | AD4: =IF(O4>0,IF(P4="1st",1,IF(P4="2nd",2,IF(P4="AN1",2,""))),"")
X5: =IF(P5="1st","Yes",IF(R5>0,"No",""))
X6: =IF(P6="1st","Yes",IF(R6>0,"No",""))
O7: =M7-N7 -> 0 | S7: =IFERROR((R7+R9+R8)/N7,0) -> 0 | U7: 0.7 | V7: =U7/$O$64*O7 -> #DIV/0! | W7: =IFERROR((R7+R9+R8)/O7,0) -> 0 | X7: =IF(P7="1st","Yes",IF(R7>0,"No","")) | AB7: =IFERROR(AC7*AD7,0) -> 0 | AC7: =O7/$O$64 -> #DIV/0! | AD7: =IF(O7>0,IF(P7="1st",1,IF(P7="2nd",2,IF(P7="AN1",2,""))),"")
X8: =IF(P8="1st","Yes",IF(R8>0,"No",""))
X9: =IF(P9="1st","Yes",IF(R9>0,"No",""))
O10: =M10-N10 -> 0 | S10: =IFERROR((R10+R12+R11)/N10,0) -> 0 | U10: 0.7 | V10: =U10/$O$64*O10 -> #DIV/0! | W10: =IFERROR((R10+R12+R11)/O10,0) -> 0 | X10: =IF(P10="1st","Yes",IF(R10>0,"No","")) | AB10: =IFERROR(AC10*AD10,0) -> 0 | AC10: =O10/$O$64 -> #DIV/0! | AD10: =IF(O10>0,IF(P10="1st",1,IF(P10="2nd",2,IF(P10="AN1",2,""))),"")
X11: =IF(P11="1st","Yes",IF(R11>0,"No",""))
X12: =IF(P12="1st","Yes",IF(R12>0,"No",""))
O13: =M13-N13 -> 0 | S13: =IFERROR((R13+R15+R14)/N13,0) -> 0 | U13: 0.7 | V13: =U13/$O$64*O13 -> #DIV/0! | W13: =IFERROR((R13+R15+R14)/O13,0) -> 0 | X13: =IF(P13="1st","Yes",IF(R13>0,"No","")) | AB13: =IFERROR(AC13*AD13,0) -> 0 | AC13: =O13/$O$64 -> #DIV/0! | AD13: =IF(O13>0,IF(P13="1st",1,IF(P13="2nd",2,IF(P13="AN1",2,""))),"")
X14: =IF(P14="1st","Yes",IF(R14>0,"No",""))
X15: =IF(P15="1st","Yes",IF(R15>0,"No",""))
O16: =M16-N16 -> 0 | S16: =IFERROR((R16+R18+R17)/N16,0) -> 0 | U16: 0.7 | V16: =U16/$O$64*O16 -> #DIV/0! | W16: =IFERROR((R16+R18+R17)/O16,0) -> 0 | X16: =IF(P16="1st","Yes",IF(R16>0,"No","")) | AB16: =IFERROR(AC16*AD16,0) -> 0 | AC16: =O16/$O$64 -> #DIV/0! | AD16: =IF(O16>0,IF(P16="1st",1,IF(P16="2nd",2,IF(P16="AN1",2,""))),"")
X17: =IF(P17="1st","Yes",IF(R17>0,"No",""))
X18: =IF(P18="1st","Yes",IF(R18>0,"No",""))
O19: =M19-N19 -> 0 | S19: =IFERROR((R19+R21+R20)/N19,0) -> 0 | U19: 0.7 | V19: =U19/$O$64*O19 -> #DIV/0! | W19: =IFERROR((R19+R21+R20)/O19,0) -> 0 | X19: =IF(P19="1st","Yes",IF(R19>0,"No","")) | AB19: =IFERROR(AC19*AD19,0) -> 0 | AC19: =O19/$O$64 -> #DIV/0! | AD19: =IF(O19>0,IF(P19="1st",1,IF(P19="2nd",2,IF(P19="AN1",2,""))),"")
X20: =IF(P20="1st","Yes",IF(R20>0,"No",""))
X21: =IF(P21="1st","Yes",IF(R21>0,"No",""))
O22: =M22-N22 -> 0 | S22: =IFERROR((R22+R24+R23)/N22,0) -> 0 | U22: 0.7 | V22: =U22/$O$64*O22 -> #DIV/0! | W22: =IFERROR((R22+R24+R23)/O22,0) -> 0 | X22: =IF(P22="1st","Yes",IF(R22>0,"No","")) | AB22: =IFERROR(AC22*AD22,0) -> 0 | AC22: =O22/$O$64 -> #DIV/0! | AD22: =IF(O22>0,IF(P22="1st",1,IF(P22="2nd",2,IF(P22="AN1",2,""))),"")
X23: =IF(P23="1st","Yes",IF(R23>0,"No",""))
X24: =IF(P24="1st","Yes",IF(R24>0,"No",""))
O25: =M25-N25 -> 0 | S25: =IFERROR((R25+R27+R26)/N25,0) -> 0 | U25: 0.7 | V25: =U25/$O$64*O25 -> #DIV/0! | W25: =IFERROR((R25+R27+R26)/O25,0) -> 0 | X25: =IF(P25="1st","Yes",IF(R25>0,"No","")) | AB25: =IFERROR(AC25*AD25,0) -> 0 | AC25: =O25/$O$64 -> #DIV/0! | AD25: =IF(O25>0,IF(P25="1st",1,IF(P25="2nd",2,IF(P25="AN1",2,""))),"")
X26: =IF(P26="1st","Yes",IF(R26>0,"No",""))
X27: =IF(P27="1st","Yes",IF(R27>0,"No",""))
O28: =M28-N28 -> 0 | S28: =IFERROR((R28+R30+R29)/N28,0) -> 0 | U28: 0.7 | V28: =U28/$O$64*O28 -> #DIV/0! | W28: =IFERROR((R28+R30+R29)/O28,0) -> 0 | X28: =IF(P28="1st","Yes",IF(R28>0,"No","")) | AB28: =IFERROR(AC28*AD28,0) -> 0 | AC28: =O28/$O$64 -> #DIV/0! | AD28: =IF(O28>0,IF(P28="1st",1,IF(P28="2nd",2,IF(P28="AN1",2,""))),"")
X29: =IF(P29="1st","Yes",IF(R29>0,"No",""))
X30: =IF(P30="1st","Yes",IF(R30>0,"No",""))
O31: =M31-N31 -> 0 | S31: =IFERROR((R31+R33+R32)/N31,0) -> 0 | U31: 0.7 | V31: =U31/$O$64*O31 -> #DIV/0! | W31: =IFERROR((R31+R33+R32)/O31,0) -> 0 | X31: =IF(P31="1st","Yes",IF(R31>0,"No","")) | AB31: =IFERROR(AC31*AD31,0) -> 0 | AC31: =O31/$O$64 -> #DIV/0! | AD31: =IF(O31>0,IF(P31="1st",1,IF(P31="2nd",2,IF(P31="AN1",2,""))),"")
X32: =IF(P32="1st","Yes",IF(R32>0,"No",""))
X33: =IF(P33="1st","Yes",IF(R33>0,"No",""))
O34: =M34-N34 -> 0 | S34: =IFERROR((R34+R36+R35)/N34,0) -> 0 | U34: 0.7 | V34: =U34/$O$64*O34 -> #DIV/0! | W34: =IFERROR((R34+R36+R35)/O34,0) -> 0 | X34: =IF(P34="1st","Yes",IF(R34>0,"No","")) | AB34: =IFERROR(AC34*AD34,0) -> 0 | AC34: =O34/$O$64 -> #DIV/0! | AD34: =IF(O34>0,IF(P34="1st",1,IF(P34="2nd",2,IF(P34="AN1",2,""))),"")
X35: =IF(P35="1st","Yes",IF(R35>0,"No",""))
X36: =IF(P36="1st","Yes",IF(R36>0,"No",""))
O37: =M37-N37 -> 0 | S37: =IFERROR((R37+R39+R38)/N37,0) -> 0 | U37: 0.7 | V37: =U37/$O$64*O37 -> #DIV/0! | W37: =IFERROR((R37+R39+R38)/O37,0) -> 0 | X37: =IF(P37="1st","Yes",IF(R37>0,"No","")) | AB37: =IFERROR(AC37*AD37,0) -> 0 | AC37: =O37/$O$64 -> #DIV/0! | AD37: =IF(O37>0,IF(P37="1st",1,IF(P37="2nd",2,IF(P37="AN1",2,""))),"")
X38: =IF(P38="1st","Yes",IF(R38>0,"No",""))
X39: =IF(P39="1st","Yes",IF(R39>0,"No",""))
O40: =M40-N40 -> 0 | S40: =IFERROR((R40+R42+R41)/N40,0) -> 0 | U40: 0.7 | V40: =U40/$O$64*O40 -> #DIV/0! | W40: =IFERROR((R40+R42+R41)/O40,0) -> 0 | X40: =IF(P40="1st","Yes",IF(R40>0,"No","")) | AB40: =IFERROR(AC40*AD40,0) -> 0 | AC40: =O40/$O$64 -> #DIV/0! | AD40: =IF(O40>0,IF(P40="1st",1,IF(P40="2nd",2,IF(P40="AN1",2,""))),"")
X41: =IF(P41="1st","Yes",IF(R41>0,"No",""))
X42: =IF(P42="1st","Yes",IF(R42>0,"No",""))
O43: =M43-N43 -> 0 | S43: =IFERROR((R43+R45+R44)/N43,0) -> 0 | U43: 0.7 | V43: =U43/$O$64*O43 -> #DIV/0! | W43: =IFERROR((R43+R45+R44)/O43,0) -> 0 | X43: =IF(P43="1st","Yes",IF(R43>0,"No","")) | AB43: =IFERROR(AC43*AD43,0) -> 0 | AC43: =O43/$O$64 -> #DIV/0! | AD43: =IF(O43>0,IF(P43="1st",1,IF(P43="2nd",2,IF(P43="AN1",2,""))),"")
X44: =IF(P44="1st","Yes",IF(R44>0,"No",""))
X45: =IF(P45="1st","Yes",IF(R45>0,"No",""))
O46: =M46-N46 -> 0 | S46: =IFERROR((R46+R48+R47)/N46,0) -> 0 | U46: 0.7 | V46: =U46/$O$64*O46 -> #DIV/0! | W46: =IFERROR((R46+R48+R47)/O46,0) -> 0 | X46: =IF(P46="1st","Yes",IF(R46>0,"No","")) | AB46: =IFERROR(AC46*AD46,0) -> 0 | AC46: =O46/$O$64 -> #DIV/0! | AD46: =IF(O46>0,IF(P46="1st",1,IF(P46="2nd",2,IF(P46="AN1",2,""))),"")
X47: =IF(P47="1st","Yes",IF(R47>0,"No",""))
X48: =IF(P48="1st","Yes",IF(R48>0,"No",""))
O49: =M49-N49 -> 0 | S49: =IFERROR((R49+R51+R50)/N49,0) -> 0 | U49: 0.7 | V49: =U49/$O$64*O49 -> #DIV/0! | W49: =IFERROR((R49+R51+R50)/O49,0) -> 0 | X49: =IF(P49="1st","Yes",IF(R49>0,"No","")) | AB49: =IFERROR(AC49*AD49,0) -> 0 | AC49: =O49/$O$64 -> #DIV/0! | AD49: =IF(O49>0,IF(P49="1st",1,IF(P49="2nd",2,IF(P49="AN1",2,""))),"")
X50: =IF(P50="1st","Yes",IF(R50>0,"No",""))
X51: =IF(P51="1st","Yes",IF(R51>0,"No",""))
O52: =M52-N52 -> 0 | S52: =IFERROR((R52+R54+R53)/N52,0) -> 0 | U52: 0.7 | V52: =U52/$O$64*O52 -> #DIV/0! | W52: =IFERROR((R52+R54+R53)/O52,0) -> 0 | X52: =IF(P52="1st","Yes",IF(R52>0,"No","")) | AB52: =IFERROR(AC52*AD52,0) -> 0 | AC52: =O52/$O$64 -> #DIV/0! | AD52: =IF(O52>0,IF(P52="1st",1,IF(P52="2nd",2,IF(P52="AN1",2,""))),"")
X53: =IF(P53="1st","Yes",IF(R53>0,"No",""))
X54: =IF(P54="1st","Yes",IF(R54>0,"No",""))
O55: =M55-N55 -> 0 | S55: =IFERROR((R55+R57+R56)/N55,0) -> 0 | U55: 0.7 | V55: =U55/$O$64*O55 -> #DIV/0! | W55: =IFERROR((R55+R57+R56)/O55,0) -> 0 | X55: =IF(P55="1st","Yes",IF(R55>0,"No","")) | AB55: =IFERROR(AC55*AD55,0) -> 0 | AC55: =O55/$O$64 -> #DIV/0! | AD55: =IF(O55>0,IF(P55="1st",1,IF(P55="2nd",2,IF(P55="AN1",2,""))),"")
X56: =IF(P56="1st","Yes",IF(R56>0,"No",""))
X57: =IF(P57="1st","Yes",IF(R57>0,"No",""))
O58: =M58-N58 -> 0 | S58: =IFERROR((R58+R60+R59)/N58,0) -> 0 | U58: 0.7 | V58: =U58/$O$64*O58 -> #DIV/0! | W58: =IFERROR((R58+R60+R59)/O58,0) -> 0 | X58: =IF(P58="1st","Yes",IF(R58>0,"No","")) | AB58: =IFERROR(AC58*AD58,0) -> 0 | AC58: =O58/$O$64 -> #DIV/0! | AD58: =IF(O58>0,IF(P58="1st",1,IF(P58="2nd",2,IF(P58="AN1",2,""))),"")
X59: =IF(P59="1st","Yes",IF(R59>0,"No",""))
X60: =IF(P60="1st","Yes",IF(R60>0,"No",""))
O61: =M61-N61 -> 0 | S61: =IFERROR((R61+R63+R62)/N61,0) -> 0 | U61: 0.7 | V61: =U61/$O$64*O61 -> #DIV/0! | W61: =IFERROR((R61+R63+R62)/O61,0) -> 0 | X61: =IF(P61="1st","Yes",IF(R61>0,"No","")) | AB61: =IFERROR(AC61*AD61,0) -> 0 | AC61: =O61/$O$64 -> #DIV/0! | AD61: =IF(O61>0,IF(P61="1st",1,IF(P61="2nd",2,IF(P61="AN1",2,""))),"")
X62: =IF(P62="1st","Yes",IF(R62>0,"No",""))
X63: =IF(P63="1st","Yes",IF(R63>0,"No",""))
B64: TOTAL: | L64: =SUM(L4:L63) -> 0 | M64: =SUM(M4:M63) -> 0 | N64: =SUM(N4:N63) -> 0 | O64: =SUM(O4:O63) -> 0 | R64: =SUMIF( $P$4:$P$63, "2nd", $R$4:$R$63 ) -> 0 | S64: =AVERAGEIF(S4:S63,">0",S4:S63) -> #DIV/0! | U64: =AVERAGEIF(M4:M63,">0",U4:U61) -> #DIV/0! | W64: =IFERROR(#REF!/O64,0) -> 0
R65: =SUMIF(Q4:Q61,"1st",R4:R61) -> 0 | U65: =SUM(V4:V61) -> #DIV/0! | AB65: LTV | AC65: 1 | AD65: 2

Sheet Properties List For Indicatives
B1: Please take screenshot and add at the bottom of the indicative for more than 11 properties
B5: Property Address | E5: Property Value | H5: Our Charge | K5: Outstading Charge
B6: =IF('Multi Property Deal'!$B$4="","",'Multi Property Deal'!$B$4) | E6: =IF('Multi Property Deal'!$M$4="","",'Multi Property Deal'!$M$4) | H6: =IF('Multi Property Deal'!$P$4="","",'Multi Property Deal'!$P$4) | K6: =IF(B6="","",IF(SUM('Multi Property Deal'!$R$4:$R$6)=0,0,SUM('Multi Property Deal'!$R$4:$R$6)))
B7: =IF('Multi Property Deal'!$B$7="","",'Multi Property Deal'!$B$7) | E7: =IF('Multi Property Deal'!$M$7="","",'Multi Property Deal'!$M$7) | H7: =IF('Multi Property Deal'!$P$7="","",'Multi Property Deal'!$P$7) | K7: =IF(B7="","",IF(SUM('Multi Property Deal'!$R$7:$R$9)=0,0,SUM('Multi Property Deal'!$R$7:$R$9)))
B8: =IF('Multi Property Deal'!$B$10="","",'Multi Property Deal'!$B$10) | E8: =IF('Multi Property Deal'!$M$10="","",'Multi Property Deal'!$M$10) | H8: =IF('Multi Property Deal'!$P$10="","",'Multi Property Deal'!$P$10) | K8: =IF(B8="","",IF(SUM('Multi Property Deal'!$R$10:$R$12)=0,0,SUM('Multi Property Deal'!$R$10:$R$12)))
B9: =IF('Multi Property Deal'!$B$13="","",'Multi Property Deal'!$B$13) | E9: =IF('Multi Property Deal'!$M$13="","",'Multi Property Deal'!$M$13) | H9: =IF('Multi Property Deal'!$P$13="","",'Multi Property Deal'!$P$13) | K9: =IF(B9="","",IF(SUM('Multi Property Deal'!$R$13:$R$15)=0,0,SUM('Multi Property Deal'!$R$13:$R$15)))
B10: =IF('Multi Property Deal'!$B$16="","",'Multi Property Deal'!$B$16) | E10: =IF('Multi Property Deal'!$M$16="","",'Multi Property Deal'!$M$16) | H10: =IF('Multi Property Deal'!$P$16="","",'Multi Property Deal'!$P$16) | K10: =IF(B10="","",IF(SUM('Multi Property Deal'!$R$16:$R$18)=0,0,SUM('Multi Property Deal'!$R$16:$R$18)))
B11: =IF('Multi Property Deal'!$B$19="","",'Multi Property Deal'!$B$19) | E11: =IF('Multi Property Deal'!$M$19="","",'Multi Property Deal'!$M$19) | H11: =IF('Multi Property Deal'!$P$19="","",'Multi Property Deal'!$P$19) | K11: =IF(B11="","",IF(SUM('Multi Property Deal'!$R$19:$R$21)=0,0,SUM('Multi Property Deal'!$R$19:$R$21)))
B12: =IF('Multi Property Deal'!$B$22="","",'Multi Property Deal'!$B$22) | E12: =IF('Multi Property Deal'!$M$22="","",'Multi Property Deal'!$M$22) | H12: =IF('Multi Property Deal'!$P$22="","",'Multi Property Deal'!$P$22) | K12: =IF(B12="","",IF(SUM('Multi Property Deal'!$R$22:$R$24)=0,0,SUM('Multi Property Deal'!$R$22:$R$24)))
B13: =IF('Multi Property Deal'!$B$25="","",'Multi Property Deal'!$B$25) | E13: =IF('Multi Property Deal'!$M$25="","",'Multi Property Deal'!$M$25) | H13: =IF('Multi Property Deal'!$P$25="","",'Multi Property Deal'!$P$25) | K13: =IF(B13="","",IF(SUM('Multi Property Deal'!$R$25:$R$27)=0,0,SUM('Multi Property Deal'!$R$25:$R$27)))
B14: =IF('Multi Property Deal'!$B$28="","",'Multi Property Deal'!$B$28) | E14: =IF('Multi Property Deal'!$M$28="","",'Multi Property Deal'!$M$28) | H14: =IF('Multi Property Deal'!$P$28="","",'Multi Property Deal'!$P$28) | K14: =IF(B14="","",IF(SUM('Multi Property Deal'!$R$28:$R$30)=0,0,SUM('Multi Property Deal'!$R$28:$R$30)))
B15: =IF('Multi Property Deal'!$B$31="","",'Multi Property Deal'!$B$31) | E15: =IF('Multi Property Deal'!$M$31="","",'Multi Property Deal'!$M$31) | H15: =IF('Multi Property Deal'!$P$31="","",'Multi Property Deal'!$P$31) | K15: =IF(B15="","",IF(SUM('Multi Property Deal'!$R$31:$R$33)=0,0,SUM('Multi Property Deal'!$R$31:$R$33)))
B16: =IF('Multi Property Deal'!$B$34="","",'Multi Property Deal'!$B$34) | E16: =IF('Multi Property Deal'!$M$34="","",'Multi Property Deal'!$M$34) | H16: =IF('Multi Property Deal'!$P$34="","",'Multi Property Deal'!$P$34) | K16: =IF(B16="","",IF(SUM('Multi Property Deal'!$R$34:$R$36)=0,0,SUM('Multi Property Deal'!$R$34:$R$36)))
B17: =IF('Multi Property Deal'!$B$37="","",'Multi Property Deal'!$B$37) | E17: =IF('Multi Property Deal'!$M$37="","",'Multi Property Deal'!$M$37) | H17: =IF('Multi Property Deal'!$P$37="","",'Multi Property Deal'!$P$37) | K17: =IF(B17="","",IF(SUM('Multi Property Deal'!$R$37:$R$39)=0,0,SUM('Multi Property Deal'!$R$37:$R$39)))
B18: =IF('Multi Property Deal'!$B$40="","",'Multi Property Deal'!$B$40) | E18: =IF('Multi Property Deal'!$M$40="","",'Multi Property Deal'!$M$40) | H18: =IF('Multi Property Deal'!$P$40="","",'Multi Property Deal'!$P$40) | K18: =IF(B18="","",IF(SUM('Multi Property Deal'!$R$40:$R$42)=0,0,SUM('Multi Property Deal'!$R$40:$R$42)))
B19: =IF('Multi Property Deal'!$B$43="","",'Multi Property Deal'!$B$43) | E19: =IF('Multi Property Deal'!$M$43="","",'Multi Property Deal'!$M$43) | H19: =IF('Multi Property Deal'!$P$43="","",'Multi Property Deal'!$P$43) | K19: =IF(B19="","",IF(SUM('Multi Property Deal'!$R$43:$R$45)=0,0,SUM('Multi Property Deal'!$R$43:$R$45)))
B20: =IF('Multi Property Deal'!$B$46="","",'Multi Property Deal'!$B$46) | E20: =IF('Multi Property Deal'!$M$46="","",'Multi Property Deal'!$M$46) | H20: =IF('Multi Property Deal'!$P$46="","",'Multi Property Deal'!$P$46) | K20: =IF(B20="","",IF(SUM('Multi Property Deal'!$R$46:$R$48)=0,0,SUM('Multi Property Deal'!$R$46:$R$48)))
B21: =IF('Multi Property Deal'!$B$49="","",'Multi Property Deal'!$B$49) | E21: =IF('Multi Property Deal'!$M$49="","",'Multi Property Deal'!$M$49) | H21: =IF('Multi Property Deal'!$P$49="","",'Multi Property Deal'!$P$49) | K21: =IF(B21="","",IF(SUM('Multi Property Deal'!$R$49:$R$51)=0,0,SUM('Multi Property Deal'!$R$49:$R$51)))
B22: =IF('Multi Property Deal'!$B$52="","",'Multi Property Deal'!$B$52) | E22: =IF('Multi Property Deal'!$M$52="","",'Multi Property Deal'!$M$52) | H22: =IF('Multi Property Deal'!$P$52="","",'Multi Property Deal'!$P$52) | K22: =IF(B22="","",IF(SUM('Multi Property Deal'!$R$52:$R$54)=0,0,SUM('Multi Property Deal'!$R$52:$R$54)))
B23: =IF('Multi Property Deal'!$B$55="","",'Multi Property Deal'!$B$55) | E23: =IF('Multi Property Deal'!$M$55="","",'Multi Property Deal'!$M$55) | H23: =IF('Multi Property Deal'!$P$55="","",'Multi Property Deal'!$P$55) | K23: =IF(B23="","",IF(SUM('Multi Property Deal'!$R$55:$R$57)=0,0,SUM('Multi Property Deal'!$R$55:$R$57)))
B24: =IF('Multi Property Deal'!$B$58="","",'Multi Property Deal'!$B$58) | E24: =IF('Multi Property Deal'!$M$58="","",'Multi Property Deal'!$M$58) | H24: =IF('Multi Property Deal'!$P$58="","",'Multi Property Deal'!$P$58) | K24: =IF(B24="","",IF(SUM('Multi Property Deal'!$R$58:$R$60)=0,0,SUM('Multi Property Deal'!$R$58:$R$60)))
B25: =IF('Multi Property Deal'!$B$61="","",'Multi Property Deal'!$B$61) | E25: =IF('Multi Property Deal'!$M$61="","",'Multi Property Deal'!$M$61) | H25: =IF('Multi Property Deal'!$P$61="","",'Multi Property Deal'!$P$61) | K25: =IF(B25="","",IF(SUM('Multi Property Deal'!$R$61:$R$63)=0,0,SUM('Multi Property Deal'!$R$61:$R$63)))

Sheet Fusion Portfolio
M3: EMV | N3: Passing Rent | O3: Gross LTV | P3: Rental Yield per Year | Q3: Rental per Sq Ft (Yearly) | R3: Term | S3: Product Fee | T3: Interest Rate proposed | U3: Deferred | V3: Rolled Up | W3: Gross Loan Amount | X3: Total Net Loan | Y3: Total NPB | Z3: Total NPB LTV | AA3: Pay rate
M4: =SUM(L9:L174) -> 0 | N4: =SUM(P9:P174) -> 0 | O4: 0.75 | P4: =AVERAGE(AD9:AD174) -> 0 | Q4: =AVERAGE(AE9:AE174) -> 0 | R4: 24 | S4: 0.0125 | T4: 0.0824 | U4: 0.02 | V4: 9 | W4: =SUM(AK9:AK174) -> 0 | X4: =SUM(AL9:AL174) -> 0 | Y4: =SUM(AM9:AM174) -> 0 | Z4: =IFERROR(Y4/M4,0) -> 0 | AA4: =T4-U4 -> 0.0624
B6: Borrower to Complete | AC6: MFS Internal Calcs
B8: No. Of Security | C8: Full Property Address | D8: Postcode | E8: Type of Property | F8: No. of Bedrooms | G8: Freehold or Leasehold | H8: Unexpired Lease Term | I8: Tenancy Start Date | J8: Tenancy End Date | K8: Size Sqft | L8: Market Value | M8: Existing Amount Outstanding (Refinance only) | N8: Occupancy Status | O8: Market Rent (if vacant) | P8: Rental Amount Charged | Q8: Ground Rent | R8: Service Charge | S8: LTV on Each Property (Refinance only) | T8: Tenant Name | U8: Tenant Profile | V8: Insurance Cost | W8: Additional Management Cost | X8: Rental Amount Paid | Y8: Deposit Amount | Z8: Any Rent Arrears | AA8: Auto-renewal Status | AB8: Rental Payments Status | AC8: Price per SqFt | AD8: Rental Yield per Year | AE8: Rental per Sq Ft (Yearly) | AF8: Operating cost | AG8: Term in months | AH8: Arrangement Fee | AI8: Interest Rate | AJ8: Rolled Up | AK8: Gross Loan Amount | AL8: Net Loan Amount | AM8: NPB amount | AN8: Rolled Interst | AO8: NPB LTV | AP8: Pay rate | AQ8: Gross ICR | AR8: Net ICR
S9: =IFERROR(M9/L9,0) -> 0 | AC9: =IFERROR(L9/K9,0) -> 0 | AD9: =IFERROR(P9*12/L9,0) -> 0 | AE9: =IFERROR(P9*12/K9,0) -> 0 | AF9: =SUM($Q9:$W9) -> 0 | AG9: =IF('Input Sheet'!$C$15="Yes",'Input Sheet'!$F$8,0) -> 0 | AH9: =IF('Input Sheet'!$C$15="Yes",Rates!$E$45,0) -> 0 | AI9: =IF('Input Sheet'!$C$15="Yes",'Input Sheet'!$F$11,0) -> 0 | AJ9: =IF('Input Sheet'!$C$15="Yes",'Input Sheet'!$F$7,0) -> 0 | AK9: =L9*S9 -> 0 | AL9: =(AK9)-(AK9*AH9)-(AK9*AP9*(AJ9/12)) -> 0 | AM9: =(AL9)+(AK9*0.75%) -> 0 | AN9: =AK9*AP9*AJ9/12 -> 0 | AO9: =IFERROR(AM9/L9,0) -> 0 | AP9: =AI9 -> 0 | AQ9: =IFERROR(P9*'Input Sheet'!$F$8/(((AI9)*AK9*2)-AN9),0) -> 0 | AR9: =IFERROR(($P9-$AF9)*'Input Sheet'!$F$8/(((AI9)*AK9*2)-AN9),0) -> 0
S10: =IFERROR(M10/L10,0) -> 0 | AC10: =IFERROR(L10/K10,0) -> 0 | AD10: =IFERROR(P10*12/L10,0) -> 0 | AE10: =IFERROR(P10*12/K10,0) -> 0 | AF10: =SUM($Q10:$W10) -> 0 | AG10: =IF('Input Sheet'!$C$15="Yes",'Input Sheet'!$F$8,0) -> 0 | AH10: =IF('Input Sheet'!$C$15="Yes",Rates!$E$45,0) -> 0 | AI10: =IF('Input Sheet'!$C$15="Yes",'Input Sheet'!$F$11,0) -> 0 | AJ10: =IF('Input Sheet'!$C$15="Yes",'Input Sheet'!$F$7,0) -> 0 | AK10: =L10*S10 -> 0 | AL10: =(AK10)-(AK10*AH10)-(AK10*AP10*(AJ10/12)) -> 0 | AM10: =(AL10)+(AK10*0.75%) -> 0 | AN10: =AK10*AP10*AJ10/12 -> 0 | AO10: =IFERROR(AM10/L10,0) -> 0 | AP10: =AI10 -> 0 | AQ10: =IFERROR(P10*'Input Sheet'!$F$8/(((AI10)*AK10*2)-AN10),0) -> 0 | AR10: =IFERROR(($P10-$AF10)*'Input Sheet'!$F$8/(((AI10)*AK10*2)-AN10),0) -> 0
S11: =IFERROR(M11/L11,0) -> 0 | AC11: =IFERROR(L11/K11,0) -> 0 | AD11: =IFERROR(P11*12/L11,0) -> 0 | AE11: =IFERROR(P11*12/K11,0) -> 0 | AF11: =SUM($Q11:$W11) -> 0 | AG11: =IF('Input Sheet'!$C$15="Yes",'Input Sheet'!$F$8,0) -> 0 | AH11: =IF('Input Sheet'!$C$15="Yes",Rates!$E$45,0) -> 0 | AI11: =IF('Input Sheet'!$C$15="Yes",'Input Sheet'!$F$11,0) -> 0 | AJ11: =IF('Input Sheet'!$C$15="Yes",'Input Sheet'!$F$7,0) -> 0 | AK11: =L11*S11 -> 0 | AL11: =(AK11)-(AK11*AH11)-(AK11*AP11*(AJ11/12)) -> 0 | AM11: =(AL11)+(AK11*0.75%) -> 0 | AN11: =AK11*AP11*AJ11/12 -> 0 | AO11: =IFERROR(AM11/L11,0) -> 0 | AP11: =AI11 -> 0 | AQ11: =IFERROR(P11*'Input Sheet'!$F$8/(((AI11)*AK11*2)-AN11),0) -> 0 | AR11: =IFERROR(($P11-$AF11)*'Input Sheet'!$F$8/(((AI11)*AK11*2)-AN11),0) -> 0
S12: =IFERROR(M12/L12,0) -> 0 | AC12: =IFERROR(L12/K12,0) -> 0 | AD12: =IFERROR(P12*12/L12,0) -> 0 | AE12: =IFERROR(P12*12/K12,0) -> 0 | AF12: =SUM($Q12:$W12) -> 0 | AG12: =IF('Input Sheet'!$C$15="Yes",'Input Sheet'!$F$8,0) -> 0 | AH12: =IF('Input Sheet'!$C$15="Yes",Rates!$E$45,0) -> 0 | AI12: =IF('Input Sheet'!$C$15="Yes",'Input Sheet'!$F$11,0) -> 0 | AJ12: =IF('Input Sheet'!$C$15="Yes",'Input Sheet'!$F$7,0) -> 0 | AK12: =L12*S12 -> 0 | AL12: =(AK12)-(AK12*AH12)-(AK12*AP12*(AJ12/12)) -> 0 | AM12: =(AL12)+(AK12*0.75%) -> 0 | AN12: =AK12*AP12*AJ12/12 -> 0 | AO12: =IFERROR(AM12/L12,0) -> 0 | AP12: =AI12 -> 0 | AQ12: =IFERROR(P12*'Input Sheet'!$F$8/(((AI12)*AK12*2)-AN12),0) -> 0 | AR12: =IFERROR(($P12-$AF12)*'Input Sheet'!$F$8/(((AI12)*AK12*2)-AN12),0) -> 0
S13: =IFERROR(M13/L13,0) -> 0 | AC13: =IFERROR(L13/K13,0) -> 0 | AD13: =IFERROR(P13*12/L13,0) -> 0 | AE13: =IFERROR(P13*12/K13,0) -> 0 | AF13: =SUM($Q13:$W13) -> 0 | AG13: =IF('Input Sheet'!$C$15="Yes",'Input Sheet'!$F$8,0) -> 0 | AH13: =IF('Input Sheet'!$C$15="Yes",Rates!$E$45,0) -> 0 | AI13: =IF('Input Sheet'!$C$15="Yes",'Input Sheet'!$F$11,0) -> 0 | AJ13: =IF('Input Sheet'!$C$15="Yes",'Input Sheet'!$F$7,0) -> 0 | AK13: =L13*S13 -> 0 | AL13: =(AK13)-(AK13*AH13)-(AK13*AP13*(AJ13/12)) -> 0 | AM13: =(AL13)+(AK13*0.75%) -> 0 | AN13: =AK13*AP13*AJ13/12 -> 0 | AO13: =IFERROR(AM13/L13,0) -> 0 | AP13: =AI13 -> 0 | AQ13: =IFERROR(P13*'Input Sheet'!$F$8/(((AI13)*AK13*2)-AN13),0) -> 0 | AR13: =IFERROR(($P13-$AF13)*'Input Sheet'!$F$8/(((AI13)*AK13*2)-AN13),0) -> 0
S14: =IFERROR(M14/L14,0) -> 0 | AC14: =IFERROR(L14/K14,0) -> 0 | AD14: =IFERROR(P14*12/L14,0) -> 0 | AE14: =IFERROR(P14*12/K14,0) -> 0 | AF14: =SUM($Q14:$W14) -> 0 | AG14: =IF('Input Sheet'!$C$15="Yes",'Input Sheet'!$F$8,0) -> 0 | AH14: =IF('Input Sheet'!$C$15="Yes",Rates!$E$45,0) -> 0 | AI14: =IF('Input Sheet'!$C$15="Yes",'Input Sheet'!$F$11,0) -> 0 | AJ14: =IF('Input Sheet'!$C$15="Yes",'Input Sheet'!$F$7,0) -> 0 | AK14: =L14*S14 -> 0 | AL14: =(AK14)-(AK14*AH14)-(AK14*AP14*(AJ14/12)) -> 0 | AM14: =(AL14)+(AK14*0.75%) -> 0 | AN14: =AK14*AP14*AJ14/12 -> 0 | AO14: =IFERROR(AM14/L14,0) -> 0 | AP14: =AI14 -> 0 | AQ14: =IFERROR(P14*'Input Sheet'!$F$8/(((AI14)*AK14*2)-AN14),0) -> 0 | AR14: =IFERROR(($P14-$AF14)*'Input Sheet'!$F$8/(((AI14)*AK14*2)-AN14),0) -> 0
S15: =IFERROR(M15/L15,0) -> 0 | AC15: =IFERROR(L15/K15,0) -> 0 | AD15: =IFERROR(P15*12/L15,0) -> 0 | AE15: =IFERROR(P15*12/K15,0) -> 0 | AF15: =SUM($Q15:$W15) -> 0 | AG15: =IF('Input Sheet'!$C$15="Yes",'Input Sheet'!$F$8,0) -> 0 | AH15: =IF('Input Sheet'!$C$15="Yes",Rates!$E$45,0) -> 0 | AI15: =IF('Input Sheet'!$C$15="Yes",'Input Sheet'!$F$11,0) -> 0 | AJ15: =IF('Input Sheet'!$C$15="Yes",'Input Sheet'!$F$7,0) -> 0 | AK15: =L15*S15 -> 0 | AL15: =(AK15)-(AK15*AH15)-(AK15*AP15*(AJ15/12)) -> 0 | AM15: =(AL15)+(AK15*0.75%) -> 0 | AN15: =AK15*AP15*AJ15/12 -> 0 | AO15: =IFERROR(AM15/L15,0) -> 0 | AP15: =AI15 -> 0 | AQ15: =IFERROR(P15*'Input Sheet'!$F$8/(((AI15)*AK15*2)-AN15),0) -> 0 | AR15: =IFERROR(($P15-$AF15)*'Input Sheet'!$F$8/(((AI15)*AK15*2)-AN15),0) -> 0
S16: =IFERROR(M16/L16,0) -> 0 | AC16: =IFERROR(L16/K16,0) -> 0 | AD16: =IFERROR(P16*12/L16,0) -> 0 | AE16: =IFERROR(P16*12/K16,0) -> 0 | AF16: =SUM($Q16:$W16) -> 0 | AG16: =IF('Input Sheet'!$C$15="Yes",'Input Sheet'!$F$8,0) -> 0 | AH16: =IF('Input Sheet'!$C$15="Yes",Rates!$E$45,0) -> 0 | AI16: =IF('Input Sheet'!$C$15="Yes",'Input Sheet'!$F$11,0) -> 0 | AJ16: =IF('Input Sheet'!$C$15="Yes",'Input Sheet'!$F$7,0) -> 0 | AK16: =L16*S16 -> 0 | AL16: =(AK16)-(AK16*AH16)-(AK16*AP16*(AJ16/12)) -> 0 | AM16: =(AL16)+(AK16*0.75%) -> 0 | AN16: =AK16*AP16*AJ16/12 -> 0 | AO16: =IFERROR(AM16/L16,0) -> 0 | AP16: =AI16 -> 0 | AQ16: =IFERROR(P16*'Input Sheet'!$F$8/(((AI16)*AK16*2)-AN16),0) -> 0 | AR16: =IFERROR(($P16-$AF16)*'Input Sheet'!$F$8/(((AI16)*AK16*2)-AN16),0) -> 0
S17: =IFERROR(M17/L17,0) -> 0 | AC17: =IFERROR(L17/K17,0) -> 0 | AD17: =IFERROR(P17*12/L17,0) -> 0 | AE17: =IFERROR(P17*12/K17,0) -> 0 | AF17: =SUM($Q17:$W17) -> 0 | AG17: =IF('Input Sheet'!$C$15="Yes",'Input Sheet'!$F$8,0) -> 0 | AH17: =IF('Input Sheet'!$C$15="Yes",Rates!$E$45,0) -> 0 | AI17: =IF('Input Sheet'!$C$15="Yes",'Input Sheet'!$F$11,0) -> 0 | AJ17: =IF('Input Sheet'!$C$15="Yes",'Input Sheet'!$F$7,0) -> 0 | AK17: =L17*S17 -> 0 | AL17: =(AK17)-(AK17*AH17)-(AK17*AP17*(AJ17/12)) -> 0 | AM17: =(AL17)+(AK17*0.75%) -> 0 | AN17: =AK17*AP17*AJ17/12 -> 0 | AO17: =IFERROR(AM17/L17,0) -> 0 | AP17: =AI17 -> 0 | AQ17: =IFERROR(P17*'Input Sheet'!$F$8/(((AI17)*AK17*2)-AN17),0) -> 0 | AR17: =IFERROR(($P17-$AF17)*'Input Sheet'!$F$8/(((AI17)*AK17*2)-AN17),0) -> 0
S18: =IFERROR(M18/L18,0) -> 0 | AC18: =IFERROR(L18/K18,0) -> 0 | AD18: =IFERROR(P18*12/L18,0) -> 0 | AE18: =IFERROR(P18*12/K18,0) -> 0 | AF18: =SUM($Q18:$W18) -> 0 | AG18: =IF('Input Sheet'!$C$15="Yes",'Input Sheet'!$F$8,0) -> 0 | AH18: =IF('Input Sheet'!$C$15="Yes",Rates!$E$45,0) -> 0 | AI18: =IF('Input Sheet'!$C$15="Yes",'Input Sheet'!$F$11,0) -> 0 | AJ18: =IF('Input Sheet'!$C$15="Yes",'Input Sheet'!$F$7,0) -> 0 | AK18: =L18*S18 -> 0 | AL18: =(AK18)-(AK18*AH18)-(AK18*AP18*(AJ18/12)) -> 0 | AM18: =(AL18)+(AK18*0.75%) -> 0 | AN18: =AK18*AP18*AJ18/12 -> 0 | AO18: =IFERROR(AM18/L18,0) -> 0 | AP18: =AI18 -> 0 | AQ18: =IFERROR(P18*'Input Sheet'!$F$8/(((AI18)*AK18*2)-AN18),0) -> 0 | AR18: =IFERROR(($P18-$AF18)*'Input Sheet'!$F$8/(((AI18)*AK18*2)-AN18),0) -> 0
S19: =IFERROR(M19/L19,0) -> 0 | AC19: =IFERROR(L19/K19,0) -> 0 | AD19: =IFERROR(P19*12/L19,0) -> 0 | AE19: =IFERROR(P19*12/K19,0) -> 0 | AF19: =SUM($Q19:$W19) -> 0 | AG19: =IF('Input Sheet'!$C$15="Yes",'Input Sheet'!$F$8,0) -> 0 | AH19: =IF('Input Sheet'!$C$15="Yes",Rates!$E$45,0) -> 0 | AI19: =IF('Input Sheet'!$C$15="Yes",'Input Sheet'!$F$11,0) -> 0 | AJ19: =IF('Input Sheet'!$C$15="Yes",'Input Sheet'!$F$7,0) -> 0 | AK19: =L19*S19 -> 0 | AL19: =(AK19)-(AK19*AH19)-(AK19*AP19*(AJ19/12)) -> 0 | AM19: =(AL19)+(AK19*0.75%) -> 0 | AN19: =AK19*AP19*AJ19/12 -> 0 | AO19: =IFERROR(AM19/L19,0) -> 0 | AP19: =AI19 -> 0 | AQ19: =IFERROR(P19*'Input Sheet'!$F$8/(((AI19)*AK19*2)-AN19),0) -> 0 | AR19: =IFERROR(($P19-$AF19)*'Input Sheet'!$F$8/(((AI19)*AK19*2)-AN19),0) -> 0
S20: =IFERROR(M20/L20,0) -> 0 | AC20: =IFERROR(L20/K20,0) -> 0 | AD20: =IFERROR(P20*12/L20,0) -> 0 | AE20: =IFERROR(P20*12/K20,0) -> 0 | AF20: =SUM($Q20:$W20) -> 0 | AG20: =IF('Input Sheet'!$C$15="Yes",'Input Sheet'!$F$8,0) -> 0 | AH20: =IF('Input Sheet'!$C$15="Yes",Rates!$E$45,0) -> 0 | AI20: =IF('Input Sheet'!$C$15="Yes",'Input Sheet'!$F$11,0) -> 0 | AJ20: =IF('Input Sheet'!$C$15="Yes",'Input Sheet'!$F$7,0) -> 0 | AK20: =L20*S20 -> 0 | AL20: =(AK20)-(AK20*AH20)-(AK20*AP20*(AJ20/12)) -> 0 | AM20: =(AL20)+(AK20*0.75%) -> 0 | AN20: =AK20*AP20*AJ20/12 -> 0 | AO20: =IFERROR(AM20/L20,0) -> 0 | AP20: =AI20 -> 0 | AQ20: =IFERROR(P20*'Input Sheet'!$F$8/(((AI20)*AK20*2)-AN20),0) -> 0 | AR20: =IFERROR(($P20-$AF20)*'Input Sheet'!$F$8/(((AI20)*AK20*2)-AN20),0) -> 0
... S659: =IFERROR(M659/L659,0) -> 0 | AC659: =IFERROR(L659/K659,0) -> 0 | AD659: =IFERROR(P659*12/L659,0) -> 0 | AE659: =IFERROR(P659*12/K659,0) -> 0 | AF659: =SUM($Q659:$W659) -> 0 | AG659: =IF('Input Sheet'!$C$15="Yes",'Input Sheet'!$F$8,0) -> 0 | AH659: =IF('Input Sheet'!$C$15="Yes",Rates!$E$45,0) -> 0 | AI659: =IF('Input Sheet'!$C$15="Yes",'Input Sheet'!$F$11,0) -> 0 | AJ659: =IF('Input Sheet'!$C$15="Yes",'Input Sheet'!$F$7,0) -> 0 | AK659: =L659*S659 -> 0 | AL659: =(AK659)-(AK659*AH659)-(AK659*AP659*(AJ659/12)) -> 0 | AM659: =(AL659)+(AK659*0.75%) -> 0 | AN659: =AK659*AP659*AJ659/12 -> 0 | AO659: =IFERROR(AM659/L659,0) -> 0 | AP659: =AI659 -> 0 | AQ659: =IFERROR(P659*'Input Sheet'!$F$8/(((AI659)*AK659*2)-AN659),0) -> 0 | AR659: =IFERROR(($P659-$AF659)*'Input Sheet'!$F$8/(((AI659)*AK659*2)-AN659),0) -> 0
P660: 10000 | S660: =IFERROR(M660/L660,0) -> 0 | AC660: =IFERROR(L660/K660,0) -> 0 | AD660: =IFERROR(P660*12/L660,0) -> 0 | AE660: =IFERROR(P660*12/K660,0) -> 0 | AF660: =SUM($Q660:$W660) -> 0 | AG660: =IF('Input Sheet'!$C$15="Yes",'Input Sheet'!$F$8,0) -> 0 | AH660: =IF('Input Sheet'!$C$15="Yes",Rates!$E$45,0) -> 0 | AI660: =IF('Input Sheet'!$C$15="Yes",'Input Sheet'!$F$11,0) -> 0 | AJ660: =IF('Input Sheet'!$C$15="Yes",'Input Sheet'!$F$7,0) -> 0 | AK660: =L660*S660 -> 0 | AL660: =(AK660)-(AK660*AH660)-(AK660*AP660*(AJ660/12)) -> 0 | AM660: =(AL660)+(AK660*0.75%) -> 0 | AN660: =AK660*AP660*AJ660/12 -> 0 | AO660: =IFERROR(AM660/L660,0) -> 0 | AP660: =AI660 -> 0 | AQ660: =IFERROR(P660*'Input Sheet'!$F$8/(((AI660)*AK660*2)-AN660),0) -> 0 | AR660: =IFERROR(($P660-$AF660)*'Input Sheet'!$F$8/(((AI660)*AK660*2)-AN660),0) -> 0
S661: =IFERROR(M661/L661,0) -> 0 | AC661: =IFERROR(L661/K661,0) -> 0 | AD661: =IFERROR(P661*12/L661,0) -> 0 | AE661: =IFERROR(P661*12/K661,0) -> 0 | AF661: =SUM($Q661:$W661) -> 0 | AG661: =IF('Input Sheet'!$C$15="Yes",'Input Sheet'!$F$8,0) -> 0 | AH661: =IF('Input Sheet'!$C$15="Yes",Rates!$E$45,0) -> 0 | AI661: =IF('Input Sheet'!$C$15="Yes",'Input Sheet'!$F$11,0) -> 0 | AJ661: =IF('Input Sheet'!$C$15="Yes",'Input Sheet'!$F$7,0) -> 0 | AK661: =L661*S661 -> 0 | AL661: =(AK661)-(AK661*AH661)-(AK661*AP661*(AJ661/12)) -> 0 | AM661: =(AL661)+(AK661*0.75%) -> 0 | AN661: =AK661*AP661*AJ661/12 -> 0 | AO661: =IFERROR(AM661/L661,0) -> 0 | AP661: =AI661 -> 0 | AQ661: =IFERROR(P661*'Input Sheet'!$F$8/(((AI661)*AK661*2)-AN661),0) -> 0 | AR661: =IFERROR(($P661-$AF661)*'Input Sheet'!$F$8/(((AI661)*AK661*2)-AN661),0) -> 0
S662: =IFERROR(M662/L662,0) -> 0 | AC662: =IFERROR(L662/K662,0) -> 0 | AD662: =IFERROR(P662*12/L662,0) -> 0 | AE662: =IFERROR(P662*12/K662,0) -> 0 | AF662: =SUM($Q662:$W662) -> 0 | AG662: =IF('Input Sheet'!$C$15="Yes",'Input Sheet'!$F$8,0) -> 0 | AH662: =IF('Input Sheet'!$C$15="Yes",Rates!$E$45,0) -> 0 | AI662: =IF('Input Sheet'!$C$15="Yes",'Input Sheet'!$F$11,0) -> 0 | AJ662: =IF('Input Sheet'!$C$15="Yes",'Input Sheet'!$F$7,0) -> 0 | AK662: =L662*S662 -> 0 | AL662: =(AK662)-(AK662*AH662)-(AK662*AP662*(AJ662/12)) -> 0 | AM662: =(AL662)+(AK662*0.75%) -> 0 | AN662: =AK662*AP662*AJ662/12 -> 0 | AO662: =IFERROR(AM662/L662,0) -> 0 | AP662: =AI662 -> 0 | AQ662: =IFERROR(P662*'Input Sheet'!$F$8/(((AI662)*AK662*2)-AN662),0) -> 0 | AR662: =IFERROR(($P662-$AF662)*'Input Sheet'!$F$8/(((AI662)*AK662*2)-AN662),0) -> 0
S663: =IFERROR(M663/L663,0) -> 0 | AC663: =IFERROR(L663/K663,0) -> 0 | AD663: =IFERROR(P663*12/L663,0) -> 0 | AE663: =IFERROR(P663*12/K663,0) -> 0 | AF663: =SUM($Q663:$W663) -> 0 | AG663: =IF('Input Sheet'!$C$15="Yes",'Input Sheet'!$F$8,0) -> 0 | AH663: =IF('Input Sheet'!$C$15="Yes",Rates!$E$45,0) -> 0 | AI663: =IF('Input Sheet'!$C$15="Yes",'Input Sheet'!$F$11,0) -> 0 | AJ663: =IF('Input Sheet'!$C$15="Yes",'Input Sheet'!$F$7,0) -> 0 | AK663: =L663*S663 -> 0 | AL663: =(AK663)-(AK663*AH663)-(AK663*AP663*(AJ663/12)) -> 0 | AM663: =(AL663)+(AK663*0.75%) -> 0 | AN663: =AK663*AP663*AJ663/12 -> 0 | AO663: =IFERROR(AM663/L663,0) -> 0 | AP663: =AI663 -> 0 | AQ663: =IFERROR(P663*'Input Sheet'!$F$8/(((AI663)*AK663*2)-AN663),0) -> 0 | AR663: =IFERROR(($P663-$AF663)*'Input Sheet'!$F$8/(((AI663)*AK663*2)-AN663),0) -> 0
S664: =IFERROR(M664/L664,0) -> 0 | AC664: =IFERROR(L664/K664,0) -> 0 | AD664: =IFERROR(P664*12/L664,0) -> 0 | AE664: =IFERROR(P664*12/K664,0) -> 0 | AF664: =SUM($Q664:$W664) -> 0 | AG664: =IF('Input Sheet'!$C$15="Yes",'Input Sheet'!$F$8,0) -> 0 | AH664: =IF('Input Sheet'!$C$15="Yes",Rates!$E$45,0) -> 0 | AI664: =IF('Input Sheet'!$C$15="Yes",'Input Sheet'!$F$11,0) -> 0 | AJ664: =IF('Input Sheet'!$C$15="Yes",'Input Sheet'!$F$7,0) -> 0 | AK664: =L664*S664 -> 0 | AL664: =(AK664)-(AK664*AH664)-(AK664*AP664*(AJ664/12)) -> 0 | AM664: =(AL664)+(AK664*0.75%) -> 0 | AN664: =AK664*AP664*AJ664/12 -> 0 | AO664: =IFERROR(AM664/L664,0) -> 0 | AP664: =AI664 -> 0 | AQ664: =IFERROR(P664*'Input Sheet'!$F$8/(((AI664)*AK664*2)-AN664),0) -> 0 | AR664: =IFERROR(($P664-$AF664)*'Input Sheet'!$F$8/(((AI664)*AK664*2)-AN664),0) -> 0
S665: =IFERROR(M665/L665,0) -> 0 | AC665: =IFERROR(L665/K665,0) -> 0 | AD665: =IFERROR(P665*12/L665,0) -> 0 | AE665: =IFERROR(P665*12/K665,0) -> 0 | AF665: =SUM($Q665:$W665) -> 0 | AG665: =IF('Input Sheet'!$C$15="Yes",'Input Sheet'!$F$8,0) -> 0 | AH665: =IF('Input Sheet'!$C$15="Yes",Rates!$E$45,0) -> 0 | AI665: =IF('Input Sheet'!$C$15="Yes",'Input Sheet'!$F$11,0) -> 0 | AJ665: =IF('Input Sheet'!$C$15="Yes",'Input Sheet'!$F$7,0) -> 0 | AK665: =L665*S665 -> 0 | AL665: =(AK665)-(AK665*AH665)-(AK665*AP665*(AJ665/12)) -> 0 | AM665: =(AL665)+(AK665*0.75%) -> 0 | AN665: =AK665*AP665*AJ665/12 -> 0 | AO665: =IFERROR(AM665/L665,0) -> 0 | AP665: =AI665 -> 0 | AQ665: =IFERROR(P665*'Input Sheet'!$F$8/(((AI665)*AK665*2)-AN665),0) -> 0 | AR665: =IFERROR(($P665-$AF665)*'Input Sheet'!$F$8/(((AI665)*AK665*2)-AN665),0) -> 0
S666: =IFERROR(M666/L666,0) -> 0 | AC666: =IFERROR(L666/K666,0) -> 0 | AD666: =IFERROR(P666*12/L666,0) -> 0 | AE666: =IFERROR(P666*12/K666,0) -> 0 | AF666: =SUM($Q666:$W666) -> 0 | AG666: =IF('Input Sheet'!$C$15="Yes",'Input Sheet'!$F$8,0) -> 0 | AH666: =IF('Input Sheet'!$C$15="Yes",Rates!$E$45,0) -> 0 | AI666: =IF('Input Sheet'!$C$15="Yes",'Input Sheet'!$F$11,0) -> 0 | AJ666: =IF('Input Sheet'!$C$15="Yes",'Input Sheet'!$F$7,0) -> 0 | AK666: =L666*S666 -> 0 | AL666: =(AK666)-(AK666*AH666)-(AK666*AP666*(AJ666/12)) -> 0 | AM666: =(AL666)+(AK666*0.75%) -> 0 | AN666: =AK666*AP666*AJ666/12 -> 0 | AO666: =IFERROR(AM666/L666,0) -> 0 | AP666: =AI666 -> 0 | AQ666: =IFERROR(P666*'Input Sheet'!$F$8/(((AI666)*AK666*2)-AN666),0) -> 0 | AR666: =IFERROR(($P666-$AF666)*'Input Sheet'!$F$8/(((AI666)*AK666*2)-AN666),0) -> 0
S667: =IFERROR(M667/L667,0) -> 0 | AC667: =IFERROR(L667/K667,0) -> 0 | AD667: =IFERROR(P667*12/L667,0) -> 0 | AE667: =IFERROR(P667*12/K667,0) -> 0 | AF667: =SUM($Q667:$W667) -> 0 | AG667: =IF('Input Sheet'!$C$15="Yes",'Input Sheet'!$F$8,0) -> 0 | AH667: =IF('Input Sheet'!$C$15="Yes",Rates!$E$45,0) -> 0 | AI667: =IF('Input Sheet'!$C$15="Yes",'Input Sheet'!$F$11,0) -> 0 | AJ667: =IF('Input Sheet'!$C$15="Yes",'Input Sheet'!$F$7,0) -> 0 | AK667: =L667*S667 -> 0 | AL667: =(AK667)-(AK667*AH667)-(AK667*AP667*(AJ667/12)) -> 0 | AM667: =(AL667)+(AK667*0.75%) -> 0 | AN667: =AK667*AP667*AJ667/12 -> 0 | AO667: =IFERROR(AM667/L667,0) -> 0 | AP667: =AI667 -> 0 | AQ667: =IFERROR(P667*'Input Sheet'!$F$8/(((AI667)*AK667*2)-AN667),0) -> 0 | AR667: =IFERROR(($P667-$AF667)*'Input Sheet'!$F$8/(((AI667)*AK667*2)-AN667),0) -> 0
S668: =IFERROR(M668/L668,0) -> 0 | AC668: =IFERROR(L668/K668,0) -> 0 | AD668: =IFERROR(P668*12/L668,0) -> 0 | AE668: =IFERROR(P668*12/K668,0) -> 0 | AF668: =SUM($Q668:$W668) -> 0 | AG668: =IF('Input Sheet'!$C$15="Yes",'Input Sheet'!$F$8,0) -> 0 | AH668: =IF('Input Sheet'!$C$15="Yes",Rates!$E$45,0) -> 0 | AI668: =IF('Input Sheet'!$C$15="Yes",'Input Sheet'!$F$11,0) -> 0 | AJ668: =IF('Input Sheet'!$C$15="Yes",'Input Sheet'!$F$7,0) -> 0 | AK668: =L668*S668 -> 0 | AL668: =(AK668)-(AK668*AH668)-(AK668*AP668*(AJ668/12)) -> 0 | AM668: =(AL668)+(AK668*0.75%) -> 0 | AN668: =AK668*AP668*AJ668/12 -> 0 | AO668: =IFERROR(AM668/L668,0) -> 0 | AP668: =AI668 -> 0 | AQ668: =IFERROR(P668*'Input Sheet'!$F$8/(((AI668)*AK668*2)-AN668),0) -> 0 | AR668: =IFERROR(($P668-$AF668)*'Input Sheet'!$F$8/(((AI668)*AK668*2)-AN668),0) -> 0

Sheet Payment Schedule
B3: Select Product | E3: Fusion | G3: Loan Start Date | J3: ='Input Sheet'!$C$10 -> 0 | L3: BBR Change
G4: =IF(K4>100,"Redemption Date", "Loan End Date") -> Loan End Date | J4: =IF(K4>100,K4,EDATE(J3,J10)) -> 731 | K4: =SUM(H19:H54) -> 0 | L4: Date of Change | M4: Effective date | P4: Rate
B5: Gross Loan Amount | E5: =IF($E$3="Fusion",'Input Sheet'!$F$12,IF($E$3="Variable",'Input Sheet'!I12)) -> 0 | L5: 45057 | M5: =IF(L5="","",EOMONTH(L5,0)+1) -> 45078 | P5: 0.045
B6: Net Principal Balance | E6: =IF($E$3="Fusion",'Input Sheet'!F14,IF($E$3="Variable",'Input Sheet'!I14)) -> 0 | G6: Term | J6: =IF($E$3="Fusion",'Input Sheet'!F8,IF($E$3="Variable",'Input Sheet'!I8)) -> 24 | L6: 45099 | M6: =IF(L6="","",EOMONTH(L6,0)+1) -> 45108 | P6: 0.05
B7: Net Loan Amount | E7: =IF($E$3="Fusion",'Input Sheet'!F15,IF($E$3="Variable",'Input Sheet'!I15)) -> 0 | G7: Rolled Term | J7: =IF($E$3="Fusion",'Input Sheet'!F7,IF($E$3="Variable",'Input Sheet'!I7)) -> 6 | L7: 45141 | M7: =IF(L7="","",EOMONTH(L7,0)+1) -> 45170 | P7: 0.0525
B8: Property Value | E8: ='Input Sheet'!C28 -> 0 | G8: Serviced Term | J8: =$J$6-$J$7 -> 18 | L8: 45505 | M8: =IF(L8="","",EOMONTH(L8,0)+1) -> 45536 | P8: 0.0475
B9: Initial Rolled int Amount | E9: =IF(E3="Fusion",('Input Sheet'!$F$11-'Input Sheet'!$F$9)/12*$E$5*$J$7,'Input Sheet'!I11*$E$5*$J$7) -> #VALUE! | G9: Extension | L9: 45542 | M9: =IF(L9="","",EOMONTH(L9,0)+1) -> 45566 | P9: 0.0475
B10: Monthly Coupon Rate | E10: =IF($E$3="Fusion",('Input Sheet'!F11-BBR-'Input Sheet'!F9)/12,IF($E$3="Variable",'Input Sheet'!I5,IF($E$3="Fixed",'Input Sheet'!L5))) -> #VALUE! | G10: Actual Term | J10: =J6+J9 -> 24 | L10: 45694 | M10: =IF(L10="","",EOMONTH(L10,0)+1) -> 45717 | P10: 0.045
B11: Pay Rate Monthly | E11: =IF($E$3="Fusion",('Input Sheet'!F11-'Input Sheet'!$F$9)/12,IF($E$3="Variable",'Input Sheet'!I5+'Input Sheet'!$C$42)) -> #VALUE! | G11: Actual Rolled term | J11: =IF($J$4="",J7,IF(J10-J12<3,3,J10-J12)) -> 6 | L11: 45785 | M11: =IF(L11="","",EOMONTH(L11,0)+1) -> 45809 | P11: 0.0425
B12: Exit Fee | E12: =IF(E3="Fixed",'Input Sheet'!L30,IF('Payment Schedule'!E3="Variable",'Input Sheet'!I30)) -> FALSE | G12: Actual Serviced term | J12: =IF(J10-J7>=0,J10-J7,0) -> 18 | M12: =IF(L12="","",EOMONTH(L12,0)+1)
B13: Input Fields | M13: =IF(L13="","",EOMONTH(L13,0)+1)
M14: =IF(L14="","",EOMONTH(L14,0)+1)
F15: Full redemption made on extended loan before loan end date
F17: Principle | I17: Initital | P17: Real | U17: Adjustment | AA17: Serviced int Amount(£)
C18: Date | D18: Rolled / Serviced | E18: Monthly Client Coupon Rate | F18: Redemption(s) | G18: Live Gross Loan Amount | H18: Full redemption date | I18: BBR Monthly | J18: Monthly Rate | K18: Annual Rate | L18: Total Interest Per Month | M18: ERC | N18: Allownance | O18: Allowance remaing | P18: BBR | Q18: BBR Monthly | R18: Monthly Rate | S18: Annual Rate | T18: Total Interest Per month | U18: Rolled int Amount | V18: Monthly Additional Interest | W18: Accumulated Outstanding Rolled Interest | X18: Collected Rolled Interest | Y18: Accumulated Collected Rolled Interest | Z18: Accumulated Outstanding Rolled Interest After int Payments | AA18: Interest Collected | AB18: Expected Serviced Interest | AC18: Collected Serviced Interest) | AD18: Outstading Interest Amount | AE18: Accumulated outstanding Serviced Interest with Adjustment
B19: 1 | C19: =EDATE('Input Sheet'!$C$10,0) -> 0 | D19: =IF(B19>$J$10,"",IF(B19<=$J$7,"Rolled","Serviced")) -> Rolled | E19: =IF(B19>$J$10,"",$E$10) -> #VALUE! | G19: =IF(B19>$J$10,"",$E$5-SUM(F19:$F$19)) -> 0 | H19: =IF(AND(F19>0,G18>0,F19>=G18),EDATE(C19,0)) -> FALSE | I19: =IF(B19>$J$10,"",'Input Sheet'!$C$42) -> 0.0033333333 | J19: =IF(B19>$J$10,"",$E$11) -> #VALUE! | K19: =IF(B19>$J$10,"",J19*12) -> #VALUE! | L19: =IFERROR(IF(B19>$J$11,G19*J19,$E$5*J19),"") | M19: =IF(AND(B19<21,$E$3="Fusion",F19<>""),F19*3%,"") | P19: =IFERROR(IF(B19>$J$10,"",IF($E$3="Fixed",BBR,INDEX($P$5:$P$14,MATCH(EOMONTH(C19,-1)+1,$M$5:$M$14)))),"") | Q19: =IFERROR(IF(B19>$J$10,"",P19/12),"") | R19: =IFERROR(IF(B19>$J$10,"",E19+Q19),"") | S19: =IFERROR(IF(B19>$J$10,"",R19*12),"") | T19: =IFERROR(IF(B19>$J$10,"",G19*R19),0) -> 0 | U19: =IF(D19="Rolled",J19*$E$5,"") -> #VALUE! | V19: =IF(B19<4,"",IF(B19>$J$11,"",T19-L19)) | W19: =IF(B19>$J$11,"",SUM($V$19:V19)) -> 0 | Y19: =IF(B19>$J$11,"",SUM($X$19:X19)) -> 0 | Z19: =IFERROR(ROUNDDOWN(W19-Y19,0),"") -> 0 | AB19: =IF(AND(D19="Serviced", B19>=$J$11+1),T19,"") | AD19: =IFERROR(IF(AND(D19="Serviced",B19>=($J$11+1)),(AB19-AC19),""),0) | AE19: =IF(B19>$J$10,0,IF(B19<=$J$11,0,ROUND(SUM($AD$19:AD19),0))) -> 0
B20: 2 | C20: =EDATE(C19,1) -> 31 | D20: =IF(B20>$J$10,"",IF(B20<=$J$7,"Rolled","Serviced")) -> Rolled | E20: =IF(B20>$J$10,"",$E$10) -> #VALUE! | G20: =IF(B20>$J$10,"",$E$5-SUM(F$19:$F20)) -> 0 | H20: =IF(AND(F20>0,G19>0,F20>=G19),EDATE(C20,0)) -> FALSE | I20: =IF(B20>$J$10,"",'Input Sheet'!$C$42) -> 0.0033333333 | J20: =IF(B20>$J$10,"",$E$11) -> #VALUE! | K20: =IF(B20>$J$10,"",J20*12) -> #VALUE! | L20: =IFERROR(IF(B20>$J$11,G20*J20,$E$5*J20),"") | M20: =IF(AND(B20<21,$E$3="Fusion",F20<>""),F20*3%,"") | P20: =IFERROR(IF(B20>$J$10,"",IF($E$3="Fixed",BBR,INDEX($P$5:$P$14,MATCH(EOMONTH(C20,-1)+1,$M$5:$M$14)))),"") | Q20: =IFERROR(IF(B20>$J$10,"",P20/12),"") | R20: =IFERROR(IF(B20>$J$10,"",E20+Q20),"") | S20: =IFERROR(IF(B20>$J$10,"",R20*12),"") | T20: =IFERROR(IF(B20>$J$10,"",G20*R20),0) -> 0 | U20: =IF(D20="Rolled",J20*$E$5,"") -> #VALUE! | V20: =IF(B20<4,"",IF(B20>$J$11,"",T20-L20)) | W20: =IF(B20>$J$11,"",SUM($V$19:V20)) -> 0 | Y20: =IF(B20>$J$11,"",SUM($X$19:X20)) -> 0 | Z20: =IFERROR(ROUNDDOWN(W20-Y20,0),"") -> 0 | AB20: =IF(AND(D20="Serviced", B20>=$J$11+1),T20,"") | AD20: =IFERROR(IF(AND(D20="Serviced",B20>=($J$11+1)),(AB20-AC20),""),0) | AE20: =IF(B20>$J$10,0,IF(B20<=$J$11,0,ROUND(SUM($AD$19:AD20),0))) -> 0
B21: 3 | C21: =EDATE(C20,1) -> 59 | D21: =IF(B21>$J$10,"",IF(B21<=$J$7,"Rolled","Serviced")) -> Rolled | E21: =IF(B21>$J$10,"",$E$10) -> #VALUE! | G21: =IF(B21>$J$10,"",$E$5-SUM(F$19:$F21)) -> 0 | H21: =IF(AND(F21>0,G20>0,F21>=G20),EDATE(C21,0)) -> FALSE | I21: =IF(B21>$J$10,"",'Input Sheet'!$C$42) -> 0.0033333333 | J21: =IF(B21>$J$10,"",$E$11) -> #VALUE! | K21: =IF(B21>$J$10,"",J21*12) -> #VALUE! | L21: =IFERROR(IF(B21>$J$11,G21*J21,$E$5*J21),"") | M21: =IF(AND(B21<21,$E$3="Fusion",F21<>""),F21*3%,"") | P21: =IFERROR(IF(B21>$J$10,"",IF($E$3="Fixed",BBR,INDEX($P$5:$P$14,MATCH(EOMONTH(C21,-1)+1,$M$5:$M$14)))),"") | Q21: =IFERROR(IF(B21>$J$10,"",P21/12),"") | R21: =IFERROR(IF(B21>$J$10,"",E21+Q21),"") | S21: =IFERROR(IF(B21>$J$10,"",R21*12),"") | T21: =IFERROR(IF(B21>$J$10,"",G21*R21),0) -> 0 | U21: =IF(D21="Rolled",J21*$E$5,"") -> #VALUE! | V21: =IF(B21<4,"",IF(B21>$J$11,"",T21-L21)) | W21: =IF(B21>$J$11,"",SUM($V$19:V21)) -> 0 | Y21: =IF(B21>$J$11,"",SUM($X$19:X21)) -> 0 | Z21: =IFERROR(ROUNDDOWN(W21-Y21,0),"") -> 0 | AB21: =IF(AND(D21="Serviced", B21>=$J$11+1),T21,"") | AD21: =IFERROR(IF(AND(D21="Serviced",B21>=($J$11+1)),(AB21-AC21),""),0) | AE21: =IF(B21>$J$10,0,IF(B21<=$J$11,0,ROUND(SUM($AD$19:AD21),0))) -> 0
B22: 4 | C22: =EDATE(C21,1) -> 88 | D22: =IF(B22>$J$10,"",IF(B22<=$J$7,"Rolled","Serviced")) -> Rolled | E22: =IF(B22>$J$10,"",$E$10) -> #VALUE! | G22: =IF(B22>$J$10,"",$E$5-SUM(F$19:$F22)) -> 0 | H22: =IF(AND(F22>0,G21>0,F22>=G21),EDATE(C22,0)) -> FALSE | I22: =IF(B22>$J$10,"",'Input Sheet'!$C$42) -> 0.0033333333 | J22: =IF(B22>$J$10,"",$E$11) -> #VALUE! | K22: =IF(B22>$J$10,"",J22*12) -> #VALUE! | L22: =IFERROR(IF(B22>$J$11,G22*J22,$E$5*J22),"") | M22: =IF(AND(B22<21,$E$3="Fusion",F22<>""),F22*3%,"") | P22: =IFERROR(IF(B22>$J$10,"",IF($E$3="Fixed",BBR,INDEX($P$5:$P$14,MATCH(EOMONTH(C22,-1)+1,$M$5:$M$14)))),"") | Q22: =IFERROR(IF(B22>$J$10,"",P22/12),"") | R22: =IFERROR(IF(B22>$J$10,"",E22+Q22),"") | S22: =IFERROR(IF(B22>$J$10,"",R22*12),"") | T22: =IFERROR(IF(B22>$J$10,"",G22*R22),0) -> 0 | U22: =IF(D22="Rolled",J22*$E$5,"") -> #VALUE! | V22: =IF(B22<4,"",IF(B22>$J$11,"",T22-L22)) -> #VALUE! | W22: =IF(B22>$J$11,"",SUM($V$19:V22)) -> #VALUE! | Y22: =IF(B22>$J$11,"",SUM($X$19:X22)) -> 0 | Z22: =IFERROR(ROUNDDOWN(W22-Y22,0),"") | AB22: =IF(AND(D22="Serviced", B22>=$J$11+1),T22,"") | AD22: =IFERROR(IF(AND(D22="Serviced",B22>=($J$11+1)),(AB22-AC22),""),0) | AE22: =IF(B22>$J$10,0,IF(B22<=$J$11,0,ROUND(SUM($AD$19:AD22),0))) -> 0
B23: 5 | C23: =EDATE(C22,1) -> 119 | D23: =IF(B23>$J$10,"",IF(B23<=$J$7,"Rolled","Serviced")) -> Rolled | E23: =IF(B23>$J$10,"",$E$10) -> #VALUE! | G23: =IF(B23>$J$10,"",$E$5-SUM(F$19:$F23)) -> 0 | H23: =IF(AND(F23>0,G22>0,F23>=G22),EDATE(C23,0)) -> FALSE | I23: =IF(B23>$J$10,"",'Input Sheet'!$C$42) -> 0.0033333333 | J23: =IF(B23>$J$10,"",$E$11) -> #VALUE! | K23: =IF(B23>$J$10,"",J23*12) -> #VALUE! | L23: =IFERROR(IF(B23>$J$11,G23*J23,$E$5*J23),"") | M23: =IF(AND(B23<21,$E$3="Fusion",F23<>""),F23*3%,"") | P23: =IFERROR(IF(B23>$J$10,"",IF($E$3="Fixed",BBR,INDEX($P$5:$P$14,MATCH(EOMONTH(C23,-1)+1,$M$5:$M$14)))),"") | Q23: =IFERROR(IF(B23>$J$10,"",P23/12),"") | R23: =IFERROR(IF(B23>$J$10,"",E23+Q23),"") | S23: =IFERROR(IF(B23>$J$10,"",R23*12),"") | T23: =IFERROR(IF(B23>$J$10,"",G23*R23),0) -> 0 | U23: =IF(D23="Rolled",J23*$E$5,"") -> #VALUE! | V23: =IF(B23<4,"",IF(B23>$J$11,"",T23-L23)) -> #VALUE! | W23: =IF(B23>$J$11,"",SUM($V$19:V23)) -> #VALUE! | Y23: =IF(B23>$J$11,"",SUM($X$19:X23)) -> 0 | Z23: =IFERROR(ROUNDDOWN(W23-Y23,0),"") | AB23: =IF(AND(D23="Serviced", B23>=$J$11+1),T23,"") | AD23: =IFERROR(IF(AND(D23="Serviced",B23>=($J$11+1)),(AB23-AC23),""),0) | AE23: =IF(B23>$J$10,0,IF(B23<=$J$11,0,ROUND(SUM($AD$19:AD23),0))) -> 0
B24: 6 | C24: =EDATE(C23,1) -> 149 | D24: =IF(B24>$J$10,"",IF(B24<=$J$7,"Rolled","Serviced")) -> Rolled | E24: =IF(B24>$J$10,"",$E$10) -> #VALUE! | G24: =IF(B24>$J$10,"",$E$5-SUM(F$19:$F24)) -> 0 | H24: =IF(AND(F24>0,G23>0,F24>=G23),EDATE(C24,0)) -> FALSE | I24: =IF(B24>$J$10,"",'Input Sheet'!$C$42) -> 0.0033333333 | J24: =IF(B24>$J$10,"",$E$11) -> #VALUE! | K24: =IF(B24>$J$10,"",J24*12) -> #VALUE! | L24: =IFERROR(IF(B24>$J$11,G24*J24,$E$5*J24),"") | M24: =IF(AND(B24<21,$E$3="Fusion",F24<>""),F24*3%,"") | P24: =IFERROR(IF(B24>$J$10,"",IF($E$3="Fixed",BBR,INDEX($P$5:$P$14,MATCH(EOMONTH(C24,-1)+1,$M$5:$M$14)))),"") | Q24: =IFERROR(IF(B24>$J$10,"",P24/12),"") | R24: =IFERROR(IF(B24>$J$10,"",E24+Q24),"") | S24: =IFERROR(IF(B24>$J$10,"",R24*12),"") | T24: =IFERROR(IF(B24>$J$10,"",G24*R24),0) -> 0 | U24: =IF(D24="Rolled",J24*$E$5,"") -> #VALUE! | V24: =IF(B24<4,"",IF(B24>$J$11,"",T24-L24)) -> #VALUE! | W24: =IF(B24>$J$11,"",SUM($V$19:V24)) -> #VALUE! | Y24: =IF(B24>$J$11,"",SUM($X$19:X24)) -> 0 | Z24: =IFERROR(ROUNDDOWN(W24-Y24,0),"") | AB24: =IF(AND(D24="Serviced", B24>=$J$11+1),T24,"") | AD24: =IFERROR(IF(AND(D24="Serviced",B24>=($J$11+1)),(AB24-AC24),""),0) | AE24: =IF(B24>$J$10,0,IF(B24<=$J$11,0,ROUND(SUM($AD$19:AD24),0))) -> 0
B25: 7 | C25: =EDATE(C24,1) -> 180 | D25: =IF(B25>$J$10,"",IF(B25<=$J$7,"Rolled","Serviced")) -> Serviced | E25: =IF(B25>$J$10,"",$E$10) -> #VALUE! | G25: =IF(B25>$J$10,"",$E$5-SUM(F$19:$F25)) -> 0 | H25: =IF(AND(F25>0,G24>0,F25>=G24),EDATE(C25,0)) -> FALSE | I25: =IF(B25>$J$10,"",'Input Sheet'!$C$42) -> 0.0033333333 | J25: =IF(B25>$J$10,"",$E$11) -> #VALUE! | K25: =IF(B25>$J$10,"",J25*12) -> #VALUE! | L25: =IFERROR(IF(B25>$J$11,G25*J25,$E$5*J25),"") | M25: =IFERROR(IF(AND($E$3="Fusion",F25>0),IF(F25>=O24,(F25-O24)*3%,""),""),"") | N25: =$E$5*25% -> 0 | O25: =IF(N25-SUM($F$25:F25)>0,N25-SUM($F$25:F25),0) -> 0 | P25: =IFERROR(IF(B25>$J$10,"",IF($E$3="Fixed",BBR,INDEX($P$5:$P$14,MATCH(EOMONTH(C25,-1)+1,$M$5:$M$14)))),"") | Q25: =IFERROR(IF(B25>$J$10,"",P25/12),"") | R25: =IFERROR(IF(B25>$J$10,"",E25+Q25),"") | S25: =IFERROR(IF(B25>$J$10,"",R25*12),"") | T25: =IFERROR(IF(B25>$J$10,"",G25*R25),0) -> 0 | U25: =IF(D25="Rolled",J25*$E$5,"") | V25: =IF(B25<4,"",IF(B25>$J$11,"",T25-L25)) | W25: =IF(B25>$J$11,"",SUM($V$19:V25)) | Y25: =IF(B25>$J$11,"",SUM($X$19:X25)) | Z25: =IFERROR(ROUNDDOWN(W25-Y25,0),"") | AB25: =IF(AND(D25="Serviced", B25>=$J$11+1),T25,"") -> 0 | AD25: =IFERROR(IF(AND(D25="Serviced",B25>=($J$11+1)),(AB25-AC25),""),0) -> 0 | AE25: =IF(B25>$J$10,0,IF(B25<=$J$11,0,ROUND(SUM($AD$19:AD25),0))) -> 0
B26: 8 | C26: =EDATE(C25,1) -> 210 | D26: =IF(B26>$J$10,"",IF(B26<=$J$7,"Rolled","Serviced")) -> Serviced | E26: =IF(B26>$J$10,"",$E$10) -> #VALUE! | G26: =IF(B26>$J$10,"",$E$5-SUM(F$19:$F26)) -> 0 | H26: =IF(AND(F26>0,G25>0,F26>=G25),EDATE(C26,0)) -> FALSE | I26: =IF(B26>$J$10,"",'Input Sheet'!$C$42) -> 0.0033333333 | J26: =IF(B26>$J$10,"",$E$11) -> #VALUE! | K26: =IF(B26>$J$10,"",J26*12) -> #VALUE! | L26: =IFERROR(IF(B26>$J$11,G26*J26,$E$5*J26),"") | M26: =IFERROR(IF(AND($E$3="Fusion",F26>0),IF(F26>=O25,(F26-O25)*3%,""),""),"") | N26: =$E$5*25% -> 0 | O26: =IF(N26-SUM($F$25:F26)>0,N26-SUM($F$25:F26),0) -> 0 | P26: =IFERROR(IF(B26>$J$10,"",IF($E$3="Fixed",BBR,INDEX($P$5:$P$14,MATCH(EOMONTH(C26,-1)+1,$M$5:$M$14)))),"") | Q26: =IFERROR(IF(B26>$J$10,"",P26/12),"") | R26: =IFERROR(IF(B26>$J$10,"",E26+Q26),"") | S26: =IFERROR(IF(B26>$J$10,"",R26*12),"") | T26: =IFERROR(IF(B26>$J$10,"",G26*R26),0) -> 0 | U26: =IF(D26="Rolled",J26*$E$5,"") | V26: =IF(B26<4,"",IF(B26>$J$11,"",T26-L26)) | W26: =IF(B26>$J$11,"",SUM($V$19:V26)) | Y26: =IF(B26>$J$11,"",SUM($X$19:X26)) | Z26: =IFERROR(ROUNDDOWN(W26-Y26,0),"") | AB26: =IF(AND(D26="Serviced", B26>=$J$11+1),T26,"") -> 0 | AD26: =IFERROR(IF(AND(D26="Serviced",B26>=($J$11+1)),(AB26-AC26),""),0) -> 0 | AE26: =IF(B26>$J$10,0,IF(B26<=$J$11,0,ROUND(SUM($AD$19:AD26),0))) -> 0
B27: 9 | C27: =EDATE(C26,1) -> 241 | D27: =IF(B27>$J$10,"",IF(B27<=$J$7,"Rolled","Serviced")) -> Serviced | E27: =IF(B27>$J$10,"",$E$10) -> #VALUE! | G27: =IF(B27>$J$10,"",$E$5-SUM(F$19:$F27)) -> 0 | H27: =IF(AND(F27>0,G26>0,F27>=G26),EDATE(C27,0)) -> FALSE | I27: =IF(B27>$J$10,"",'Input Sheet'!$C$42) -> 0.0033333333 | J27: =IF(B27>$J$10,"",$E$11) -> #VALUE! | K27: =IF(B27>$J$10,"",J27*12) -> #VALUE! | L27: =IFERROR(IF(B27>$J$11,G27*J27,$E$5*J27),"") | M27: =IFERROR(IF(AND($E$3="Fusion",F27>0),IF(F27>=O26,(F27-O26)*3%,""),""),"") | N27: =$E$5*25% -> 0 | O27: =IF(N27-SUM($F$25:F27)>0,N27-SUM($F$25:F27),0) -> 0 | P27: =IFERROR(IF(B27>$J$10,"",IF($E$3="Fixed",BBR,INDEX($P$5:$P$14,MATCH(EOMONTH(C27,-1)+1,$M$5:$M$14)))),"") | Q27: =IFERROR(IF(B27>$J$10,"",P27/12),"") | R27: =IFERROR(IF(B27>$J$10,"",E27+Q27),"") | S27: =IFERROR(IF(B27>$J$10,"",R27*12),"") | T27: =IFERROR(IF(B27>$J$10,"",G27*R27),0) -> 0 | U27: =IF(D27="Rolled",J27*$E$5,"") | V27: =IF(B27<4,"",IF(B27>$J$11,"",T27-L27)) | W27: =IF(B27>$J$11,"",SUM($V$19:V27)) | Y27: =IF(B27>$J$11,"",SUM($X$19:X27)) | Z27: =IFERROR(ROUNDDOWN(W27-Y27,0),"") | AB27: =IF(AND(D27="Serviced", B27>=$J$11+1),T27,"") -> 0 | AD27: =IFERROR(IF(AND(D27="Serviced",B27>=($J$11+1)),(AB27-AC27),""),0) -> 0 | AE27: =IF(B27>$J$10,0,IF(B27<=$J$11,0,ROUND(SUM($AD$19:AD27),0))) -> 0
B28: 10 | C28: =EDATE(C27,1) -> 272 | D28: =IF(B28>$J$10,"",IF(B28<=$J$7,"Rolled","Serviced")) -> Serviced | E28: =IF(B28>$J$10,"",$E$10) -> #VALUE! | G28: =IF(B28>$J$10,"",$E$5-SUM(F$19:$F28)) -> 0 | H28: =IF(AND(F28>0,G27>0,F28>=G27),EDATE(C28,0)) -> FALSE | I28: =IF(B28>$J$10,"",'Input Sheet'!$C$42) -> 0.0033333333 | J28: =IF(B28>$J$10,"",$E$11) -> #VALUE! | K28: =IF(B28>$J$10,"",J28*12) -> #VALUE! | L28: =IFERROR(IF(B28>$J$11,G28*J28,$E$5*J28),"") | M28: =IFERROR(IF(AND($E$3="Fusion",F28>0),IF(F28>=O27,(F28-O27)*3%,""),""),"") | N28: =$E$5*25% -> 0 | O28: =IF(N28-SUM($F$25:F28)>0,N28-SUM($F$25:F28),0) -> 0 | P28: =IFERROR(IF(B28>$J$10,"",IF($E$3="Fixed",BBR,INDEX($P$5:$P$14,MATCH(EOMONTH(C28,-1)+1,$M$5:$M$14)))),"") | Q28: =IFERROR(IF(B28>$J$10,"",P28/12),"") | R28: =IFERROR(IF(B28>$J$10,"",E28+Q28),"") | S28: =IFERROR(IF(B28>$J$10,"",R28*12),"") | T28: =IFERROR(IF(B28>$J$10,"",G28*R28),0) -> 0 | U28: =IF(D28="Rolled",J28*$E$5,"") | V28: =IF(B28<4,"",IF(B28>$J$11,"",T28-L28)) | W28: =IF(B28>$J$11,"",SUM($V$19:V28)) | Y28: =IF(B28>$J$11,"",SUM($X$19:X28)) | Z28: =IFERROR(ROUNDDOWN(W28-Y28,0),"") | AB28: =IF(AND(D28="Serviced", B28>=$J$11+1),T28,"") -> 0 | AD28: =IFERROR(IF(AND(D28="Serviced",B28>=($J$11+1)),(AB28-AC28),""),0) -> 0 | AE28: =IF(B28>$J$10,0,IF(B28<=$J$11,0,ROUND(SUM($AD$19:AD28),0))) -> 0
B29: 11 | C29: =EDATE(C28,1) -> 302 | D29: =IF(B29>$J$10,"",IF(B29<=$J$7,"Rolled","Serviced")) -> Serviced | E29: =IF(B29>$J$10,"",$E$10) -> #VALUE! | G29: =IF(B29>$J$10,"",$E$5-SUM(F$19:$F29)) -> 0 | H29: =IF(AND(F29>0,G28>0,F29>=G28),EDATE(C29,0)) -> FALSE | I29: =IF(B29>$J$10,"",'Input Sheet'!$C$42) -> 0.0033333333 | J29: =IF(B29>$J$10,"",$E$11) -> #VALUE! | K29: =IF(B29>$J$10,"",J29*12) -> #VALUE! | L29: =IFERROR(IF(B29>$J$11,G29*J29,$E$5*J29),"") | M29: =IFERROR(IF(AND($E$3="Fusion",F29>0),IF(F29>=O28,(F29-O28)*3%,""),""),"") | N29: =$E$5*25% -> 0 | O29: =IF(N29-SUM($F$25:F29)>0,N29-SUM($F$25:F29),0) -> 0 | P29: =IFERROR(IF(B29>$J$10,"",IF($E$3="Fixed",BBR,INDEX($P$5:$P$14,MATCH(EOMONTH(C29,-1)+1,$M$5:$M$14)))),"") | Q29: =IFERROR(IF(B29>$J$10,"",P29/12),"") | R29: =IFERROR(IF(B29>$J$10,"",E29+Q29),"") | S29: =IFERROR(IF(B29>$J$10,"",R29*12),"") | T29: =IFERROR(IF(B29>$J$10,"",G29*R29),0) -> 0 | U29: =IF(D29="Rolled",J29*$E$5,"") | V29: =IF(B29<4,"",IF(B29>$J$11,"",T29-L29)) | W29: =IF(B29>$J$11,"",SUM($V$19:V29)) | Y29: =IF(B29>$J$11,"",SUM($X$19:X29)) | Z29: =IFERROR(ROUNDDOWN(W29-Y29,0),"") | AB29: =IF(AND(D29="Serviced", B29>=$J$11+1),T29,"") -> 0 | AD29: =IFERROR(IF(AND(D29="Serviced",B29>=($J$11+1)),(AB29-AC29),""),0) -> 0 | AE29: =IF(B29>$J$10,0,IF(B29<=$J$11,0,ROUND(SUM($AD$19:AD29),0))) -> 0
B30: 12 | C30: =EDATE(C29,1) -> 333 | D30: =IF(B30>$J$10,"",IF(B30<=$J$7,"Rolled","Serviced")) -> Serviced | E30: =IF(B30>$J$10,"",$E$10) -> #VALUE! | G30: =IF(B30>$J$10,"",$E$5-SUM(F$19:$F30)) -> 0 | H30: =IF(AND(F30>0,G29>0,F30>=G29),EDATE(C30,0)) -> FALSE | I30: =IF(B30>$J$10,"",'Input Sheet'!$C$42) -> 0.0033333333 | J30: =IF(B30>$J$10,"",$E$11) -> #VALUE! | K30: =IF(B30>$J$10,"",J30*12) -> #VALUE! | L30: =IFERROR(IF(B30>$J$11,G30*J30,$E$5*J30),"") | M30: =IFERROR(IF(AND($E$3="Fusion",F30>0),IF(F30>=O29,(F30-O29)*3%,""),""),"") | N30: =$E$5*25% -> 0 | O30: =IF(N30-SUM($F$25:F30)>0,N30-SUM($F$25:F30),0) -> 0 | P30: =IFERROR(IF(B30>$J$10,"",IF($E$3="Fixed",BBR,INDEX($P$5:$P$14,MATCH(EOMONTH(C30,-1)+1,$M$5:$M$14)))),"") | Q30: =IFERROR(IF(B30>$J$10,"",P30/12),"") | R30: =IFERROR(IF(B30>$J$10,"",E30+Q30),"") | S30: =IFERROR(IF(B30>$J$10,"",R30*12),"") | T30: =IFERROR(IF(B30>$J$10,"",G30*R30),0) -> 0 | U30: =IF(D30="Rolled",J30*$E$5,"") | V30: =IF(B30<4,"",IF(B30>$J$11,"",T30-L30)) | W30: =IF(B30>$J$11,"",SUM($V$19:V30)) | Y30: =IF(B30>$J$11,"",SUM($X$19:X30)) | Z30: =IFERROR(ROUNDDOWN(W30-Y30,0),"") | AB30: =IF(AND(D30="Serviced", B30>=$J$11+1),T30,"") -> 0 | AD30: =IFERROR(IF(AND(D30="Serviced",B30>=($J$11+1)),(AB30-AC30),""),0) -> 0 | AE30: =IF(B30>$J$10,0,IF(B30<=$J$11,0,ROUND(SUM($AD$19:AD30),0))) -> 0
B31: 13 | C31: =EDATE(C30,1) -> 363 | D31: =IF(B31>$J$10,"",IF(B31<=$J$7,"Rolled","Serviced")) -> Serviced | E31: =IF(B31>$J$10,"",$E$10) -> #VALUE! | G31: =IF(B31>$J$10,"",$E$5-SUM(F$19:$F31)) -> 0 | H31: =IF(AND(F31>0,G30>0,F31>=G30),EDATE(C31,0)) -> FALSE | I31: =IF(B31>$J$10,"",'Input Sheet'!$C$42) -> 0.0033333333 | J31: =IF(B31>$J$10,"",$E$11) -> #VALUE! | K31: =IF(B31>$J$10,"",J31*12) -> #VALUE! | L31: =IFERROR(IF(B31>$J$11,G31*J31,$E$5*J31),"") | M31: =IFERROR(IF(AND($E$3="Fusion",F31>0),IF(F31>=O30,(F31-O30)*1.5%,""),""),"") | N31: =$E$5*25% -> 0 | O31: =IF(N31-SUM($F$25:F31)>0,N31-SUM($F$25:F31),0) -> 0 | P31: =IFERROR(IF(B31>$J$10,"",IF($E$3="Fixed",BBR,INDEX($P$5:$P$14,MATCH(EOMONTH(C31,-1)+1,$M$5:$M$14)))),"") | Q31: =IFERROR(IF(B31>$J$10,"",P31/12),"") | R31: =IFERROR(IF(B31>$J$10,"",E31+Q31),"") | S31: =IFERROR(IF(B31>$J$10,"",R31*12),"") | T31: =IFERROR(IF(B31>$J$10,"",G31*R31),0) -> 0 | U31: =IF(D31="Rolled",J31*$E$5,"") | V31: =IF(B31<4,"",IF(B31>$J$11,"",T31-L31)) | W31: =IF(B31>$J$11,"",SUM($V$19:V31)) | Y31: =IF(B31>$J$11,"",SUM($X$19:X31)) | Z31: =IFERROR(ROUNDDOWN(W31-Y31,0),"") | AB31: =IF(AND(D31="Serviced", B31>=$J$11+1),T31,"") -> 0 | AD31: =IFERROR(IF(AND(D31="Serviced",B31>=($J$11+1)),(AB31-AC31),""),0) -> 0 | AE31: =IF(B31>$J$10,0,IF(B31<=$J$11,0,ROUND(SUM($AD$19:AD31),0))) -> 0
